Workbook
Name Analysis_year: 'Project description'!$B$29
Name FinalYear_BC: Calculations!$B$3
Name FinalYear_PP: Calculations!$B$2
Name HurdleRateBasis: 'Project description'!$B$27
Name ReturnType: 'Project description'!$B$28
Name Start_Yr: 'Project description'!$B$10

Sheet Guidance
A2: This spreadsheet is for the applicant to fill in information about the 'Proposed project' (ie, the project for which Concenssions Loan funds are sought) and also a 'Base Case' (ie, the outcomes if the project were not to proceed).
A3: For example, the Proposed Project could be the replacement of a coal-fired boiler with a biomass boiler, whereas the Base Case could be the coal-fired boiler continuing to operate.
A5: The spreadsheet consists of two tabs:
A6: Project description in which basic information is input
A8: Project description. This has some input cells for applicants to fill in regarding the name and type of project,starting dates and the applicant's investment criteria.
A9: Inputs. This is the main tab for the applicant to fill in projected Capex and Opex cashflows for the Proposed Project and the Base Case, as well as projected fuel consumption for both situations.
A10: Scratch. This is a tab which applicants can use if they wish to do their own bespoke calculations - noting that the rest of the spreadsheet is 'locked-down' to enable EECA to extract and evaluate data in a rigorous fashion.

Sheet Project description
A1: Input data
A2: Project information | B2: Information should be included on the proposed project (assuming the loan is given) and the base case (what you would do without the loan)
A3: Field | B3: Value | C3: Notes
A4: ProjectID | B4: CL-001
A5: Applicant's name | B5: Oliver's Meatworks
A6: Sector | B6: Agriculture, Forestry and Fishing
A7: Region | B7: Gisborne
A8: Name for proposed project | B8: Heat pump gas replacement
A9: Date of application submission (dd/mm/yy) | B9: 45702
A10: First year of expenditure (yyyy) | B10: 2026
A11: Expected commissioning date of proposed project (dd/mm/yy) | B11: 46388
A13: Project type | B13: Early replacement of asset | C13: =IF(B13="Retrofit of existing asset","Project assumed to last only as long as the life of the existing asset","")
A14: =INDEX(Lists!$C$2:$C$5,MATCH(Lists!B6,Lists!$B$2:$B$5,0)) -> Expected final year of operation/use of existing asset if not replaced early | B14: 2035
A15: If not a retrofit, what is the expected economic or useful life of the new investment? | B15: 20 | C15: ="Final year = "&FinalYear_PP -> Final year = 2047
A16: =INDEX(Lists!E2:E5,MATCH(Lists!B6,Lists!$B$2:$B$5,0)) -> Without the loan, what would the existing asset be replaced with at the end of its life? | B16: The same as the the proposed project
A17: =INDEX(Lists!F2:F5,MATCH(Lists!B6,Lists!$B$2:$B$5,0)) -> What would be the expected life of the replacement asset in the base case (no loan) | B17: 20 | C17: ="Final year = "&FinalYear_BC -> Final year = 2047
A19: Does the project replace the use of coal for industrial process heat? | B19: No
A20: If this project replaces coal consumption for industrial process heat, does the project bring forward the time of replacement from the start of 2037? | B20: Yes | C20: =IF(AND(B20="Yes",B19="Yes"),"The base case used for analysis should be that of just meeting the regulated coal phase-out date of 2037","")
A21: Is this a heat pump project? | B21: Yes
A23: What level of loan contribution are you requesting? ($) | B23: 950000
A24: Start date? (dd/mm/yyyy) | B24: 45992
A25: How long would the loan be for? (years) | B25: 10 | C25: ="Full repayment by "&Start_Yr+B25 -> Full repayment by 2036
A26: What is your hurdle rate for this investment (%) | B26: 0.2
A27: What basis is used for the hurdle rate? | B27: Pre-tax Nominal
A28: Is the hurdle rate for the return on equity only or for the whole invstment | B28: Return on Equity
A29: Analysis year | B29: =YEAR(TODAY()) -> 2025

Sheet Inputs
A2: Inflation
A3: Cashflow values may be specified in real (ie, current year values) or nominal (values for the year of the cost or revenue item)
A4: ="All values for the current year ("&'Project description'!B29&") should be in current dollar values" -> All values for the current year (2025) should be in current dollar values
A5: I will include my own inflation assumptions | B5: No
A6: If an inflation rate has been used to produce a future nominal value, please note it below | G6: 2025 | H6: =G6+1 -> 2026 | I6: =H6+1 -> 2027 | J6: =I6+1 -> 2028 | K6: =J6+1 -> 2029 | L6: =K6+1 -> 2030 | M6: =L6+1 -> 2031 | N6: =M6+1 -> 2032 | O6: =N6+1 -> 2033 | ... AZ6: =AY6+1 -> 2070
A7: Inflation rate in the year | G7: 0.03 | H7: 0.02 | I7: 0.02 | J7: 0.02 | K7: 0.02 | L7: 0.02 | M7: 0.02 | N7: 0.02 | O7: 0.02 | P7: 0.02 | Q7: 0.02 | R7: 0.02 | S7: 0.02 | T7: 0.02 | U7: 0.02 | V7: 0.02 | W7: 0.02 | X7: 0.02 | Y7: 0.02 | Z7: 0.02 | AA7: 0.02 | AB7: 0.02 | AC7: 0.02 | AD7: 0.02 | AE7: 0.02 | AF7: 0.02 | AG7: =AF7 -> 0.02 | AH7: =AG7 -> 0.02 | AI7: =AH7 -> 0.02 | AJ7: =AI7 -> 0.02 | AK7: =AJ7 -> 0.02 | AL7: =AK7 -> 0.02 | AM7: =AL7 -> 0.02 | AN7: =AM7 -> 0.02 | ... AZ7: =AY7 -> 0.02
A8: Default inflation rates | G8: =Data!L33 -> 0.022 | H8: =Data!M33 -> 0.02 | I8: =Data!N33 -> 0.02 | J8: =Data!O33 -> 0.02 | K8: =Data!P33 -> 0.02 | L8: =Data!Q33 -> 0.02 | M8: =Data!R33 -> 0.02 | N8: =Data!S33 -> 0.02 | ... AZ8: =Data!BE33 -> 0.02
A9: Inflator - use this to convert real values to nominal | G9: 1 | H9: =G9*IF($B$5="Yes",(1+G7/2)*(1+H7/2),(1+G8/2)*(1+H8/2)) -> 1.02111 | I9: =H9*IF($B$5="Yes",(1+H7/2)*(1+I7/2),(1+H8/2)*(1+I8/2)) -> 1.0416343 | J9: =I9*IF($B$5="Yes",(1+I7/2)*(1+J7/2),(1+I8/2)*(1+J8/2)) -> 1.0625712 | K9: =J9*IF($B$5="Yes",(1+J7/2)*(1+K7/2),(1+J8/2)*(1+K8/2)) -> 1.0839288 | L9: =K9*IF($B$5="Yes",(1+K7/2)*(1+L7/2),(1+K8/2)*(1+L8/2)) -> 1.1057158 | M9: =L9*IF($B$5="Yes",(1+L7/2)*(1+M7/2),(1+L8/2)*(1+M8/2)) -> 1.1279407 | N9: =M9*IF($B$5="Yes",(1+M7/2)*(1+N7/2),(1+M8/2)*(1+N8/2)) -> 1.1506123 | O9: =N9*IF($B$5="Yes",(1+N7/2)*(1+O7/2),(1+N8/2)*(1+O8/2)) -> 1.1737396 | ... AZ9: =AY9*IF($B$5="Yes",(1+AY7/2)*(1+AZ7/2),(1+AY8/2)*(1+AZ8/2)) -> 2.4510571
A10: Deflator - use this to convert nominal values to real | G10: 1 | H10: =1/((1/G10)*IF($B$5="Yes",(1+G7/2)*(1+H7/2),(1+G8/2)*(1+H8/2))) -> 0.97932642 | I10: =1/((1/H10)*IF($B$5="Yes",(1+H7/2)*(1+I7/2),(1+H8/2)*(1+I8/2))) -> 0.96002982 | J10: =1/((1/I10)*IF($B$5="Yes",(1+I7/2)*(1+J7/2),(1+I8/2)*(1+J8/2))) -> 0.94111344 | K10: =1/((1/J10)*IF($B$5="Yes",(1+J7/2)*(1+K7/2),(1+J8/2)*(1+K8/2))) -> 0.92256979 | L10: =1/((1/K10)*IF($B$5="Yes",(1+K7/2)*(1+L7/2),(1+K8/2)*(1+L8/2))) -> 0.90439152 | M10: =1/((1/L10)*IF($B$5="Yes",(1+L7/2)*(1+M7/2),(1+L8/2)*(1+M8/2))) -> 0.88657143 | N10: =1/((1/M10)*IF($B$5="Yes",(1+M7/2)*(1+N7/2),(1+M8/2)*(1+N8/2))) -> 0.86910247 | O10: =1/((1/N10)*IF($B$5="Yes",(1+N7/2)*(1+O7/2),(1+N8/2)*(1+O8/2))) -> 0.85197772 | ... AZ10: =1/((1/AY10)*IF($B$5="Yes",(1+AY7/2)*(1+AZ7/2),(1+AY8/2)*(1+AZ8/2))) -> 0.40798724
A12: 1) Capital expenditure (CAPEX) ($) - please enter all costs as positive numbers
D13: Value basis | E13: Nominal
A14: Proposed Project (PP) | D14: Capex item | E14: Value basis | G14: Applicant comment | H14: 2026 | I14: 2027 | J14: 2028 | K14: 2029 | L14: 2030 | M14: 2031 | N14: 2032 | O14: 2033 | P14: 2034 | Q14: 2035 | R14: 2036 | S14: 2037 | T14: 2038 | U14: 2039 | V14: 2040 | W14: 2041 | X14: 2042 | Y14: 2043 | Z14: 2044 | AA14: 2045 | AB14: 2046 | AC14: 2047 | AD14: 2048 | AE14: 2049 | AF14: 2050 | AG14: 2051 | AH14: 2052 | AI14: 2053 | AJ14: 2054 | AK14: 2055 | AL14: 2056 | AM14: 2057 | AN14: 2058 | AO14: 2059 | AP14: 2060 | AQ14: 2061 | AR14: 2062 | AS14: 2063 | AT14: 2064 | AU14: 2065 | AV14: 2066 | AW14: 2067 | AX14: 2068 | AY14: 2069 | AZ14: 2070
A15: ="Please provide data through to "&FinalYear_PP -> Please provide data through to 2047 | D15: Equipment purchase | E15: =E$13 -> Nominal | H15: 800000 | I15: 800000
D16: Civil works | E16: =E$13 -> Nominal | H16: 80000
D17: Electrical works | E17: =E$13 -> Nominal | H17: 250000
D18: Installation | E18: =E$13 -> Nominal | H18: 100000
D19: Indirect costs | E19: =E$13 -> Nominal | H19: 50000 | I19: 50000
D20: Project management | E20: =E$13 -> Nominal
D21: Other | E21: =E$13 -> Nominal
D22: ="Total capex in "&Analysis_year&" dollars" -> Total capex in 2025 dollars | H22: =SUM(H15:H21)*IF($E$13="Real",1,H$10) -> 1253537.8 | I22: =SUM(I15:I21)*IF($E$13="Real",1,I$10) -> 816025.35 | J22: =SUM(J15:J21)*IF($E$13="Real",1,J$10) -> 0 | K22: =SUM(K15:K21)*IF($E$13="Real",1,K$10) -> 0 | L22: =SUM(L15:L21)*IF($E$13="Real",1,L$10) -> 0 | M22: =SUM(M15:M21)*IF($E$13="Real",1,M$10) -> 0 | N22: =SUM(N15:N21)*IF($E$13="Real",1,N$10) -> 0 | O22: =SUM(O15:O21)*IF($E$13="Real",1,O$10) -> 0 | ... AZ22: =SUM(AZ15:AZ21)*IF($E$13="Real",1,AZ$10) -> 0
D23: Total capex in nominal dollars | H23: =SUM(H15:H21)*IF($E$13="Real",H9,1) -> 1280000 | I23: =SUM(I15:I21)*IF($E$13="Real",I9,1) -> 850000 | J23: =SUM(J15:J21)*IF($E$13="Real",J9,1) -> 0 | K23: =SUM(K15:K21)*IF($E$13="Real",K9,1) -> 0 | L23: =SUM(L15:L21)*IF($E$13="Real",L9,1) -> 0 | M23: =SUM(M15:M21)*IF($E$13="Real",M9,1) -> 0 | N23: =SUM(N15:N21)*IF($E$13="Real",N9,1) -> 0 | O23: =SUM(O15:O21)*IF($E$13="Real",O9,1) -> 0 | ... AZ23: =SUM(AZ15:AZ21)*IF($E$13="Real",AZ9,1) -> 0
D25: Value basis | E25: Nominal
A26: Base Case (BC) | D26: Capex item | E26: Value basis | G26: Applicant comment | H26: 2026 | I26: 2027 | J26: 2028 | K26: 2029 | L26: 2030 | M26: 2031 | N26: 2032 | O26: 2033 | P26: 2034 | Q26: 2035 | R26: 2036 | S26: 2037 | T26: 2038 | U26: 2039 | V26: 2040 | W26: 2041 | X26: 2042 | Y26: 2043 | Z26: 2044 | AA26: 2045 | AB26: 2046 | AC26: 2047 | AD26: 2048 | AE26: 2049 | AF26: 2050 | AG26: 2051 | AH26: 2052 | AI26: 2053 | AJ26: 2054 | AK26: 2055 | AL26: 2056 | AM26: 2057 | AN26: 2058 | AO26: 2059 | AP26: 2060 | AQ26: 2061 | AR26: 2062 | AS26: 2063 | AT26: 2064 | AU26: 2065 | AV26: 2066 | AW26: 2067 | AX26: 2068 | AY26: 2069 | AZ26: 2070
A27: Expand if more items | D27: Equipment purchase | E27: =$E$25 -> Nominal | H27: 0 | I27: 0
D28: Civil works | E28: =$E$25 -> Nominal
D29: Electrical works | E29: =$E$25 -> Nominal
D30: Installation | E30: =$E$25 -> Nominal
D31: Indirect costs | E31: =$E$25 -> Nominal
D32: Project management | E32: =$E$25 -> Nominal
D33: Other | E33: =$E$25 -> Nominal
D34: ="Total capex in "&Analysis_year&" dollars" -> Total capex in 2025 dollars | H34: =SUM(H27:H33)*IF($E$25="Real",1,H$10) -> 0 | I34: =SUM(I27:I33)*IF($E$25="Real",1,I$10) -> 0 | J34: =SUM(J27:J33)*IF($E$25="Real",1,J$10) -> 0 | K34: =SUM(K27:K33)*IF($E$25="Real",1,K$10) -> 0 | L34: =SUM(L27:L33)*IF($E$25="Real",1,L$10) -> 0 | M34: =SUM(M27:M33)*IF($E$25="Real",1,M$10) -> 0 | N34: =SUM(N27:N33)*IF($E$25="Real",1,N$10) -> 0 | O34: =SUM(O27:O33)*IF($E$25="Real",1,O$10) -> 0 | ... AZ34: =SUM(AZ27:AZ33)*IF($E$25="Real",1,AZ$10) -> 0
D35: Total capex in nominal dollars | H35: =SUM(H27:H33)*IF($E$25="Real",H$9,1) -> 0 | I35: =SUM(I27:I33)*IF($E$25="Real",I$9,1) -> 0 | J35: =SUM(J27:J33)*IF($E$25="Real",J$9,1) -> 0 | K35: =SUM(K27:K33)*IF($E$25="Real",K$9,1) -> 0 | L35: =SUM(L27:L33)*IF($E$25="Real",L$9,1) -> 0 | M35: =SUM(M27:M33)*IF($E$25="Real",M$9,1) -> 0 | N35: =SUM(N27:N33)*IF($E$25="Real",N$9,1) -> 0 | O35: =SUM(O27:O33)*IF($E$25="Real",O$9,1) -> 0 | ... AZ35: =SUM(AZ27:AZ33)*IF($E$25="Real",AZ$9,1) -> 0
A38: 2) Operating & Maintenance Expenditure (OPEX) ($) - please enter all costs as positive numbers
A39: 2a) Non-fuel opex | D39: Value basis | E39: nominal
A40: Proposed Project (PP) | D40: Opex item | E40: Value basis | G40: Applicant comment | H40: 2026 | I40: 2027 | J40: 2028 | K40: 2029 | L40: 2030 | M40: 2031 | N40: 2032 | O40: 2033 | P40: 2034 | Q40: 2035 | R40: 2036 | S40: 2037 | T40: 2038 | U40: 2039 | V40: 2040 | W40: 2041 | X40: 2042 | Y40: 2043 | Z40: 2044 | AA40: 2045 | AB40: 2046 | AC40: 2047 | AD40: 2048 | AE40: 2049 | AF40: 2050 | AG40: 2051 | AH40: 2052 | AI40: 2053 | AJ40: 2054 | AK40: 2055 | AL40: 2056 | AM40: 2057 | AN40: 2058 | AO40: 2059 | AP40: 2060 | AQ40: 2061 | AR40: 2062 | AS40: 2063 | AT40: 2064 | AU40: 2065 | AV40: 2066 | AW40: 2067 | AX40: 2068 | AY40: 2069 | AZ40: 2070
A41: ="Please provide data through to "&FinalYear_PP -> Please provide data through to 2047 | D41: Energy costs (already handled separately) | E41: =$E$39 -> nominal
D42: Equipment Operation Costs | E42: =$E$39 -> nominal | H42: 100000 | I42: =H42 -> 100000 | J42: =I42 -> 100000 | K42: =J42 -> 100000 | L42: =K42 -> 100000 | M42: =L42 -> 100000 | N42: =M42 -> 100000 | O42: =N42 -> 100000 | P42: =O42 -> 100000 | ... AC42: =AB42 -> 100000
D43: Maintenance, Repairs, Inspections | E43: =$E$39 -> nominal | H43: 20000 | I43: 20000 | J43: 20000 | K43: 20000 | L43: 20000 | M43: 20000 | N43: 20000 | O43: 20000 | P43: 20000 | Q43: 20000 | R43: 20000 | S43: 20000 | T43: 20000 | U43: 20000 | V43: 20000 | W43: 20000 | X43: 20000 | Y43: 20000 | Z43: 20000 | AA43: 20000 | AB43: 20000 | AC43: 20000
D44: Compliance Testing | E44: =$E$39 -> nominal | H44: 10000 | I44: 10000
D45: Optimisation | E45: =$E$39 -> nominal
D46: Utilities and Consumables | E46: =$E$39 -> nominal
D47: Other | E47: =$E$39 -> nominal
D48: ="Total non-fuel opex in "&Analysis_year&" dollars" -> Total non-fuel opex in 2025 dollars | H48: =SUM(H41:H47)*IF($E$39="Real",1,H$10) -> 127312.43 | I48: =SUM(I41:I47)*IF($E$39="Real",1,I$10) -> 124803.88 | J48: =SUM(J41:J47)*IF($E$39="Real",1,J$10) -> 112933.61 | K48: =SUM(K41:K47)*IF($E$39="Real",1,K$10) -> 110708.37 | L48: =SUM(L41:L47)*IF($E$39="Real",1,L$10) -> 108526.98 | M48: =SUM(M41:M47)*IF($E$39="Real",1,M$10) -> 106388.57 | N48: =SUM(N41:N47)*IF($E$39="Real",1,N$10) -> 104292.3 | O48: =SUM(O41:O47)*IF($E$39="Real",1,O$10) -> 102237.33 | ... AZ48: =SUM(AZ41:AZ47)*IF($E$39="Real",1,AZ$10) -> 0
D49: Total non-fuel opex in nominal dollars | H49: =SUM(H41:H47)*IF($E$39="Real",H$9,1) -> 130000 | I49: =SUM(I41:I47)*IF($E$39="Real",I$9,1) -> 130000 | J49: =SUM(J41:J47)*IF($E$39="Real",J$9,1) -> 120000 | K49: =SUM(K41:K47)*IF($E$39="Real",K$9,1) -> 120000 | L49: =SUM(L41:L47)*IF($E$39="Real",L$9,1) -> 120000 | M49: =SUM(M41:M47)*IF($E$39="Real",M$9,1) -> 120000 | N49: =SUM(N41:N47)*IF($E$39="Real",N$9,1) -> 120000 | O49: =SUM(O41:O47)*IF($E$39="Real",O$9,1) -> 120000 | ... AZ49: =SUM(AZ41:AZ47)*IF($E$39="Real",AZ$9,1) -> 0
D51: Value basis | E51: nominal
A52: Base Case (BC) | D52: Opex item | E52: Value basis | G52: Applicant comment | H52: 2026 | I52: 2027 | J52: 2028 | K52: 2029 | L52: 2030 | M52: 2031 | N52: 2032 | O52: 2033 | P52: 2034 | Q52: 2035 | R52: 2036 | S52: 2037 | T52: 2038 | U52: 2039 | V52: 2040 | W52: 2041 | X52: 2042 | Y52: 2043 | Z52: 2044 | AA52: 2045 | AB52: 2046 | AC52: 2047 | AD52: 2048 | AE52: 2049 | AF52: 2050 | AG52: 2051 | AH52: 2052 | AI52: 2053 | AJ52: 2054 | AK52: 2055 | AL52: 2056 | AM52: 2057 | AN52: 2058 | AO52: 2059 | AP52: 2060 | AQ52: 2061 | AR52: 2062 | AS52: 2063 | AT52: 2064 | AU52: 2065 | AV52: 2066 | AW52: 2067 | AX52: 2068 | AY52: 2069 | AZ52: 2070
A53: ="Please provide data through to "&FinalYear_BC -> Please provide data through to 2047 | D53: Energy costs (already handled separately) | E53: =$E$51 -> nominal
D54: Equipment Operation Costs | E54: =$E$51 -> nominal | H54: 90000 | I54: =H54 -> 90000 | J54: =I54 -> 90000 | K54: =J54 -> 90000 | L54: =K54 -> 90000 | M54: =L54 -> 90000 | N54: =M54 -> 90000 | O54: =N54 -> 90000 | P54: =O54 -> 90000 | ... AC54: =AB54 -> 90000
D55: Maintenance, Repairs, Inspections | E55: =$E$51 -> nominal | H55: 100000 | I55: 100000 | J55: 100000 | K55: 100000 | L55: 100000 | M55: 100000 | N55: 100000 | O55: 100000 | P55: 100000 | Q55: 100000 | R55: 100000 | S55: 100000 | T55: 100000 | U55: 100000 | V55: 100000 | W55: 100000 | X55: 100000 | Y55: 100000 | Z55: 100000 | AA55: 100000 | AB55: 100000 | AC55: 100000
D56: Compliance Testing | E56: =$E$51 -> nominal
D57: Optimisation | E57: =$E$51 -> nominal
D58: Utilities and Consumables | E58: =$E$51 -> nominal
D59: Other | E59: =$E$51 -> nominal
D60: ="Total non-fuel opex in "&Analysis_year&" dollars" -> Total non-fuel opex in 2025 dollars | H60: =SUM(H53:H59)*IF($E$51="Real",1,H$10) -> 186072.02 | I60: =SUM(I53:I59)*IF($E$51="Nominal",I$10,1) -> 182405.67 | J60: =SUM(J53:J59)*IF($E$51="Nominal",J$10,1) -> 178811.55 | K60: =SUM(K53:K59)*IF($E$51="Nominal",K$10,1) -> 175288.26 | L60: =SUM(L53:L59)*IF($E$51="Nominal",L$10,1) -> 171834.39 | M60: =SUM(M53:M59)*IF($E$51="Nominal",M$10,1) -> 168448.57 | N60: =SUM(N53:N59)*IF($E$51="Nominal",N$10,1) -> 165129.47 | O60: =SUM(O53:O59)*IF($E$51="Nominal",O$10,1) -> 161875.77 | P60: =SUM(P53:P59)*IF($E$51="Nominal",P$10,1) -> 158686.17 | ... AZ60: =SUM(AZ53:AZ59)*IF($E$51="Nominal",AZ$10,1) -> 0
D61: Total non-fuel opex in nominal dollars | H61: =SUM(H53:H59)*IF($E$51="Real",H9,1) -> 190000 | I61: =SUM(I53:I59)*IF($E$51="Real",I9,1) -> 190000 | J61: =SUM(J53:J59)*IF($E$51="Real",J9,1) -> 190000 | K61: =SUM(K53:K59)*IF($E$51="Real",K9,1) -> 190000 | L61: =SUM(L53:L59)*IF($E$51="Real",L9,1) -> 190000 | M61: =SUM(M53:M59)*IF($E$51="Real",M9,1) -> 190000 | N61: =SUM(N53:N59)*IF($E$51="Real",N9,1) -> 190000 | O61: =SUM(O53:O59)*IF($E$51="Real",O9,1) -> 190000 | ... AZ61: =SUM(AZ53:AZ59)*IF($E$51="Real",AZ9,1) -> 0
A63: 2b) Fuel consumption
A64: Proposed Project (PP) | D64: Fuel type | E64: Units | G64: Applicant comment | H64: 2026 | I64: 2027 | J64: 2028 | K64: 2029 | L64: 2030 | M64: 2031 | N64: 2032 | O64: 2033 | P64: 2034 | Q64: 2035 | R64: 2036 | S64: 2037 | T64: 2038 | U64: 2039 | V64: 2040 | W64: 2041 | X64: 2042 | Y64: 2043 | Z64: 2044 | AA64: 2045 | AB64: 2046 | AC64: 2047 | AD64: 2048 | AE64: 2049 | AF64: 2050 | AG64: 2051 | AH64: 2052 | AI64: 2053 | AJ64: 2054 | AK64: 2055 | AL64: 2056 | AM64: 2057 | AN64: 2058 | AO64: 2059 | AP64: 2060 | AQ64: 2061 | AR64: 2062 | AS64: 2063 | AT64: 2064 | AU64: 2065 | AV64: 2066 | AW64: 2067 | AX64: 2068 | AY64: 2069 | AZ64: 2070
A65: ="Please provide data through to "&FinalYear_PP -> Please provide data through to 2047 | D65: =Data!D3 -> Electricity | E65: =Data!E3 -> MWh | H65: 120 | I65: =Scratch!$L$9 -> 5008.8928 | J65: =Scratch!$L$9 -> 5008.8928 | K65: =Scratch!$L$9 -> 5008.8928 | L65: =Scratch!$L$9 -> 5008.8928 | M65: =Scratch!$L$9 -> 5008.8928 | N65: =Scratch!$L$9 -> 5008.8928 | O65: =Scratch!$L$9 -> 5008.8928 | P65: =Scratch!$L$9 -> 5008.8928 | ... AC65: =Scratch!$L$9 -> 5008.8928
D66: =Data!D4 -> Natural Gas | E66: =Data!E4 -> GJ | H66: 70000
D67: =Data!D5 -> Coal - sub bituminous | E67: =Data!E5 -> tonnes
D68: =Data!D6 -> Coal - bituminous | E68: =Data!E6 -> tonnes
D69: =Data!D7 -> Coal - lignite | E69: =Data!E7 -> tonnes
D70: =Data!D8 -> Diesel | E70: =Data!E8 -> litres
D71: =Data!D9 -> LPG | E71: =Data!E9 -> m3
D72: =Data!D10 -> Light fuel oil | E72: =Data!E10 -> litres
D73: =Data!D11 -> Heavy fuel oil | E73: =Data!E11 -> litres
D74: =Data!D12 -> Geothermal | E74: =Data!E12 -> kWh
D75: =Data!D13 -> Wood or wood chips | E75: =Data!E13 -> tonnes
A77: Base Case (BC) | D77: Fuel type | E77: Units | G77: Applicant comment | H77: 2026 | I77: 2027 | J77: 2028 | K77: 2029 | L77: 2030 | M77: 2031 | N77: 2032 | O77: 2033 | P77: 2034 | Q77: 2035 | R77: 2036 | S77: 2037 | T77: 2038 | U77: 2039 | V77: 2040 | W77: 2041 | X77: 2042 | Y77: 2043 | Z77: 2044 | AA77: 2045 | AB77: 2046 | AC77: 2047 | AD77: 2048 | AE77: 2049 | AF77: 2050 | AG77: 2051 | AH77: 2052 | AI77: 2053 | AJ77: 2054 | AK77: 2055 | AL77: 2056 | AM77: 2057 | AN77: 2058 | AO77: 2059 | AP77: 2060 | AQ77: 2061 | AR77: 2062 | AS77: 2063 | AT77: 2064 | AU77: 2065 | AV77: 2066 | AW77: 2067 | AX77: 2068 | AY77: 2069 | AZ77: 2070
A78: ="Please provide data through to "&FinalYear_BC -> Please provide data through to 2047 | D78: =Data!D3 -> Electricity | E78: =Data!E3 -> MWh | H78: 120 | I78: 120 | J78: 120 | K78: 120 | L78: 120 | M78: 120 | N78: 120 | O78: 120 | P78: 120 | Q78: 120 | R78: 120 | S78: 120 | T78: 120 | U78: 120 | V78: 120 | W78: 120 | X78: 120 | Y78: 120 | Z78: 120 | AA78: 120 | AB78: 120 | AC78: 120
D79: =Data!D4 -> Natural Gas | E79: =Data!E4 -> GJ | H79: 70000 | I79: 70000 | J79: 70000 | K79: 70000 | L79: 70000 | M79: 70000 | N79: 70000 | O79: 70000 | P79: 70000 | Q79: 70000 | R79: 70000 | S79: 70000 | T79: 70000 | U79: 70000 | V79: 70000 | W79: 70000 | X79: 70000 | Y79: 70000 | Z79: 70000 | AA79: 70000 | AB79: 70000 | AC79: 70000
D80: =Data!D5 -> Coal - sub bituminous | E80: =Data!E5 -> tonnes
D81: =Data!D6 -> Coal - bituminous | E81: =Data!E6 -> tonnes
D82: =Data!D7 -> Coal - lignite | E82: =Data!E7 -> tonnes
D83: =Data!D8 -> Diesel | E83: =Data!E8 -> litres
D84: =Data!D9 -> LPG | E84: =Data!E9 -> m3
D85: =Data!D10 -> Light fuel oil | E85: =Data!E10 -> litres
D86: =Data!D11 -> Heavy fuel oil | E86: =Data!E11 -> litres
D87: =Data!D12 -> Geothermal | E87: =Data!E12 -> kWh
D88: =Data!D13 -> Wood or wood chips | E88: =Data!E13 -> tonnes
A90: 2b) Expected fuel prices (excl GST)
A91: Proposed Project (PP) | B91: Fuel type | C91: Units | D91: ETS cost included? | E91: Value basis | G91: Applicant comment | H91: =Start_Yr -> 2026 | I91: =H91+1 -> 2027 | J91: =I91+1 -> 2028 | K91: =J91+1 -> 2029 | L91: =K91+1 -> 2030 | M91: =L91+1 -> 2031 | N91: =M91+1 -> 2032 | O91: =N91+1 -> 2033 | P91: =O91+1 -> 2034 | ... AZ91: =AY91+1 -> 2070
A92: ="Please provide data through to "&FinalYear_PP -> Please provide data through to 2047 | B92: =Data!D3 -> Electricity | C92: ="$/"&IF(RIGHT(E65,1)="s",LEFT(E65,LEN(E65)-1),E65) -> $/MWh | D92: Yes | E92: Real | H92: 250 | I92: 250 | J92: 250 | K92: 250 | L92: 250 | M92: 250 | N92: 250 | O92: 250 | P92: 250 | Q92: 250 | R92: 250 | S92: 250 | T92: 250 | U92: 250 | V92: 250 | W92: 250 | X92: 250 | Y92: 250 | Z92: 250 | AA92: 250 | AB92: 250 | AC92: 250
B93: =Data!D4 -> Natural Gas | C93: ="$/"&IF(RIGHT(E66,1)="s",LEFT(E66,LEN(E66)-1),E66) -> $/GJ | D93: Yes | E93: Real | H93: 10 | I93: 10 | J93: 10 | K93: 10 | L93: 10 | M93: 10 | N93: 10 | O93: 10 | P93: 10 | Q93: 10 | R93: 10 | S93: 10 | T93: 10 | U93: 10 | V93: 10 | W93: 10 | X93: 10 | Y93: 10 | Z93: 10 | AA93: 10 | AB93: 10 | AC93: 10
B94: =Data!D5 -> Coal - sub bituminous | C94: ="$/"&IF(RIGHT(E67,1)="s",LEFT(E67,LEN(E67)-1),E67) -> $/tonne | D94: Yes | E94: Real | H94: 150 | I94: 150 | J94: 150 | K94: 150 | L94: 150 | M94: 150 | N94: 150 | O94: 150 | P94: 150 | Q94: 150 | R94: 150 | S94: 150 | T94: 150 | U94: 150 | V94: 150 | W94: 150 | X94: 150 | Y94: 150 | Z94: 150 | AA94: 150 | AB94: 150 | AC94: 150
B95: =Data!D6 -> Coal - bituminous | C95: ="$/"&IF(RIGHT(E68,1)="s",LEFT(E68,LEN(E68)-1),E68) -> $/tonne | D95: Yes | E95: Real
B96: =Data!D7 -> Coal - lignite | C96: ="$/"&IF(RIGHT(E69,1)="s",LEFT(E69,LEN(E69)-1),E69) -> $/tonne | D96: Yes | E96: Real
B97: =Data!D8 -> Diesel | C97: ="$/"&IF(RIGHT(E70,1)="s",LEFT(E70,LEN(E70)-1),E70) -> $/litre | D97: Yes | E97: Real | H97: 2 | I97: 2 | J97: 2 | K97: 2 | L97: 2 | M97: 2 | N97: 2 | O97: 2 | P97: 2 | Q97: 2 | R97: 2 | S97: 2 | T97: 2 | U97: 2 | V97: 2 | W97: 2 | X97: 2 | Y97: 0 | Z97: 0 | AA97: 0 | AB97: 0 | AC97: 0 | AD97: 0 | AE97: 0 | AF97: 0 | AG97: 0 | AH97: 0 | AI97: 0 | AJ97: 0 | AK97: 0 | AL97: 0 | AM97: 0 | AN97: 0 | AO97: 0 | AP97: 0 | AQ97: 0 | AR97: 0 | AS97: 0 | AT97: 0 | AU97: 0 | AV97: 0 | AW97: 0 | AX97: 0 | AY97: 0 | AZ97: 0
B98: =Data!D9 -> LPG | C98: ="$/"&IF(RIGHT(E71,1)="s",LEFT(E71,LEN(E71)-1),E71) -> $/m3 | D98: Yes | E98: Real
B99: =Data!D10 -> Light fuel oil | C99: ="$/"&IF(RIGHT(E72,1)="s",LEFT(E72,LEN(E72)-1),E72) -> $/litre | D99: Yes | E99: Real
B100: =Data!D11 -> Heavy fuel oil | C100: ="$/"&IF(RIGHT(E73,1)="s",LEFT(E73,LEN(E73)-1),E73) -> $/litre | D100: Yes | E100: Real
B101: =Data!D12 -> Geothermal | C101: ="$/"&IF(RIGHT(E74,1)="s",LEFT(E74,LEN(E74)-1),E74) -> $/kWh | D101: Yes | E101: Real
B102: =Data!D13 -> Wood or wood chips | C102: ="$/"&IF(RIGHT(E75,1)="s",LEFT(E75,LEN(E75)-1),E75) -> $/tonne | D102: Yes | E102: Real
A104: Base Case (BC) | B104: Fuel type | C104: Units | D104: ETS cost included? | E104: Value basis | G104: Applicant comment | H104: =Start_Yr -> 2026 | I104: =H104+1 -> 2027 | J104: =I104+1 -> 2028 | K104: =J104+1 -> 2029 | L104: =K104+1 -> 2030 | M104: =L104+1 -> 2031 | N104: =M104+1 -> 2032 | O104: =N104+1 -> 2033 | P104: =O104+1 -> 2034 | ... AZ104: =AY104+1 -> 2070
A105: ="Please provide data through to "&FinalYear_BC -> Please provide data through to 2047 | B105: =Data!D3 -> Electricity | C105: ="$/"&IF(RIGHT(E78,1)="s",LEFT(E78,LEN(E78)-1),E78) -> $/MWh | D105: Yes | E105: Real | H105: 250 | I105: 250 | J105: 250 | K105: 250 | L105: 250 | M105: 250 | N105: 250 | O105: 250 | P105: 250 | Q105: 250 | R105: 250 | S105: 250 | T105: 250 | U105: 250 | V105: 250 | W105: 250 | X105: 250 | Y105: 250 | Z105: 250 | AA105: 250 | AB105: 250 | AC105: 250
B106: =Data!D4 -> Natural Gas | C106: ="$/"&IF(RIGHT(E79,1)="s",LEFT(E79,LEN(E79)-1),E79) -> $/GJ | D106: Yes | E106: Real | H106: 10 | I106: 10 | J106: 10 | K106: 10 | L106: 10 | M106: 10 | N106: 10 | O106: 10 | P106: 10 | Q106: 10 | R106: 10 | S106: 10 | T106: 10 | U106: 10 | V106: 10 | W106: 10 | X106: 10 | Y106: 10 | Z106: 10 | AA106: 10 | AB106: 10 | AC106: 10
B107: =Data!D5 -> Coal - sub bituminous | C107: ="$/"&IF(RIGHT(E80,1)="s",LEFT(E80,LEN(E80)-1),E80) -> $/tonne | D107: Yes | E107: Real | H107: 150 | I107: 150 | J107: 150 | K107: 150 | L107: 150 | M107: 150 | N107: 150 | O107: 150 | P107: 150 | Q107: 150 | R107: 150 | S107: 150 | T107: 150 | U107: 150 | V107: 150 | W107: 150 | X107: 150 | Y107: 150 | Z107: 150 | AA107: 150 | AB107: 150 | AC107: 150
B108: =Data!D6 -> Coal - bituminous | C108: ="$/"&IF(RIGHT(E81,1)="s",LEFT(E81,LEN(E81)-1),E81) -> $/tonne | D108: Yes | E108: Real
B109: =Data!D7 -> Coal - lignite | C109: ="$/"&IF(RIGHT(E82,1)="s",LEFT(E82,LEN(E82)-1),E82) -> $/tonne | D109: Yes | E109: Real
B110: =Data!D8 -> Diesel | C110: ="$/"&IF(RIGHT(E83,1)="s",LEFT(E83,LEN(E83)-1),E83) -> $/litre | D110: Yes | E110: Real | H110: 2 | I110: 2 | J110: 2 | K110: 2 | L110: 2 | M110: 2 | N110: 2 | O110: 2 | P110: 2 | Q110: 2 | R110: 2 | S110: 2 | T110: 2 | U110: 2 | V110: 2 | W110: 2 | X110: 2 | Y110: 2 | Z110: 2 | AA110: 2 | AB110: 2 | AC110: 2 | AD110: 2 | AE110: 2 | AF110: 2 | AG110: 2 | AH110: 2 | AI110: 2 | AJ110: 2 | AK110: 2 | AL110: 2 | AM110: 2 | AN110: 2 | AO110: 2 | AP110: 2 | AQ110: 2 | AR110: 2 | AS110: 2 | AT110: 2 | AU110: 2 | AV110: 2 | AW110: 2 | AX110: 2 | AY110: 2 | AZ110: 2
...

Sheet Scratch
A3: Base | F3: Heat demand (GJ) | K3: Project
A5: Annual gas (GJ) | B5: 70000 | F5: =B5*B15 -> 56000 | K5: Annual electricity for same work (GJ) | L5: =F5/B14 -> 16000
A6: Annual electricity (mWh) | B6: 120 | K6: mWh conversion | L6: =L5*B18 -> 4444.448
K7: Demand growth (rebound) | L7: 1.1
K9: New electricity demand (mWh) | L9: =(L6*L7)+B6 -> 5008.8928
A14: COP of heat pump | B14: 3.5
A15: Efficiency of gas | B15: =0.8 -> 0.8
A18: GJ to MWH conversion | B18: =0.277778 -> 0.277778

Sheet Real values
A2: Financial projection basis
A4: Inflator - use this to convert real values to nominal | G4: =Inputs!G9 -> 1 | H4: =Inputs!H9 -> 1.02111 | I4: =Inputs!I9 -> 1.0416343 | J4: =Inputs!J9 -> 1.0625712 | K4: =Inputs!K9 -> 1.0839288 | L4: =Inputs!L9 -> 1.1057158 | M4: =Inputs!M9 -> 1.1279407 | N4: =Inputs!N9 -> 1.1506123 | ... AZ4: =Inputs!AZ9 -> 2.4510571
A5: Deflator - use this to convert nominal values to real | G5: =Inputs!G10 -> 1 | H5: =Inputs!H10 -> 0.97932642 | I5: =Inputs!I10 -> 0.96002982 | J5: =Inputs!J10 -> 0.94111344 | K5: =Inputs!K10 -> 0.92256979 | L5: =Inputs!L10 -> 0.90439152 | M5: =Inputs!M10 -> 0.88657143 | N5: =Inputs!N10 -> 0.86910247 | ... AZ5: =Inputs!AZ10 -> 0.40798724
A7: 1) Capital expenditure (CAPEX) ($) - please enter all costs as positive numbers
A9: Proposed Project (PP) | D9: Capex item | E9: Value basis | F9: Base year | G9: Applicant comment | H9: 2026 | I9: 2027 | J9: 2028 | K9: 2029 | L9: 2030 | M9: 2031 | N9: 2032 | O9: 2033 | P9: 2034 | Q9: 2035 | R9: 2036 | S9: 2037 | T9: 2038 | U9: 2039 | V9: 2040 | W9: 2041 | X9: 2042 | Y9: 2043 | Z9: 2044 | AA9: 2045 | AB9: 2046 | AC9: 2047 | AD9: 2048 | AE9: 2049 | AF9: 2050 | AG9: 2051 | AH9: 2052 | AI9: 2053 | AJ9: 2054 | AK9: 2055 | AL9: 2056 | AM9: 2057 | AN9: 2058 | AO9: 2059 | AP9: 2060 | AQ9: 2061 | AR9: 2062 | AS9: 2063 | AT9: 2064 | AU9: 2065 | AV9: 2066 | AW9: 2067 | AX9: 2068 | AY9: 2069 | AZ9: 2070
D10: Equipment purchase | E10: Real | F10: =Analysis_year -> 2025 | G10: =Inputs!G15 -> 0 | H10: =Inputs!H15*IF(Inputs!$E15="Real",1,H$5) -> 783461.14 | I10: =Inputs!I15*IF(Inputs!$E15="Real",1,I$5) -> 768023.86 | J10: =Inputs!J15*IF(Inputs!$E15="Real",1,J$5) -> 0 | K10: =Inputs!K15*IF(Inputs!$E15="Real",1,K$5) -> 0 | L10: =Inputs!L15*IF(Inputs!$E15="Real",1,L$5) -> 0 | M10: =Inputs!M15*IF(Inputs!$E15="Real",1,M$5) -> 0 | N10: =Inputs!N15*IF(Inputs!$E15="Real",1,N$5) -> 0 | O10: =Inputs!O15*IF(Inputs!$E15="Real",1,O$5) -> 0 | ... AZ10: =Inputs!AZ15*IF(Inputs!$E15="Real",1,AZ$5) -> 0
D11: Civil works | E11: Real | F11: =Analysis_year -> 2025 | G11: =Inputs!G16 -> 0 | H11: =Inputs!H16*IF(Inputs!$E16="Real",1,H$5) -> 78346.114 | I11: =Inputs!I16*IF(Inputs!$E16="Real",1,I$5) -> 0 | J11: =Inputs!J16*IF(Inputs!$E16="Real",1,J$5) -> 0 | K11: =Inputs!K16*IF(Inputs!$E16="Real",1,K$5) -> 0 | L11: =Inputs!L16*IF(Inputs!$E16="Real",1,L$5) -> 0 | M11: =Inputs!M16*IF(Inputs!$E16="Real",1,M$5) -> 0 | N11: =Inputs!N16*IF(Inputs!$E16="Real",1,N$5) -> 0 | O11: =Inputs!O16*IF(Inputs!$E16="Real",1,O$5) -> 0 | ... AZ11: =Inputs!AZ16*IF(Inputs!$E16="Real",1,AZ$5) -> 0
D12: Electrical works | E12: Real | F12: =Analysis_year -> 2025 | G12: =Inputs!G17 -> 0 | H12: =Inputs!H17*IF(Inputs!$E17="Real",1,H$5) -> 244831.6 | I12: =Inputs!I17*IF(Inputs!$E17="Real",1,I$5) -> 0 | J12: =Inputs!J17*IF(Inputs!$E17="Real",1,J$5) -> 0 | K12: =Inputs!K17*IF(Inputs!$E17="Real",1,K$5) -> 0 | L12: =Inputs!L17*IF(Inputs!$E17="Real",1,L$5) -> 0 | M12: =Inputs!M17*IF(Inputs!$E17="Real",1,M$5) -> 0 | N12: =Inputs!N17*IF(Inputs!$E17="Real",1,N$5) -> 0 | O12: =Inputs!O17*IF(Inputs!$E17="Real",1,O$5) -> 0 | ... AZ12: =Inputs!AZ17*IF(Inputs!$E17="Real",1,AZ$5) -> 0
D13: Installation | E13: Real | F13: =Analysis_year -> 2025 | G13: =Inputs!G18 -> 0 | H13: =Inputs!H18*IF(Inputs!$E18="Real",1,H$5) -> 97932.642 | I13: =Inputs!I18*IF(Inputs!$E18="Real",1,I$5) -> 0 | J13: =Inputs!J18*IF(Inputs!$E18="Real",1,J$5) -> 0 | K13: =Inputs!K18*IF(Inputs!$E18="Real",1,K$5) -> 0 | L13: =Inputs!L18*IF(Inputs!$E18="Real",1,L$5) -> 0 | M13: =Inputs!M18*IF(Inputs!$E18="Real",1,M$5) -> 0 | N13: =Inputs!N18*IF(Inputs!$E18="Real",1,N$5) -> 0 | O13: =Inputs!O18*IF(Inputs!$E18="Real",1,O$5) -> 0 | ... AZ13: =Inputs!AZ18*IF(Inputs!$E18="Real",1,AZ$5) -> 0
D14: Indirect costs | E14: Real | F14: =Analysis_year -> 2025 | G14: =Inputs!G19 -> 0 | H14: =Inputs!H19*IF(Inputs!$E19="Real",1,H$5) -> 48966.321 | I14: =Inputs!I19*IF(Inputs!$E19="Real",1,I$5) -> 48001.491 | J14: =Inputs!J19*IF(Inputs!$E19="Real",1,J$5) -> 0 | K14: =Inputs!K19*IF(Inputs!$E19="Real",1,K$5) -> 0 | L14: =Inputs!L19*IF(Inputs!$E19="Real",1,L$5) -> 0 | M14: =Inputs!M19*IF(Inputs!$E19="Real",1,M$5) -> 0 | N14: =Inputs!N19*IF(Inputs!$E19="Real",1,N$5) -> 0 | O14: =Inputs!O19*IF(Inputs!$E19="Real",1,O$5) -> 0 | ... AZ14: =Inputs!AZ19*IF(Inputs!$E19="Real",1,AZ$5) -> 0
D15: Project management | E15: Real | F15: =Analysis_year -> 2025 | G15: =Inputs!G20 -> 0 | H15: =Inputs!H20*IF(Inputs!$E20="Real",1,H$5) -> 0 | I15: =Inputs!I20*IF(Inputs!$E20="Real",1,I$5) -> 0 | J15: =Inputs!J20*IF(Inputs!$E20="Real",1,J$5) -> 0 | K15: =Inputs!K20*IF(Inputs!$E20="Real",1,K$5) -> 0 | L15: =Inputs!L20*IF(Inputs!$E20="Real",1,L$5) -> 0 | M15: =Inputs!M20*IF(Inputs!$E20="Real",1,M$5) -> 0 | N15: =Inputs!N20*IF(Inputs!$E20="Real",1,N$5) -> 0 | O15: =Inputs!O20*IF(Inputs!$E20="Real",1,O$5) -> 0 | ... AZ15: =Inputs!AZ20*IF(Inputs!$E20="Real",1,AZ$5) -> 0
D16: Other | E16: Real | F16: =Analysis_year -> 2025 | G16: =Inputs!G21 -> 0 | H16: =Inputs!H21*IF(Inputs!$E21="Real",1,H$5) -> 0 | I16: =Inputs!I21*IF(Inputs!$E21="Real",1,I$5) -> 0 | J16: =Inputs!J21*IF(Inputs!$E21="Real",1,J$5) -> 0 | K16: =Inputs!K21*IF(Inputs!$E21="Real",1,K$5) -> 0 | L16: =Inputs!L21*IF(Inputs!$E21="Real",1,L$5) -> 0 | M16: =Inputs!M21*IF(Inputs!$E21="Real",1,M$5) -> 0 | N16: =Inputs!N21*IF(Inputs!$E21="Real",1,N$5) -> 0 | O16: =Inputs!O21*IF(Inputs!$E21="Real",1,O$5) -> 0 | ... AZ16: =Inputs!AZ21*IF(Inputs!$E21="Real",1,AZ$5) -> 0
D17: ="Total capex in "&Analysis_year&" dollars" -> Total capex in 2025 dollars | H17: =SUBTOTAL(109,Capex_PP[2026]) -> 1253537.8 | I17: =SUM(I10:I16)*IF($E$8="Real",1,I$5) -> 783408.67 | J17: =SUM(J10:J16)*IF($E$8="Real",1,J$5) -> 0 | K17: =SUM(K10:K16)*IF($E$8="Real",1,K$5) -> 0 | L17: =SUM(L10:L16)*IF($E$8="Real",1,L$5) -> 0 | M17: =SUM(M10:M16)*IF($E$8="Real",1,M$5) -> 0 | N17: =SUM(N10:N16)*IF($E$8="Real",1,N$5) -> 0 | O17: =SUM(O10:O16)*IF($E$8="Real",1,O$5) -> 0 | P17: =SUM(P10:P16)*IF($E$8="Real",1,P$5) -> 0 | ... AZ17: =SUM(AZ10:AZ16)*IF($E$8="Real",1,AZ$5) -> 0
A19: Base Case (BC) | D19: Capex item | E19: Value basis | F19: Base year | G19: Applicant comment | H19: 2026 | I19: 2027 | J19: 2028 | K19: 2029 | L19: 2030 | M19: 2031 | N19: 2032 | O19: 2033 | P19: 2034 | Q19: 2035 | R19: 2036 | S19: 2037 | T19: 2038 | U19: 2039 | V19: 2040 | W19: 2041 | X19: 2042 | Y19: 2043 | Z19: 2044 | AA19: 2045 | AB19: 2046 | AC19: 2047 | AD19: 2048 | AE19: 2049 | AF19: 2050 | AG19: 2051 | AH19: 2052 | AI19: 2053 | AJ19: 2054 | AK19: 2055 | AL19: 2056 | AM19: 2057 | AN19: 2058 | AO19: 2059 | AP19: 2060 | AQ19: 2061 | AR19: 2062 | AS19: 2063 | AT19: 2064 | AU19: 2065 | AV19: 2066 | AW19: 2067 | AX19: 2068 | AY19: 2069 | AZ19: 2070
A20: Expand if more items | D20: Equipment purchase | E20: Real | F20: =Analysis_year -> 2025 | G20: =Inputs!G27 -> 0 | H20: =Inputs!H27*IF(Inputs!$E27="Real",1,H$5) -> 0 | I20: =Inputs!I27*IF(Inputs!$E27="Real",1,I$5) -> 0 | J20: =Inputs!J27*IF(Inputs!$E27="Real",1,J$5) -> 0 | K20: =Inputs!K27*IF(Inputs!$E27="Real",1,K$5) -> 0 | L20: =Inputs!L27*IF(Inputs!$E27="Real",1,L$5) -> 0 | M20: =Inputs!M27*IF(Inputs!$E27="Real",1,M$5) -> 0 | N20: =Inputs!N27*IF(Inputs!$E27="Real",1,N$5) -> 0 | O20: =Inputs!O27*IF(Inputs!$E27="Real",1,O$5) -> 0 | ... AZ20: =Inputs!AZ27*IF(Inputs!$E27="Real",1,AZ$5) -> 0
D21: Civil works | E21: Real | F21: =Analysis_year -> 2025 | G21: =Inputs!G28 -> 0 | H21: =Inputs!H28*IF(Inputs!$E28="Real",1,H$5) -> 0 | I21: =Inputs!I28*IF(Inputs!$E28="Real",1,I$5) -> 0 | J21: =Inputs!J28*IF(Inputs!$E28="Real",1,J$5) -> 0 | K21: =Inputs!K28*IF(Inputs!$E28="Real",1,K$5) -> 0 | L21: =Inputs!L28*IF(Inputs!$E28="Real",1,L$5) -> 0 | M21: =Inputs!M28*IF(Inputs!$E28="Real",1,M$5) -> 0 | N21: =Inputs!N28*IF(Inputs!$E28="Real",1,N$5) -> 0 | O21: =Inputs!O28*IF(Inputs!$E28="Real",1,O$5) -> 0 | ... AZ21: =Inputs!AZ28*IF(Inputs!$E28="Real",1,AZ$5) -> 0
D22: Electrical works | E22: Real | F22: =Analysis_year -> 2025 | G22: =Inputs!G29 -> 0 | H22: =Inputs!H29*IF(Inputs!$E29="Real",1,H$5) -> 0 | I22: =Inputs!I29*IF(Inputs!$E29="Real",1,I$5) -> 0 | J22: =Inputs!J29*IF(Inputs!$E29="Real",1,J$5) -> 0 | K22: =Inputs!K29*IF(Inputs!$E29="Real",1,K$5) -> 0 | L22: =Inputs!L29*IF(Inputs!$E29="Real",1,L$5) -> 0 | M22: =Inputs!M29*IF(Inputs!$E29="Real",1,M$5) -> 0 | N22: =Inputs!N29*IF(Inputs!$E29="Real",1,N$5) -> 0 | O22: =Inputs!O29*IF(Inputs!$E29="Real",1,O$5) -> 0 | ... AZ22: =Inputs!AZ29*IF(Inputs!$E29="Real",1,AZ$5) -> 0
D23: Installation | E23: Real | F23: =Analysis_year -> 2025 | G23: =Inputs!G30 -> 0 | H23: =Inputs!H30*IF(Inputs!$E30="Real",1,H$5) -> 0 | I23: =Inputs!I30*IF(Inputs!$E30="Real",1,I$5) -> 0 | J23: =Inputs!J30*IF(Inputs!$E30="Real",1,J$5) -> 0 | K23: =Inputs!K30*IF(Inputs!$E30="Real",1,K$5) -> 0 | L23: =Inputs!L30*IF(Inputs!$E30="Real",1,L$5) -> 0 | M23: =Inputs!M30*IF(Inputs!$E30="Real",1,M$5) -> 0 | N23: =Inputs!N30*IF(Inputs!$E30="Real",1,N$5) -> 0 | O23: =Inputs!O30*IF(Inputs!$E30="Real",1,O$5) -> 0 | ... AZ23: =Inputs!AZ30*IF(Inputs!$E30="Real",1,AZ$5) -> 0
D24: Indirect costs | E24: Real | F24: =Analysis_year -> 2025 | G24: =Inputs!G31 -> 0 | H24: =Inputs!H31*IF(Inputs!$E31="Real",1,H$5) -> 0 | I24: =Inputs!I31*IF(Inputs!$E31="Real",1,I$5) -> 0 | J24: =Inputs!J31*IF(Inputs!$E31="Real",1,J$5) -> 0 | K24: =Inputs!K31*IF(Inputs!$E31="Real",1,K$5) -> 0 | L24: =Inputs!L31*IF(Inputs!$E31="Real",1,L$5) -> 0 | M24: =Inputs!M31*IF(Inputs!$E31="Real",1,M$5) -> 0 | N24: =Inputs!N31*IF(Inputs!$E31="Real",1,N$5) -> 0 | O24: =Inputs!O31*IF(Inputs!$E31="Real",1,O$5) -> 0 | ... AZ24: =Inputs!AZ31*IF(Inputs!$E31="Real",1,AZ$5) -> 0
D25: Project management | E25: Real | F25: =Analysis_year -> 2025 | G25: =Inputs!G32 -> 0 | H25: =Inputs!H32*IF(Inputs!$E32="Real",1,H$5) -> 0 | I25: =Inputs!I32*IF(Inputs!$E32="Real",1,I$5) -> 0 | J25: =Inputs!J32*IF(Inputs!$E32="Real",1,J$5) -> 0 | K25: =Inputs!K32*IF(Inputs!$E32="Real",1,K$5) -> 0 | L25: =Inputs!L32*IF(Inputs!$E32="Real",1,L$5) -> 0 | M25: =Inputs!M32*IF(Inputs!$E32="Real",1,M$5) -> 0 | N25: =Inputs!N32*IF(Inputs!$E32="Real",1,N$5) -> 0 | O25: =Inputs!O32*IF(Inputs!$E32="Real",1,O$5) -> 0 | ... AZ25: =Inputs!AZ32*IF(Inputs!$E32="Real",1,AZ$5) -> 0
D26: Other | E26: Real | F26: =Analysis_year -> 2025 | G26: =Inputs!G33 -> 0 | H26: =Inputs!H33*IF(Inputs!$E33="Real",1,H$5) -> 0 | I26: =Inputs!I33*IF(Inputs!$E33="Real",1,I$5) -> 0 | J26: =Inputs!J33*IF(Inputs!$E33="Real",1,J$5) -> 0 | K26: =Inputs!K33*IF(Inputs!$E33="Real",1,K$5) -> 0 | L26: =Inputs!L33*IF(Inputs!$E33="Real",1,L$5) -> 0 | M26: =Inputs!M33*IF(Inputs!$E33="Real",1,M$5) -> 0 | N26: =Inputs!N33*IF(Inputs!$E33="Real",1,N$5) -> 0 | O26: =Inputs!O33*IF(Inputs!$E33="Real",1,O$5) -> 0 | ... AZ26: =Inputs!AZ33*IF(Inputs!$E33="Real",1,AZ$5) -> 0
D27: ="Total capex in "&Analysis_year&" dollars" -> Total capex in 2025 dollars | H27: =SUBTOTAL(109,Capex_BC[2026]) -> 0 | I27: =SUBTOTAL(109,Capex_BC[2027]) -> 0 | J27: =SUBTOTAL(109,Capex_BC[2028]) -> 0 | K27: =SUBTOTAL(109,Capex_BC[2029]) -> 0 | L27: =SUBTOTAL(109,Capex_BC[2030]) -> 0 | M27: =SUBTOTAL(109,Capex_BC[2031]) -> 0 | N27: =SUBTOTAL(109,Capex_BC[2032]) -> 0 | O27: =SUBTOTAL(109,Capex_BC[2033]) -> 0 | P27: =SUBTOTAL(109,Capex_BC[2034]) -> 0 | Q27: =SUBTOTAL(109,Capex_BC[2035]) -> 0 | R27: =SUBTOTAL(109,Capex_BC[2036]) -> 0 | S27: =SUBTOTAL(109,Capex_BC[2037]) -> 0 | T27: =SUBTOTAL(109,Capex_BC[2038]) -> 0 | U27: =SUBTOTAL(109,Capex_BC[2039]) -> 0 | V27: =SUBTOTAL(109,Capex_BC[2040]) -> 0 | W27: =SUBTOTAL(109,Capex_BC[2041]) -> 0 | X27: =SUBTOTAL(109,Capex_BC[2042]) -> 0 | Y27: =SUBTOTAL(109,Capex_BC[2043]) -> 0 | Z27: =SUBTOTAL(109,Capex_BC[2044]) -> 0 | AA27: =SUBTOTAL(109,Capex_BC[2045]) -> 0 | AB27: =SUBTOTAL(109,Capex_BC[2046]) -> 0 | AC27: =SUBTOTAL(109,Capex_BC[2047]) -> 0 | AD27: =SUBTOTAL(109,Capex_BC[2048]) -> 0 | AE27: =SUBTOTAL(109,Capex_BC[2049]) -> 0 | AF27: =SUBTOTAL(109,Capex_BC[2050]) -> 0 | AG27: =SUBTOTAL(109,Capex_BC[2051]) -> 0 | AH27: =SUBTOTAL(109,Capex_BC[2052]) -> 0 | AI27: =SUBTOTAL(109,Capex_BC[2053]) -> 0 | AJ27: =SUBTOTAL(109,Capex_BC[2054]) -> 0 | AK27: =SUBTOTAL(109,Capex_BC[2055]) -> 0 | AL27: =SUBTOTAL(109,Capex_BC[2056]) -> 0 | AM27: =SUBTOTAL(109,Capex_BC[2057]) -> 0 | AN27: =SUBTOTAL(109,Capex_BC[2058]) -> 0 | AO27: =SUBTOTAL(109,Capex_BC[2059]) -> 0 | AP27: =SUBTOTAL(109,Capex_BC[2060]) -> 0 | AQ27: =SUBTOTAL(109,Capex_BC[2061]) -> 0 | AR27: =SUBTOTAL(109,Capex_BC[2062]) -> 0 | AS27: =SUBTOTAL(109,Capex_BC[2063]) -> 0 | AT27: =SUBTOTAL(109,Capex_BC[2064]) -> 0 | AU27: =SUBTOTAL(109,Capex_BC[2065]) -> 0 | AV27: =SUBTOTAL(109,Capex_BC[2066]) -> 0 | AW27: =SUBTOTAL(109,Capex_BC[2067]) -> 0 | AX27: =SUBTOTAL(109,Capex_BC[2068]) -> 0 | AY27: =SUBTOTAL(109,Capex_BC[2069]) -> 0 | AZ27: =SUBTOTAL(109,Capex_BC[2070]) -> 0
A29: 2) Operating & Maintenance Expenditure (OPEX) ($) - please enter all costs as positive numbers
A30: 2a) Non-fuel opex
A31: Proposed Project (PP) | D31: Opex item | E31: Value basis | F31: Base year | G31: Applicant comment | H31: 2026 | I31: 2027 | J31: 2028 | K31: 2029 | L31: 2030 | M31: 2031 | N31: 2032 | O31: 2033 | P31: 2034 | Q31: 2035 | R31: 2036 | S31: 2037 | T31: 2038 | U31: 2039 | V31: 2040 | W31: 2041 | X31: 2042 | Y31: 2043 | Z31: 2044 | AA31: 2045 | AB31: 2046 | AC31: 2047 | AD31: 2048 | AE31: 2049 | AF31: 2050 | AG31: 2051 | AH31: 2052 | AI31: 2053 | AJ31: 2054 | AK31: 2055 | AL31: 2056 | AM31: 2057 | AN31: 2058 | AO31: 2059 | AP31: 2060 | AQ31: 2061 | AR31: 2062 | AS31: 2063 | AT31: 2064 | AU31: 2065 | AV31: 2066 | AW31: 2067 | AX31: 2068 | AY31: 2069 | AZ31: 2070
D32: Energy costs (already handled separately) | E32: Real | F32: =Analysis_year -> 2025 | G32: =Inputs!G41 -> 0 | H32: =Inputs!H41*IF(Inputs!$E41="Real",1,H$5) -> 0 | I32: =Inputs!I41*IF(Inputs!$E41="Real",1,I$5) -> 0 | J32: =Inputs!J41*IF(Inputs!$E41="Real",1,J$5) -> 0 | K32: =Inputs!K41*IF(Inputs!$E41="Real",1,K$5) -> 0 | L32: =Inputs!L41*IF(Inputs!$E41="Real",1,L$5) -> 0 | M32: =Inputs!M41*IF(Inputs!$E41="Real",1,M$5) -> 0 | N32: =Inputs!N41*IF(Inputs!$E41="Real",1,N$5) -> 0 | O32: =Inputs!O41*IF(Inputs!$E41="Real",1,O$5) -> 0 | ... AZ32: =Inputs!AZ41*IF(Inputs!$E41="Real",1,AZ$5) -> 0
D33: Equipment Operation Costs | E33: Real | F33: =Analysis_year -> 2025 | G33: =Inputs!G42 -> 0 | H33: =Inputs!H42*IF(Inputs!$E42="Real",1,H$5) -> 97932.642 | I33: =Inputs!I42*IF(Inputs!$E42="Real",1,I$5) -> 96002.982 | J33: =Inputs!J42*IF(Inputs!$E42="Real",1,J$5) -> 94111.344 | K33: =Inputs!K42*IF(Inputs!$E42="Real",1,K$5) -> 92256.979 | L33: =Inputs!L42*IF(Inputs!$E42="Real",1,L$5) -> 90439.152 | M33: =Inputs!M42*IF(Inputs!$E42="Real",1,M$5) -> 88657.143 | N33: =Inputs!N42*IF(Inputs!$E42="Real",1,N$5) -> 86910.247 | O33: =Inputs!O42*IF(Inputs!$E42="Real",1,O$5) -> 85197.772 | ... AZ33: =Inputs!AZ42*IF(Inputs!$E42="Real",1,AZ$5) -> 0
D34: Maintenance, Repairs, Inspections | E34: Real | F34: =Analysis_year -> 2025 | G34: =Inputs!G43 -> 0 | H34: =Inputs!H43*IF(Inputs!$E43="Real",1,H$5) -> 19586.528 | I34: =Inputs!I43*IF(Inputs!$E43="Real",1,I$5) -> 19200.596 | J34: =Inputs!J43*IF(Inputs!$E43="Real",1,J$5) -> 18822.269 | K34: =Inputs!K43*IF(Inputs!$E43="Real",1,K$5) -> 18451.396 | L34: =Inputs!L43*IF(Inputs!$E43="Real",1,L$5) -> 18087.83 | M34: =Inputs!M43*IF(Inputs!$E43="Real",1,M$5) -> 17731.429 | N34: =Inputs!N43*IF(Inputs!$E43="Real",1,N$5) -> 17382.049 | O34: =Inputs!O43*IF(Inputs!$E43="Real",1,O$5) -> 17039.554 | ... AZ34: =Inputs!AZ43*IF(Inputs!$E43="Real",1,AZ$5) -> 0
D35: Compliance Testing | E35: Real | F35: =Analysis_year -> 2025 | G35: =Inputs!G44 -> 0 | H35: =Inputs!H44*IF(Inputs!$E44="Real",1,H$5) -> 9793.2642 | I35: =Inputs!I44*IF(Inputs!$E44="Real",1,I$5) -> 9600.2982 | J35: =Inputs!J44*IF(Inputs!$E44="Real",1,J$5) -> 0 | K35: =Inputs!K44*IF(Inputs!$E44="Real",1,K$5) -> 0 | L35: =Inputs!L44*IF(Inputs!$E44="Real",1,L$5) -> 0 | M35: =Inputs!M44*IF(Inputs!$E44="Real",1,M$5) -> 0 | N35: =Inputs!N44*IF(Inputs!$E44="Real",1,N$5) -> 0 | O35: =Inputs!O44*IF(Inputs!$E44="Real",1,O$5) -> 0 | ... AZ35: =Inputs!AZ44*IF(Inputs!$E44="Real",1,AZ$5) -> 0
D36: Optimisation | E36: Real | F36: =Analysis_year -> 2025 | G36: =Inputs!G45 -> 0 | H36: =Inputs!H45*IF(Inputs!$E45="Real",1,H$5) -> 0 | I36: =Inputs!I45*IF(Inputs!$E45="Real",1,I$5) -> 0 | J36: =Inputs!J45*IF(Inputs!$E45="Real",1,J$5) -> 0 | K36: =Inputs!K45*IF(Inputs!$E45="Real",1,K$5) -> 0 | L36: =Inputs!L45*IF(Inputs!$E45="Real",1,L$5) -> 0 | M36: =Inputs!M45*IF(Inputs!$E45="Real",1,M$5) -> 0 | N36: =Inputs!N45*IF(Inputs!$E45="Real",1,N$5) -> 0 | O36: =Inputs!O45*IF(Inputs!$E45="Real",1,O$5) -> 0 | ... AZ36: =Inputs!AZ45*IF(Inputs!$E45="Real",1,AZ$5) -> 0
D37: Utilities and Consumables | E37: Real | F37: =Analysis_year -> 2025 | G37: =Inputs!G46 -> 0 | H37: =Inputs!H46*IF(Inputs!$E46="Real",1,H$5) -> 0 | I37: =Inputs!I46*IF(Inputs!$E46="Real",1,I$5) -> 0 | J37: =Inputs!J46*IF(Inputs!$E46="Real",1,J$5) -> 0 | K37: =Inputs!K46*IF(Inputs!$E46="Real",1,K$5) -> 0 | L37: =Inputs!L46*IF(Inputs!$E46="Real",1,L$5) -> 0 | M37: =Inputs!M46*IF(Inputs!$E46="Real",1,M$5) -> 0 | N37: =Inputs!N46*IF(Inputs!$E46="Real",1,N$5) -> 0 | O37: =Inputs!O46*IF(Inputs!$E46="Real",1,O$5) -> 0 | ... AZ37: =Inputs!AZ46*IF(Inputs!$E46="Real",1,AZ$5) -> 0
D38: Other | E38: Real | F38: =Analysis_year -> 2025 | G38: =Inputs!G47 -> 0 | H38: =Inputs!H47*IF(Inputs!$E47="Real",1,H$5) -> 0 | I38: =Inputs!I47*IF(Inputs!$E47="Real",1,I$5) -> 0 | J38: =Inputs!J47*IF(Inputs!$E47="Real",1,J$5) -> 0 | K38: =Inputs!K47*IF(Inputs!$E47="Real",1,K$5) -> 0 | L38: =Inputs!L47*IF(Inputs!$E47="Real",1,L$5) -> 0 | M38: =Inputs!M47*IF(Inputs!$E47="Real",1,M$5) -> 0 | N38: =Inputs!N47*IF(Inputs!$E47="Real",1,N$5) -> 0 | O38: =Inputs!O47*IF(Inputs!$E47="Real",1,O$5) -> 0 | ... AZ38: =Inputs!AZ47*IF(Inputs!$E47="Real",1,AZ$5) -> 0
D39: ="Total non-fuel opex in "&Analysis_year&" dollars" -> Total non-fuel opex in 2025 dollars | H39: =SUBTOTAL(109,Opex_NonFuel_PP[2026]) -> 127312.43 | I39: =SUBTOTAL(109,Opex_NonFuel_PP[2027]) -> 124803.88 | J39: =SUBTOTAL(109,Opex_NonFuel_PP[2028]) -> 112933.61 | K39: =SUBTOTAL(109,Opex_NonFuel_PP[2029]) -> 110708.37 | L39: =SUBTOTAL(109,Opex_NonFuel_PP[2030]) -> 108526.98 | M39: =SUBTOTAL(109,Opex_NonFuel_PP[2031]) -> 106388.57 | N39: =SUBTOTAL(109,Opex_NonFuel_PP[2032]) -> 104292.3 | O39: =SUBTOTAL(109,Opex_NonFuel_PP[2033]) -> 102237.33 | P39: =SUBTOTAL(109,Opex_NonFuel_PP[2034]) -> 100222.85 | Q39: =SUBTOTAL(109,Opex_NonFuel_PP[2035]) -> 98248.061 | R39: =SUBTOTAL(109,Opex_NonFuel_PP[2036]) -> 96312.186 | S39: =SUBTOTAL(109,Opex_NonFuel_PP[2037]) -> 94414.456 | T39: =SUBTOTAL(109,Opex_NonFuel_PP[2038]) -> 92554.118 | U39: =SUBTOTAL(109,Opex_NonFuel_PP[2039]) -> 90730.436 | V39: =SUBTOTAL(109,Opex_NonFuel_PP[2040]) -> 88942.688 | W39: =SUBTOTAL(109,Opex_NonFuel_PP[2041]) -> 87190.166 | X39: =SUBTOTAL(109,Opex_NonFuel_PP[2042]) -> 85472.175 | Y39: =SUBTOTAL(109,Opex_NonFuel_PP[2043]) -> 83788.036 | Z39: =SUBTOTAL(109,Opex_NonFuel_PP[2044]) -> 82137.08 | AA39: =SUBTOTAL(109,Opex_NonFuel_PP[2045]) -> 80518.655 | AB39: =SUBTOTAL(109,Opex_NonFuel_PP[2046]) -> 78932.12 | AC39: =SUBTOTAL(109,Opex_NonFuel_PP[2047]) -> 77376.845 | AD39: =SUBTOTAL(109,Opex_NonFuel_PP[2048]) -> 0 | AE39: =SUBTOTAL(109,Opex_NonFuel_PP[2049]) -> 0 | AF39: =SUBTOTAL(109,Opex_NonFuel_PP[2050]) -> 0 | AG39: =SUBTOTAL(109,Opex_NonFuel_PP[2051]) -> 0 | AH39: =SUBTOTAL(109,Opex_NonFuel_PP[2052]) -> 0 | AI39: =SUBTOTAL(109,Opex_NonFuel_PP[2053]) -> 0 | AJ39: =SUBTOTAL(109,Opex_NonFuel_PP[2054]) -> 0 | AK39: =SUBTOTAL(109,Opex_NonFuel_PP[2055]) -> 0 | AL39: =SUBTOTAL(109,Opex_NonFuel_PP[2056]) -> 0 | AM39: =SUBTOTAL(109,Opex_NonFuel_PP[2057]) -> 0 | AN39: =SUBTOTAL(109,Opex_NonFuel_PP[2058]) -> 0 | AO39: =SUBTOTAL(109,Opex_NonFuel_PP[2059]) -> 0 | AP39: =SUBTOTAL(109,Opex_NonFuel_PP[2060]) -> 0 | AQ39: =SUBTOTAL(109,Opex_NonFuel_PP[2061]) -> 0 | AR39: =SUBTOTAL(109,Opex_NonFuel_PP[2062]) -> 0 | AS39: =SUBTOTAL(109,Opex_NonFuel_PP[2063]) -> 0 | AT39: =SUBTOTAL(109,Opex_NonFuel_PP[2064]) -> 0 | AU39: =SUBTOTAL(109,Opex_NonFuel_PP[2065]) -> 0 | AV39: =SUBTOTAL(109,Opex_NonFuel_PP[2066]) -> 0 | AW39: =SUBTOTAL(109,Opex_NonFuel_PP[2067]) -> 0 | AX39: =SUBTOTAL(109,Opex_NonFuel_PP[2068]) -> 0 | AY39: =SUBTOTAL(109,Opex_NonFuel_PP[2069]) -> 0 | AZ39: =SUBTOTAL(109,Opex_NonFuel_PP[2070]) -> 0
A41: Base Case (BC) | D41: Opex item | E41: Value basis | F41: Base year | G41: Applicant comment | H41: 2026 | I41: 2027 | J41: 2028 | K41: 2029 | L41: 2030 | M41: 2031 | N41: 2032 | O41: 2033 | P41: 2034 | Q41: 2035 | R41: 2036 | S41: 2037 | T41: 2038 | U41: 2039 | V41: 2040 | W41: 2041 | X41: 2042 | Y41: 2043 | Z41: 2044 | AA41: 2045 | AB41: 2046 | AC41: 2047 | AD41: 2048 | AE41: 2049 | AF41: 2050 | AG41: 2051 | AH41: 2052 | AI41: 2053 | AJ41: 2054 | AK41: 2055 | AL41: 2056 | AM41: 2057 | AN41: 2058 | AO41: 2059 | AP41: 2060 | AQ41: 2061 | AR41: 2062 | AS41: 2063 | AT41: 2064 | AU41: 2065 | AV41: 2066 | AW41: 2067 | AX41: 2068 | AY41: 2069 | AZ41: 2070
D42: Energy costs (already handled separately) | E42: Real | F42: =Analysis_year -> 2025 | G42: =Inputs!G53 -> 0 | H42: =Inputs!H53*IF(Inputs!$E53="Real",1,H$5) -> 0 | I42: =Inputs!I53*IF(Inputs!$E53="Real",1,I$5) -> 0 | J42: =Inputs!J53*IF(Inputs!$E53="Real",1,J$5) -> 0 | K42: =Inputs!K53*IF(Inputs!$E53="Real",1,K$5) -> 0 | L42: =Inputs!L53*IF(Inputs!$E53="Real",1,L$5) -> 0 | M42: =Inputs!M53*IF(Inputs!$E53="Real",1,M$5) -> 0 | N42: =Inputs!N53*IF(Inputs!$E53="Real",1,N$5) -> 0 | O42: =Inputs!O53*IF(Inputs!$E53="Real",1,O$5) -> 0 | ... AZ42: =Inputs!AZ53*IF(Inputs!$E53="Real",1,AZ$5) -> 0
D43: Equipment Operation Costs | E43: Real | F43: =Analysis_year -> 2025 | G43: =Inputs!G54 -> 0 | H43: =Inputs!H54*IF(Inputs!$E54="Real",1,H$5) -> 88139.378 | I43: =Inputs!I54*IF(Inputs!$E54="Real",1,I$5) -> 86402.684 | J43: =Inputs!J54*IF(Inputs!$E54="Real",1,J$5) -> 84700.21 | K43: =Inputs!K54*IF(Inputs!$E54="Real",1,K$5) -> 83031.281 | L43: =Inputs!L54*IF(Inputs!$E54="Real",1,L$5) -> 81395.237 | M43: =Inputs!M54*IF(Inputs!$E54="Real",1,M$5) -> 79791.429 | N43: =Inputs!N54*IF(Inputs!$E54="Real",1,N$5) -> 78219.222 | O43: =Inputs!O54*IF(Inputs!$E54="Real",1,O$5) -> 76677.995 | ... AZ43: =Inputs!AZ54*IF(Inputs!$E54="Real",1,AZ$5) -> 0
D44: Maintenance, Repairs, Inspections | E44: Real | F44: =Analysis_year -> 2025 | G44: =Inputs!G55 -> 0 | H44: =Inputs!H55*IF(Inputs!$E55="Real",1,H$5) -> 97932.642 | I44: =Inputs!I55*IF(Inputs!$E55="Real",1,I$5) -> 96002.982 | J44: =Inputs!J55*IF(Inputs!$E55="Real",1,J$5) -> 94111.344 | K44: =Inputs!K55*IF(Inputs!$E55="Real",1,K$5) -> 92256.979 | L44: =Inputs!L55*IF(Inputs!$E55="Real",1,L$5) -> 90439.152 | M44: =Inputs!M55*IF(Inputs!$E55="Real",1,M$5) -> 88657.143 | N44: =Inputs!N55*IF(Inputs!$E55="Real",1,N$5) -> 86910.247 | O44: =Inputs!O55*IF(Inputs!$E55="Real",1,O$5) -> 85197.772 | ... AZ44: =Inputs!AZ55*IF(Inputs!$E55="Real",1,AZ$5) -> 0
D45: Compliance Testing | E45: Real | F45: =Analysis_year -> 2025 | G45: =Inputs!G56 -> 0 | H45: =Inputs!H56*IF(Inputs!$E56="Real",1,H$5) -> 0 | I45: =Inputs!I56*IF(Inputs!$E56="Real",1,I$5) -> 0 | J45: =Inputs!J56*IF(Inputs!$E56="Real",1,J$5) -> 0 | K45: =Inputs!K56*IF(Inputs!$E56="Real",1,K$5) -> 0 | L45: =Inputs!L56*IF(Inputs!$E56="Real",1,L$5) -> 0 | M45: =Inputs!M56*IF(Inputs!$E56="Real",1,M$5) -> 0 | N45: =Inputs!N56*IF(Inputs!$E56="Real",1,N$5) -> 0 | O45: =Inputs!O56*IF(Inputs!$E56="Real",1,O$5) -> 0 | ... AZ45: =Inputs!AZ56*IF(Inputs!$E56="Real",1,AZ$5) -> 0
D46: Optimisation | E46: Real | F46: =Analysis_year -> 2025 | G46: =Inputs!G57 -> 0 | H46: =Inputs!H57*IF(Inputs!$E57="Real",1,H$5) -> 0 | I46: =Inputs!I57*IF(Inputs!$E57="Real",1,I$5) -> 0 | J46: =Inputs!J57*IF(Inputs!$E57="Real",1,J$5) -> 0 | K46: =Inputs!K57*IF(Inputs!$E57="Real",1,K$5) -> 0 | L46: =Inputs!L57*IF(Inputs!$E57="Real",1,L$5) -> 0 | M46: =Inputs!M57*IF(Inputs!$E57="Real",1,M$5) -> 0 | N46: =Inputs!N57*IF(Inputs!$E57="Real",1,N$5) -> 0 | O46: =Inputs!O57*IF(Inputs!$E57="Real",1,O$5) -> 0 | ... AZ46: =Inputs!AZ57*IF(Inputs!$E57="Real",1,AZ$5) -> 0
D47: Utilities and Consumables | E47: Real | F47: =Analysis_year -> 2025 | G47: =Inputs!G58 -> 0 | H47: =Inputs!H58*IF(Inputs!$E58="Real",1,H$5) -> 0 | I47: =Inputs!I58*IF(Inputs!$E58="Real",1,I$5) -> 0 | J47: =Inputs!J58*IF(Inputs!$E58="Real",1,J$5) -> 0 | K47: =Inputs!K58*IF(Inputs!$E58="Real",1,K$5) -> 0 | L47: =Inputs!L58*IF(Inputs!$E58="Real",1,L$5) -> 0 | M47: =Inputs!M58*IF(Inputs!$E58="Real",1,M$5) -> 0 | N47: =Inputs!N58*IF(Inputs!$E58="Real",1,N$5) -> 0 | O47: =Inputs!O58*IF(Inputs!$E58="Real",1,O$5) -> 0 | ... AZ47: =Inputs!AZ58*IF(Inputs!$E58="Real",1,AZ$5) -> 0
D48: Other | E48: Real | F48: =Analysis_year -> 2025 | G48: =Inputs!G59 -> 0 | H48: =Inputs!H59*IF(Inputs!$E59="Real",1,H$5) -> 0 | I48: =Inputs!I59*IF(Inputs!$E59="Real",1,I$5) -> 0 | J48: =Inputs!J59*IF(Inputs!$E59="Real",1,J$5) -> 0 | K48: =Inputs!K59*IF(Inputs!$E59="Real",1,K$5) -> 0 | L48: =Inputs!L59*IF(Inputs!$E59="Real",1,L$5) -> 0 | M48: =Inputs!M59*IF(Inputs!$E59="Real",1,M$5) -> 0 | N48: =Inputs!N59*IF(Inputs!$E59="Real",1,N$5) -> 0 | O48: =Inputs!O59*IF(Inputs!$E59="Real",1,O$5) -> 0 | ... AZ48: =Inputs!AZ59*IF(Inputs!$E59="Real",1,AZ$5) -> 0
D49: ="Total non-fuel opex in "&Analysis_year&" dollars" -> Total non-fuel opex in 2025 dollars | H49: =SUBTOTAL(109,Opex_NonFuel_BC[2026]) -> 186072.02 | I49: =SUBTOTAL(109,Opex_NonFuel_BC[2027]) -> 182405.67 | J49: =SUBTOTAL(109,Opex_NonFuel_BC[2028]) -> 178811.55 | K49: =SUBTOTAL(109,Opex_NonFuel_BC[2029]) -> 175288.26 | L49: =SUBTOTAL(109,Opex_NonFuel_BC[2030]) -> 171834.39 | M49: =SUBTOTAL(109,Opex_NonFuel_BC[2031]) -> 168448.57 | N49: =SUBTOTAL(109,Opex_NonFuel_BC[2032]) -> 165129.47 | O49: =SUBTOTAL(109,Opex_NonFuel_BC[2033]) -> 161875.77 | P49: =SUBTOTAL(109,Opex_NonFuel_BC[2034]) -> 158686.17 | Q49: =SUBTOTAL(109,Opex_NonFuel_BC[2035]) -> 155559.43 | R49: =SUBTOTAL(109,Opex_NonFuel_BC[2036]) -> 152494.29 | S49: =SUBTOTAL(109,Opex_NonFuel_BC[2037]) -> 149489.55 | T49: =SUBTOTAL(109,Opex_NonFuel_BC[2038]) -> 146544.02 | U49: =SUBTOTAL(109,Opex_NonFuel_BC[2039]) -> 143656.52 | V49: =SUBTOTAL(109,Opex_NonFuel_BC[2040]) -> 140825.92 | W49: =SUBTOTAL(109,Opex_NonFuel_BC[2041]) -> 138051.1 | X49: =SUBTOTAL(109,Opex_NonFuel_BC[2042]) -> 135330.94 | Y49: =SUBTOTAL(109,Opex_NonFuel_BC[2043]) -> 132664.39 | Z49: =SUBTOTAL(109,Opex_NonFuel_BC[2044]) -> 130050.38 | AA49: =SUBTOTAL(109,Opex_NonFuel_BC[2045]) -> 127487.87 | AB49: =SUBTOTAL(109,Opex_NonFuel_BC[2046]) -> 124975.86 | AC49: =SUBTOTAL(109,Opex_NonFuel_BC[2047]) -> 122513.34 | AD49: =SUBTOTAL(109,Opex_NonFuel_BC[2048]) -> 0 | AE49: =SUBTOTAL(109,Opex_NonFuel_BC[2049]) -> 0 | AF49: =SUBTOTAL(109,Opex_NonFuel_BC[2050]) -> 0 | AG49: =SUBTOTAL(109,Opex_NonFuel_BC[2051]) -> 0 | AH49: =SUBTOTAL(109,Opex_NonFuel_BC[2052]) -> 0 | AI49: =SUBTOTAL(109,Opex_NonFuel_BC[2053]) -> 0 | AJ49: =SUBTOTAL(109,Opex_NonFuel_BC[2054]) -> 0 | AK49: =SUBTOTAL(109,Opex_NonFuel_BC[2055]) -> 0 | AL49: =SUBTOTAL(109,Opex_NonFuel_BC[2056]) -> 0 | AM49: =SUBTOTAL(109,Opex_NonFuel_BC[2057]) -> 0 | AN49: =SUBTOTAL(109,Opex_NonFuel_BC[2058]) -> 0 | AO49: =SUBTOTAL(109,Opex_NonFuel_BC[2059]) -> 0 | AP49: =SUBTOTAL(109,Opex_NonFuel_BC[2060]) -> 0 | AQ49: =SUBTOTAL(109,Opex_NonFuel_BC[2061]) -> 0 | AR49: =SUBTOTAL(109,Opex_NonFuel_BC[2062]) -> 0 | AS49: =SUBTOTAL(109,Opex_NonFuel_BC[2063]) -> 0 | AT49: =SUBTOTAL(109,Opex_NonFuel_BC[2064]) -> 0 | AU49: =SUBTOTAL(109,Opex_NonFuel_BC[2065]) -> 0 | AV49: =SUBTOTAL(109,Opex_NonFuel_BC[2066]) -> 0 | AW49: =SUBTOTAL(109,Opex_NonFuel_BC[2067]) -> 0 | AX49: =SUBTOTAL(109,Opex_NonFuel_BC[2068]) -> 0 | AY49: =SUBTOTAL(109,Opex_NonFuel_BC[2069]) -> 0 | AZ49: =SUBTOTAL(109,Opex_NonFuel_BC[2070]) -> 0
A51: 2b) Fuel consumption
A52: Proposed Project (PP) | E52: Fuel type | F52: Units | G52: Applicant comment | H52: 2026 | I52: 2027 | J52: 2028 | K52: 2029 | L52: 2030 | M52: 2031 | N52: 2032 | O52: 2033 | P52: 2034 | Q52: 2035 | R52: 2036 | S52: 2037 | T52: 2038 | U52: 2039 | V52: 2040 | W52: 2041 | X52: 2042 | Y52: 2043 | Z52: 2044 | AA52: 2045 | AB52: 2046 | AC52: 2047 | AD52: 2048 | AE52: 2049 | AF52: 2050 | AG52: 2051 | AH52: 2052 | AI52: 2053 | AJ52: 2054 | AK52: 2055 | AL52: 2056 | AM52: 2057 | AN52: 2058 | AO52: 2059 | AP52: 2060 | AQ52: 2061 | AR52: 2062 | AS52: 2063 | AT52: 2064 | AU52: 2065 | AV52: 2066 | AW52: 2067 | AX52: 2068 | AY52: 2069 | AZ52: 2070
E53: =Inputs!D65 -> Electricity | F53: GJ | G53: =Inputs!G65 -> 0 | H53: =Inputs!H65*Data!$F3 -> 432 | I53: =Inputs!I65*Data!$F3 -> 18032.014 | J53: =Inputs!J65*Data!$F3 -> 18032.014 | K53: =Inputs!K65*Data!$F3 -> 18032.014 | L53: =Inputs!L65*Data!$F3 -> 18032.014 | M53: =Inputs!M65*Data!$F3 -> 18032.014 | N53: =Inputs!N65*Data!$F3 -> 18032.014 | O53: =Inputs!O65*Data!$F3 -> 18032.014 | ... AZ53: =Inputs!AZ65*Data!$F3 -> 0
E54: =Inputs!D66 -> Natural Gas | F54: GJ | G54: =Inputs!G72 -> 0 | H54: =Inputs!H66*Data!$F4 -> 70000 | I54: =Inputs!I66*Data!$F4 -> 0 | J54: =Inputs!J66*Data!$F4 -> 0 | K54: =Inputs!K66*Data!$F4 -> 0 | L54: =Inputs!L66*Data!$F4 -> 0 | M54: =Inputs!M66*Data!$F4 -> 0 | N54: =Inputs!N66*Data!$F4 -> 0 | O54: =Inputs!O66*Data!$F4 -> 0 | ... AZ54: =Inputs!AZ66*Data!$F4 -> 0
E55: =Inputs!D67 -> Coal - sub bituminous | F55: GJ | G55: =Inputs!G67 -> 0 | H55: =Inputs!H67*Data!$F5 -> 0 | I55: =Inputs!I67*Data!$F5 -> 0 | J55: =Inputs!J67*Data!$F5 -> 0 | K55: =Inputs!K67*Data!$F5 -> 0 | L55: =Inputs!L67*Data!$F5 -> 0 | M55: =Inputs!M67*Data!$F5 -> 0 | N55: =Inputs!N67*Data!$F5 -> 0 | O55: =Inputs!O67*Data!$F5 -> 0 | ... AZ55: =Inputs!AZ67*Data!$F5 -> 0
E56: =Inputs!D68 -> Coal - bituminous | F56: GJ | G56: =Inputs!G68 -> 0 | H56: =Inputs!H68*Data!$F6 -> 0 | I56: =Inputs!I68*Data!$F6 -> 0 | J56: =Inputs!J68*Data!$F6 -> 0 | K56: =Inputs!K68*Data!$F6 -> 0 | L56: =Inputs!L68*Data!$F6 -> 0 | M56: =Inputs!M68*Data!$F6 -> 0 | N56: =Inputs!N68*Data!$F6 -> 0 | O56: =Inputs!O68*Data!$F6 -> 0 | ... AZ56: =Inputs!AZ68*Data!$F6 -> 0
E57: =Inputs!D69 -> Coal - lignite | F57: GJ | G57: =Inputs!G69 -> 0 | H57: =Inputs!H69*Data!$F7 -> 0 | I57: =Inputs!I69*Data!$F7 -> 0 | J57: =Inputs!J69*Data!$F7 -> 0 | K57: =Inputs!K69*Data!$F7 -> 0 | L57: =Inputs!L69*Data!$F7 -> 0 | M57: =Inputs!M69*Data!$F7 -> 0 | N57: =Inputs!N69*Data!$F7 -> 0 | O57: =Inputs!O69*Data!$F7 -> 0 | ... AZ57: =Inputs!AZ69*Data!$F7 -> 0
E58: =Inputs!D70 -> Diesel | F58: GJ | G58: =Inputs!G67 -> 0 | H58: =Inputs!H70*Data!$F8 -> 0 | I58: =Inputs!I70*Data!$F8 -> 0 | J58: =Inputs!J70*Data!$F8 -> 0 | K58: =Inputs!K70*Data!$F8 -> 0 | L58: =Inputs!L70*Data!$F8 -> 0 | M58: =Inputs!M70*Data!$F8 -> 0 | N58: =Inputs!N70*Data!$F8 -> 0 | O58: =Inputs!O70*Data!$F8 -> 0 | ... AZ58: =Inputs!AZ70*Data!$F8 -> 0
E59: =Inputs!D71 -> LPG | F59: GJ | G59: =Inputs!G71 -> 0 | H59: =Inputs!H71*Data!$F9 -> 0 | I59: =Inputs!I71*Data!$F9 -> 0 | J59: =Inputs!J71*Data!$F9 -> 0 | K59: =Inputs!K71*Data!$F9 -> 0 | L59: =Inputs!L71*Data!$F9 -> 0 | M59: =Inputs!M71*Data!$F9 -> 0 | N59: =Inputs!N71*Data!$F9 -> 0 | O59: =Inputs!O71*Data!$F9 -> 0 | ... AZ59: =Inputs!AZ71*Data!$F9 -> 0
E60: =Inputs!D72 -> Light fuel oil | F60: GJ | G60: =Inputs!G72 -> 0 | H60: =Inputs!H72*Data!$F10 -> 0 | I60: =Inputs!I72*Data!$F10 -> 0 | J60: =Inputs!J72*Data!$F10 -> 0 | K60: =Inputs!K72*Data!$F10 -> 0 | L60: =Inputs!L72*Data!$F10 -> 0 | M60: =Inputs!M72*Data!$F10 -> 0 | N60: =Inputs!N72*Data!$F10 -> 0 | O60: =Inputs!O72*Data!$F10 -> 0 | ... AZ60: =Inputs!AZ72*Data!$F10 -> 0
E61: =Inputs!D73 -> Heavy fuel oil | F61: GJ | G61: =Inputs!G73 -> 0 | H61: =Inputs!H73*Data!$F11 -> 0 | I61: =Inputs!I73*Data!$F11 -> 0 | J61: =Inputs!J73*Data!$F11 -> 0 | K61: =Inputs!K73*Data!$F11 -> 0 | L61: =Inputs!L73*Data!$F11 -> 0 | M61: =Inputs!M73*Data!$F11 -> 0 | N61: =Inputs!N73*Data!$F11 -> 0 | O61: =Inputs!O73*Data!$F11 -> 0 | ... AZ61: =Inputs!AZ73*Data!$F11 -> 0
E62: =Inputs!D74 -> Geothermal | F62: GJ | G62: =Inputs!G74 -> 0 | H62: =Inputs!H74*Data!$F12 -> 0 | I62: =Inputs!I74*Data!$F12 -> 0 | J62: =Inputs!J74*Data!$F12 -> 0 | K62: =Inputs!K74*Data!$F12 -> 0 | L62: =Inputs!L74*Data!$F12 -> 0 | M62: =Inputs!M74*Data!$F12 -> 0 | N62: =Inputs!N74*Data!$F12 -> 0 | O62: =Inputs!O74*Data!$F12 -> 0 | ... AZ62: =Inputs!AZ74*Data!$F12 -> 0
E63: =Inputs!D75 -> Wood or wood chips | F63: GJ | G63: =Inputs!G75 -> 0 | H63: =Inputs!H75*Data!$F13 -> 0 | I63: =Inputs!I75*Data!$F13 -> 0 | J63: =Inputs!J75*Data!$F13 -> 0 | K63: =Inputs!K75*Data!$F13 -> 0 | L63: =Inputs!L75*Data!$F13 -> 0 | M63: =Inputs!M75*Data!$F13 -> 0 | N63: =Inputs!N75*Data!$F13 -> 0 | O63: =Inputs!O75*Data!$F13 -> 0 | ... AZ63: =Inputs!AZ75*Data!$F13 -> 0
A65: Base Case (BC) | E65: Fuel type | F65: Units | G65: Applicant comment | H65: 2026 | I65: 2027 | J65: 2028 | K65: 2029 | L65: 2030 | M65: 2031 | N65: 2032 | O65: 2033 | P65: 2034 | Q65: 2035 | R65: 2036 | S65: 2037 | T65: 2038 | U65: 2039 | V65: 2040 | W65: 2041 | X65: 2042 | Y65: 2043 | Z65: 2044 | AA65: 2045 | AB65: 2046 | AC65: 2047 | AD65: 2048 | AE65: 2049 | AF65: 2050 | AG65: 2051 | AH65: 2052 | AI65: 2053 | AJ65: 2054 | AK65: 2055 | AL65: 2056 | AM65: 2057 | AN65: 2058 | AO65: 2059 | AP65: 2060 | AQ65: 2061 | AR65: 2062 | AS65: 2063 | AT65: 2064 | AU65: 2065 | AV65: 2066 | AW65: 2067 | AX65: 2068 | AY65: 2069 | AZ65: 2070
E66: =Inputs!D78 -> Electricity | F66: GJ | G66: =Inputs!G78 -> 0 | H66: =Inputs!H78*Data!$F3 -> 432 | I66: =Inputs!I78*Data!$F3 -> 432 | J66: =Inputs!J78*Data!$F3 -> 432 | K66: =Inputs!K78*Data!$F3 -> 432 | L66: =Inputs!L78*Data!$F3 -> 432 | M66: =Inputs!M78*Data!$F3 -> 432 | N66: =Inputs!N78*Data!$F3 -> 432 | O66: =Inputs!O78*Data!$F3 -> 432 | ... AZ66: =Inputs!AZ78*Data!$F3 -> 0
E67: =Inputs!D79 -> Natural Gas | F67: GJ | G67: =Inputs!G79 -> 0 | H67: =Inputs!H79*Data!$F4 -> 70000 | I67: =Inputs!I79*Data!$F4 -> 70000 | J67: =Inputs!J79*Data!$F4 -> 70000 | K67: =Inputs!K79*Data!$F4 -> 70000 | L67: =Inputs!L79*Data!$F4 -> 70000 | M67: =Inputs!M79*Data!$F4 -> 70000 | N67: =Inputs!N79*Data!$F4 -> 70000 | O67: =Inputs!O79*Data!$F4 -> 70000 | ... AZ67: =Inputs!AZ79*Data!$F4 -> 0
E68: =Inputs!D80 -> Coal - sub bituminous | F68: GJ | G68: =Inputs!G80 -> 0 | H68: =Inputs!H80*Data!$F5 -> 0 | I68: =Inputs!I80*Data!$F5 -> 0 | J68: =Inputs!J80*Data!$F5 -> 0 | K68: =Inputs!K80*Data!$F5 -> 0 | L68: =Inputs!L80*Data!$F5 -> 0 | M68: =Inputs!M80*Data!$F5 -> 0 | N68: =Inputs!N80*Data!$F5 -> 0 | O68: =Inputs!O80*Data!$F5 -> 0 | ... AZ68: =Inputs!AZ80*Data!$F5 -> 0
E69: =Inputs!D81 -> Coal - bituminous | F69: GJ | G69: =Inputs!G81 -> 0 | H69: =Inputs!H81*Data!$F6 -> 0 | I69: =Inputs!I81*Data!$F6 -> 0 | J69: =Inputs!J81*Data!$F6 -> 0 | K69: =Inputs!K81*Data!$F6 -> 0 | L69: =Inputs!L81*Data!$F6 -> 0 | M69: =Inputs!M81*Data!$F6 -> 0 | N69: =Inputs!N81*Data!$F6 -> 0 | O69: =Inputs!O81*Data!$F6 -> 0 | ... AZ69: =Inputs!AZ81*Data!$F6 -> 0
E70: =Inputs!D82 -> Coal - lignite | F70: GJ | G70: =Inputs!G82 -> 0 | H70: =Inputs!H82*Data!$F7 -> 0 | I70: =Inputs!I82*Data!$F7 -> 0 | J70: =Inputs!J82*Data!$F7 -> 0 | K70: =Inputs!K82*Data!$F7 -> 0 | L70: =Inputs!L82*Data!$F7 -> 0 | M70: =Inputs!M82*Data!$F7 -> 0 | N70: =Inputs!N82*Data!$F7 -> 0 | O70: =Inputs!O82*Data!$F7 -> 0 | ... AZ70: =Inputs!AZ82*Data!$F7 -> 0
E71: =Inputs!D83 -> Diesel | F71: GJ | G71: =Inputs!G83 -> 0 | H71: =Inputs!H83*Data!$F8 -> 0 | I71: =Inputs!I83*Data!$F8 -> 0 | J71: =Inputs!J83*Data!$F8 -> 0 | K71: =Inputs!K83*Data!$F8 -> 0 | L71: =Inputs!L83*Data!$F8 -> 0 | M71: =Inputs!M83*Data!$F8 -> 0 | N71: =Inputs!N83*Data!$F8 -> 0 | O71: =Inputs!O83*Data!$F8 -> 0 | ... AZ71: =Inputs!AZ83*Data!$F8 -> 0
E72: =Inputs!D84 -> LPG | F72: GJ | G72: =Inputs!G84 -> 0 | H72: =Inputs!H84*Data!$F9 -> 0 | I72: =Inputs!I84*Data!$F9 -> 0 | J72: =Inputs!J84*Data!$F9 -> 0 | K72: =Inputs!K84*Data!$F9 -> 0 | L72: =Inputs!L84*Data!$F9 -> 0 | M72: =Inputs!M84*Data!$F9 -> 0 | N72: =Inputs!N84*Data!$F9 -> 0 | O72: =Inputs!O84*Data!$F9 -> 0 | ... AZ72: =Inputs!AZ84*Data!$F9 -> 0
E73: =Inputs!D85 -> Light fuel oil | F73: GJ | G73: =Inputs!G85 -> 0 | H73: =Inputs!H85*Data!$F10 -> 0 | I73: =Inputs!I85*Data!$F10 -> 0 | J73: =Inputs!J85*Data!$F10 -> 0 | K73: =Inputs!K85*Data!$F10 -> 0 | L73: =Inputs!L85*Data!$F10 -> 0 | M73: =Inputs!M85*Data!$F10 -> 0 | N73: =Inputs!N85*Data!$F10 -> 0 | O73: =Inputs!O85*Data!$F10 -> 0 | ... AZ73: =Inputs!AZ85*Data!$F10 -> 0
E74: =Inputs!D86 -> Heavy fuel oil | F74: GJ | G74: =Inputs!G86 -> 0 | H74: =Inputs!H86*Data!$F11 -> 0 | I74: =Inputs!I86*Data!$F11 -> 0 | J74: =Inputs!J86*Data!$F11 -> 0 | K74: =Inputs!K86*Data!$F11 -> 0 | L74: =Inputs!L86*Data!$F11 -> 0 | M74: =Inputs!M86*Data!$F11 -> 0 | N74: =Inputs!N86*Data!$F11 -> 0 | O74: =Inputs!O86*Data!$F11 -> 0 | ... AZ74: =Inputs!AZ86*Data!$F11 -> 0
E75: =Inputs!D87 -> Geothermal | F75: GJ | G75: =Inputs!G87 -> 0 | H75: =Inputs!H87*Data!$F12 -> 0 | I75: =Inputs!I87*Data!$F12 -> 0 | J75: =Inputs!J87*Data!$F12 -> 0 | K75: =Inputs!K87*Data!$F12 -> 0 | L75: =Inputs!L87*Data!$F12 -> 0 | M75: =Inputs!M87*Data!$F12 -> 0 | N75: =Inputs!N87*Data!$F12 -> 0 | O75: =Inputs!O87*Data!$F12 -> 0 | ... AZ75: =Inputs!AZ87*Data!$F12 -> 0
E76: =Inputs!D88 -> Wood or wood chips | F76: GJ | G76: =Inputs!G88 -> 0 | H76: =Inputs!H88*Data!$F13 -> 0 | I76: =Inputs!I88*Data!$F13 -> 0 | J76: =Inputs!J88*Data!$F13 -> 0 | K76: =Inputs!K88*Data!$F13 -> 0 | L76: =Inputs!L88*Data!$F13 -> 0 | M76: =Inputs!M88*Data!$F13 -> 0 | N76: =Inputs!N88*Data!$F13 -> 0 | O76: =Inputs!O88*Data!$F13 -> 0 | ... AZ76: =Inputs!AZ88*Data!$F13 -> 0
A78: 2b) Expected fuel prices (excl GST)
A79: Proposed Project (PP) | B79: Fuel type | C79: Units | D79: ETS cost included? | E79: Value basis | F79: Base year | G79: Applicant comment | H79: 2026 | I79: 2027 | J79: 2028 | K79: 2029 | L79: 2030 | M79: 2031 | N79: 2032 | O79: 2033 | P79: 2034 | Q79: 2035 | R79: 2036 | S79: 2037 | T79: 2038 | U79: 2039 | V79: 2040 | W79: 2041 | X79: 2042 | Y79: 2043 | Z79: 2044 | AA79: 2045 | AB79: 2046 | AC79: 2047 | AD79: 2048 | AE79: 2049 | AF79: 2050 | AG79: 2051 | AH79: 2052 | AI79: 2053 | AJ79: 2054 | AK79: 2055 | AL79: 2056 | AM79: 2057 | AN79: 2058 | AO79: 2059 | AP79: 2060 | AQ79: 2061 | AR79: 2062 | AS79: 2063 | AT79: 2064 | AU79: 2065 | AV79: 2066 | AW79: 2067 | AX79: 2068 | AY79: 2069 | AZ79: 2070
B80: =Inputs!B92 -> Electricity | C80: $/GJ | D80: No | E80: Real | F80: =Analysis_year -> 2025 | G80: =Inputs!G92 -> 0 | H80: =Data!M22/Data!$F3 -> 45.410647 | I80: =Data!N22/Data!$F3 -> 43.405726 | J80: =Data!O22/Data!$F3 -> 40.705038 | K80: =Data!P22/Data!$F3 -> 38.924093 | L80: =Data!Q22/Data!$F3 -> 37.142659 | M80: =Data!R22/Data!$F3 -> 35.360941 | N80: =Data!S22/Data!$F3 -> 33.385247 | O80: =Data!T22/Data!$F3 -> 31.680438 | ... AZ80: =Data!BE22/Data!$F3 -> 32.6224
B81: =Inputs!B93 -> Natural Gas | C81: $/GJ | D81: No | E81: Real | F81: =Analysis_year -> 2025 | G81: =Inputs!G93 -> 0 | H81: =Inputs!H93*IF(Inputs!$E93="Real",1,H$5)/Data!$F4 -> 10 | I81: =Inputs!I93*IF(Inputs!$E93="Real",1,I$5)/Data!$F4 -> 10 | J81: =Inputs!J93*IF(Inputs!$E93="Real",1,J$5)/Data!$F4 -> 10 | K81: =Inputs!K93*IF(Inputs!$E93="Real",1,K$5)/Data!$F4 -> 10 | L81: =Inputs!L93*IF(Inputs!$E93="Real",1,L$5)/Data!$F4 -> 10 | M81: =Inputs!M93*IF(Inputs!$E93="Real",1,M$5)/Data!$F4 -> 10 | N81: =Inputs!N93*IF(Inputs!$E93="Real",1,N$5)/Data!$F4 -> 10 | O81: =Inputs!O93*IF(Inputs!$E93="Real",1,O$5)/Data!$F4 -> 10 | ... AZ81: =Inputs!AZ93*IF(Inputs!$E93="Real",1,AZ$5)/Data!$F4 -> 0
B82: =Inputs!B94 -> Coal - sub bituminous | C82: $/GJ | D82: No | E82: Real | F82: =Analysis_year -> 2025 | G82: =Inputs!G94 -> 0 | H82: =Inputs!H94*IF(Inputs!$E94="Real",1,H$5)/Data!$F5 -> 6.8181818 | I82: =Inputs!I94*IF(Inputs!$E94="Real",1,I$5)/Data!$F5 -> 6.8181818 | J82: =Inputs!J94*IF(Inputs!$E94="Real",1,J$5)/Data!$F5 -> 6.8181818 | K82: =Inputs!K94*IF(Inputs!$E94="Real",1,K$5)/Data!$F5 -> 6.8181818 | L82: =Inputs!L94*IF(Inputs!$E94="Real",1,L$5)/Data!$F5 -> 6.8181818 | M82: =Inputs!M94*IF(Inputs!$E94="Real",1,M$5)/Data!$F5 -> 6.8181818 | N82: =Inputs!N94*IF(Inputs!$E94="Real",1,N$5)/Data!$F5 -> 6.8181818 | O82: =Inputs!O94*IF(Inputs!$E94="Real",1,O$5)/Data!$F5 -> 6.8181818 | ... AZ82: =Inputs!AZ94*IF(Inputs!$E94="Real",1,AZ$5)/Data!$F5 -> 0
B83: =Inputs!B95 -> Coal - bituminous | C83: $/GJ | D83: No | E83: Real | F83: =Analysis_year -> 2025 | G83: =Inputs!G95 -> 0 | H83: =Inputs!H95*IF(Inputs!$E95="Real",1,H$5)/Data!$F6 -> 0 | I83: =Inputs!I95*IF(Inputs!$E95="Real",1,I$5)/Data!$F6 -> 0 | J83: =Inputs!J95*IF(Inputs!$E95="Real",1,J$5)/Data!$F6 -> 0 | K83: =Inputs!K95*IF(Inputs!$E95="Real",1,K$5)/Data!$F6 -> 0 | L83: =Inputs!L95*IF(Inputs!$E95="Real",1,L$5)/Data!$F6 -> 0 | M83: =Inputs!M95*IF(Inputs!$E95="Real",1,M$5)/Data!$F6 -> 0 | N83: =Inputs!N95*IF(Inputs!$E95="Real",1,N$5)/Data!$F6 -> 0 | O83: =Inputs!O95*IF(Inputs!$E95="Real",1,O$5)/Data!$F6 -> 0 | ... AZ83: =Inputs!AZ95*IF(Inputs!$E95="Real",1,AZ$5)/Data!$F6 -> 0
B84: =Inputs!B96 -> Coal - lignite | C84: $/GJ | D84: No | E84: Real | F84: =Analysis_year -> 2025 | G84: =Inputs!G96 -> 0 | H84: =Inputs!H96*IF(Inputs!$E96="Real",1,H$5)/Data!$F7 -> 0 | I84: =Inputs!I96*IF(Inputs!$E96="Real",1,I$5)/Data!$F7 -> 0 | J84: =Inputs!J96*IF(Inputs!$E96="Real",1,J$5)/Data!$F7 -> 0 | K84: =Inputs!K96*IF(Inputs!$E96="Real",1,K$5)/Data!$F7 -> 0 | L84: =Inputs!L96*IF(Inputs!$E96="Real",1,L$5)/Data!$F7 -> 0 | M84: =Inputs!M96*IF(Inputs!$E96="Real",1,M$5)/Data!$F7 -> 0 | N84: =Inputs!N96*IF(Inputs!$E96="Real",1,N$5)/Data!$F7 -> 0 | O84: =Inputs!O96*IF(Inputs!$E96="Real",1,O$5)/Data!$F7 -> 0 | ... AZ84: =Inputs!AZ96*IF(Inputs!$E96="Real",1,AZ$5)/Data!$F7 -> 0
B85: =Inputs!B97 -> Diesel | C85: $/GJ | D85: No | E85: Real | F85: =Analysis_year -> 2025 | G85: =Inputs!G97 -> 0 | H85: =Inputs!H97*IF(Inputs!$E97="Real",1,H$5)/Data!$F8 -> 0.056022409 | I85: =Inputs!I97*IF(Inputs!$E97="Real",1,I$5)/Data!$F8 -> 0.056022409 | J85: =Inputs!J97*IF(Inputs!$E97="Real",1,J$5)/Data!$F8 -> 0.056022409 | K85: =Inputs!K97*IF(Inputs!$E97="Real",1,K$5)/Data!$F8 -> 0.056022409 | L85: =Inputs!L97*IF(Inputs!$E97="Real",1,L$5)/Data!$F8 -> 0.056022409 | M85: =Inputs!M97*IF(Inputs!$E97="Real",1,M$5)/Data!$F8 -> 0.056022409 | N85: =Inputs!N97*IF(Inputs!$E97="Real",1,N$5)/Data!$F8 -> 0.056022409 | O85: =Inputs!O97*IF(Inputs!$E97="Real",1,O$5)/Data!$F8 -> 0.056022409 | ... AZ85: =Inputs!AZ97*IF(Inputs!$E97="Real",1,AZ$5)/Data!$F8 -> 0
B86: =Inputs!B98 -> LPG | C86: $/GJ | D86: No | E86: Real | F86: =Analysis_year -> 2025 | G86: =Inputs!G98 -> 0 | H86: =Inputs!H98*IF(Inputs!$E98="Real",1,H$5)/Data!$F9 -> 0 | I86: =Inputs!I98*IF(Inputs!$E98="Real",1,I$5)/Data!$F9 -> 0 | J86: =Inputs!J98*IF(Inputs!$E98="Real",1,J$5)/Data!$F9 -> 0 | K86: =Inputs!K98*IF(Inputs!$E98="Real",1,K$5)/Data!$F9 -> 0 | L86: =Inputs!L98*IF(Inputs!$E98="Real",1,L$5)/Data!$F9 -> 0 | M86: =Inputs!M98*IF(Inputs!$E98="Real",1,M$5)/Data!$F9 -> 0 | N86: =Inputs!N98*IF(Inputs!$E98="Real",1,N$5)/Data!$F9 -> 0 | O86: =Inputs!O98*IF(Inputs!$E98="Real",1,O$5)/Data!$F9 -> 0 | ... AZ86: =Inputs!AZ98*IF(Inputs!$E98="Real",1,AZ$5)/Data!$F9 -> 0
B87: =Inputs!B99 -> Light fuel oil | C87: $/GJ | D87: No | E87: Real | F87: =Analysis_year -> 2025 | G87: =Inputs!G99 -> 0 | H87: =Inputs!H99*IF(Inputs!$E99="Real",1,H$5)/Data!$F10 -> 0 | I87: =Inputs!I99*IF(Inputs!$E99="Real",1,I$5)/Data!$F10 -> 0 | J87: =Inputs!J99*IF(Inputs!$E99="Real",1,J$5)/Data!$F10 -> 0 | K87: =Inputs!K99*IF(Inputs!$E99="Real",1,K$5)/Data!$F10 -> 0 | L87: =Inputs!L99*IF(Inputs!$E99="Real",1,L$5)/Data!$F10 -> 0 | M87: =Inputs!M99*IF(Inputs!$E99="Real",1,M$5)/Data!$F10 -> 0 | N87: =Inputs!N99*IF(Inputs!$E99="Real",1,N$5)/Data!$F10 -> 0 | O87: =Inputs!O99*IF(Inputs!$E99="Real",1,O$5)/Data!$F10 -> 0 | ... AZ87: =Inputs!AZ99*IF(Inputs!$E99="Real",1,AZ$5)/Data!$F10 -> 0
B88: =Inputs!B100 -> Heavy fuel oil | C88: $/GJ | D88: No | E88: Real | F88: =Analysis_year -> 2025 | G88: =Inputs!G100 -> 0 | H88: =Inputs!H100*IF(Inputs!$E100="Real",1,H$5)/Data!$F11 -> 0 | I88: =Inputs!I100*IF(Inputs!$E100="Real",1,I$5)/Data!$F11 -> 0 | J88: =Inputs!J100*IF(Inputs!$E100="Real",1,J$5)/Data!$F11 -> 0 | K88: =Inputs!K100*IF(Inputs!$E100="Real",1,K$5)/Data!$F11 -> 0 | L88: =Inputs!L100*IF(Inputs!$E100="Real",1,L$5)/Data!$F11 -> 0 | M88: =Inputs!M100*IF(Inputs!$E100="Real",1,M$5)/Data!$F11 -> 0 | N88: =Inputs!N100*IF(Inputs!$E100="Real",1,N$5)/Data!$F11 -> 0 | O88: =Inputs!O100*IF(Inputs!$E100="Real",1,O$5)/Data!$F11 -> 0 | ... AZ88: =Inputs!AZ100*IF(Inputs!$E100="Real",1,AZ$5)/Data!$F11 -> 0
B89: =Inputs!B101 -> Geothermal | C89: $/GJ | D89: No | E89: Real | F89: =Analysis_year -> 2025 | G89: =Inputs!G101 -> 0 | H89: =Inputs!H101*IF(Inputs!$E101="Real",1,H$5)/Data!$F12 -> 0 | I89: =Inputs!I101*IF(Inputs!$E101="Real",1,I$5)/Data!$F12 -> 0 | J89: =Inputs!J101*IF(Inputs!$E101="Real",1,J$5)/Data!$F12 -> 0 | K89: =Inputs!K101*IF(Inputs!$E101="Real",1,K$5)/Data!$F12 -> 0 | L89: =Inputs!L101*IF(Inputs!$E101="Real",1,L$5)/Data!$F12 -> 0 | M89: =Inputs!M101*IF(Inputs!$E101="Real",1,M$5)/Data!$F12 -> 0 | N89: =Inputs!N101*IF(Inputs!$E101="Real",1,N$5)/Data!$F12 -> 0 | O89: =Inputs!O101*IF(Inputs!$E101="Real",1,O$5)/Data!$F12 -> 0 | ... AZ89: =Inputs!AZ101*IF(Inputs!$E101="Real",1,AZ$5)/Data!$F12 -> 0
B90: =Inputs!B102 -> Wood or wood chips | C90: $/GJ | D90: No | E90: Real | F90: =Analysis_year -> 2025 | G90: =Inputs!G102 -> 0 | H90: =Inputs!H102*IF(Inputs!$E102="Real",1,H$5)/Data!$F13 -> 0 | I90: =Inputs!I102*IF(Inputs!$E102="Real",1,I$5)/Data!$F13 -> 0 | J90: =Inputs!J102*IF(Inputs!$E102="Real",1,J$5)/Data!$F13 -> 0 | K90: =Inputs!K102*IF(Inputs!$E102="Real",1,K$5)/Data!$F13 -> 0 | L90: =Inputs!L102*IF(Inputs!$E102="Real",1,L$5)/Data!$F13 -> 0 | M90: =Inputs!M102*IF(Inputs!$E102="Real",1,M$5)/Data!$F13 -> 0 | N90: =Inputs!N102*IF(Inputs!$E102="Real",1,N$5)/Data!$F13 -> 0 | O90: =Inputs!O102*IF(Inputs!$E102="Real",1,O$5)/Data!$F13 -> 0 | ... AZ90: =Inputs!AZ102*IF(Inputs!$E102="Real",1,AZ$5)/Data!$F13 -> 0
A92: Base Case (BC) | B92: Fuel type | C92: Units | D92: ETS cost included? | E92: Value basis | F92: Base year | G92: Applicant comment | H92: 2026 | I92: 2027 | J92: 2028 | K92: 2029 | L92: 2030 | M92: 2031 | N92: 2032 | O92: 2033 | P92: 2034 | Q92: 2035 | R92: 2036 | S92: 2037 | T92: 2038 | U92: 2039 | V92: 2040 | W92: 2041 | X92: 2042 | Y92: 2043 | Z92: 2044 | AA92: 2045 | AB92: 2046 | AC92: 2047 | AD92: 2048 | AE92: 2049 | AF92: 2050 | AG92: 2051 | AH92: 2052 | AI92: 2053 | AJ92: 2054 | AK92: 2055 | AL92: 2056 | AM92: 2057 | AN92: 2058 | AO92: 2059 | AP92: 2060 | AQ92: 2061 | AR92: 2062 | AS92: 2063 | AT92: 2064 | AU92: 2065 | AV92: 2066 | AW92: 2067 | AX92: 2068 | AY92: 2069 | AZ92: 2070
B93: =Inputs!B105 -> Electricity | C93: $/GJ | D93: No | E93: Real | F93: =Analysis_year -> 2025 | G93: =Inputs!G105 -> 0 | H93: =Data!M22/Data!$F3 -> 45.410647 | I93: =Data!N22/Data!$F3 -> 43.405726 | J93: =Data!O22/Data!$F3 -> 40.705038 | K93: =Data!P22/Data!$F3 -> 38.924093 | L93: =Data!Q22/Data!$F3 -> 37.142659 | M93: =Data!R22/Data!$F3 -> 35.360941 | N93: =Data!S22/Data!$F3 -> 33.385247 | O93: =Data!T22/Data!$F3 -> 31.680438 | ... AZ93: =Data!BE22/Data!$F3 -> 32.6224
B94: =Inputs!B106 -> Natural Gas | C94: $/GJ | D94: No | E94: Real | F94: =Analysis_year -> 2025 | G94: =Inputs!G106 -> 0 | H94: =Inputs!H106*IF(Inputs!$E106="Real",1,H$5)/Data!$F4 -> 10 | I94: =Inputs!I106*IF(Inputs!$E106="Real",1,I$5)/Data!$F4 -> 10 | J94: =Inputs!J106*IF(Inputs!$E106="Real",1,J$5)/Data!$F4 -> 10 | K94: =Inputs!K106*IF(Inputs!$E106="Real",1,K$5)/Data!$F4 -> 10 | L94: =Inputs!L106*IF(Inputs!$E106="Real",1,L$5)/Data!$F4 -> 10 | M94: =Inputs!M106*IF(Inputs!$E106="Real",1,M$5)/Data!$F4 -> 10 | N94: =Inputs!N106*IF(Inputs!$E106="Real",1,N$5)/Data!$F4 -> 10 | O94: =Inputs!O106*IF(Inputs!$E106="Real",1,O$5)/Data!$F4 -> 10 | ... AZ94: =Inputs!AZ106*IF(Inputs!$E106="Real",1,AZ$5)/Data!$F4 -> 0
B95: =Inputs!B107 -> Coal - sub bituminous | C95: $/GJ | D95: No | E95: Real | F95: =Analysis_year -> 2025 | G95: =Inputs!G107 -> 0 | H95: =Inputs!H107*IF(Inputs!$E107="Real",1,H$5)/Data!$F5 -> 6.8181818 | I95: =Inputs!I107*IF(Inputs!$E107="Real",1,I$5)/Data!$F5 -> 6.8181818 | J95: =Inputs!J107*IF(Inputs!$E107="Real",1,J$5)/Data!$F5 -> 6.8181818 | K95: =Inputs!K107*IF(Inputs!$E107="Real",1,K$5)/Data!$F5 -> 6.8181818 | L95: =Inputs!L107*IF(Inputs!$E107="Real",1,L$5)/Data!$F5 -> 6.8181818 | M95: =Inputs!M107*IF(Inputs!$E107="Real",1,M$5)/Data!$F5 -> 6.8181818 | N95: =Inputs!N107*IF(Inputs!$E107="Real",1,N$5)/Data!$F5 -> 6.8181818 | O95: =Inputs!O107*IF(Inputs!$E107="Real",1,O$5)/Data!$F5 -> 6.8181818 | ... AZ95: =Inputs!AZ107*IF(Inputs!$E107="Real",1,AZ$5)/Data!$F5 -> 0
B96: =Inputs!B108 -> Coal - bituminous | C96: $/GJ | D96: No | E96: Real | F96: =Analysis_year -> 2025 | G96: =Inputs!G108 -> 0 | H96: =Inputs!H108*IF(Inputs!$E108="Real",1,H$5)/Data!$F6 -> 0 | I96: =Inputs!I108*IF(Inputs!$E108="Real",1,I$5)/Data!$F6 -> 0 | J96: =Inputs!J108*IF(Inputs!$E108="Real",1,J$5)/Data!$F6 -> 0 | K96: =Inputs!K108*IF(Inputs!$E108="Real",1,K$5)/Data!$F6 -> 0 | L96: =Inputs!L108*IF(Inputs!$E108="Real",1,L$5)/Data!$F6 -> 0 | M96: =Inputs!M108*IF(Inputs!$E108="Real",1,M$5)/Data!$F6 -> 0 | N96: =Inputs!N108*IF(Inputs!$E108="Real",1,N$5)/Data!$F6 -> 0 | O96: =Inputs!O108*IF(Inputs!$E108="Real",1,O$5)/Data!$F6 -> 0 | ... AZ96: =Inputs!AZ108*IF(Inputs!$E108="Real",1,AZ$5)/Data!$F6 -> 0
B97: =Inputs!B109 -> Coal - lignite | C97: $/GJ | D97: No | E97: Real | F97: =Analysis_year -> 2025 | G97: =Inputs!G109 -> 0 | H97: =Inputs!H109*IF(Inputs!$E109="Real",1,H$5)/Data!$F7 -> 0 | I97: =Inputs!I109*IF(Inputs!$E109="Real",1,I$5)/Data!$F7 -> 0 | J97: =Inputs!J109*IF(Inputs!$E109="Real",1,J$5)/Data!$F7 -> 0 | K97: =Inputs!K109*IF(Inputs!$E109="Real",1,K$5)/Data!$F7 -> 0 | L97: =Inputs!L109*IF(Inputs!$E109="Real",1,L$5)/Data!$F7 -> 0 | M97: =Inputs!M109*IF(Inputs!$E109="Real",1,M$5)/Data!$F7 -> 0 | N97: =Inputs!N109*IF(Inputs!$E109="Real",1,N$5)/Data!$F7 -> 0 | O97: =Inputs!O109*IF(Inputs!$E109="Real",1,O$5)/Data!$F7 -> 0 | ... AZ97: =Inputs!AZ109*IF(Inputs!$E109="Real",1,AZ$5)/Data!$F7 -> 0
B98: =Inputs!B110 -> Diesel | C98: $/GJ | D98: No | E98: Real | F98: =Analysis_year -> 2025 | G98: =Inputs!G110 -> 0 | H98: =Inputs!H110*IF(Inputs!$E110="Real",1,H$5)/Data!$F8 -> 0.056022409 | I98: =Inputs!I110*IF(Inputs!$E110="Real",1,I$5)/Data!$F8 -> 0.056022409 | J98: =Inputs!J110*IF(Inputs!$E110="Real",1,J$5)/Data!$F8 -> 0.056022409 | K98: =Inputs!K110*IF(Inputs!$E110="Real",1,K$5)/Data!$F8 -> 0.056022409 | L98: =Inputs!L110*IF(Inputs!$E110="Real",1,L$5)/Data!$F8 -> 0.056022409 | M98: =Inputs!M110*IF(Inputs!$E110="Real",1,M$5)/Data!$F8 -> 0.056022409 | N98: =Inputs!N110*IF(Inputs!$E110="Real",1,N$5)/Data!$F8 -> 0.056022409 | O98: =Inputs!O110*IF(Inputs!$E110="Real",1,O$5)/Data!$F8 -> 0.056022409 | ... AZ98: =Inputs!AZ110*IF(Inputs!$E110="Real",1,AZ$5)/Data!$F8 -> 0.056022409
B99: =Inputs!B111 -> LPG | C99: $/GJ | D99: No | E99: Real | F99: =Analysis_year -> 2025 | G99: =Inputs!G111 -> 0 | H99: =Inputs!H111*IF(Inputs!$E111="Real",1,H$5)/Data!$F9 -> 0 | I99: =Inputs!I111*IF(Inputs!$E111="Real",1,I$5)/Data!$F9 -> 0 | J99: =Inputs!J111*IF(Inputs!$E111="Real",1,J$5)/Data!$F9 -> 0 | K99: =Inputs!K111*IF(Inputs!$E111="Real",1,K$5)/Data!$F9 -> 0 | L99: =Inputs!L111*IF(Inputs!$E111="Real",1,L$5)/Data!$F9 -> 0 | M99: =Inputs!M111*IF(Inputs!$E111="Real",1,M$5)/Data!$F9 -> 0 | N99: =Inputs!N111*IF(Inputs!$E111="Real",1,N$5)/Data!$F9 -> 0 | O99: =Inputs!O111*IF(Inputs!$E111="Real",1,O$5)/Data!$F9 -> 0 | ... AZ99: =Inputs!AZ111*IF(Inputs!$E111="Real",1,AZ$5)/Data!$F9 -> 0
B100: =Inputs!B112 -> Light fuel oil | C100: $/GJ | D100: No | E100: Real | F100: =Analysis_year -> 2025 | G100: =Inputs!G112 -> 0 | H100: =Inputs!H112*IF(Inputs!$E112="Real",1,H$5)/Data!$F10 -> 0 | I100: =Inputs!I112*IF(Inputs!$E112="Real",1,I$5)/Data!$F10 -> 0 | J100: =Inputs!J112*IF(Inputs!$E112="Real",1,J$5)/Data!$F10 -> 0 | K100: =Inputs!K112*IF(Inputs!$E112="Real",1,K$5)/Data!$F10 -> 0 | L100: =Inputs!L112*IF(Inputs!$E112="Real",1,L$5)/Data!$F10 -> 0 | M100: =Inputs!M112*IF(Inputs!$E112="Real",1,M$5)/Data!$F10 -> 0 | N100: =Inputs!N112*IF(Inputs!$E112="Real",1,N$5)/Data!$F10 -> 0 | O100: =Inputs!O112*IF(Inputs!$E112="Real",1,O$5)/Data!$F10 -> 0 | ... AZ100: =Inputs!AZ112*IF(Inputs!$E112="Real",1,AZ$5)/Data!$F10 -> 0
B101: =Inputs!B113 -> Heavy fuel oil | C101: $/GJ | D101: No | E101: Real | F101: =Analysis_year -> 2025 | G101: =Inputs!G113 -> 0 | H101: =Inputs!H113*IF(Inputs!$E113="Real",1,H$5)/Data!$F11 -> 0 | I101: =Inputs!I113*IF(Inputs!$E113="Real",1,I$5)/Data!$F11 -> 0 | J101: =Inputs!J113*IF(Inputs!$E113="Real",1,J$5)/Data!$F11 -> 0 | K101: =Inputs!K113*IF(Inputs!$E113="Real",1,K$5)/Data!$F11 -> 0 | L101: =Inputs!L113*IF(Inputs!$E113="Real",1,L$5)/Data!$F11 -> 0 | M101: =Inputs!M113*IF(Inputs!$E113="Real",1,M$5)/Data!$F11 -> 0 | N101: =Inputs!N113*IF(Inputs!$E113="Real",1,N$5)/Data!$F11 -> 0 | O101: =Inputs!O113*IF(Inputs!$E113="Real",1,O$5)/Data!$F11 -> 0 | ... AZ101: =Inputs!AZ113*IF(Inputs!$E113="Real",1,AZ$5)/Data!$F11 -> 0
B102: =Inputs!B114 -> Geothermal | C102: $/GJ | D102: No | E102: Real | F102: =Analysis_year -> 2025 | G102: =Inputs!G114 -> 0 | H102: =Inputs!H114*IF(Inputs!$E114="Real",1,H$5)/Data!$F12 -> 0 | I102: =Inputs!I114*IF(Inputs!$E114="Real",1,I$5)/Data!$F12 -> 0 | J102: =Inputs!J114*IF(Inputs!$E114="Real",1,J$5)/Data!$F12 -> 0 | K102: =Inputs!K114*IF(Inputs!$E114="Real",1,K$5)/Data!$F12 -> 0 | L102: =Inputs!L114*IF(Inputs!$E114="Real",1,L$5)/Data!$F12 -> 0 | M102: =Inputs!M114*IF(Inputs!$E114="Real",1,M$5)/Data!$F12 -> 0 | N102: =Inputs!N114*IF(Inputs!$E114="Real",1,N$5)/Data!$F12 -> 0 | O102: =Inputs!O114*IF(Inputs!$E114="Real",1,O$5)/Data!$F12 -> 0 | ... AZ102: =Inputs!AZ114*IF(Inputs!$E114="Real",1,AZ$5)/Data!$F12 -> 0
B103: =Inputs!B115 -> Wood or wood chips | C103: $/GJ | D103: No | E103: Real | F103: =Analysis_year -> 2025 | G103: =Inputs!G115 -> 0 | H103: =Inputs!H115*IF(Inputs!$E115="Real",1,H$5)/Data!$F13 -> 0 | I103: =Inputs!I115*IF(Inputs!$E115="Real",1,I$5)/Data!$F13 -> 0 | J103: =Inputs!J115*IF(Inputs!$E115="Real",1,J$5)/Data!$F13 -> 0 | K103: =Inputs!K115*IF(Inputs!$E115="Real",1,K$5)/Data!$F13 -> 0 | L103: =Inputs!L115*IF(Inputs!$E115="Real",1,L$5)/Data!$F13 -> 0 | M103: =Inputs!M115*IF(Inputs!$E115="Real",1,M$5)/Data!$F13 -> 0 | N103: =Inputs!N115*IF(Inputs!$E115="Real",1,N$5)/Data!$F13 -> 0 | O103: =Inputs!O115*IF(Inputs!$E115="Real",1,O$5)/Data!$F13 -> 0 | ... AZ103: =Inputs!AZ115*IF(Inputs!$E115="Real",1,AZ$5)/Data!$F13 -> 0
A105: 2c) Fuel costs
A106: Proposed Project | D106: Fuel type | E106: Value basis | F106: Base year | G106: Applicant comment | H106: 2026 | I106: 2027 | J106: 2028 | K106: 2029 | L106: 2030 | M106: 2031 | N106: 2032 | O106: 2033 | P106: 2034 | Q106: 2035 | R106: 2036 | S106: 2037 | T106: 2038 | U106: 2039 | V106: 2040 | W106: 2041 | X106: 2042 | Y106: 2043 | Z106: 2044 | AA106: 2045 | AB106: 2046 | AC106: 2047 | AD106: 2048 | AE106: 2049 | AF106: 2050 | AG106: 2051 | AH106: 2052 | AI106: 2053 | AJ106: 2054 | AK106: 2055 | AL106: 2056 | AM106: 2057 | AN106: 2058 | AO106: 2059 | AP106: 2060 | AQ106: 2061 | AR106: 2062 | AS106: 2063 | AT106: 2064 | AU106: 2065 | AV106: 2066 | AW106: 2067 | AX106: 2068 | AY106: 2069 | AZ106: 2070
D107: =IF(E53="<Select>","",E53) -> Electricity | E107: =E80 -> Real | F107: =Analysis_year -> 2025 | G107: =Inputs!G119 -> 0 | H107: =H53*H80 -> 19617.4 | I107: =I53*I80 -> 782692.66 | J107: =J53*J80 -> 733993.82 | K107: =K53*K80 -> 701879.79 | L107: =L53*L80 -> 669756.95 | M107: =M53*M80 -> 637628.99 | N107: =N53*N80 -> 602003.24 | O107: =O53*O80 -> 571262.1 | ... AZ107: =AZ53*AZ80 -> 0
D108: =IF(E54="<Select>","",E54) -> Natural Gas | E108: =E81 -> Real | F108: =Analysis_year -> 2025 | G108: =Inputs!G120 -> 0 | H108: =H54*H81 -> 700000 | I108: =I54*I81 -> 0 | J108: =J54*J81 -> 0 | K108: =K54*K81 -> 0 | L108: =L54*L81 -> 0 | M108: =M54*M81 -> 0 | N108: =N54*N81 -> 0 | O108: =O54*O81 -> 0 | ... AZ108: =AZ54*AZ81 -> 0
D109: =IF(E55="<Select>","",E55) -> Coal - sub bituminous | E109: =E82 -> Real | F109: =Analysis_year -> 2025 | G109: =Inputs!G121 -> 0 | H109: =H55*H82 -> 0 | I109: =I55*I82 -> 0 | J109: =J55*J82 -> 0 | K109: =K55*K82 -> 0 | L109: =L55*L82 -> 0 | M109: =M55*M82 -> 0 | N109: =N55*N82 -> 0 | O109: =O55*O82 -> 0 | ... AZ109: =AZ55*AZ82 -> 0
D110: =IF(E56="<Select>","",E56) -> Coal - bituminous | E110: =E83 -> Real | F110: =Analysis_year -> 2025 | G110: =Inputs!G122 -> 0 | H110: =H56*H83 -> 0 | I110: =I56*I83 -> 0 | J110: =J56*J83 -> 0 | K110: =K56*K83 -> 0 | L110: =L56*L83 -> 0 | M110: =M56*M83 -> 0 | N110: =N56*N83 -> 0 | O110: =O56*O83 -> 0 | ... AZ110: =AZ56*AZ83 -> 0
D111: =IF(E57="<Select>","",E57) -> Coal - lignite | E111: =E84 -> Real | F111: =Analysis_year -> 2025 | G111: =Inputs!G123 -> 0 | H111: =H57*H84 -> 0 | I111: =I57*I84 -> 0 | J111: =J57*J84 -> 0 | K111: =K57*K84 -> 0 | L111: =L57*L84 -> 0 | M111: =M57*M84 -> 0 | N111: =N57*N84 -> 0 | O111: =O57*O84 -> 0 | ... AZ111: =AZ57*AZ84 -> 0
D112: =IF(E58="<Select>","",E58) -> Diesel | E112: =E85 -> Real | F112: =Analysis_year -> 2025 | G112: =Inputs!G124 -> 0 | H112: =H58*H85 -> 0 | I112: =I58*I85 -> 0 | J112: =J58*J85 -> 0 | K112: =K58*K85 -> 0 | L112: =L58*L85 -> 0 | M112: =M58*M85 -> 0 | N112: =N58*N85 -> 0 | O112: =O58*O85 -> 0 | ... AZ112: =AZ58*AZ85 -> 0
...

Sheet Calculations
B1: Final Year
A2: Proposed Project | B2: =IF('Project description'!B13="Retrofit of existing asset",'Project description'!B14,YEAR('Project description'!B11)+'Project description'!B15) -> 2047
A3: Base Case | B3: =IF('Project description'!B13="Retrofit of existing asset",'Project description'!B14,YEAR('Project description'!B11)+'Project description'!B17) -> 2047
A5: Emissions
B6: Fuel type | C6: 2026 | D6: 2027 | E6: 2028 | F6: 2029 | G6: 2030 | H6: 2031 | I6: 2032 | J6: 2033 | K6: 2034 | L6: 2035 | M6: 2036 | N6: 2037 | O6: 2038 | P6: 2039 | Q6: 2040 | R6: 2041 | S6: 2042 | T6: 2043 | U6: 2044 | V6: 2045 | W6: 2046 | X6: 2047 | Y6: 2048 | Z6: 2049 | AA6: 2050 | AB6: 2051 | AC6: 2052 | AD6: 2053 | AE6: 2054 | AF6: 2055 | AG6: 2056 | AH6: 2057 | AI6: 2058 | AJ6: 2059 | AK6: 2060 | AL6: 2061 | AM6: 2062 | AN6: 2063 | AO6: 2064 | AP6: 2065 | AQ6: 2066 | AR6: 2067 | AS6: 2068 | AT6: 2069 | AU6: 2070
A7: PP | B7: Electricity | C7: =Inputs!H65*Data!M2 -> 8.0918911 | D7: =Inputs!I65*Data!N2 -> 338.32076 | E7: =Inputs!J65*Data!O2 -> 326.68902 | F7: =Inputs!K65*Data!P2 -> 306.20368 | G7: =Inputs!L65*Data!Q2 -> 274.51783 | H7: =Inputs!M65*Data!R2 -> 269.14981 | I7: =Inputs!N65*Data!S2 -> 275.11837 | J7: =Inputs!O65*Data!T2 -> 275.17089 | ... AU7: =Inputs!AZ65*Data!BE2 -> 0
B8: Natural Gas | C8: =Inputs!H66*Data!M3 -> 4004.84 | D8: =Inputs!I66*Data!N3 -> 0 | E8: =Inputs!J66*Data!O3 -> 0 | F8: =Inputs!K66*Data!P3 -> 0 | G8: =Inputs!L66*Data!Q3 -> 0 | H8: =Inputs!M66*Data!R3 -> 0 | I8: =Inputs!N66*Data!S3 -> 0 | J8: =Inputs!O66*Data!T3 -> 0 | ... AU8: =Inputs!AZ66*Data!BE3 -> 0
B9: Coal - sub bituminous | C9: =Inputs!H67*Data!M4 -> 0 | D9: =Inputs!I67*Data!N4 -> 0 | E9: =Inputs!J67*Data!O4 -> 0 | F9: =Inputs!K67*Data!P4 -> 0 | G9: =Inputs!L67*Data!Q4 -> 0 | H9: =Inputs!M67*Data!R4 -> 0 | I9: =Inputs!N67*Data!S4 -> 0 | J9: =Inputs!O67*Data!T4 -> 0 | ... AU9: =Inputs!AZ67*Data!BE4 -> 0
B10: Coal - bituminous | C10: =Inputs!H68*Data!M5 -> 0 | D10: =Inputs!I68*Data!N5 -> 0 | E10: =Inputs!J68*Data!O5 -> 0 | F10: =Inputs!K68*Data!P5 -> 0 | G10: =Inputs!L68*Data!Q5 -> 0 | H10: =Inputs!M68*Data!R5 -> 0 | I10: =Inputs!N68*Data!S5 -> 0 | J10: =Inputs!O68*Data!T5 -> 0 | ... AU10: =Inputs!AZ68*Data!BE5 -> 0
B11: Coal - lignite | C11: =Inputs!H69*Data!M6 -> 0 | D11: =Inputs!I69*Data!N6 -> 0 | E11: =Inputs!J69*Data!O6 -> 0 | F11: =Inputs!K69*Data!P6 -> 0 | G11: =Inputs!L69*Data!Q6 -> 0 | H11: =Inputs!M69*Data!R6 -> 0 | I11: =Inputs!N69*Data!S6 -> 0 | J11: =Inputs!O69*Data!T6 -> 0 | ... AU11: =Inputs!AZ69*Data!BE6 -> 0
B12: Diesel | C12: =Inputs!H70*Data!M7 -> 0 | D12: =Inputs!I70*Data!N7 -> 0 | E12: =Inputs!J70*Data!O7 -> 0 | F12: =Inputs!K70*Data!P7 -> 0 | G12: =Inputs!L70*Data!Q7 -> 0 | H12: =Inputs!M70*Data!R7 -> 0 | I12: =Inputs!N70*Data!S7 -> 0 | J12: =Inputs!O70*Data!T7 -> 0 | ... AU12: =Inputs!AZ70*Data!BE7 -> 0
B13: LPG | C13: =Inputs!H71*Data!M8 -> 0 | D13: =Inputs!I71*Data!N8 -> 0 | E13: =Inputs!J71*Data!O8 -> 0 | F13: =Inputs!K71*Data!P8 -> 0 | G13: =Inputs!L71*Data!Q8 -> 0 | H13: =Inputs!M71*Data!R8 -> 0 | I13: =Inputs!N71*Data!S8 -> 0 | J13: =Inputs!O71*Data!T8 -> 0 | ... AU13: =Inputs!AZ71*Data!BE8 -> 0
B14: Light fuel oil | C14: =Inputs!H72*Data!M9 -> 0 | D14: =Inputs!I72*Data!N9 -> 0 | E14: =Inputs!J72*Data!O9 -> 0 | F14: =Inputs!K72*Data!P9 -> 0 | G14: =Inputs!L72*Data!Q9 -> 0 | H14: =Inputs!M72*Data!R9 -> 0 | I14: =Inputs!N72*Data!S9 -> 0 | J14: =Inputs!O72*Data!T9 -> 0 | ... AU14: =Inputs!AZ72*Data!BE9 -> 0
B15: Heavy fuel oil | C15: =Inputs!H73*Data!M10 -> 0 | D15: =Inputs!I73*Data!N10 -> 0 | E15: =Inputs!J73*Data!O10 -> 0 | F15: =Inputs!K73*Data!P10 -> 0 | G15: =Inputs!L73*Data!Q10 -> 0 | H15: =Inputs!M73*Data!R10 -> 0 | I15: =Inputs!N73*Data!S10 -> 0 | J15: =Inputs!O73*Data!T10 -> 0 | ... AU15: =Inputs!AZ73*Data!BE10 -> 0
B16: Geothermal | C16: =Inputs!H74*Data!M11 -> 0 | D16: =Inputs!I74*Data!N11 -> 0 | E16: =Inputs!J74*Data!O11 -> 0 | F16: =Inputs!K74*Data!P11 -> 0 | G16: =Inputs!L74*Data!Q11 -> 0 | H16: =Inputs!M74*Data!R11 -> 0 | I16: =Inputs!N74*Data!S11 -> 0 | J16: =Inputs!O74*Data!T11 -> 0 | ... AU16: =Inputs!AZ74*Data!BE11 -> 0
B17: Wood or wood chips | C17: =Inputs!H75*Data!M12 -> 0 | D17: =Inputs!I75*Data!N12 -> 0 | E17: =Inputs!J75*Data!O12 -> 0 | F17: =Inputs!K75*Data!P12 -> 0 | G17: =Inputs!L75*Data!Q12 -> 0 | H17: =Inputs!M75*Data!R12 -> 0 | I17: =Inputs!N75*Data!S12 -> 0 | J17: =Inputs!O75*Data!T12 -> 0 | ... AU17: =Inputs!AZ75*Data!BE12 -> 0
A18: BC | B18: Electricity | C18: =Inputs!H78*Data!M2 -> 8.0918911 | D18: =Inputs!I78*Data!N2 -> 8.1052825 | E18: =Inputs!J78*Data!O2 -> 7.8266164 | F18: =Inputs!K78*Data!P2 -> 7.3358411 | G18: =Inputs!L78*Data!Q2 -> 6.5767307 | H18: =Inputs!M78*Data!R2 -> 6.448127 | I18: =Inputs!N78*Data!S2 -> 6.5911182 | J18: =Inputs!O78*Data!T2 -> 6.5923763 | ... AU18: =Inputs!AZ78*Data!BE2 -> 0
B19: Natural Gas | C19: =Inputs!H79*Data!M3 -> 4004.84 | D19: =Inputs!I79*Data!N3 -> 4004.84 | E19: =Inputs!J79*Data!O3 -> 4004.84 | F19: =Inputs!K79*Data!P3 -> 4004.84 | G19: =Inputs!L79*Data!Q3 -> 4004.84 | H19: =Inputs!M79*Data!R3 -> 4004.84 | I19: =Inputs!N79*Data!S3 -> 4004.84 | J19: =Inputs!O79*Data!T3 -> 4004.84 | ... AU19: =Inputs!AZ79*Data!BE3 -> 0
B20: Coal - sub bituminous | C20: =Inputs!H80*Data!M4 -> 0 | D20: =Inputs!I80*Data!N4 -> 0 | E20: =Inputs!J80*Data!O4 -> 0 | F20: =Inputs!K80*Data!P4 -> 0 | G20: =Inputs!L80*Data!Q4 -> 0 | H20: =Inputs!M80*Data!R4 -> 0 | I20: =Inputs!N80*Data!S4 -> 0 | J20: =Inputs!O80*Data!T4 -> 0 | ... AU20: =Inputs!AZ80*Data!BE4 -> 0
B21: Coal - bituminous | C21: =Inputs!H81*Data!M5 -> 0 | D21: =Inputs!I81*Data!N5 -> 0 | E21: =Inputs!J81*Data!O5 -> 0 | F21: =Inputs!K81*Data!P5 -> 0 | G21: =Inputs!L81*Data!Q5 -> 0 | H21: =Inputs!M81*Data!R5 -> 0 | I21: =Inputs!N81*Data!S5 -> 0 | J21: =Inputs!O81*Data!T5 -> 0 | ... AU21: =Inputs!AZ81*Data!BE5 -> 0
B22: Coal - lignite | C22: =Inputs!H82*Data!M6 -> 0 | D22: =Inputs!I82*Data!N6 -> 0 | E22: =Inputs!J82*Data!O6 -> 0 | F22: =Inputs!K82*Data!P6 -> 0 | G22: =Inputs!L82*Data!Q6 -> 0 | H22: =Inputs!M82*Data!R6 -> 0 | I22: =Inputs!N82*Data!S6 -> 0 | J22: =Inputs!O82*Data!T6 -> 0 | ... AU22: =Inputs!AZ82*Data!BE6 -> 0
B23: Diesel | C23: =Inputs!H83*Data!M7 -> 0 | D23: =Inputs!I83*Data!N7 -> 0 | E23: =Inputs!J83*Data!O7 -> 0 | F23: =Inputs!K83*Data!P7 -> 0 | G23: =Inputs!L83*Data!Q7 -> 0 | H23: =Inputs!M83*Data!R7 -> 0 | I23: =Inputs!N83*Data!S7 -> 0 | J23: =Inputs!O83*Data!T7 -> 0 | ... AU23: =Inputs!AZ83*Data!BE7 -> 0
B24: LPG | C24: =Inputs!H84*Data!M8 -> 0 | D24: =Inputs!I84*Data!N8 -> 0 | E24: =Inputs!J84*Data!O8 -> 0 | F24: =Inputs!K84*Data!P8 -> 0 | G24: =Inputs!L84*Data!Q8 -> 0 | H24: =Inputs!M84*Data!R8 -> 0 | I24: =Inputs!N84*Data!S8 -> 0 | J24: =Inputs!O84*Data!T8 -> 0 | ... AU24: =Inputs!AZ84*Data!BE8 -> 0
B25: Light fuel oil | C25: =Inputs!H85*Data!M9 -> 0 | D25: =Inputs!I85*Data!N9 -> 0 | E25: =Inputs!J85*Data!O9 -> 0 | F25: =Inputs!K85*Data!P9 -> 0 | G25: =Inputs!L85*Data!Q9 -> 0 | H25: =Inputs!M85*Data!R9 -> 0 | I25: =Inputs!N85*Data!S9 -> 0 | J25: =Inputs!O85*Data!T9 -> 0 | ... AU25: =Inputs!AZ85*Data!BE9 -> 0
B26: Heavy fuel oil | C26: =Inputs!H86*Data!M10 -> 0 | D26: =Inputs!I86*Data!N10 -> 0 | E26: =Inputs!J86*Data!O10 -> 0 | F26: =Inputs!K86*Data!P10 -> 0 | G26: =Inputs!L86*Data!Q10 -> 0 | H26: =Inputs!M86*Data!R10 -> 0 | I26: =Inputs!N86*Data!S10 -> 0 | J26: =Inputs!O86*Data!T10 -> 0 | ... AU26: =Inputs!AZ86*Data!BE10 -> 0
B27: Geothermal | C27: =Inputs!H87*Data!M11 -> 0 | D27: =Inputs!I87*Data!N11 -> 0 | E27: =Inputs!J87*Data!O11 -> 0 | F27: =Inputs!K87*Data!P11 -> 0 | G27: =Inputs!L87*Data!Q11 -> 0 | H27: =Inputs!M87*Data!R11 -> 0 | I27: =Inputs!N87*Data!S11 -> 0 | J27: =Inputs!O87*Data!T11 -> 0 | ... AU27: =Inputs!AZ87*Data!BE11 -> 0
B28: Wood or wood chips | C28: =Inputs!H88*Data!M12 -> 0 | D28: =Inputs!I88*Data!N12 -> 0 | E28: =Inputs!J88*Data!O12 -> 0 | F28: =Inputs!K88*Data!P12 -> 0 | G28: =Inputs!L88*Data!Q12 -> 0 | H28: =Inputs!M88*Data!R12 -> 0 | I28: =Inputs!N88*Data!S12 -> 0 | J28: =Inputs!O88*Data!T12 -> 0 | ... AU28: =Inputs!AZ88*Data!BE12 -> 0
A29: Total PP | C29: =SUM(C7:C17) -> 4012.9319 | D29: =SUM(D7:D17) -> 338.32076 | E29: =SUM(E7:E17) -> 326.68902 | F29: =SUM(F7:F17) -> 306.20368 | G29: =SUM(G7:G17) -> 274.51783 | H29: =SUM(H7:H17) -> 269.14981 | I29: =SUM(I7:I17) -> 275.11837 | J29: =SUM(J7:J17) -> 275.17089 | ... AU29: =SUM(AU7:AU17) -> 0
A30: Total BC | C30: =SUM(C18:C28) -> 4012.9319 | D30: =SUM(D18:D28) -> 4012.9453 | E30: =SUM(E18:E28) -> 4012.6666 | F30: =SUM(F18:F28) -> 4012.1758 | G30: =SUM(G18:G28) -> 4011.4167 | H30: =SUM(H18:H28) -> 4011.2881 | I30: =SUM(I18:I28) -> 4011.4311 | J30: =SUM(J18:J28) -> 4011.4324 | ... AU30: =SUM(AU18:AU28) -> 0
A32: Fuel costs without ETS costs
B33: Fuel type
A34: PP | B34: =B7 -> Electricity | C34: =IF(Inputs!$E92="Real",Inputs!H119,Inputs!H119/Inputs!H$10)-C7*INDEX(Data!$L$26:$BE$26,MATCH(C$6,Data!$L$17:$BE$17,0)) -> 28575.827 | D34: =IF(Inputs!$E92="Real",Inputs!I119,Inputs!I119/Inputs!I$10)-D7*INDEX(Data!$L$26:$BE$26,MATCH(D$6,Data!$L$17:$BE$17,0)) -> 1187603.9 | E34: =IF(Inputs!$E92="Real",Inputs!J119,Inputs!J119/Inputs!J$10)-E7*INDEX(Data!$L$26:$BE$26,MATCH(E$6,Data!$L$17:$BE$17,0)) -> 1184925.3 | F34: =IF(Inputs!$E92="Real",Inputs!K119,Inputs!K119/Inputs!K$10)-F7*INDEX(Data!$L$26:$BE$26,MATCH(F$6,Data!$L$17:$BE$17,0)) -> 1184246 | G34: =IF(Inputs!$E92="Real",Inputs!L119,Inputs!L119/Inputs!L$10)-G7*INDEX(Data!$L$26:$BE$26,MATCH(G$6,Data!$L$17:$BE$17,0)) -> 1187162.5 | H34: =IF(Inputs!$E92="Real",Inputs!M119,Inputs!M119/Inputs!M$10)-H7*INDEX(Data!$L$26:$BE$26,MATCH(H$6,Data!$L$17:$BE$17,0)) -> 1186550.6 | I34: =IF(Inputs!$E92="Real",Inputs!N119,Inputs!N119/Inputs!N$10)-I7*INDEX(Data!$L$26:$BE$26,MATCH(I$6,Data!$L$17:$BE$17,0)) -> 1183168.5 | J34: =IF(Inputs!$E92="Real",Inputs!O119,Inputs!O119/Inputs!O$10)-J7*INDEX(Data!$L$26:$BE$26,MATCH(J$6,Data!$L$17:$BE$17,0)) -> 1180953.9 | ... AU34: =IF(Inputs!$E92="Real",Inputs!AZ119,Inputs!AZ119/Inputs!AZ$10)-AU7*INDEX(Data!$L$26:$BE$26,MATCH(AU$6,Data!$L$17:$BE$17,0)) -> 0
B35: =B14 -> Light fuel oil | C35: =IF(Inputs!$E93="Real",Inputs!H127,Inputs!H127/Inputs!H$10)-C14*INDEX(Data!$L$26:$BE$26,MATCH(C$6,Data!$L$17:$BE$17,0)) -> 0 | D35: =IF(Inputs!$E93="Real",Inputs!I127,Inputs!I127/Inputs!I$10)-D14*INDEX(Data!$L$26:$BE$26,MATCH(D$6,Data!$L$17:$BE$17,0)) -> 0 | E35: =IF(Inputs!$E93="Real",Inputs!J127,Inputs!J127/Inputs!J$10)-E14*INDEX(Data!$L$26:$BE$26,MATCH(E$6,Data!$L$17:$BE$17,0)) -> 0 | F35: =IF(Inputs!$E93="Real",Inputs!K127,Inputs!K127/Inputs!K$10)-F14*INDEX(Data!$L$26:$BE$26,MATCH(F$6,Data!$L$17:$BE$17,0)) -> 0 | G35: =IF(Inputs!$E93="Real",Inputs!L127,Inputs!L127/Inputs!L$10)-G14*INDEX(Data!$L$26:$BE$26,MATCH(G$6,Data!$L$17:$BE$17,0)) -> 0 | H35: =IF(Inputs!$E93="Real",Inputs!M127,Inputs!M127/Inputs!M$10)-H14*INDEX(Data!$L$26:$BE$26,MATCH(H$6,Data!$L$17:$BE$17,0)) -> 0 | I35: =IF(Inputs!$E93="Real",Inputs!N127,Inputs!N127/Inputs!N$10)-I14*INDEX(Data!$L$26:$BE$26,MATCH(I$6,Data!$L$17:$BE$17,0)) -> 0 | J35: =IF(Inputs!$E93="Real",Inputs!O127,Inputs!O127/Inputs!O$10)-J14*INDEX(Data!$L$26:$BE$26,MATCH(J$6,Data!$L$17:$BE$17,0)) -> 0 | ... AU35: =IF(Inputs!$E93="Real",Inputs!AZ127,Inputs!AZ127/Inputs!AZ$10)-AU14*INDEX(Data!$L$26:$BE$26,MATCH(AU$6,Data!$L$17:$BE$17,0)) -> 0
B36: =B15 -> Heavy fuel oil | C36: =IF(Inputs!$E94="Real",Inputs!H128,Inputs!H128/Inputs!H$10)-C15*INDEX(Data!$L$26:$BE$26,MATCH(C$6,Data!$L$17:$BE$17,0)) -> 0 | D36: =IF(Inputs!$E94="Real",Inputs!I128,Inputs!I128/Inputs!I$10)-D15*INDEX(Data!$L$26:$BE$26,MATCH(D$6,Data!$L$17:$BE$17,0)) -> 0 | E36: =IF(Inputs!$E94="Real",Inputs!J128,Inputs!J128/Inputs!J$10)-E15*INDEX(Data!$L$26:$BE$26,MATCH(E$6,Data!$L$17:$BE$17,0)) -> 0 | F36: =IF(Inputs!$E94="Real",Inputs!K128,Inputs!K128/Inputs!K$10)-F15*INDEX(Data!$L$26:$BE$26,MATCH(F$6,Data!$L$17:$BE$17,0)) -> 0 | G36: =IF(Inputs!$E94="Real",Inputs!L128,Inputs!L128/Inputs!L$10)-G15*INDEX(Data!$L$26:$BE$26,MATCH(G$6,Data!$L$17:$BE$17,0)) -> 0 | H36: =IF(Inputs!$E94="Real",Inputs!M128,Inputs!M128/Inputs!M$10)-H15*INDEX(Data!$L$26:$BE$26,MATCH(H$6,Data!$L$17:$BE$17,0)) -> 0 | I36: =IF(Inputs!$E94="Real",Inputs!N128,Inputs!N128/Inputs!N$10)-I15*INDEX(Data!$L$26:$BE$26,MATCH(I$6,Data!$L$17:$BE$17,0)) -> 0 | J36: =IF(Inputs!$E94="Real",Inputs!O128,Inputs!O128/Inputs!O$10)-J15*INDEX(Data!$L$26:$BE$26,MATCH(J$6,Data!$L$17:$BE$17,0)) -> 0 | ... AU36: =IF(Inputs!$E94="Real",Inputs!AZ128,Inputs!AZ128/Inputs!AZ$10)-AU15*INDEX(Data!$L$26:$BE$26,MATCH(AU$6,Data!$L$17:$BE$17,0)) -> 0
B37: =B16 -> Geothermal | C37: =IF(Inputs!$E102="Real",Inputs!H129,Inputs!H129/Inputs!H$10)-C16*INDEX(Data!$L$26:$BE$26,MATCH(C$6,Data!$L$17:$BE$17,0)) -> 0 | D37: =IF(Inputs!$E102="Real",Inputs!I129,Inputs!I129/Inputs!I$10)-D16*INDEX(Data!$L$26:$BE$26,MATCH(D$6,Data!$L$17:$BE$17,0)) -> 0 | E37: =IF(Inputs!$E102="Real",Inputs!J129,Inputs!J129/Inputs!J$10)-E16*INDEX(Data!$L$26:$BE$26,MATCH(E$6,Data!$L$17:$BE$17,0)) -> 0 | F37: =IF(Inputs!$E102="Real",Inputs!K129,Inputs!K129/Inputs!K$10)-F16*INDEX(Data!$L$26:$BE$26,MATCH(F$6,Data!$L$17:$BE$17,0)) -> 0 | G37: =IF(Inputs!$E102="Real",Inputs!L129,Inputs!L129/Inputs!L$10)-G16*INDEX(Data!$L$26:$BE$26,MATCH(G$6,Data!$L$17:$BE$17,0)) -> 0 | H37: =IF(Inputs!$E102="Real",Inputs!M129,Inputs!M129/Inputs!M$10)-H16*INDEX(Data!$L$26:$BE$26,MATCH(H$6,Data!$L$17:$BE$17,0)) -> 0 | I37: =IF(Inputs!$E102="Real",Inputs!N129,Inputs!N129/Inputs!N$10)-I16*INDEX(Data!$L$26:$BE$26,MATCH(I$6,Data!$L$17:$BE$17,0)) -> 0 | J37: =IF(Inputs!$E102="Real",Inputs!O129,Inputs!O129/Inputs!O$10)-J16*INDEX(Data!$L$26:$BE$26,MATCH(J$6,Data!$L$17:$BE$17,0)) -> 0 | ... AU37: =IF(Inputs!$E102="Real",Inputs!AZ129,Inputs!AZ129/Inputs!AZ$10)-AU16*INDEX(Data!$L$26:$BE$26,MATCH(AU$6,Data!$L$17:$BE$17,0)) -> 0
B38: =B17 -> Wood or wood chips | C38: =IF(Inputs!$E103="Real",Inputs!H130,Inputs!H130/Inputs!H$10)-C17*INDEX(Data!$L$26:$BE$26,MATCH(C$6,Data!$L$17:$BE$17,0)) -> 745410.3 | D38: =IF(Inputs!$E103="Real",Inputs!I130,Inputs!I130/Inputs!I$10)-D17*INDEX(Data!$L$26:$BE$26,MATCH(D$6,Data!$L$17:$BE$17,0)) -> 1304358.7 | E38: =IF(Inputs!$E103="Real",Inputs!J130,Inputs!J130/Inputs!J$10)-E17*INDEX(Data!$L$26:$BE$26,MATCH(E$6,Data!$L$17:$BE$17,0)) -> 1330576.3 | F38: =IF(Inputs!$E103="Real",Inputs!K130,Inputs!K130/Inputs!K$10)-F17*INDEX(Data!$L$26:$BE$26,MATCH(F$6,Data!$L$17:$BE$17,0)) -> 1357320.8 | G38: =IF(Inputs!$E103="Real",Inputs!L130,Inputs!L130/Inputs!L$10)-G17*INDEX(Data!$L$26:$BE$26,MATCH(G$6,Data!$L$17:$BE$17,0)) -> 1384603 | H38: =IF(Inputs!$E103="Real",Inputs!M130,Inputs!M130/Inputs!M$10)-H17*INDEX(Data!$L$26:$BE$26,MATCH(H$6,Data!$L$17:$BE$17,0)) -> 1412433.5 | I38: =IF(Inputs!$E103="Real",Inputs!N130,Inputs!N130/Inputs!N$10)-I17*INDEX(Data!$L$26:$BE$26,MATCH(I$6,Data!$L$17:$BE$17,0)) -> 1440823.4 | J38: =IF(Inputs!$E103="Real",Inputs!O130,Inputs!O130/Inputs!O$10)-J17*INDEX(Data!$L$26:$BE$26,MATCH(J$6,Data!$L$17:$BE$17,0)) -> 1469784 | ... AU38: =IF(Inputs!$E103="Real",Inputs!AZ130,Inputs!AZ130/Inputs!AZ$10)-AU17*INDEX(Data!$L$26:$BE$26,MATCH(AU$6,Data!$L$17:$BE$17,0)) -> 0
A39: BC | B39: =B18 -> Electricity | C39: =IF(Inputs!$E105="Real",Inputs!H134,Inputs!H134/Inputs!H$10)-C18*INDEX(Data!$L$26:$BE$26,MATCH(C$6,Data!$L$17:$BE$17,0)) -> 28575.827 | D39: =IF(Inputs!$E105="Real",Inputs!I134,Inputs!I134/Inputs!I$10)-D18*INDEX(Data!$L$26:$BE$26,MATCH(D$6,Data!$L$17:$BE$17,0)) -> 28451.891 | E39: =IF(Inputs!$E105="Real",Inputs!J134,Inputs!J134/Inputs!J$10)-E18*INDEX(Data!$L$26:$BE$26,MATCH(E$6,Data!$L$17:$BE$17,0)) -> 28387.717 | F39: =IF(Inputs!$E105="Real",Inputs!K134,Inputs!K134/Inputs!K$10)-F18*INDEX(Data!$L$26:$BE$26,MATCH(F$6,Data!$L$17:$BE$17,0)) -> 28371.443 | G39: =IF(Inputs!$E105="Real",Inputs!L134,Inputs!L134/Inputs!L$10)-G18*INDEX(Data!$L$26:$BE$26,MATCH(G$6,Data!$L$17:$BE$17,0)) -> 28441.315 | H39: =IF(Inputs!$E105="Real",Inputs!M134,Inputs!M134/Inputs!M$10)-H18*INDEX(Data!$L$26:$BE$26,MATCH(H$6,Data!$L$17:$BE$17,0)) -> 28426.657 | I39: =IF(Inputs!$E105="Real",Inputs!N134,Inputs!N134/Inputs!N$10)-I18*INDEX(Data!$L$26:$BE$26,MATCH(I$6,Data!$L$17:$BE$17,0)) -> 28345.629 | J39: =IF(Inputs!$E105="Real",Inputs!O134,Inputs!O134/Inputs!O$10)-J18*INDEX(Data!$L$26:$BE$26,MATCH(J$6,Data!$L$17:$BE$17,0)) -> 28292.575 | ... AU39: =IF(Inputs!$E105="Real",Inputs!AZ134,Inputs!AZ134/Inputs!AZ$10)-AU18*INDEX(Data!$L$26:$BE$26,MATCH(AU$6,Data!$L$17:$BE$17,0)) -> 0
B40: =B25 -> Light fuel oil | C40: =IF(Inputs!$E113="Real",Inputs!H142,Inputs!H142/Inputs!H$10)-C25*INDEX(Data!$L$26:$BE$26,MATCH(C$6,Data!$L$17:$BE$17,0)) -> 0 | D40: =IF(Inputs!$E113="Real",Inputs!I142,Inputs!I142/Inputs!I$10)-D25*INDEX(Data!$L$26:$BE$26,MATCH(D$6,Data!$L$17:$BE$17,0)) -> 0 | E40: =IF(Inputs!$E113="Real",Inputs!J142,Inputs!J142/Inputs!J$10)-E25*INDEX(Data!$L$26:$BE$26,MATCH(E$6,Data!$L$17:$BE$17,0)) -> 0 | F40: =IF(Inputs!$E113="Real",Inputs!K142,Inputs!K142/Inputs!K$10)-F25*INDEX(Data!$L$26:$BE$26,MATCH(F$6,Data!$L$17:$BE$17,0)) -> 0 | G40: =IF(Inputs!$E113="Real",Inputs!L142,Inputs!L142/Inputs!L$10)-G25*INDEX(Data!$L$26:$BE$26,MATCH(G$6,Data!$L$17:$BE$17,0)) -> 0 | H40: =IF(Inputs!$E113="Real",Inputs!M142,Inputs!M142/Inputs!M$10)-H25*INDEX(Data!$L$26:$BE$26,MATCH(H$6,Data!$L$17:$BE$17,0)) -> 0 | I40: =IF(Inputs!$E113="Real",Inputs!N142,Inputs!N142/Inputs!N$10)-I25*INDEX(Data!$L$26:$BE$26,MATCH(I$6,Data!$L$17:$BE$17,0)) -> 0 | J40: =IF(Inputs!$E113="Real",Inputs!O142,Inputs!O142/Inputs!O$10)-J25*INDEX(Data!$L$26:$BE$26,MATCH(J$6,Data!$L$17:$BE$17,0)) -> 0 | ... AU40: =IF(Inputs!$E113="Real",Inputs!AZ142,Inputs!AZ142/Inputs!AZ$10)-AU25*INDEX(Data!$L$26:$BE$26,MATCH(AU$6,Data!$L$17:$BE$17,0)) -> 0
B41: =B26 -> Heavy fuel oil | C41: =IF(Inputs!$E114="Real",Inputs!H143,Inputs!H143/Inputs!H$10)-C26*INDEX(Data!$L$26:$BE$26,MATCH(C$6,Data!$L$17:$BE$17,0)) -> 0 | D41: =IF(Inputs!$E114="Real",Inputs!I143,Inputs!I143/Inputs!I$10)-D26*INDEX(Data!$L$26:$BE$26,MATCH(D$6,Data!$L$17:$BE$17,0)) -> 0 | E41: =IF(Inputs!$E114="Real",Inputs!J143,Inputs!J143/Inputs!J$10)-E26*INDEX(Data!$L$26:$BE$26,MATCH(E$6,Data!$L$17:$BE$17,0)) -> 0 | F41: =IF(Inputs!$E114="Real",Inputs!K143,Inputs!K143/Inputs!K$10)-F26*INDEX(Data!$L$26:$BE$26,MATCH(F$6,Data!$L$17:$BE$17,0)) -> 0 | G41: =IF(Inputs!$E114="Real",Inputs!L143,Inputs!L143/Inputs!L$10)-G26*INDEX(Data!$L$26:$BE$26,MATCH(G$6,Data!$L$17:$BE$17,0)) -> 0 | H41: =IF(Inputs!$E114="Real",Inputs!M143,Inputs!M143/Inputs!M$10)-H26*INDEX(Data!$L$26:$BE$26,MATCH(H$6,Data!$L$17:$BE$17,0)) -> 0 | I41: =IF(Inputs!$E114="Real",Inputs!N143,Inputs!N143/Inputs!N$10)-I26*INDEX(Data!$L$26:$BE$26,MATCH(I$6,Data!$L$17:$BE$17,0)) -> 0 | J41: =IF(Inputs!$E114="Real",Inputs!O143,Inputs!O143/Inputs!O$10)-J26*INDEX(Data!$L$26:$BE$26,MATCH(J$6,Data!$L$17:$BE$17,0)) -> 0 | ... AU41: =IF(Inputs!$E114="Real",Inputs!AZ143,Inputs!AZ143/Inputs!AZ$10)-AU26*INDEX(Data!$L$26:$BE$26,MATCH(AU$6,Data!$L$17:$BE$17,0)) -> 0
B42: =B27 -> Geothermal | C42: =IF(Inputs!$E115="Real",Inputs!H144,Inputs!H144/Inputs!H$10)-C27*INDEX(Data!$L$26:$BE$26,MATCH(C$6,Data!$L$17:$BE$17,0)) -> 0 | D42: =IF(Inputs!$E115="Real",Inputs!I144,Inputs!I144/Inputs!I$10)-D27*INDEX(Data!$L$26:$BE$26,MATCH(D$6,Data!$L$17:$BE$17,0)) -> 0 | E42: =IF(Inputs!$E115="Real",Inputs!J144,Inputs!J144/Inputs!J$10)-E27*INDEX(Data!$L$26:$BE$26,MATCH(E$6,Data!$L$17:$BE$17,0)) -> 0 | F42: =IF(Inputs!$E115="Real",Inputs!K144,Inputs!K144/Inputs!K$10)-F27*INDEX(Data!$L$26:$BE$26,MATCH(F$6,Data!$L$17:$BE$17,0)) -> 0 | G42: =IF(Inputs!$E115="Real",Inputs!L144,Inputs!L144/Inputs!L$10)-G27*INDEX(Data!$L$26:$BE$26,MATCH(G$6,Data!$L$17:$BE$17,0)) -> 0 | H42: =IF(Inputs!$E115="Real",Inputs!M144,Inputs!M144/Inputs!M$10)-H27*INDEX(Data!$L$26:$BE$26,MATCH(H$6,Data!$L$17:$BE$17,0)) -> 0 | I42: =IF(Inputs!$E115="Real",Inputs!N144,Inputs!N144/Inputs!N$10)-I27*INDEX(Data!$L$26:$BE$26,MATCH(I$6,Data!$L$17:$BE$17,0)) -> 0 | J42: =IF(Inputs!$E115="Real",Inputs!O144,Inputs!O144/Inputs!O$10)-J27*INDEX(Data!$L$26:$BE$26,MATCH(J$6,Data!$L$17:$BE$17,0)) -> 0 | ... AU42: =IF(Inputs!$E115="Real",Inputs!AZ144,Inputs!AZ144/Inputs!AZ$10)-AU27*INDEX(Data!$L$26:$BE$26,MATCH(AU$6,Data!$L$17:$BE$17,0)) -> 0
A44: Shadow costs
A45: PP | C45: =C29*Data!M24 -> 529707.01 | D45: =D29*Data!N24 -> 48379.868 | E45: =E29*Data!O24 -> 50636.799 | F45: =F29*Data!P24 -> 50829.811 | G45: =G29*Data!Q24 -> 48864.173 | H45: =H29*Data!R24 -> 49254.414 | I45: =I29*Data!S24 -> 51997.372 | J45: =J29*Data!T24 -> 53383.152 | ... AU45: =AU29*Data!BE24 -> 0
A46: BC | C46: =C30*Data!M24 -> 529707.01 | D46: =D30*Data!N24 -> 573851.18 | E46: =E30*Data!O24 -> 621963.33 | F46: =F30*Data!P24 -> 666021.19 | G46: =G30*Data!Q24 -> 714032.18 | H46: =H30*Data!R24 -> 734065.73 | I46: =I30*Data!S24 -> 758160.48 | J46: =J30*Data!T24 -> 778217.88 | ... AU46: =AU30*Data!BE24 -> 0
A47: ETS costs
A48: PP | C48: =(C7/Data!M2*Data!M19+SUM(Calculations!C8:C17))*Data!M23 -> 284780.69 | D48: =(D7/Data!N2*Data!N19+SUM(Calculations!D8:D17))*Data!N23 -> 200987.93 | E48: =(E7/Data!O2*Data!O19+SUM(Calculations!E8:E17))*Data!O23 -> 208119.5 | F48: =(F7/Data!P2*Data!P19+SUM(Calculations!F8:F17))*Data!P23 -> 198210.23 | G48: =(G7/Data!Q2*Data!Q19+SUM(Calculations!G8:G17))*Data!Q23 -> 188298.2 | H48: =(H7/Data!R2*Data!R19+SUM(Calculations!H8:H17))*Data!R23 -> 178388.93 | I48: =(I7/Data!S2*Data!S19+SUM(Calculations!I8:I17))*Data!S23 -> 168476.89 | J48: =(J7/Data!T2*Data!T19+SUM(Calculations!J8:J17))*Data!T23 -> 158567.63 | ... AU48: =(AU7/Data!BE2*Data!BE19+SUM(Calculations!AU8:AU17))*Data!BE23 -> 0
A49: BC | C49: =(C18/Data!M2*Data!M19+SUM(C19:C28))*Data!M23 -> 284780.69 | D49: =(D18/Data!N2*Data!N19+SUM(D19:D28))*Data!N23 -> 294885.71 | E49: =(E18/Data!O2*Data!O19+SUM(E19:E28))*Data!O23 -> 305349 | F49: =(F18/Data!P2*Data!P19+SUM(F19:F28))*Data!P23 -> 290810.32 | G49: =(G18/Data!Q2*Data!Q19+SUM(G19:G28))*Data!Q23 -> 276267.56 | H49: =(H18/Data!R2*Data!R19+SUM(H19:H28))*Data!R23 -> 261728.88 | I49: =(I18/Data!S2*Data!S19+SUM(I19:I28))*Data!S23 -> 247186.12 | J49: =(J18/Data!T2*Data!T19+SUM(J19:J28))*Data!T23 -> 232647.44 | ... AU49: =(AU18/Data!BE2*Data!BE19+SUM(AU19:AU28))*Data!BE23 -> 0
A51: Summary - National Perspective | C51: 2026 | D51: 2027 | E51: 2028 | F51: 2029 | G51: 2030 | H51: 2031 | I51: 2032 | J51: 2033 | K51: 2034 | L51: 2035 | M51: 2036 | N51: 2037 | O51: 2038 | P51: 2039 | Q51: 2040 | R51: 2041 | S51: 2042 | T51: 2043 | U51: 2044 | V51: 2045 | W51: 2046 | X51: 2047 | Y51: 2048 | Z51: 2049 | AA51: 2050 | AB51: 2051 | AC51: 2052 | AD51: 2053 | AE51: 2054 | AF51: 2055 | AG51: 2056 | AH51: 2057 | AI51: 2058 | AJ51: 2059 | AK51: 2060 | AL51: 2061 | AM51: 2062 | AN51: 2063 | AO51: 2064 | AP51: 2065 | AQ51: 2066 | AR51: 2067 | AS51: 2068 | AT51: 2069 | AU51: 2070
A52: PP | B52: Capex | C52: ='Real values'!H17 -> 1253537.8 | D52: ='Real values'!I17 -> 783408.67 | E52: ='Real values'!J17 -> 0 | F52: ='Real values'!K17 -> 0 | G52: ='Real values'!L17 -> 0 | H52: ='Real values'!M17 -> 0 | I52: ='Real values'!N17 -> 0 | J52: ='Real values'!O17 -> 0 | ... AU52: ='Real values'!AZ17 -> 0
B53: Non-fuel opex | C53: ='Real values'!H39 -> 127312.43 | D53: ='Real values'!I39 -> 124803.88 | E53: ='Real values'!J39 -> 112933.61 | F53: ='Real values'!K39 -> 110708.37 | G53: ='Real values'!L39 -> 108526.98 | H53: ='Real values'!M39 -> 106388.57 | I53: ='Real values'!N39 -> 104292.3 | J53: ='Real values'!O39 -> 102237.33 | ... AU53: ='Real values'!AZ39 -> 0
B54: Fuel opex | C54: ='Real values'!H118 -> 719617.4 | D54: ='Real values'!I118 -> 782692.66 | E54: ='Real values'!J118 -> 733993.82 | F54: ='Real values'!K118 -> 701879.79 | G54: ='Real values'!L118 -> 669756.95 | H54: ='Real values'!M118 -> 637628.99 | I54: ='Real values'!N118 -> 602003.24 | J54: ='Real values'!O118 -> 571262.1 | ... AU54: ='Real values'!AZ118 -> 0
B55: Emission costs | C55: =C45 -> 529707.01 | D55: =D45 -> 48379.868 | E55: =E45 -> 50636.799 | F55: =F45 -> 50829.811 | G55: =G45 -> 48864.173 | H55: =H45 -> 49254.414 | I55: =I45 -> 51997.372 | J55: =J45 -> 53383.152 | ... AU55: =AU45 -> 0
B56: Total costs | C56: =SUM(C52:C55) -> 2630174.7 | D56: =SUM(D52:D55) -> 1739285.1 | E56: =SUM(E52:E55) -> 897564.23 | F56: =SUM(F52:F55) -> 863417.97 | G56: =SUM(G52:G55) -> 827148.11 | H56: =SUM(H52:H55) -> 793271.97 | I56: =SUM(I52:I55) -> 758292.91 | J56: =SUM(J52:J55) -> 726882.58 | ... AU56: =SUM(AU52:AU55) -> 0
B57: Revenues | C57: {=Revenue_PP[2026]} -> 979326.42 | D57: {=Revenue_PP[2027]} -> 1056032.8 | E57: {=Revenue_PP[2028]} -> 1035224.8 | F57: {=Revenue_PP[2029]} -> 1014826.8 | G57: {=Revenue_PP[2030]} -> 994830.67 | H57: {=Revenue_PP[2031]} -> 975228.57 | I57: {=Revenue_PP[2032]} -> 956012.72 | J57: {=Revenue_PP[2033]} -> 937175.49 | K57: {=Revenue_PP[2034]} -> 918709.43 | L57: {=Revenue_PP[2035]} -> 900607.23 | M57: {=Revenue_PP[2036]} -> 882861.71 | N57: {=Revenue_PP[2037]} -> 865465.84 | O57: {=Revenue_PP[2038]} -> 848412.75 | P57: {=Revenue_PP[2039]} -> 831695.66 | Q57: {=Revenue_PP[2040]} -> 815307.97 | R57: {=Revenue_PP[2041]} -> 799243.19 | S57: {=Revenue_PP[2042]} -> 783494.94 | T57: {=Revenue_PP[2043]} -> 768056.99 | U57: {=Revenue_PP[2044]} -> 752923.24 | V57: {=Revenue_PP[2045]} -> 738087.67 | W57: {=Revenue_PP[2046]} -> 723544.43 | X57: {=Revenue_PP[2047]} -> 709287.75 | Y57: {=Revenue_PP[2048]} -> 0 | Z57: {=Revenue_PP[2049]} -> 0 | AA57: {=Revenue_PP[2050]} -> 0 | AB57: {=Revenue_PP[2051]} -> 0 | AC57: {=Revenue_PP[2052]} -> 0 | AD57: {=Revenue_PP[2053]} -> 0 | AE57: {=Revenue_PP[2054]} -> 0 | AF57: {=Revenue_PP[2055]} -> 0 | AG57: {=Revenue_PP[2056]} -> 0 | AH57: {=Revenue_PP[2057]} -> 0 | AI57: {=Revenue_PP[2058]} -> 0 | AJ57: {=Revenue_PP[2059]} -> 0 | AK57: {=Revenue_PP[2060]} -> 0 | AL57: {=Revenue_PP[2061]} -> 0 | AM57: {=Revenue_PP[2062]} -> 0 | AN57: {=Revenue_PP[2063]} -> 0 | AO57: {=Revenue_PP[2064]} -> 0 | AP57: {=Revenue_PP[2065]} -> 0 | AQ57: {=Revenue_PP[2066]} -> 0 | AR57: {=Revenue_PP[2067]} -> 0 | AS57: {=Revenue_PP[2068]} -> 0 | AT57: {=Revenue_PP[2069]} -> 0 | AU57: {=Revenue_PP[2070]} -> 0
B58: Net | C58: =C57-C56 -> -1650848.2 | D58: =D57-D56 -> -683252.27 | E58: =E57-E56 -> 137660.55 | F58: =F57-F56 -> 151408.79 | G58: =G57-G56 -> 167682.56 | H58: =H57-H56 -> 181956.6 | I58: =I57-I56 -> 197719.81 | J58: =J57-J56 -> 210292.92 | ... AU58: =AU57-AU56 -> 0
A59: BC | B59: Capex | C59: ='Real values'!H27 -> 0 | D59: ='Real values'!I27 -> 0 | E59: ='Real values'!J27 -> 0 | F59: ='Real values'!K27 -> 0 | G59: ='Real values'!L27 -> 0 | H59: ='Real values'!M27 -> 0 | I59: ='Real values'!N27 -> 0 | J59: ='Real values'!O27 -> 0 | ... AU59: ='Real values'!AZ27 -> 0
B60: =B53 -> Non-fuel opex | C60: ='Real values'!H49 -> 186072.02 | D60: ='Real values'!I49 -> 182405.67 | E60: ='Real values'!J49 -> 178811.55 | F60: ='Real values'!K49 -> 175288.26 | G60: ='Real values'!L49 -> 171834.39 | H60: ='Real values'!M49 -> 168448.57 | I60: ='Real values'!N49 -> 165129.47 | J60: ='Real values'!O49 -> 161875.77 | ... AU60: ='Real values'!AZ49 -> 0
B61: =B54 -> Fuel opex | C61: ='Real values'!H132 -> 719617.4 | D61: ='Real values'!I132 -> 718751.27 | E61: ='Real values'!J132 -> 717584.58 | F61: ='Real values'!K132 -> 716815.21 | G61: ='Real values'!L132 -> 716045.63 | H61: ='Real values'!M132 -> 715275.93 | I61: ='Real values'!N132 -> 714422.43 | J61: ='Real values'!O132 -> 713685.95 | ... AU61: ='Real values'!AZ132 -> 0
B62: Emission costs | C62: =C46 -> 529707.01 | D62: =D46 -> 573851.18 | E62: =E46 -> 621963.33 | F62: =F46 -> 666021.19 | G62: =G46 -> 714032.18 | H62: =H46 -> 734065.73 | I62: =I46 -> 758160.48 | J62: =J46 -> 778217.88 | ... AU62: =AU46 -> 0
B63: Total costs | C63: =SUM(C59:C62) -> 1435396.4 | D63: =SUM(D59:D62) -> 1475008.1 | E63: =SUM(E59:E62) -> 1518359.5 | F63: =SUM(F59:F62) -> 1558124.7 | G63: =SUM(G59:G62) -> 1601912.2 | H63: =SUM(H59:H62) -> 1617790.2 | I63: =SUM(I59:I62) -> 1637712.4 | J63: =SUM(J59:J62) -> 1653779.6 | ... AU63: =SUM(AU59:AU62) -> 0
B64: Revenues | C64: {=Revenue_BC[2026]} -> 979326.42 | D64: {=Revenue_BC[2027]} -> 960029.82 | E64: {=Revenue_BC[2028]} -> 941113.44 | F64: {=Revenue_BC[2029]} -> 922569.79 | G64: {=Revenue_BC[2030]} -> 904391.52 | H64: {=Revenue_BC[2031]} -> 886571.43 | I64: {=Revenue_BC[2032]} -> 869102.47 | J64: {=Revenue_BC[2033]} -> 851977.72 | K64: {=Revenue_BC[2034]} -> 835190.39 | L64: {=Revenue_BC[2035]} -> 818733.84 | M64: {=Revenue_BC[2036]} -> 802601.55 | N64: {=Revenue_BC[2037]} -> 786787.13 | O64: {=Revenue_BC[2038]} -> 771284.32 | P64: {=Revenue_BC[2039]} -> 756086.97 | Q64: {=Revenue_BC[2040]} -> 741189.07 | R64: {=Revenue_BC[2041]} -> 726584.71 | S64: {=Revenue_BC[2042]} -> 712268.13 | T64: {=Revenue_BC[2043]} -> 698233.63 | U64: {=Revenue_BC[2044]} -> 684475.67 | V64: {=Revenue_BC[2045]} -> 670988.79 | W64: {=Revenue_BC[2046]} -> 657767.66 | X64: {=Revenue_BC[2047]} -> 644807.04 | Y64: {=Revenue_BC[2048]} -> 0 | Z64: {=Revenue_BC[2049]} -> 0 | AA64: {=Revenue_BC[2050]} -> 0 | AB64: {=Revenue_BC[2051]} -> 0 | AC64: {=Revenue_BC[2052]} -> 0 | AD64: {=Revenue_BC[2053]} -> 0 | AE64: {=Revenue_BC[2054]} -> 0 | AF64: {=Revenue_BC[2055]} -> 0 | AG64: {=Revenue_BC[2056]} -> 0 | AH64: {=Revenue_BC[2057]} -> 0 | AI64: {=Revenue_BC[2058]} -> 0 | AJ64: {=Revenue_BC[2059]} -> 0 | AK64: {=Revenue_BC[2060]} -> 0 | AL64: {=Revenue_BC[2061]} -> 0 | AM64: {=Revenue_BC[2062]} -> 0 | AN64: {=Revenue_BC[2063]} -> 0 | AO64: {=Revenue_BC[2064]} -> 0 | AP64: {=Revenue_BC[2065]} -> 0 | AQ64: {=Revenue_BC[2066]} -> 0 | AR64: {=Revenue_BC[2067]} -> 0 | AS64: {=Revenue_BC[2068]} -> 0 | AT64: {=Revenue_BC[2069]} -> 0 | AU64: {=Revenue_BC[2070]} -> 0
B65: Net | C65: =C64-C63 -> -456070.01 | D65: =D64-D63 -> -514978.29 | E65: =E64-E63 -> -577246.02 | F65: =F64-F63 -> -635554.87 | G65: =G64-G63 -> -697520.68 | H65: =H64-H63 -> -731218.79 | I65: =I64-I63 -> -768609.91 | J65: =J64-J63 -> -801801.88 | ... AU65: =AU64-AU63 -> 0
A68: Discount factor | B68: DR | C68: 2026 | D68: 2027 | E68: 2028 | F68: 2029 | G68: 2030 | H68: 2031 | I68: 2032 | J68: 2033 | K68: 2034 | L68: 2035 | M68: 2036 | N68: 2037 | O68: 2038 | P68: 2039 | Q68: 2040 | R68: 2041 | S68: 2042 | T68: 2043 | U68: 2044 | V68: 2045 | W68: 2046 | X68: 2047 | Y68: 2048 | Z68: 2049 | AA68: 2050 | AB68: 2051 | AC68: 2052 | AD68: 2053 | AE68: 2054 | AF68: 2055 | AG68: 2056 | AH68: 2057 | AI68: 2058 | AJ68: 2059 | AK68: 2060 | AL68: 2061 | AM68: 2062 | AN68: 2063 | AO68: 2064 | AP68: 2065 | AQ68: 2066 | AR68: 2067 | AS68: 2068 | AT68: 2069 | AU68: 2070
B69: 0.02 | C69: =1/((1+$B69)^(C$68-'Project description'!$B$29)) -> 0.98039216 | D69: =1/((1+$B69)^(D$68-'Project description'!$B$29)) -> 0.96116878 | E69: =1/((1+$B69)^(E$68-'Project description'!$B$29)) -> 0.94232233 | F69: =1/((1+$B69)^(F$68-'Project description'!$B$29)) -> 0.92384543 | G69: =1/((1+$B69)^(G$68-'Project description'!$B$29)) -> 0.90573081 | H69: =1/((1+$B69)^(H$68-'Project description'!$B$29)) -> 0.88797138 | I69: =1/((1+$B69)^(I$68-'Project description'!$B$29)) -> 0.87056018 | J69: =1/((1+$B69)^(J$68-'Project description'!$B$29)) -> 0.85349037 | ... AU69: =1/((1+$B69)^(AU$68-'Project description'!$B$29)) -> 0.4101968
B70: 0.08 | C70: =1/((1+$B70)^(C$68-'Project description'!$B$29)) -> 0.92592593 | D70: =1/((1+$B70)^(D$68-'Project description'!$B$29)) -> 0.85733882 | E70: =1/((1+$B70)^(E$68-'Project description'!$B$29)) -> 0.79383224 | F70: =1/((1+$B70)^(F$68-'Project description'!$B$29)) -> 0.73502985 | G70: =1/((1+$B70)^(G$68-'Project description'!$B$29)) -> 0.6805832 | H70: =1/((1+$B70)^(H$68-'Project description'!$B$29)) -> 0.63016963 | I70: =1/((1+$B70)^(I$68-'Project description'!$B$29)) -> 0.5834904 | J70: =1/((1+$B70)^(J$68-'Project description'!$B$29)) -> 0.54026888 | ... AU70: =1/((1+$B70)^(AU$68-'Project description'!$B$29)) -> 0.03132788
A71: Final year for assessment (PP) | B71: =FinalYear_PP -> 2047 | C71: =IF(C$68>$B71,0,1) -> 1 | D71: =IF(D$68>$B71,0,1) -> 1 | E71: =IF(E$68>$B71,0,1) -> 1 | F71: =IF(F$68>$B71,0,1) -> 1 | G71: =IF(G$68>$B71,0,1) -> 1 | H71: =IF(H$68>$B71,0,1) -> 1 | I71: =IF(I$68>$B71,0,1) -> 1 | J71: =IF(J$68>$B71,0,1) -> 1 | ... AU71: =IF(AU$68>$B71,0,1) -> 0
A72: Final year for assessment (BC) | B72: =FinalYear_BC -> 2047 | C72: =IF(C$68>$B72,0,1) -> 1 | D72: =IF(D$68>$B72,0,1) -> 1 | E72: =IF(E$68>$B72,0,1) -> 1 | F72: =IF(F$68>$B72,0,1) -> 1 | G72: =IF(G$68>$B72,0,1) -> 1 | H72: =IF(H$68>$B72,0,1) -> 1 | I72: =IF(I$68>$B72,0,1) -> 1 | J72: =IF(J$68>$B72,0,1) -> 1 | ... AU72: =IF(AU$68>$B72,0,1) -> 0
A74: NPV | C74: 0.02 | D74: 0.08
B75: PP | C75: =SUMPRODUCT($C$58:$AU$58,$C$69:$AU$69,$C71:$AU71) -> -467103.28 | D75: =SUMPRODUCT($C$58:$AU$58,$C$70:$AU$70,$C72:$AU72) -> -999211.31
B76: BC | C76: =SUMPRODUCT($C$65:$AU$65,$C$69:$AU$69,$C71:$AU71) -> -15905412 | D76: =SUMPRODUCT($C$65:$AU$65,$C$70:$AU$70,$C72:$AU72) -> -8270002.4
B77: Preferred: | C77: =IF(C75>C76,$B75,$B76) -> PP | D77: =IF(D75>D76,$B75,$B76) -> PP
B79: Basis | C79: 2026 | D79: 2027 | E79: 2028 | F79: 2029 | G79: 2030 | H79: 2031 | I79: 2032 | J79: 2033 | K79: 2034 | L79: 2035 | M79: 2036 | N79: 2037 | O79: 2038 | P79: 2039 | Q79: 2040 | R79: 2041 | S79: 2042 | T79: 2043 | U79: 2044 | V79: 2045 | W79: 2046 | X79: 2047 | Y79: 2048 | Z79: 2049 | AA79: 2050 | AB79: 2051 | AC79: 2052 | AD79: 2053 | AE79: 2054 | AF79: 2055 | AG79: 2056 | AH79: 2057 | AI79: 2058 | AJ79: 2059 | AK79: 2060 | AL79: 2061 | AM79: 2062 | AN79: 2063 | AO79: 2064 | AP79: 2065 | AQ79: 2066 | AR79: 2067 | AS79: 2068 | AT79: 2069 | AU79: 2070
A80: Hurdle factor | B80: =HurdleRateBasis -> Pre-tax Nominal | C80: =1/((1+'Project description'!$B$26)^(C$79-Analysis_year)) -> 0.83333333 | D80: =1/((1+'Project description'!$B$26)^(D$79-Analysis_year)) -> 0.69444444 | E80: =1/((1+'Project description'!$B$26)^(E$79-Analysis_year)) -> 0.5787037 | F80: =1/((1+'Project description'!$B$26)^(F$79-Analysis_year)) -> 0.48225309 | G80: =1/((1+'Project description'!$B$26)^(G$79-Analysis_year)) -> 0.40187757 | H80: =1/((1+'Project description'!$B$26)^(H$79-Analysis_year)) -> 0.33489798 | I80: =1/((1+'Project description'!$B$26)^(I$79-Analysis_year)) -> 0.27908165 | J80: =1/((1+'Project description'!$B$26)^(J$79-Analysis_year)) -> 0.23256804 | ... AU80: =1/((1+'Project description'!$B$26)^(AU$79-Analysis_year)) -> 0.00027342859
A81: PP | B81: Net costs/revenues | C81: {=OFFSET(G1,SUMPRODUCT(($I$86:$I$89=HurdleRateBasis)*(Calculations!$J$85:$K$85=ReturnType)*(Calculations!$J$86:$K$89))-1,0)*C71} -> -1144808.5 | D81: {=OFFSET(H1,SUMPRODUCT(($I$86:$I$89=HurdleRateBasis)*(Calculations!$J$85:$K$85=ReturnType)*(Calculations!$J$86:$K$89))-1,0)*D71} -> -661304.88 | E81: {=OFFSET(I1,SUMPRODUCT(($I$86:$I$89=HurdleRateBasis)*(Calculations!$J$85:$K$85=ReturnType)*(Calculations!$J$86:$K$89))-1,0)*E71} -> 200079.33 | F81: {=OFFSET(J1,SUMPRODUCT(($I$86:$I$89=HurdleRateBasis)*(Calculations!$J$85:$K$85=ReturnType)*(Calculations!$J$86:$K$89))-1,0)*F71} -> 219212.26 | G81: {=OFFSET(K1,SUMPRODUCT(($I$86:$I$89=HurdleRateBasis)*(Calculations!$J$85:$K$85=ReturnType)*(Calculations!$J$86:$K$89))-1,0)*G71} -> 239439.15 | H81: {=OFFSET(L1,SUMPRODUCT(($I$86:$I$89=HurdleRateBasis)*(Calculations!$J$85:$K$85=ReturnType)*(Calculations!$J$86:$K$89))-1,0)*H71} -> 260792.31 | I81: {=OFFSET(M1,SUMPRODUCT(($I$86:$I$89=HurdleRateBasis)*(Calculations!$J$85:$K$85=ReturnType)*(Calculations!$J$86:$K$89))-1,0)*I71} -> 287327.66 | J81: {=OFFSET(N1,SUMPRODUCT(($I$86:$I$89=HurdleRateBasis)*(Calculations!$J$85:$K$85=ReturnType)*(Calculations!$J$86:$K$89))-1,0)*J71} -> 309487.05 | ... AU81: {=OFFSET(AY1,SUMPRODUCT(($I$86:$I$89=HurdleRateBasis)*(Calculations!$J$85:$K$85=ReturnType)*(Calculations!$J$86:$K$89))-1,0)*AU71} -> 0
A82: BC | B82: Net costs/revenues | C82: {=OFFSET(G1,SUMPRODUCT(($I$86:$I$89=HurdleRateBasis)*(Calculations!$L$85:$M$85=ReturnType)*(Calculations!$L$86:$M$89))-1,0)*C72} -> 75191.477 | D82: {=OFFSET(H1,SUMPRODUCT(($I$86:$I$89=HurdleRateBasis)*(Calculations!$L$85:$M$85=ReturnType)*(Calculations!$L$86:$M$89))-1,0)*D72} -> 61324.012 | E82: {=OFFSET(I1,SUMPRODUCT(($I$86:$I$89=HurdleRateBasis)*(Calculations!$L$85:$M$85=ReturnType)*(Calculations!$L$86:$M$89))-1,0)*E72} -> 47515.324 | F82: {=OFFSET(J1,SUMPRODUCT(($I$86:$I$89=HurdleRateBasis)*(Calculations!$L$85:$M$85=ReturnType)*(Calculations!$L$86:$M$89))-1,0)*F72} -> 33023.322 | G82: {=OFFSET(K1,SUMPRODUCT(($I$86:$I$89=HurdleRateBasis)*(Calculations!$L$85:$M$85=ReturnType)*(Calculations!$L$86:$M$89))-1,0)*G72} -> 18257.027 | H82: {=OFFSET(L1,SUMPRODUCT(($I$86:$I$89=HurdleRateBasis)*(Calculations!$L$85:$M$85=ReturnType)*(Calculations!$L$86:$M$89))-1,0)*H72} -> 3211.1718 | I82: {=OFFSET(M1,SUMPRODUCT(($I$86:$I$89=HurdleRateBasis)*(Calculations!$L$85:$M$85=ReturnType)*(Calculations!$L$86:$M$89))-1,0)*I72} -> -12023.236 | J82: {=OFFSET(N1,SUMPRODUCT(($I$86:$I$89=HurdleRateBasis)*(Calculations!$L$85:$M$85=ReturnType)*(Calculations!$L$86:$M$89))-1,0)*J72} -> -27681.47 | ... AU82: {=OFFSET(AY1,SUMPRODUCT(($I$86:$I$89=HurdleRateBasis)*(Calculations!$L$85:$M$85=ReturnType)*(Calculations!$L$86:$M$89))-1,0)*AU72} -> 0
A84: Private Returns | B84: =HurdleRateBasis -> Pre-tax Nominal | I84: Row No | J84: PP | L84: BC
B85: =ReturnType -> Return on Equity | J85: =Lists!A18 -> Return on Equity | K85: =Lists!A19 -> Return on Whole Investment | L85: =J85 -> Return on Equity | M85: =K85 -> Return on Whole Investment
A86: PP | B86: =SUMPRODUCT($C$81:$AU$81,$C$80:$AU$80) -> -623430.52 | C86: =IFERROR(IRR(C81:AU81,0.05),"No feasible solution") -> 0.098125932 | I86: =Lists!A12 -> Pre-tax Real | J86: =ROW(A137) -> 137 | K86: =J86+1 -> 138 | L86: =J86+16 -> 153 | M86: =K86+16 -> 154
A87: BC | B87: =SUMPRODUCT($C$82:$AU$82,$C$80:$AU$80) -> 24222.319 | C87: =IFERROR(IRR(C82:AU82,0.05),"No feasible solution") -> 0.18369181 | I87: =Lists!A13 -> Post-tax Real | J87: =ROW(G140) -> 140 | K87: =J87+1 -> 141 | L87: =J87+16 -> 156 | M87: =K87+16 -> 157
A88: Preferred: | B88: =IF(B86>B87,$A86,$A87) -> BC | I88: =Lists!A14 -> Pre-tax Nominal | J88: =ROW(G104) -> 104 | K88: =J88+1 -> 105 | L88: =J88+16 -> 120 | M88: =K88+16 -> 121
I89: =Lists!A15 -> Post-tax Nominal | J89: =ROW(G107) -> 107 | K89: =J89+1 -> 108 | L89: =J89+16 -> 123 | M89: =K89+16 -> 124
A92: Summary - Private perspective
A93: a) Nominal
A94: Proposed Project (PP) | G94: =Start_Yr -> 2026 | H94: =G94+1 -> 2027 | I94: =H94+1 -> 2028 | J94: =I94+1 -> 2029 | K94: =J94+1 -> 2030 | L94: =K94+1 -> 2031 | M94: =L94+1 -> 2032 | N94: =M94+1 -> 2033 | O94: =N94+1 -> 2034 | ... AY94: =AX94+1 -> 2070
A95: Capex - equity funded | F95: Nominal | G95: =G97-G96 -> 1280000 | H95: =H97-H96 -> 816025.35 | I95: =I97-I96 -> 0 | J95: =J97-J96 -> 0 | K95: =K97-K96 -> 0 | L95: =L97-L96 -> 0 | M95: =M97-M96 -> 0 | N95: =N97-N96 -> 0 | ... AY95: =AY97-AY96 -> 0
A96: Capex - debt funded | F96: Nominal | G96: ='Real values'!H136*'Real values'!H4 -> 0 | H96: ='Real values'!I136*'Real values'!I4 -> 0 | I96: ='Real values'!J136*'Real values'!J4 -> 0 | J96: ='Real values'!K136*'Real values'!K4 -> 0 | K96: ='Real values'!L136*'Real values'!L4 -> 0 | L96: ='Real values'!M136*'Real values'!M4 -> 0 | M96: ='Real values'!N136*'Real values'!N4 -> 0 | N96: ='Real values'!O136*'Real values'!O4 -> 0 | ... AY96: ='Real values'!AZ136*'Real values'!AZ4 -> 0
A97: Capex total | F97: Nominal | G97: =Calculations!C52*'Real values'!H4 -> 1280000 | H97: =Calculations!D52*'Real values'!I4 -> 816025.35 | I97: =Calculations!E52*'Real values'!J4 -> 0 | J97: =Calculations!F52*'Real values'!K4 -> 0 | K97: =Calculations!G52*'Real values'!L4 -> 0 | L97: =Calculations!H52*'Real values'!M4 -> 0 | M97: =Calculations!I52*'Real values'!N4 -> 0 | N97: =Calculations!J52*'Real values'!O4 -> 0 | ... AY97: =Calculations!AU52*'Real values'!AZ4 -> 0
A98: Non-fuel opex | F98: Nominal | G98: =G131*'Real values'!H$4 -> 130000 | H98: =H131*'Real values'!I$4 -> 130000 | I98: =I131*'Real values'!J$4 -> 120000 | J98: =J131*'Real values'!K$4 -> 120000 | K98: =K131*'Real values'!L$4 -> 120000 | L98: =L131*'Real values'!M$4 -> 120000 | M98: =M131*'Real values'!N$4 -> 120000 | N98: =N131*'Real values'!O$4 -> 120000 | ... AY98: =AY131*'Real values'!AZ$4 -> 0
A99: Fuel opex | F99: Nominal | G99: =G132*'Real values'!H$4 -> 734808.52 | H99: =H132*'Real values'!I$4 -> 815279.53 | I99: =I132*'Real values'!J$4 -> 779920.67 | J99: =J132*'Real values'!K$4 -> 760787.74 | K99: =K132*'Real values'!L$4 -> 740560.85 | L99: =L132*'Real values'!M$4 -> 719207.69 | M99: =M132*'Real values'!N$4 -> 692672.34 | N99: =N132*'Real values'!O$4 -> 670512.95 | ... AY99: =AY132*'Real values'!AZ$4 -> 0
A100: Cost of debt | F100: Nominal | G100: =G133*'Real values'!H$4 -> 0 | H100: =H133*'Real values'!I$4 -> 0 | I100: =I133*'Real values'!J$4 -> 0 | J100: =J133*'Real values'!K$4 -> 0 | K100: =K133*'Real values'!L$4 -> 0 | L100: =L133*'Real values'!M$4 -> 0 | M100: =M133*'Real values'!N$4 -> 0 | N100: =N133*'Real values'!O$4 -> 0 | ... AY100: =AY133*'Real values'!AZ$4 -> 0
A101: Total annual costs (ROE basis) | F101: Nominal | G101: =G95+SUM(G98:G100) -> 2144808.5 | H101: =H95+SUM(H98:H100) -> 1761304.9 | I101: =I95+SUM(I98:I100) -> 899920.67 | J101: =J95+SUM(J98:J100) -> 880787.74 | K101: =K95+SUM(K98:K100) -> 860560.85 | L101: =L95+SUM(L98:L100) -> 839207.69 | M101: =M95+SUM(M98:M100) -> 812672.34 | N101: =N95+SUM(N98:N100) -> 790512.95 | ... AY101: =AY95+SUM(AY98:AY100) -> 0
A102: Total annual costs (ROI basis) | F102: Nominal | G102: =SUM(G97:G99) -> 2144808.5 | H102: =SUM(H97:H99) -> 1761304.9 | I102: =SUM(I97:I99) -> 899920.67 | J102: =SUM(J97:J99) -> 880787.74 | K102: =SUM(K97:K99) -> 860560.85 | L102: =SUM(L97:L99) -> 839207.69 | M102: =SUM(M97:M99) -> 812672.34 | N102: =SUM(N97:N99) -> 790512.95 | ... AY102: =SUM(AY97:AY99) -> 0
A103: Revenue | F103: Nominal | G103: =G136*'Real values'!H$4 -> 1000000 | H103: =H136*'Real values'!I$4 -> 1100000 | I103: =I136*'Real values'!J$4 -> 1100000 | J103: =J136*'Real values'!K$4 -> 1100000 | K103: =K136*'Real values'!L$4 -> 1100000 | L103: =L136*'Real values'!M$4 -> 1100000 | M103: =M136*'Real values'!N$4 -> 1100000 | N103: =N136*'Real values'!O$4 -> 1100000 | ... AY103: =AY136*'Real values'!AZ$4 -> 0
A104: Net costs/revenue before tax (ROE) | F104: Nominal | G104: =G103-G101 -> -1144808.5 | H104: =H103-H101 -> -661304.88 | I104: =I103-I101 -> 200079.33 | J104: =J103-J101 -> 219212.26 | K104: =K103-K101 -> 239439.15 | L104: =L103-L101 -> 260792.31 | M104: =M103-M101 -> 287327.66 | N104: =N103-N101 -> 309487.05 | ... AY104: =AY103-AY101 -> 0
A105: Net costs/revenue before tax (ROI) | F105: Nominal | G105: =G103-G102 -> -1144808.5 | H105: =H103-H102 -> -661304.88 | I105: =I103-I102 -> 200079.33 | J105: =J103-J102 -> 219212.26 | K105: =K103-K102 -> 239439.15 | L105: =L103-L102 -> 260792.31 | M105: =M103-M102 -> 287327.66 | N105: =N103-N102 -> 309487.05 | ... AY105: =AY103-AY102 -> 0
A106: Tax | F106: Nominal | G106: =Inputs!H182 -> 0 | H106: =Inputs!I182 -> 0 | I106: =Inputs!J182 -> 0 | J106: =Inputs!K182 -> 0 | K106: =Inputs!L182 -> 0 | L106: =Inputs!M182 -> 0 | M106: =Inputs!N182 -> 0 | N106: =Inputs!O182 -> 0 | ... AY106: =Inputs!AZ182 -> 0
A107: Net costs/revenue after tax (ROE) | F107: Nominal | G107: =G104-G$106 -> -1144808.5 | H107: =H104-H$106 -> -661304.88 | I107: =I104-I$106 -> 200079.33 | J107: =J104-J$106 -> 219212.26 | K107: =K104-K$106 -> 239439.15 | L107: =L104-L$106 -> 260792.31 | M107: =M104-M$106 -> 287327.66 | N107: =N104-N$106 -> 309487.05 | ... AY107: =AY104-AY$106 -> 0
A108: Net costs/revenue after tax (ROI) | F108: Nominal | G108: =G105-G$106 -> -1144808.5 | H108: =H105-H$106 -> -661304.88 | I108: =I105-I$106 -> 200079.33 | J108: =J105-J$106 -> 219212.26 | K108: =K105-K$106 -> 239439.15 | L108: =L105-L$106 -> 260792.31 | M108: =M105-M$106 -> 287327.66 | N108: =N105-N$106 -> 309487.05 | ... AY108: =AY105-AY$106 -> 0
A110: Base Case (BC) | G110: =Start_Yr -> 2026 | H110: =G110+1 -> 2027 | I110: =H110+1 -> 2028 | J110: =I110+1 -> 2029 | K110: =J110+1 -> 2030 | L110: =K110+1 -> 2031 | M110: =L110+1 -> 2032 | N110: =M110+1 -> 2033 | O110: =N110+1 -> 2034 | ... AY110: =AX110+1 -> 2070
A111: Capex - equity funded | F111: Nominal | G111: =G113-G112 -> 0 | H111: =H113-H112 -> 0 | I111: =I113-I112 -> 0 | J111: =J113-J112 -> 0 | K111: =K113-K112 -> 0 | L111: =L113-L112 -> 0 | M111: =M113-M112 -> 0 | N111: =N113-N112 -> 0 | ... AY111: =AY113-AY112 -> 0
A112: Capex - debt funded | F112: Nominal | G112: ='Real values'!H147*'Real values'!H$4 -> 0 | H112: ='Real values'!I147*'Real values'!I$4 -> 0 | I112: ='Real values'!J147*'Real values'!J$4 -> 0 | J112: ='Real values'!K147*'Real values'!K$4 -> 0 | K112: ='Real values'!L147*'Real values'!L$4 -> 0 | L112: ='Real values'!M147*'Real values'!M$4 -> 0 | M112: ='Real values'!N147*'Real values'!N$4 -> 0 | N112: ='Real values'!O147*'Real values'!O$4 -> 0 | ... AY112: ='Real values'!AZ147*'Real values'!AZ$4 -> 0
...

Sheet Results
A1: National perspective
A2: NPV | B2: 2% | C2: 8%
A3: PP | B3: =Calculations!C75 -> -467103.28 | C3: =Calculations!D75 -> -999211.31
A4: BC | B4: =Calculations!C76 -> -15905412 | C4: =Calculations!D76 -> -8270002.4
A5: Preferred: | B5: =IF(B3>B4,$A3,$A4) -> PP | C5: =IF(C3>C4,$A3,$A4) -> PP
A8: Private perspective
A9: Private Returns | B9: Pre-tax Nominal | C9: Column1
B10: =ReturnType -> Return on Equity | C10: IRR
A11: PP | B11: =Calculations!B86 -> -623430.52 | C11: =Calculations!C86 -> 0.098125932
A12: BC | B12: =Calculations!B87 -> 24222.319 | C12: =Calculations!C87 -> 0.18369181
A13: Preferred: | B13: =IF(B11>B12,$A11,$A12) -> BC | C13: =IF(C11>C12,$A11,$A12) -> BC

Sheet Data
A1: Sectors | B1: Regions | D1: Fuel | E1: Consump-tion unit | F1: GJ conversion | G1: Unit for Emission Factor | H1: Emission factor (kg CO2-e/unit) | I1: Emission factor (t CO2-e/ consumption unit) | K1: Emission factors by year | L1: 2025 | M1: 2026 | N1: 2027 | O1: 2028 | P1: 2029 | Q1: 2030 | R1: 2031 | S1: 2032 | T1: 2033 | U1: 2034 | V1: 2035 | W1: 2036 | X1: 2037 | Y1: 2038 | Z1: 2039 | AA1: 2040 | AB1: 2041 | AC1: 2042 | AD1: 2043 | AE1: 2044 | AF1: 2045 | AG1: 2046 | AH1: 2047 | AI1: 2048 | AJ1: 2049 | AK1: 2050 | AL1: 2051 | AM1: 2052 | AN1: 2053 | AO1: 2054 | AP1: 2055 | AQ1: 2056 | AR1: 2057 | AS1: 2058 | AT1: 2059 | AU1: 2060 | AV1: 2061 | AW1: 2062 | AX1: 2063 | AY1: 2064 | AZ1: 2065 | BA1: 2066 | BB1: 2067 | BC1: 2068 | BD1: 2069 | BE1: 2070
A2: <Select> | B2: <Select> | D2: <Select> | K2: =D3 -> Electricity | L2: =L18 -> 0.066978754 | M2: =M18 -> 0.067432426 | N2: =N18 -> 0.067544021 | O2: =O18 -> 0.065221804 | P2: =P18 -> 0.061132009 | Q2: =Q18 -> 0.054806089 | R2: =R18 -> 0.053734391 | S2: =S18 -> 0.054925985 | ... AK2: =AK18 -> 0.04070517 | AL2: =AK2 -> 0.04070517 | AM2: =AL2 -> 0.04070517 | AN2: =AM2 -> 0.04070517 | AO2: =AN2 -> 0.04070517 | AP2: =AO2 -> 0.04070517 | AQ2: =AP2 -> 0.04070517 | AR2: =AQ2 -> 0.04070517 | AS2: =AR2 -> 0.04070517 | ... BE2: =BD2 -> 0.04070517
A3: Commercial | B3: Northland | D3: Electricity | E3: MWh | F3: 3.6 | G3: kWh | K3: =D4 -> Natural Gas | L3: =I4 -> 0.057212 | M3: =L3 -> 0.057212 | N3: =M3 -> 0.057212 | O3: =N3 -> 0.057212 | P3: =O3 -> 0.057212 | Q3: =P3 -> 0.057212 | R3: =Q3 -> 0.057212 | S3: =R3 -> 0.057212 | T3: =S3 -> 0.057212 | ... BE3: =BD3 -> 0.057212
A4: Construction | B4: Auckland | D4: Natural Gas | E4: GJ | F4: 1 | G4: GJ | H4: 57.212 | I4: {=IF(E4=G4,H4/1000,(H4/$H$20)*INDEX($H$18:$H$23,MATCH(1,(G4=$E$18:$E$23)*(E4=$G$18:$G$23),0)))} -> 0.057212 | K4: =D5 -> Coal - sub bituminous | L4: =I5 -> 2.0125536 | M4: =L4 -> 2.0125536 | N4: =M4 -> 2.0125536 | O4: =N4 -> 2.0125536 | P4: =O4 -> 2.0125536 | Q4: =P4 -> 2.0125536 | R4: =Q4 -> 2.0125536 | S4: =R4 -> 2.0125536 | T4: =S4 -> 2.0125536 | ... BE4: =BD4 -> 2.0125536
A5: Agriculture, Forestry and Fishing | B5: Waikato | D5: Coal - sub bituminous | E5: tonnes | F5: 22 | G5: kg | H5: 2.0125536 | I5: {=IF(E5=G5,H5/1000,(H5/$H$20)*INDEX($H$18:$H$23,MATCH(1,(G5=$E$18:$E$23)*(E5=$G$18:$G$23),0)))} -> 2.0125536 | K5: =D6 -> Coal - bituminous | L5: =I6 -> 2.6225536 | M5: =L5 -> 2.6225536 | N5: =M5 -> 2.6225536 | O5: =N5 -> 2.6225536 | P5: =O5 -> 2.6225536 | Q5: =P5 -> 2.6225536 | R5: =Q5 -> 2.6225536 | S5: =R5 -> 2.6225536 | T5: =S5 -> 2.6225536 | ... BE5: =BD5 -> 2.6225536
A6: Dairy Product Manufacturing | B6: Bay of Plenty | D6: Coal - bituminous | E6: tonnes | F6: 27 | G6: kg | H6: 2.6225536 | I6: {=IF(E6=G6,H6/1000,(H6/$H$20)*INDEX($H$18:$H$23,MATCH(1,(G6=$E$18:$E$23)*(E6=$G$18:$G$23),0)))} -> 2.6225536 | K6: =D7 -> Coal - lignite | L6: =I7 -> 1.4325536 | M6: =L6 -> 1.4325536 | N6: =M6 -> 1.4325536 | O6: =N6 -> 1.4325536 | P6: =O6 -> 1.4325536 | Q6: =P6 -> 1.4325536 | R6: =Q6 -> 1.4325536 | S6: =R6 -> 1.4325536 | T6: =S6 -> 1.4325536 | ... BE6: =BD6 -> 1.4325536
A7: Industrial others | B7: Gisborne | D7: Coal - lignite | E7: tonnes | F7: 19 | G7: kg | H7: 1.4325536 | I7: {=IF(E7=G7,H7/1000,(H7/$H$20)*INDEX($H$18:$H$23,MATCH(1,(G7=$E$18:$E$23)*(E7=$G$18:$G$23),0)))} -> 1.4325536 | K7: =D8 -> Diesel | L7: =I8 -> 0.00266 | M7: =L7 -> 0.00266 | N7: =M7 -> 0.00266 | O7: =N7 -> 0.00266 | P7: =O7 -> 0.00266 | Q7: =P7 -> 0.00266 | R7: =Q7 -> 0.00266 | S7: =R7 -> 0.00266 | T7: =S7 -> 0.00266 | ... BE7: =BD7 -> 0.00266
A8: Meat and Meat Product Manufacturing and Seafood | B8: Hawke’s Bay | D8: Diesel | E8: litres | F8: 35.7 | G8: litres | H8: 2.66 | I8: {=IF(E8=G8,H8/1000,(H8/$H$20)*INDEX($H$18:$H$23,MATCH(1,(G8=$E$18:$E$23)*(E8=$G$18:$G$23),0)))} -> 0.00266 | K8: =D9 -> LPG | L8: =I9 -> 0.00164892 | M8: =L8 -> 0.00164892 | N8: =M8 -> 0.00164892 | O8: =N8 -> 0.00164892 | P8: =O8 -> 0.00164892 | Q8: =P8 -> 0.00164892 | R8: =Q8 -> 0.00164892 | S8: =R8 -> 0.00164892 | T8: =S8 -> 0.00164892 | ... BE8: =BD8 -> 0.00164892
A9: Mining | B9: Taranaki | D9: LPG | E9: m3 | F9: =0.025/0.546 -> 0.045787546 | G9: kg | H9: 3.02 | I9: {=IF(E9=G9,H9/1000,(H9/$H$20)*INDEX($H$18:$H$23,MATCH(1,(G9=$E$18:$E$23)*(E9=$G$18:$G$23),0)))} -> 0.00164892 | K9: =D10 -> Light fuel oil | L9: =I10 -> 0.00292 | M9: =L9 -> 0.00292 | N9: =M9 -> 0.00292 | O9: =N9 -> 0.00292 | P9: =O9 -> 0.00292 | Q9: =P9 -> 0.00292 | R9: =Q9 -> 0.00292 | S9: =R9 -> 0.00292 | T9: =S9 -> 0.00292 | ... BE9: =BD9 -> 0.00292
A10: Non-Metallic Mineral Product Manufacturing | B10: Manawatu-Whanganui | D10: Light fuel oil | E10: litres | F10: 37.3 | G10: litres | H10: 2.92 | I10: {=IF(E10=G10,H10/1000,(H10/$H$20)*INDEX($H$18:$H$23,MATCH(1,(G10=$E$18:$E$23)*(E10=$G$18:$G$23),0)))} -> 0.00292 | K10: =D11 -> Heavy fuel oil | L10: =I11 -> 0.00302 | M10: =L10 -> 0.00302 | N10: =M10 -> 0.00302 | O10: =N10 -> 0.00302 | P10: =O10 -> 0.00302 | Q10: =P10 -> 0.00302 | R10: =Q10 -> 0.00302 | S10: =R10 -> 0.00302 | T10: =S10 -> 0.00302 | ... BE10: =BD10 -> 0.00302
A11: Other Food Product Manufacturing | B11: Wellington | D11: Heavy fuel oil | E11: litres | F11: 38.4 | G11: litres | H11: 3.02 | I11: {=IF(E11=G11,H11/1000,(H11/$H$20)*INDEX($H$18:$H$23,MATCH(1,(G11=$E$18:$E$23)*(E11=$G$18:$G$23),0)))} -> 0.00302 | K11: =D12 -> Geothermal | L11: =I12 -> 6.2e-05 | M11: =L11 -> 6.2e-05 | N11: =M11 -> 6.2e-05 | O11: =N11 -> 6.2e-05 | P11: =O11 -> 6.2e-05 | Q11: =P11 -> 6.2e-05 | R11: =Q11 -> 6.2e-05 | S11: =R11 -> 6.2e-05 | T11: =S11 -> 6.2e-05 | ... BE11: =BD11 -> 6.2e-05
A12: Petroleum, Basic Chemical and Rubber Product Manufacturing | B12: Tasman | D12: Geothermal | E12: kWh | F12: =3.6/1000 -> 0.0036 | G12: kWh | H12: 0.062 | I12: {=IF(E12=G12,H12/1000,(H12/$H$20)*INDEX($H$18:$H$23,MATCH(1,(G12=$E$18:$E$23)*(E12=$G$18:$G$23),0)))} -> 6.2e-05 | K12: =D13 -> Wood or wood chips | L12: =I13 -> 0.0201072 | M12: =L12 -> 0.0201072 | N12: =M12 -> 0.0201072 | O12: =N12 -> 0.0201072 | P12: =O12 -> 0.0201072 | Q12: =P12 -> 0.0201072 | R12: =Q12 -> 0.0201072 | S12: =R12 -> 0.0201072 | T12: =S12 -> 0.0201072 | ... BE12: =BD12 -> 0.0201072
A13: Primary Metal and Metal Product Manufacturing | B13: Nelson | D13: Wood or wood chips | E13: tonnes | F13: 10 | G13: kg | H13: 0.0201072 | I13: {=IF(E13=G13,H13/1000,(H13/$H$20)*INDEX($H$18:$H$23,MATCH(1,(G13=$E$18:$E$23)*(E13=$G$18:$G$23),0)))} -> 0.0201072
A14: Pulp, Paper and Converted Paper Product Manufacturing | B14: Marlborough
A15: Wood Product Manufacturing | B15: West Coast
B16: Canterbury | K16: Electricity emisisons
B17: Otago | D17: Fuel | E17: Unit 1 | G17: Unit 2 | H17: Multiplier | K17: Parameter | L17: 2025 | M17: 2026 | N17: 2027 | O17: 2028 | P17: 2029 | Q17: 2030 | R17: 2031 | S17: 2032 | T17: 2033 | U17: 2034 | V17: 2035 | W17: 2036 | X17: 2037 | Y17: 2038 | Z17: 2039 | AA17: 2040 | AB17: 2041 | AC17: 2042 | AD17: 2043 | AE17: 2044 | AF17: 2045 | AG17: 2046 | AH17: 2047 | AI17: 2048 | AJ17: 2049 | AK17: 2050 | AL17: 2051 | AM17: 2052 | AN17: 2053 | AO17: 2054 | AP17: 2055 | AQ17: 2056 | AR17: 2057 | AS17: 2058 | AT17: 2059 | AU17: 2060 | AV17: 2061 | AW17: 2062 | AX17: 2063 | AY17: 2064 | AZ17: 2065 | BA17: 2066 | BB17: 2067 | BC17: 2068 | BD17: 2069 | BE17: 2070
B18: Southland | D18: Any | E18: kWh | G18: MWh | H18: 1000 | K18: EDGS - Reference scenario | L18: 0.066978754 | M18: 0.067432426 | N18: 0.067544021 | O18: 0.065221804 | P18: 0.061132009 | Q18: 0.054806089 | R18: 0.053734391 | S18: 0.054925985 | T18: 0.054936469 | U18: 0.054465043 | V18: 0.05468982 | W18: 0.054134259 | X18: 0.039401193 | Y18: 0.038607524 | Z18: 0.038397025 | AA18: 0.038662375 | AB18: 0.038547358 | AC18: 0.039380983 | AD18: 0.040377288 | AE18: 0.040909475 | AF18: 0.040725118 | AG18: 0.040571248 | AH18: 0.040806592 | AI18: 0.04072376 | AJ18: 0.040516878 | AK18: 0.04070517 | AL18: =AK18 -> 0.04070517 | AM18: =AL18 -> 0.04070517 | AN18: =AM18 -> 0.04070517 | AO18: =AN18 -> 0.04070517 | AP18: =AO18 -> 0.04070517 | AQ18: =AP18 -> 0.04070517 | AR18: =AQ18 -> 0.04070517 | AS18: =AR18 -> 0.04070517 | ... BE18: =BD18 -> 0.04070517
D19: Any | E19: MWh | G19: kWh | H19: 0.001 | K19: Electricity Allocation Factor (t CO2e/MWh) | L19: 0.554 | M19: =L19 -> 0.554 | N19: =M19 -> 0.554 | O19: =N19 -> 0.554 | P19: =O19 -> 0.554 | Q19: =P19 -> 0.554 | R19: =Q19 -> 0.554 | S19: =R19 -> 0.554 | T19: =S19 -> 0.554 | ... BE19: =BD19 -> 0.554
D20: Any | E20: kg | G20: tonnes | H20: 1000 | K20: Wholesale price projection no ETS ($/MWh) | L20: =L30 -> 123.04524 | M20: =M30 -> 113.47833 | N20: =N30 -> 106.26061 | O20: =O30 -> 96.538137 | P20: =P30 -> 90.126734 | Q20: =Q30 -> 83.713572 | R20: =R30 -> 77.299388 | S20: =S30 -> 70.186889 | ... AK20: =AK30 -> 67.44064 | AL20: =AK20 -> 67.44064 | AM20: =AL20 -> 67.44064 | AN20: =AM20 -> 67.44064 | AO20: =AN20 -> 67.44064 | AP20: =AO20 -> 67.44064 | AQ20: =AP20 -> 67.44064 | AR20: =AQ20 -> 67.44064 | AS20: =AR20 -> 67.44064 | ... BE20: =BD20 -> 67.44064
D21: Any | E21: tonnes | G21: kg | H21: 0.001 | K21: Distribution costs ($/MWh) | L21: 50 | M21: =L21 -> 50 | N21: =M21 -> 50 | O21: =N21 -> 50 | P21: =O21 -> 50 | Q21: =P21 -> 50 | R21: =Q21 -> 50 | S21: =R21 -> 50 | T21: =S21 -> 50 | ... BE21: =BD21 -> 50
D22: LPG | E22: m3 | G22: kg | H22: 1.8315 | K22: Total marginal cost ($/MWh) | L22: =L20+L21 -> 173.04524 | M22: =M20+M21 -> 163.47833 | N22: =N20+N21 -> 156.26061 | O22: =O20+O21 -> 146.53814 | P22: =P20+P21 -> 140.12673 | Q22: =Q20+Q21 -> 133.71357 | R22: =R20+R21 -> 127.29939 | S22: =S20+S21 -> 120.18689 | ... BE22: =BE20+BE21 -> 117.44064
D23: LPG | E23: kg | G23: m3 | H23: 0.546 | K23: NZU Price projection | L23: 67.551 | M23: 69.948 | N23: 72.43 | O23: 75 | P23: 71.429 | Q23: 67.857 | R23: 64.286 | S23: 60.714 | T23: 57.143 | U23: 53.571 | V23: 50 | W23: 50 | X23: 50 | Y23: 50 | Z23: 50 | AA23: 50 | AB23: 50 | AC23: 50 | AD23: 50 | AE23: 50 | AF23: 50 | AG23: 50 | AH23: 50 | AI23: 50 | AJ23: 50 | AK23: 50 | AL23: =AK23 -> 50 | AM23: =AL23 -> 50 | AN23: =AM23 -> 50 | AO23: =AN23 -> 50 | AP23: =AO23 -> 50 | AQ23: =AP23 -> 50 | AR23: =AQ23 -> 50 | AS23: =AR23 -> 50 | ... BE23: =BD23 -> 50
K24: Shadow price (central) | L24: 120 | M24: 132 | N24: 143 | O24: 155 | P24: 166 | Q24: 178 | R24: 183 | S24: 189 | T24: 194 | U24: 200 | V24: 206 | W24: 212 | X24: 219 | Y24: 225 | Z24: 232 | AA24: 239 | AB24: 246 | AC24: 253 | AD24: 261 | AE24: 269 | AF24: 277 | AG24: 285 | AH24: 294 | AI24: 303 | AJ24: 312 | AK24: 321 | AL24: 331 | AM24: 341 | AN24: 351 | AO24: 361 | AP24: 372 | AQ24: 383 | AR24: 395 | AS24: 407 | AT24: 419 | AU24: 432 | AV24: 444 | AW24: 458 | AX24: 472 | AY24: 486 | AZ24: 500 | BA24: 515 | BB24: 531 | BC24: 547 | BD24: 563 | BE24: 580
K25: Shadow price (low) | L25: 80 | M25: 88 | N25: 96 | O25: 103 | P25: 111 | Q25: 119 | R25: 122 | S25: 126 | T25: 130 | U25: 133 | V25: 137 | W25: 142 | X25: 146 | Y25: 150 | Z25: 155 | AA25: 159 | AB25: 164 | AC25: 169 | AD25: 174 | AE25: 179 | AF25: 185 | AG25: 190 | AH25: 196 | AI25: 202 | AJ25: 208 | AK25: 214 | AL25: 216 | AM25: 218 | AN25: 221 | AO25: 223 | AP25: 225 | AQ25: 227 | AR25: 230 | AS25: 232 | AT25: 234 | AU25: 236 | AV25: 239 | AW25: 241 | AX25: 244 | AY25: 246 | AZ25: 249 | BA25: 251 | BB25: 254 | BC25: 256 | BD25: 259 | BE25: 261
K26: Shadow price (chigh) | L26: 161 | M26: 176 | N26: 191 | O26: 206 | P26: 222 | Q26: 237 | R26: 244 | S26: 251 | T26: 259 | U26: 267 | V26: 275 | W26: 283 | X26: 292 | Y26: 300 | Z26: 309 | AA26: 319 | AB26: 328 | AC26: 338 | AD26: 348 | AE26: 359 | AF26: 369 | AG26: 380 | AH26: 392 | AI26: 404 | AJ26: 416 | AK26: 428 | AL26: 450 | AM26: 472 | AN26: 496 | AO26: 520 | AP26: 546 | AQ26: 574 | AR26: 602 | AS26: 633 | AT26: 664 | AU26: 697 | AV26: 732 | AW26: 769 | AX26: 807 | AY26: 848 | AZ26: 890 | BA26: 935 | BB26: 981 | BC26: 1030 | BD26: 1082 | BE26: 1136
K28: CCC Current Policy Reference ($/MWh) | L28: 160.60644 | M28: 152.36913 | N28: 146.48101 | O28: 138.08814 | P28: 129.69816 | Q28: 121.30643 | R28: 112.91367 | S28: 103.8226 | T28: 95.706718 | U28: 95.64526 | V28: 95.664687 | W28: 95.643748 | X28: 95.880619 | Y28: 95.837553 | Z28: 95.779528 | AA28: 95.721738 | AB28: 95.663761 | AC28: 95.6058 | AD28: 95.547798 | AE28: 95.489736 | AF28: 95.431571 | AG28: 95.373442 | AH28: 95.31523 | AI28: 95.257074 | AJ28: 95.198909 | AK28: 95.14064
K29: Carbon price assumption | L29: 67.8 | M29: 70.2 | N29: 72.6 | O29: 75 | P29: 71.428571 | Q29: 67.857143 | R29: 64.285714 | S29: 60.714286 | T29: 57.142857 | U29: 53.571429 | V29: 50 | W29: 50 | X29: 50 | Y29: 50 | Z29: 50 | AA29: 50 | AB29: 50 | AC29: 50 | AD29: 50 | AE29: 50 | AF29: 50 | AG29: 50 | AH29: 50 | AI29: 50 | AJ29: 50 | AK29: 50
K30: Ex ETS | L30: =L28-L19*L29 -> 123.04524 | M30: =M28-M19*M29 -> 113.47833 | N30: =N28-N19*N29 -> 106.26061 | O30: =O28-O19*O29 -> 96.538137 | P30: =P28-P19*P29 -> 90.126734 | Q30: =Q28-Q19*Q29 -> 83.713572 | R30: =R28-R19*R29 -> 77.299388 | S30: =S28-S19*S29 -> 70.186889 | ... AK30: =AK28-AK19*AK29 -> 67.44064
K32: Inflation | L32: 2025 | M32: 2026 | N32: 2027 | O32: 2028 | P32: 2029 | Q32: 2030 | R32: 2031 | S32: 2032 | T32: 2033 | U32: 2034 | V32: 2035 | W32: 2036 | X32: 2037 | Y32: 2038 | Z32: 2039 | AA32: 2040 | AB32: 2041 | AC32: 2042 | AD32: 2043 | AE32: 2044 | AF32: 2045 | AG32: 2046 | AH32: 2047 | AI32: 2048 | AJ32: 2049 | AK32: 2050 | AL32: 2051 | AM32: 2052 | AN32: 2053 | AO32: 2054 | AP32: 2055 | AQ32: 2056 | AR32: 2057 | AS32: 2058 | AT32: 2059 | AU32: 2060 | AV32: 2061 | AW32: 2062 | AX32: 2063 | AY32: 2064 | AZ32: 2065 | BA32: 2066 | BB32: 2067 | BC32: 2068 | BD32: 2069 | BE32: 2070
L33: 0.022 | M33: 0.02 | N33: 0.02 | O33: 0.02 | P33: 0.02 | Q33: 0.02 | R33: 0.02 | S33: 0.02 | T33: 0.02 | U33: 0.02 | V33: 0.02 | W33: 0.02 | X33: 0.02 | Y33: 0.02 | Z33: 0.02 | AA33: 0.02 | AB33: 0.02 | AC33: 0.02 | AD33: 0.02 | AE33: 0.02 | AF33: 0.02 | AG33: 0.02 | AH33: 0.02 | AI33: 0.02 | AJ33: 0.02 | AK33: 0.02 | AL33: 0.02 | AM33: 0.02 | AN33: 0.02 | AO33: 0.02 | AP33: 0.02 | AQ33: 0.02 | AR33: 0.02 | AS33: 0.02 | AT33: 0.02 | AU33: 0.02 | AV33: 0.02 | AW33: 0.02 | AX33: 0.02 | AY33: 0.02 | AZ33: 0.02 | BA33: 0.02 | BB33: 0.02 | BC33: 0.02 | BD33: 0.02 | BE33: 0.02
L36: INPUT DATA FROM GIDI SPREADSHEET - TO REMOVE
M37: Electricity | N37: Wood - pellet | O37: Wood - hog | P37: Wood - chips | Q37: Coal - bituminous | R37: Coal - sub bituminous | S37: Coal - lignite | T37: Diesel | U37: LPG | V37: Light fuel oil | W37: Heavy fuel oil | X37: Natural Gas | Y37: Geothermal
L38: Emissions unit | M38: kWh | N38: kg | O38: kg | P38: kg | Q38: kg | R38: kg | S38: kg | T38: litre | U38: kg | V38: litre | W38: litre | X38: GJ | Y38: kWh
L39: Default emissions factor (kgCO2-e/unit) | M39: =1.08*0.054 -> 0.05832 | N39: 0.0201072 | O39: 0.0201072 | P39: 0.0201072 | Q39: 2.6225536 | R39: 2.0125536 | S39: 1.4325536 | T39: 2.66 | U39: 3.02 | V39: 2.92 | W39: 3.02 | X39: =54+3.212 -> 57.212 | Y39: 0.062

Sheet Lists
A1: Project Options | C1: Q2 | D1: Final year | E1: Q3 | F1: Q4
A2: <Select> | B2: 0 | D2: 2026
A3: Retrofit of existing asset | B3: 1 | C3: Expected final year of operation/use of existing asset | D3: ='Project description'!B14 -> 2035 | E3: Information not required | F3: =E3 -> Information not required
A4: Replacing asset at the end of its life | B4: 2 | C4: Information not required | D4: =YEAR('Project description'!B11)+'Project description'!B15 -> 2047 | E4: Without the loan, what would the existing asset be replaced with at the end of its life? | F4: What would be the expected life of the replacement asset in the base case (no loan)
A5: Early replacement of asset | B5: 3 | C5: Expected final year of operation/use of existing asset if not replaced early | D5: =IF('Project description'!B16=Lists!E10,Lists!D3,Lists!D4) -> 2035 | E5: Without the loan, what would the existing asset be replaced with at the end of its life? | F5: What would be the expected life of the replacement asset in the base case (no loan)
A6: Choice | B6: =INDEX(B2:B5,MATCH('Project description'!B13,$A$2:$A$5,0)) -> 3 | D6: =INDEX(D2:D5,MATCH(B6,B2:B5,0)) -> 2035
E7: Options
E8: <Select>
E9: The same as the current asset
A10: Hurdle rate | E10: The same as the the proposed project
A11: <Select> | E11: Something different
A12: Pre-tax Real | B12: 1
A13: Post-tax Real | B13: 2
A14: Pre-tax Nominal | B14: 3
A15: Post-tax Nominal | B15: 4
A17: <Select>
A18: Return on Equity | B18: 1
A19: Return on Whole Investment | B19: 2

Sheet Output
