Workbook
Name Analysis_year: 'Project description'!$B$13
Name FinalYear_BC: Calculations!$B$3
Name FinalYear_PP: Calculations!$B$2
Name HurdleRateBasis: 'Project description'!$B$29
Name Occasion: Lists!$A$21:$A$32
Name ReturnType: 'Project description'!$B$30
Name Start_Yr: 'Project description'!$B$11

Sheet Guidance
B1: Concessionary Loans Application Template
B3: This spreadsheet is for the applicant to fill in information about the 'Proposed Project' (i.e., the project for which Concessions Loan funds are sought) and also a 'Base Case' (i.e., the outcomes if the project were not to proceed). For example, the Proposed Project could be the replacement of a coal-fired boiler with a biomass boiler, whereas the Base Case could be the coal-fired boiler continuing to operate.
B6: The spreadsheet consists of the following tabs:
B7: Project description: | E7: This has some input cells for applicants to fill in regarding the name and type of project, starting dates and the applicant's investment criteria.
B8: Inputs: | E8: This is the main tab for the applicant to fill in projected Capex and Opex cashflows for the Proposed Project and the Base Case, as well as projected fuel consumption for both situations.
B9: Scratch: | E9: This is a tab which applicants can use if they wish to do their own bespoke calculations - noting that the rest of the spreadsheet is 'locked-down' to enable EECA to extract and evaluate data in a rigorous fashion.
B11: Real values: | E11: This tab includes calculated values derived from both the Project description and Inputs tabs.
B12: Results: | E12: This tab shows a summary of energy savings (GJ and $), as well as repayments. NOTE: a row to enter payments made to date is include in repayments.

Sheet Project description
A1: Input data
A2: Project information | B2: Information should be included on the proposed project (assuming the loan is given) and the base case (what you would do without the loan)
A3: Field | B3: Value | C3: Notes
A4: Occasion | B4: <Select>
A5: ProjectID | C5: For EECA use only
A6: Applicant's name
A7: Sector | B7: <Select>
A8: Region | B8: <Select>
A9: Name for proposed project
A10: Date of application submission (dd/mm/yy)
A11: First year of expenditure (yyyy)
A12: Expected commissioning date of proposed project (dd/mm/yy)
A13: Analysis year - this should be the current year
A15: Project type | B15: <Select> | C15: =IF(B15="Retrofit of existing asset","Project assumed to last only as long as the life of the existing asset","")
A16: =INDEX(Lists!$C$2:$C$5,MATCH(Lists!B6,Lists!$B$2:$B$5,0))
A17: =IF(INDEX(Lists!G2:G5,MATCH(Lists!B6,Lists!$B$2:$B$6,0))=0,"",INDEX(Lists!G2:G5,MATCH(Lists!B6,Lists!$B$2:$B$6,0))) | C17: =IF(FinalYear_PP = 1900, "", "Final year = "&FinalYear_PP)
A18: =IF(INDEX(Lists!E2:E5,MATCH(Lists!B6,Lists!$B$2:$B$5,0))=0,"",INDEX(Lists!E2:E5,MATCH(Lists!B6,Lists!$B$2:$B$5,0))) | B18: <Select>
A19: =IF(INDEX(Lists!F2:F5,MATCH(Lists!B6,Lists!$B$2:$B$5,0))=0,"",INDEX(Lists!F2:F5,MATCH(Lists!B6,Lists!$B$2:$B$5,0))) | C19: =IF(FinalYear_BC=1900, "", "Final year = "&FinalYear_BC)
A21: Does the project replace the use of coal for industrial process heat? | B21: <Select>
A22: If this project replaces coal consumption for industrial process heat, does the project bring forward the time of replacement from the start of 2037? | B22: <Select> | C22: =IF(AND(B22="Yes",B21="Yes"),"The base case used for analysis should be that of just meeting the regulated coal phase-out date of 2037","")
A23: Is this a heat pump project? | B23: <Select>
A25: What level of loan contribution are you requesting? ($)
A26: Start date? (dd/mm/yyyy)
A27: How long would the loan be for? (years) | C27: =IF(Start_Yr+B27=0, "", "Full repayment by "&Start_Yr+B27)
A28: What is your hurdle rate for this investment (%)
A29: What basis is used for the hurdle rate? | B29: <Select>
A30: Is the hurdle rate for the return on equity only or for the whole investment | B30: <Select>

Sheet Inputs
A2: Inflation
A3: Cashflow values may be specified in real (ie, current year values) or nominal (values for the year of the cost or revenue item)
A4: ="All values for the current year ("&'Project description'!B13&") should be in current dollar values" -> All values for the current year () should be in current dollar values
A5: I will include my own inflation assumptions | B5: Yes
A6: If an inflation rate has been used to produce a future nominal value, please note it below | H6: 2025 | I6: =H6+1 -> 2026 | J6: =I6+1 -> 2027 | K6: =J6+1 -> 2028 | L6: =K6+1 -> 2029 | M6: =L6+1 -> 2030 | N6: =M6+1 -> 2031 | O6: =N6+1 -> 2032 | P6: =O6+1 -> 2033 | ... BA6: =AZ6+1 -> 2070
A7: Inflation rate in the year | B7: Please enter the inflation rate you have assumed here: | H7: 0.03 | I7: 0.02 | J7: 0.02 | K7: 0.02 | L7: 0.02 | M7: 0.02 | N7: 0.02 | O7: 0.02 | P7: 0.02 | Q7: 0.02 | R7: 0.02 | S7: 0.02 | T7: 0.02 | U7: 0.02 | V7: 0.02 | W7: 0.02 | X7: 0.02 | Y7: 0.02 | Z7: 0.02 | AA7: 0.02 | AB7: 0.02 | AC7: 0.02 | AD7: 0.02 | AE7: 0.02 | AF7: 0.02 | AG7: 0.02 | AH7: =AG7 -> 0.02 | AI7: =AH7 -> 0.02 | AJ7: =AI7 -> 0.02 | AK7: =AJ7 -> 0.02 | AL7: =AK7 -> 0.02 | AM7: =AL7 -> 0.02 | AN7: =AM7 -> 0.02 | AO7: =AN7 -> 0.02 | ... BA7: =AZ7 -> 0.02
A8: =IF(B5="Yes","Inflation rate","Default inflation rate") -> Inflation rate | H8: =IF($B$5="Yes",H7,Data!L33) -> 0.03 | I8: =IF($B$5="Yes",I7,Data!M33) -> 0.02 | J8: =IF($B$5="Yes",J7,Data!N33) -> 0.02 | K8: =IF($B$5="Yes",K7,Data!O33) -> 0.02 | L8: =IF($B$5="Yes",L7,Data!P33) -> 0.02 | M8: =IF($B$5="Yes",M7,Data!Q33) -> 0.02 | N8: =IF($B$5="Yes",N7,Data!R33) -> 0.02 | O8: =IF($B$5="Yes",O7,Data!S33) -> 0.02 | ... BA8: =IF($B$5="Yes",BA7,Data!BE33) -> 0.02
A9: Proportion of year | H9: =IF(YEAR('Project description'!B10)=H6,(DATE(H6,12,31)-'Project description'!B12)/365,1) -> 1 | I9: =IF(YEAR('Project description'!C10)=I6,(DATE(I6,12,31)-'Project description'!C12)/365,1) -> 1 | J9: =IF(YEAR('Project description'!D10)=J6,(DATE(J6,12,31)-'Project description'!D12)/365,1) -> 1 | K9: =IF(YEAR('Project description'!E10)=K6,(DATE(K6,12,31)-'Project description'!E12)/365,1) -> 1 | L9: =IF(YEAR('Project description'!F10)=L6,(DATE(L6,12,31)-'Project description'!F12)/365,1) -> 1 | M9: =IF(YEAR('Project description'!G10)=M6,(DATE(M6,12,31)-'Project description'!G12)/365,1) -> 1 | N9: =IF(YEAR('Project description'!H10)=N6,(DATE(N6,12,31)-'Project description'!H12)/365,1) -> 1 | O9: =IF(YEAR('Project description'!I10)=O6,(DATE(O6,12,31)-'Project description'!I12)/365,1) -> 1 | ... BA9: =IF(YEAR('Project description'!AU10)=BA6,(DATE(BA6,12,31)-'Project description'!AU12)/365,1) -> 1
A10: Inflator to end of year - use this to convert real values to nominal | H10: =IF(H6=Analysis_year,1+(H8*H9),IF(H6<Analysis_year,1/((1/I10)*(1+I8*I9)),G10*(1+G8*G9))) -> 0 | I10: =IF(I6=Analysis_year,1+(I8*I9),IF(I6<Analysis_year,1/((1/J10)*(1+J8*J9)),H10*(1+H8*H9))) -> 0 | J10: =IF(J6=Analysis_year,1+(J8*J9),IF(J6<Analysis_year,1/((1/K10)*(1+K8*K9)),I10*(1+I8*I9))) -> 0 | K10: =IF(K6=Analysis_year,1+(K8*K9),IF(K6<Analysis_year,1/((1/L10)*(1+L8*L9)),J10*(1+J8*J9))) -> 0 | L10: =IF(L6=Analysis_year,1+(L8*L9),IF(L6<Analysis_year,1/((1/M10)*(1+M8*M9)),K10*(1+K8*K9))) -> 0 | M10: =IF(M6=Analysis_year,1+(M8*M9),IF(M6<Analysis_year,1/((1/N10)*(1+N8*N9)),L10*(1+L8*L9))) -> 0 | N10: =IF(N6=Analysis_year,1+(N8*N9),IF(N6<Analysis_year,1/((1/O10)*(1+O8*O9)),M10*(1+M8*M9))) -> 0 | O10: =IF(O6=Analysis_year,1+(O8*O9),IF(O6<Analysis_year,1/((1/P10)*(1+P8*P9)),N10*(1+N8*N9))) -> 0 | ... BA10: =IF(BA6=Analysis_year,1+(BA8*BA9),IF(BA6<Analysis_year,1/((1/BB10)*(1+BB8*BB9)),AZ10*(1+AZ8*AZ9))) -> 0
A11: Deflator - use this to convert nominal values to real | H11: =IFERROR(1/H10,0) -> 0 | I11: =IFERROR(1/I10,0) -> 0 | J11: =IFERROR(1/J10,0) -> 0 | K11: =IFERROR(1/K10,0) -> 0 | L11: =IFERROR(1/L10,0) -> 0 | M11: =IFERROR(1/M10,0) -> 0 | N11: =IFERROR(1/N10,0) -> 0 | O11: =IFERROR(1/O10,0) -> 0 | ... BA11: =IFERROR(1/BA10,0) -> 0
A13: 1) Capital expenditure (CAPEX) ($) - please enter all costs as positive numbers
D14: Value basis | E14: Nominal
A15: Proposed Project (PP) | D15: Capex item | E15: Value basis | G15: Applicant comment | H15: 2025 | I15: 2026 | J15: 2027 | K15: 2028 | L15: 2029 | M15: 2030 | N15: 2031 | O15: 2032 | P15: 2033 | Q15: 2034 | R15: 2035 | S15: 2036 | T15: 2037 | U15: 2038 | V15: 2039 | W15: 2040 | X15: 2041 | Y15: 2042 | Z15: 2043 | AA15: 2044 | AB15: 2045 | AC15: 2046 | AD15: 2047 | AE15: 2048 | AF15: 2049 | AG15: 2050 | AH15: 2051 | AI15: 2052 | AJ15: 2053 | AK15: 2054 | AL15: 2055 | AM15: 2056 | AN15: 2057 | AO15: 2058 | AP15: 2059 | AQ15: 2060 | AR15: 2061 | AS15: 2062 | AT15: 2063 | AU15: 2064 | AV15: 2065 | AW15: 2066 | AX15: 2067 | AY15: 2068 | AZ15: 2069 | BA15: 2070
A16: ="Please provide data through to "&FinalYear_PP -> Please provide data through to 1900 | D16: Equipment purchase | E16: =E$14 -> Nominal | F16: =IF(E16="Nominal","",Analysis_year&" values")
D17: Civil works | E17: =E$14 -> Nominal | F17: =IF(E17="Nominal","",Analysis_year&" values")
D18: Electrical works | E18: =E$14 -> Nominal | F18: =IF(E18="Nominal","",Analysis_year&" values")
D19: Installation | E19: =E$14 -> Nominal | F19: =IF(E19="Nominal","",Analysis_year&" values")
D20: Indirect costs | E20: =E$14 -> Nominal | F20: =IF(E20="Nominal","",Analysis_year&" values")
D21: Project management | E21: =E$14 -> Nominal | F21: =IF(E21="Nominal","",Analysis_year&" values")
D22: Other | E22: =E$14 -> Nominal | F22: =IF(E22="Nominal","",Analysis_year&" values")
D23: ="Total capex in "&Analysis_year&" dollars" -> Total capex in dollars | H23: =SUM(H16:H22)*IF($E$14="Real",1,H$11) -> 0 | I23: =SUM(I16:I22)*IF($E$14="Real",1,I$11) -> 0 | J23: =SUM(J16:J22)*IF($E$14="Real",1,J$11) -> 0 | K23: =SUM(K16:K22)*IF($E$14="Real",1,K$11) -> 0 | L23: =SUM(L16:L22)*IF($E$14="Real",1,L$11) -> 0 | M23: =SUM(M16:M22)*IF($E$14="Real",1,M$11) -> 0 | N23: =SUM(N16:N22)*IF($E$14="Real",1,N$11) -> 0 | O23: =SUM(O16:O22)*IF($E$14="Real",1,O$11) -> 0 | ... BA23: =SUM(BA16:BA22)*IF($E$14="Real",1,BA$11) -> 0
D24: Total capex in nominal dollars | H24: =SUM(H16:H22)*IF($E$14="Real",H10,1) -> 0 | I24: =SUM(I16:I22)*IF($E$14="Real",I10,1) -> 0 | J24: =SUM(J16:J22)*IF($E$14="Real",J10,1) -> 0 | K24: =SUM(K16:K22)*IF($E$14="Real",K10,1) -> 0 | L24: =SUM(L16:L22)*IF($E$14="Real",L10,1) -> 0 | M24: =SUM(M16:M22)*IF($E$14="Real",M10,1) -> 0 | N24: =SUM(N16:N22)*IF($E$14="Real",N10,1) -> 0 | O24: =SUM(O16:O22)*IF($E$14="Real",O10,1) -> 0 | ... BA24: =SUM(BA16:BA22)*IF($E$14="Real",BA10,1) -> 0
D26: Value basis | E26: Real
A27: Base Case (BC) | D27: Capex item | E27: Value basis | G27: Applicant comment | H27: 2025 | I27: 2026 | J27: 2027 | K27: 2028 | L27: 2029 | M27: 2030 | N27: 2031 | O27: 2032 | P27: 2033 | Q27: 2034 | R27: 2035 | S27: 2036 | T27: 2037 | U27: 2038 | V27: 2039 | W27: 2040 | X27: 2041 | Y27: 2042 | Z27: 2043 | AA27: 2044 | AB27: 2045 | AC27: 2046 | AD27: 2047 | AE27: 2048 | AF27: 2049 | AG27: 2050 | AH27: 2051 | AI27: 2052 | AJ27: 2053 | AK27: 2054 | AL27: 2055 | AM27: 2056 | AN27: 2057 | AO27: 2058 | AP27: 2059 | AQ27: 2060 | AR27: 2061 | AS27: 2062 | AT27: 2063 | AU27: 2064 | AV27: 2065 | AW27: 2066 | AX27: 2067 | AY27: 2068 | AZ27: 2069 | BA27: 2070
A28: ="Please provide data through to "&FinalYear_BC -> Please provide data through to 1900 | D28: Equipment purchase | E28: =$E$26 -> Real | F28: =IF(E28="Nominal","",Analysis_year&" values") -> values
D29: Civil works | E29: =$E$26 -> Real | F29: =IF(E29="Nominal","",Analysis_year&" values") -> values
D30: Electrical works | E30: =$E$26 -> Real | F30: =IF(E30="Nominal","",Analysis_year&" values") -> values
D31: Installation | E31: =$E$26 -> Real | F31: =IF(E31="Nominal","",Analysis_year&" values") -> values
D32: Indirect costs | E32: =$E$26 -> Real | F32: =IF(E32="Nominal","",Analysis_year&" values") -> values
D33: Project management | E33: =$E$26 -> Real | F33: =IF(E33="Nominal","",Analysis_year&" values") -> values
D34: Other | E34: =$E$26 -> Real | F34: =IF(E34="Nominal","",Analysis_year&" values") -> values
D35: ="Total capex in "&Analysis_year&" dollars" -> Total capex in dollars | H35: =SUM(H28:H34)*IF($E$26="Real",1,H$11) -> 0 | I35: =SUM(I28:I34)*IF($E$26="Real",1,I$11) -> 0 | J35: =SUM(J28:J34)*IF($E$26="Real",1,J$11) -> 0 | K35: =SUM(K28:K34)*IF($E$26="Real",1,K$11) -> 0 | L35: =SUM(L28:L34)*IF($E$26="Real",1,L$11) -> 0 | M35: =SUM(M28:M34)*IF($E$26="Real",1,M$11) -> 0 | N35: =SUM(N28:N34)*IF($E$26="Real",1,N$11) -> 0 | O35: =SUM(O28:O34)*IF($E$26="Real",1,O$11) -> 0 | ... BA35: =SUM(BA28:BA34)*IF($E$26="Real",1,BA$11) -> 0
D36: Total capex in nominal dollars | H36: =SUM(H28:H34)*IF($E$26="Real",H$10,1) -> 0 | I36: =SUM(I28:I34)*IF($E$26="Real",I$10,1) -> 0 | J36: =SUM(J28:J34)*IF($E$26="Real",J$10,1) -> 0 | K36: =SUM(K28:K34)*IF($E$26="Real",K$10,1) -> 0 | L36: =SUM(L28:L34)*IF($E$26="Real",L$10,1) -> 0 | M36: =SUM(M28:M34)*IF($E$26="Real",M$10,1) -> 0 | N36: =SUM(N28:N34)*IF($E$26="Real",N$10,1) -> 0 | O36: =SUM(O28:O34)*IF($E$26="Real",O$10,1) -> 0 | ... BA36: =SUM(BA28:BA34)*IF($E$26="Real",BA$10,1) -> 0
A39: 2) Operating & Maintenance Expenditure (OPEX) ($) - please enter all costs as positive numbers
A40: 2a) Non-fuel opex | D40: Value basis | E40: Nominal
A41: Proposed Project (PP) | D41: Opex item | E41: Value basis | G41: Applicant comment | H41: 2025 | I41: 2026 | J41: 2027 | K41: 2028 | L41: 2029 | M41: 2030 | N41: 2031 | O41: 2032 | P41: 2033 | Q41: 2034 | R41: 2035 | S41: 2036 | T41: 2037 | U41: 2038 | V41: 2039 | W41: 2040 | X41: 2041 | Y41: 2042 | Z41: 2043 | AA41: 2044 | AB41: 2045 | AC41: 2046 | AD41: 2047 | AE41: 2048 | AF41: 2049 | AG41: 2050 | AH41: 2051 | AI41: 2052 | AJ41: 2053 | AK41: 2054 | AL41: 2055 | AM41: 2056 | AN41: 2057 | AO41: 2058 | AP41: 2059 | AQ41: 2060 | AR41: 2061 | AS41: 2062 | AT41: 2063 | AU41: 2064 | AV41: 2065 | AW41: 2066 | AX41: 2067 | AY41: 2068 | AZ41: 2069 | BA41: 2070
A42: ="Please provide data through to "&FinalYear_PP -> Please provide data through to 1900 | D42: Equipment Operation Costs | E42: =$E$40 -> Nominal | F42: =IF(E42="Nominal","",Analysis_year&" values")
D43: Maintenance, Repairs, Inspections | E43: =$E$40 -> Nominal | F43: =IF(E43="Nominal","",Analysis_year&" values")
D44: Compliance Testing | E44: =$E$40 -> Nominal | F44: =IF(E44="Nominal","",Analysis_year&" values")
D45: Optimisation | E45: =$E$40 -> Nominal | F45: =IF(E45="Nominal","",Analysis_year&" values")
D46: Utilities and Consumables | E46: =$E$40 -> Nominal | F46: =IF(E46="Nominal","",Analysis_year&" values")
D47: Other | E47: =$E$40 -> Nominal | F47: =IF(E47="Nominal","",Analysis_year&" values")
D48: ="Total non-fuel opex in "&Analysis_year&" dollars" -> Total non-fuel opex in dollars | H48: =SUM(H42:H47)*IF($E$40="Real",1,H$11) -> 0 | I48: =SUM(I42:I47)*IF($E$40="Real",1,I$11) -> 0 | J48: =SUM(J42:J47)*IF($E$40="Real",1,J$11) -> 0 | K48: =SUM(K42:K47)*IF($E$40="Real",1,K$11) -> 0 | L48: =SUM(L42:L47)*IF($E$40="Real",1,L$11) -> 0 | M48: =SUM(M42:M47)*IF($E$40="Real",1,M$11) -> 0 | N48: =SUM(N42:N47)*IF($E$40="Real",1,N$11) -> 0 | O48: =SUM(O42:O47)*IF($E$40="Real",1,O$11) -> 0 | ... BA48: =SUM(BA42:BA47)*IF($E$40="Real",1,BA$11) -> 0
D49: Total non-fuel opex in nominal dollars | H49: =SUM(H42:H47)*IF($E$40="Real",H$10,1) -> 0 | I49: =SUM(I42:I47)*IF($E$40="Real",I$10,1) -> 0 | J49: =SUM(J42:J47)*IF($E$40="Real",J$10,1) -> 0 | K49: =SUM(K42:K47)*IF($E$40="Real",K$10,1) -> 0 | L49: =SUM(L42:L47)*IF($E$40="Real",L$10,1) -> 0 | M49: =SUM(M42:M47)*IF($E$40="Real",M$10,1) -> 0 | N49: =SUM(N42:N47)*IF($E$40="Real",N$10,1) -> 0 | O49: =SUM(O42:O47)*IF($E$40="Real",O$10,1) -> 0 | ... BA49: =SUM(BA42:BA47)*IF($E$40="Real",BA$10,1) -> 0
D51: Value basis | E51: Real
A52: Base Case (BC) | D52: Opex item | E52: Value basis | G52: Applicant comment | H52: 2025 | I52: 2026 | J52: 2027 | K52: 2028 | L52: 2029 | M52: 2030 | N52: 2031 | O52: 2032 | P52: 2033 | Q52: 2034 | R52: 2035 | S52: 2036 | T52: 2037 | U52: 2038 | V52: 2039 | W52: 2040 | X52: 2041 | Y52: 2042 | Z52: 2043 | AA52: 2044 | AB52: 2045 | AC52: 2046 | AD52: 2047 | AE52: 2048 | AF52: 2049 | AG52: 2050 | AH52: 2051 | AI52: 2052 | AJ52: 2053 | AK52: 2054 | AL52: 2055 | AM52: 2056 | AN52: 2057 | AO52: 2058 | AP52: 2059 | AQ52: 2060 | AR52: 2061 | AS52: 2062 | AT52: 2063 | AU52: 2064 | AV52: 2065 | AW52: 2066 | AX52: 2067 | AY52: 2068 | AZ52: 2069 | BA52: 2070
A53: ="Please provide data through to "&FinalYear_BC -> Please provide data through to 1900 | D53: Equipment Operation Costs | E53: =$E$51 -> Real | F53: =IF(E53="Nominal","",Analysis_year&" values") -> values
D54: Maintenance, Repairs, Inspections | E54: =$E$51 -> Real | F54: =IF(E54="Nominal","",Analysis_year&" values") -> values
D55: Compliance Testing | E55: =$E$51 -> Real | F55: =IF(E55="Nominal","",Analysis_year&" values") -> values
D56: Optimisation | E56: =$E$51 -> Real | F56: =IF(E56="Nominal","",Analysis_year&" values") -> values
D57: Utilities and Consumables | E57: =$E$51 -> Real | F57: =IF(E57="Nominal","",Analysis_year&" values") -> values
D58: Other | E58: =$E$51 -> Real | F58: =IF(E58="Nominal","",Analysis_year&" values") -> values
D59: ="Total non-fuel opex in "&Analysis_year&" dollars" -> Total non-fuel opex in dollars | H59: =SUM(H53:H58)*IF($E$51="Real",1,H$11) -> 0 | I59: =SUM(I53:I58)*IF($E$51="Real",1,I$11) -> 0 | J59: =SUM(J53:J58)*IF($E$51="Real",1,J$11) -> 0 | K59: =SUM(K53:K58)*IF($E$51="Real",1,K$11) -> 0 | L59: =SUM(L53:L58)*IF($E$51="Real",1,L$11) -> 0 | M59: =SUM(M53:M58)*IF($E$51="Real",1,M$11) -> 0 | N59: =SUM(N53:N58)*IF($E$51="Real",1,N$11) -> 0 | O59: =SUM(O53:O58)*IF($E$51="Real",1,O$11) -> 0 | ... BA59: =SUM(BA53:BA58)*IF($E$51="Real",1,BA$11) -> 0
D60: Total non-fuel opex in nominal dollars | H60: =SUM(H53:H58)*IF($E$51="Real",H10,1) -> 0 | I60: =SUM(I53:I58)*IF($E$51="Real",I10,1) -> 0 | J60: =SUM(J53:J58)*IF($E$51="Real",J10,1) -> 0 | K60: =SUM(K53:K58)*IF($E$51="Real",K10,1) -> 0 | L60: =SUM(L53:L58)*IF($E$51="Real",L10,1) -> 0 | M60: =SUM(M53:M58)*IF($E$51="Real",M10,1) -> 0 | N60: =SUM(N53:N58)*IF($E$51="Real",N10,1) -> 0 | O60: =SUM(O53:O58)*IF($E$51="Real",O10,1) -> 0 | ... BA60: =SUM(BA53:BA58)*IF($E$51="Real",BA10,1) -> 0
A62: 2b) Fuel consumption
A63: Proposed Project (PP) | D63: Fuel type | E63: Units | G63: Applicant comment | H63: 2025 | I63: 2026 | J63: 2027 | K63: 2028 | L63: 2029 | M63: 2030 | N63: 2031 | O63: 2032 | P63: 2033 | Q63: 2034 | R63: 2035 | S63: 2036 | T63: 2037 | U63: 2038 | V63: 2039 | W63: 2040 | X63: 2041 | Y63: 2042 | Z63: 2043 | AA63: 2044 | AB63: 2045 | AC63: 2046 | AD63: 2047 | AE63: 2048 | AF63: 2049 | AG63: 2050 | AH63: 2051 | AI63: 2052 | AJ63: 2053 | AK63: 2054 | AL63: 2055 | AM63: 2056 | AN63: 2057 | AO63: 2058 | AP63: 2059 | AQ63: 2060 | AR63: 2061 | AS63: 2062 | AT63: 2063 | AU63: 2064 | AV63: 2065 | AW63: 2066 | AX63: 2067 | AY63: 2068 | AZ63: 2069 | BA63: 2070
A64: ="Please provide data through to "&FinalYear_PP -> Please provide data through to 1900 | D64: =Data!D3 -> Electricity | E64: =Data!E3 -> MWh
D65: =Data!D4 -> Natural Gas | E65: =Data!E4 -> GJ
D66: =Data!D5 -> Coal - sub bituminous | E66: =Data!E5 -> tonnes
D67: =Data!D6 -> Coal - bituminous | E67: =Data!E6 -> tonnes
D68: =Data!D7 -> Coal - lignite | E68: =Data!E7 -> tonnes
D69: =Data!D8 -> Diesel | E69: =Data!E8 -> litres
D70: =Data!D9 -> LPG | E70: =Data!E9 -> m3
D71: =Data!D10 -> Light fuel oil | E71: =Data!E10 -> litres
D72: =Data!D11 -> Heavy fuel oil | E72: =Data!E11 -> litres
D73: =Data!D12 -> Geothermal | E73: =Data!E12 -> kWh
D74: =Data!D13 -> Wood or wood chips | E74: =Data!E13 -> tonnes
A76: Base Case (BC) | D76: Fuel type | E76: Units | G76: Applicant comment | H76: 2025 | I76: 2026 | J76: 2027 | K76: 2028 | L76: 2029 | M76: 2030 | N76: 2031 | O76: 2032 | P76: 2033 | Q76: 2034 | R76: 2035 | S76: 2036 | T76: 2037 | U76: 2038 | V76: 2039 | W76: 2040 | X76: 2041 | Y76: 2042 | Z76: 2043 | AA76: 2044 | AB76: 2045 | AC76: 2046 | AD76: 2047 | AE76: 2048 | AF76: 2049 | AG76: 2050 | AH76: 2051 | AI76: 2052 | AJ76: 2053 | AK76: 2054 | AL76: 2055 | AM76: 2056 | AN76: 2057 | AO76: 2058 | AP76: 2059 | AQ76: 2060 | AR76: 2061 | AS76: 2062 | AT76: 2063 | AU76: 2064 | AV76: 2065 | AW76: 2066 | AX76: 2067 | AY76: 2068 | AZ76: 2069 | BA76: 2070
A77: ="Please provide data through to "&FinalYear_BC -> Please provide data through to 1900 | D77: =Data!D3 -> Electricity | E77: =Data!E3 -> MWh
D78: =Data!D4 -> Natural Gas | E78: =Data!E4 -> GJ
D79: =Data!D5 -> Coal - sub bituminous | E79: =Data!E5 -> tonnes
D80: =Data!D6 -> Coal - bituminous | E80: =Data!E6 -> tonnes
D81: =Data!D7 -> Coal - lignite | E81: =Data!E7 -> tonnes
D82: =Data!D8 -> Diesel | E82: =Data!E8 -> litres
D83: =Data!D9 -> LPG | E83: =Data!E9 -> m3
D84: =Data!D10 -> Light fuel oil | E84: =Data!E10 -> litres
D85: =Data!D11 -> Heavy fuel oil | E85: =Data!E11 -> litres
D86: =Data!D12 -> Geothermal | E86: =Data!E12 -> kWh
D87: =Data!D13 -> Wood or wood chips | E87: =Data!E13 -> tonnes
A89: 2b) Expected fuel prices (excl GST)
A90: Proposed Project (PP) | B90: Fuel type | C90: Units | D90: ETS cost included? | E90: Value basis | G90: Applicant comment | H90: 2025 | I90: 2026 | J90: 2027 | K90: 2028 | L90: 2029 | M90: 2030 | N90: 2031 | O90: 2032 | P90: 2033 | Q90: 2034 | R90: 2035 | S90: 2036 | T90: 2037 | U90: 2038 | V90: 2039 | W90: 2040 | X90: 2041 | Y90: 2042 | Z90: 2043 | AA90: 2044 | AB90: 2045 | AC90: 2046 | AD90: 2047 | AE90: 2048 | AF90: 2049 | AG90: 2050 | AH90: 2051 | AI90: 2052 | AJ90: 2053 | AK90: 2054 | AL90: 2055 | AM90: 2056 | AN90: 2057 | AO90: 2058 | AP90: 2059 | AQ90: 2060 | AR90: 2061 | AS90: 2062 | AT90: 2063 | AU90: 2064 | AV90: 2065 | AW90: 2066 | AX90: 2067 | AY90: 2068 | AZ90: 2069 | BA90: 2070
A91: ="Please provide data through to "&FinalYear_PP -> Please provide data through to 1900 | B91: =Data!D3 -> Electricity | C91: ="$/"&IF(RIGHT(E64,1)="s",LEFT(E64,LEN(E64)-1),E64) -> $/MWh | D91: Yes | E91: Real | F91: =IF(E91="Nominal","",Analysis_year&" values") -> values | H91: 250 | I91: 250 | J91: 250 | K91: 250 | L91: 250 | M91: 250 | N91: 250 | O91: 250 | P91: 250 | Q91: 250 | R91: 250 | S91: 250 | T91: 250 | U91: 250 | V91: 250 | W91: 250 | X91: 250 | Y91: 250 | Z91: 250 | AA91: 250 | AB91: 250 | AC91: 250
B92: =Data!D4 -> Natural Gas | C92: ="$/"&IF(RIGHT(E65,1)="s",LEFT(E65,LEN(E65)-1),E65) -> $/GJ | D92: Yes | E92: Real | F92: =IF(E92="Nominal","",Analysis_year&" values") -> values | H92: 10 | I92: 10 | J92: 10 | K92: 10 | L92: 10 | M92: 10 | N92: 10 | O92: 10 | P92: 10 | Q92: 10 | R92: 10 | S92: 10 | T92: 10 | U92: 10 | V92: 10 | W92: 10 | X92: 10 | Y92: 10 | Z92: 10 | AA92: 10 | AB92: 10 | AC92: 10
B93: =Data!D5 -> Coal - sub bituminous | C93: ="$/"&IF(RIGHT(E66,1)="s",LEFT(E66,LEN(E66)-1),E66) -> $/tonne | D93: Yes | E93: Real | F93: =IF(E93="Nominal","",Analysis_year&" values") -> values | H93: 150 | I93: 150 | J93: 150 | K93: 150 | L93: 150 | M93: 150 | N93: 150 | O93: 150 | P93: 150 | Q93: 150 | R93: 150 | S93: 150 | T93: 150 | U93: 150 | V93: 150 | W93: 150 | X93: 150 | Y93: 150 | Z93: 150 | AA93: 150 | AB93: 150 | AC93: 150
B94: =Data!D6 -> Coal - bituminous | C94: ="$/"&IF(RIGHT(E67,1)="s",LEFT(E67,LEN(E67)-1),E67) -> $/tonne | D94: Yes | E94: Real | F94: =IF(E94="Nominal","",Analysis_year&" values") -> values
B95: =Data!D7 -> Coal - lignite | C95: ="$/"&IF(RIGHT(E68,1)="s",LEFT(E68,LEN(E68)-1),E68) -> $/tonne | D95: Yes | E95: Real | F95: =IF(E95="Nominal","",Analysis_year&" values") -> values
B96: =Data!D8 -> Diesel | C96: ="$/"&IF(RIGHT(E69,1)="s",LEFT(E69,LEN(E69)-1),E69) -> $/litre | D96: Yes | E96: Real | F96: =IF(E96="Nominal","",Analysis_year&" values") -> values | H96: 2 | I96: 2 | J96: 2 | K96: 2 | L96: 2 | M96: 2 | N96: 2 | O96: 2 | P96: 2 | Q96: 2 | R96: 2 | S96: 2 | T96: 2 | U96: 2 | V96: 2 | W96: 2 | X96: 2 | Y96: 0 | Z96: 0 | AA96: 0 | AB96: 0 | AC96: 0 | AD96: 0 | AE96: 0 | AF96: 0 | AG96: 0 | AH96: 0 | AI96: 0 | AJ96: 0 | AK96: 0 | AL96: 0 | AM96: 0 | AN96: 0 | AO96: 0 | AP96: 0 | AQ96: 0 | AR96: 0 | AS96: 0 | AT96: 0 | AU96: 0 | AV96: 0 | AW96: 0 | AX96: 0 | AY96: 0 | AZ96: 0 | BA96: 1
B97: =Data!D9 -> LPG | C97: ="$/"&IF(RIGHT(E70,1)="s",LEFT(E70,LEN(E70)-1),E70) -> $/m3 | D97: Yes | E97: Real | F97: =IF(E97="Nominal","",Analysis_year&" values") -> values
B98: =Data!D10 -> Light fuel oil | C98: ="$/"&IF(RIGHT(E71,1)="s",LEFT(E71,LEN(E71)-1),E71) -> $/litre | D98: Yes | E98: Real | F98: =IF(E98="Nominal","",Analysis_year&" values") -> values
B99: =Data!D11 -> Heavy fuel oil | C99: ="$/"&IF(RIGHT(E72,1)="s",LEFT(E72,LEN(E72)-1),E72) -> $/litre | D99: Yes | E99: Real | F99: =IF(E99="Nominal","",Analysis_year&" values") -> values
B100: =Data!D12 -> Geothermal | C100: ="$/"&IF(RIGHT(E73,1)="s",LEFT(E73,LEN(E73)-1),E73) -> $/kWh | D100: Yes | E100: Real | F100: =IF(E100="Nominal","",Analysis_year&" values") -> values
B101: =Data!D13 -> Wood or wood chips | C101: ="$/"&IF(RIGHT(E74,1)="s",LEFT(E74,LEN(E74)-1),E74) -> $/tonne | D101: Yes | E101: Real | F101: =IF(E101="Nominal","",Analysis_year&" values") -> values
A103: Base Case (BC) | B103: Fuel type | C103: Units | D103: ETS cost included? | E103: Value basis | G103: Applicant comment | H103: 2025 | I103: 2026 | J103: 2027 | K103: 2028 | L103: 2029 | M103: 2030 | N103: 2031 | O103: 2032 | P103: 2033 | Q103: 2034 | R103: 2035 | S103: 2036 | T103: 2037 | U103: 2038 | V103: 2039 | W103: 2040 | X103: 2041 | Y103: 2042 | Z103: 2043 | AA103: 2044 | AB103: 2045 | AC103: 2046 | AD103: 2047 | AE103: 2048 | AF103: 2049 | AG103: 2050 | AH103: 2051 | AI103: 2052 | AJ103: 2053 | AK103: 2054 | AL103: 2055 | AM103: 2056 | AN103: 2057 | AO103: 2058 | AP103: 2059 | AQ103: 2060 | AR103: 2061 | AS103: 2062 | AT103: 2063 | AU103: 2064 | AV103: 2065 | AW103: 2066 | AX103: 2067 | AY103: 2068 | AZ103: 2069 | BA103: 2070
A104: ="Please provide data through to "&FinalYear_BC -> Please provide data through to 1900 | B104: =Data!D3 -> Electricity | C104: ="$/"&IF(RIGHT(E77,1)="s",LEFT(E77,LEN(E77)-1),E77) -> $/MWh | D104: Yes | E104: Real | F104: =IF(E104="Nominal","",Analysis_year&" values") -> values | H104: 250 | I104: 250 | J104: 250 | K104: 250 | L104: 250 | M104: 250 | N104: 250 | O104: 250 | P104: 250 | Q104: 250 | R104: 250 | S104: 250 | T104: 250 | U104: 250 | V104: 250 | W104: 250 | X104: 250 | Y104: 250 | Z104: 250 | AA104: 250 | AB104: 250 | AC104: 250
B105: =Data!D4 -> Natural Gas | C105: ="$/"&IF(RIGHT(E78,1)="s",LEFT(E78,LEN(E78)-1),E78) -> $/GJ | D105: Yes | E105: Real | F105: =IF(E105="Nominal","",Analysis_year&" values") -> values | H105: 10 | I105: 10 | J105: 10 | K105: 10 | L105: 10 | M105: 10 | N105: 10 | O105: 10 | P105: 10 | Q105: 10 | R105: 10 | S105: 10 | T105: 10 | U105: 10 | V105: 10 | W105: 10 | X105: 10 | Y105: 10 | Z105: 10 | AA105: 10 | AB105: 10 | AC105: 10
B106: =Data!D5 -> Coal - sub bituminous | C106: ="$/"&IF(RIGHT(E79,1)="s",LEFT(E79,LEN(E79)-1),E79) -> $/tonne | D106: Yes | E106: Real | F106: =IF(E106="Nominal","",Analysis_year&" values") -> values | H106: 150 | I106: 150 | J106: 150 | K106: 150 | L106: 150 | M106: 150 | N106: 150 | O106: 150 | P106: 150 | Q106: 150 | R106: 150 | S106: 150 | T106: 150 | U106: 150 | V106: 150 | W106: 150 | X106: 150 | Y106: 150 | Z106: 150 | AA106: 150 | AB106: 150 | AC106: 150
B107: =Data!D6 -> Coal - bituminous | C107: ="$/"&IF(RIGHT(E80,1)="s",LEFT(E80,LEN(E80)-1),E80) -> $/tonne | D107: Yes | E107: Real | F107: =IF(E107="Nominal","",Analysis_year&" values") -> values
B108: =Data!D7 -> Coal - lignite | C108: ="$/"&IF(RIGHT(E81,1)="s",LEFT(E81,LEN(E81)-1),E81) -> $/tonne | D108: Yes | E108: Real | F108: =IF(E108="Nominal","",Analysis_year&" values") -> values
B109: =Data!D8 -> Diesel | C109: ="$/"&IF(RIGHT(E82,1)="s",LEFT(E82,LEN(E82)-1),E82) -> $/litre | D109: Yes | E109: Real | F109: =IF(E109="Nominal","",Analysis_year&" values") -> values | H109: 2 | I109: 2 | J109: 2 | K109: 2 | L109: 2 | M109: 2 | N109: 2 | O109: 2 | P109: 2 | Q109: 2 | R109: 2 | S109: 2 | T109: 2 | U109: 2 | V109: 2 | W109: 2 | X109: 2 | Y109: 2 | Z109: 2 | AA109: 2 | AB109: 2 | AC109: 2 | AD109: 2 | AE109: 2 | AF109: 2 | AG109: 2 | AH109: 2 | AI109: 2 | AJ109: 2 | AK109: 2 | AL109: 2 | AM109: 2 | AN109: 2 | AO109: 2 | AP109: 2 | AQ109: 2 | AR109: 2 | AS109: 2 | AT109: 2 | AU109: 2 | AV109: 2 | AW109: 2 | AX109: 2 | AY109: 2 | AZ109: 2 | BA109: 2
B110: =Data!D9 -> LPG | C110: ="$/"&IF(RIGHT(E83,1)="s",LEFT(E83,LEN(E83)-1),E83) -> $/m3 | D110: Yes | E110: Real | F110: =IF(E110="Nominal","",Analysis_year&" values") -> values
...

Sheet Scratch

Sheet Real values
A2: Financial projection basis
L3: =Inputs!H6 -> 2025 | M3: =Inputs!I6 -> 2026 | N3: =Inputs!J6 -> 2027 | O3: =Inputs!K6 -> 2028 | P3: =Inputs!L6 -> 2029 | Q3: =Inputs!M6 -> 2030 | R3: =Inputs!N6 -> 2031 | S3: =Inputs!O6 -> 2032 | ... BE3: =Inputs!BA6 -> 2070
A4: Inflator - use this to convert real values to nominal | L4: =Inputs!H10 -> 0 | M4: =Inputs!I10 -> 0 | N4: =Inputs!J10 -> 0 | O4: =Inputs!K10 -> 0 | P4: =Inputs!L10 -> 0 | Q4: =Inputs!M10 -> 0 | R4: =Inputs!N10 -> 0 | S4: =Inputs!O10 -> 0 | ... BE4: =Inputs!BA10 -> 0
A5: Deflator - use this to convert nominal values to real | L5: =Inputs!H11 -> 0 | M5: =Inputs!I11 -> 0 | N5: =Inputs!J11 -> 0 | O5: =Inputs!K11 -> 0 | P5: =Inputs!L11 -> 0 | Q5: =Inputs!M11 -> 0 | R5: =Inputs!N11 -> 0 | S5: =Inputs!O11 -> 0 | ... BE5: =Inputs!BA11 -> 0
A7: 1) Capital expenditure (CAPEX) ($) - please enter all costs as positive numbers
A9: Proposed Project (PP) | D9: ProjectId | E9: LifeCycleMonths | F9: Scenario | G9: ExpenseType | H9: Capex item | I9: Value basis | J9: Base year | K9: Applicant comment | L9: 2025 | M9: 2026 | N9: 2027 | O9: 2028 | P9: 2029 | Q9: 2030 | R9: 2031 | S9: 2032 | T9: 2033 | U9: 2034 | V9: 2035 | W9: 2036 | X9: 2037 | Y9: 2038 | Z9: 2039 | AA9: 2040 | AB9: 2041 | AC9: 2042 | AD9: 2043 | AE9: 2044 | AF9: 2045 | AG9: 2046 | AH9: 2047 | AI9: 2048 | AJ9: 2049 | AK9: 2050 | AL9: 2051 | AM9: 2052 | AN9: 2053 | AO9: 2054 | AP9: 2055 | AQ9: 2056 | AR9: 2057 | AS9: 2058 | AT9: 2059 | AU9: 2060 | AV9: 2061 | AW9: 2062 | AX9: 2063 | AY9: 2064 | AZ9: 2065 | BA9: 2066 | BB9: 2067 | BC9: 2068 | BD9: 2069 | BE9: 2070
D10: ='Project description'!$B$5 -> 0 | E10: =Lists!$B$34 | F10: PP | G10: capex | H10: Equipment purchase | I10: Real | J10: =Analysis_year -> 0 | K10: =IF(Inputs!G16="","",Inputs!G16) | L10: =Inputs!H16*IF(Inputs!$E16="Real",1,L$5) -> 0 | M10: =Inputs!I16*IF(Inputs!$E16="Real",1,M$5) -> 0 | N10: =Inputs!J16*IF(Inputs!$E16="Real",1,N$5) -> 0 | O10: =Inputs!K16*IF(Inputs!$E16="Real",1,O$5) -> 0 | P10: =Inputs!L16*IF(Inputs!$E16="Real",1,P$5) -> 0 | Q10: =Inputs!M16*IF(Inputs!$E16="Real",1,Q$5) -> 0 | R10: =Inputs!N16*IF(Inputs!$E16="Real",1,R$5) -> 0 | S10: =Inputs!O16*IF(Inputs!$E16="Real",1,S$5) -> 0 | ... BE10: =Inputs!BA16*IF(Inputs!$E16="Real",1,BE$5) -> 0
D11: ='Project description'!$B$5 -> 0 | E11: =Lists!$B$34 | F11: PP | G11: capex | H11: Civil works | I11: Real | J11: =Analysis_year -> 0 | K11: =IF(Inputs!G17="","",Inputs!G17) | L11: =Inputs!H17*IF(Inputs!$E17="Real",1,L$5) -> 0 | M11: =Inputs!I17*IF(Inputs!$E17="Real",1,M$5) -> 0 | N11: =Inputs!J17*IF(Inputs!$E17="Real",1,N$5) -> 0 | O11: =Inputs!K17*IF(Inputs!$E17="Real",1,O$5) -> 0 | P11: =Inputs!L17*IF(Inputs!$E17="Real",1,P$5) -> 0 | Q11: =Inputs!M17*IF(Inputs!$E17="Real",1,Q$5) -> 0 | R11: =Inputs!N17*IF(Inputs!$E17="Real",1,R$5) -> 0 | S11: =Inputs!O17*IF(Inputs!$E17="Real",1,S$5) -> 0 | ... BE11: =Inputs!BA17*IF(Inputs!$E17="Real",1,BE$5) -> 0
D12: ='Project description'!$B$5 -> 0 | E12: =Lists!$B$34 | F12: PP | G12: capex | H12: Electrical works | I12: Real | J12: =Analysis_year -> 0 | K12: =IF(Inputs!G18="","",Inputs!G18) | L12: =Inputs!H18*IF(Inputs!$E18="Real",1,L$5) -> 0 | M12: =Inputs!I18*IF(Inputs!$E18="Real",1,M$5) -> 0 | N12: =Inputs!J18*IF(Inputs!$E18="Real",1,N$5) -> 0 | O12: =Inputs!K18*IF(Inputs!$E18="Real",1,O$5) -> 0 | P12: =Inputs!L18*IF(Inputs!$E18="Real",1,P$5) -> 0 | Q12: =Inputs!M18*IF(Inputs!$E18="Real",1,Q$5) -> 0 | R12: =Inputs!N18*IF(Inputs!$E18="Real",1,R$5) -> 0 | S12: =Inputs!O18*IF(Inputs!$E18="Real",1,S$5) -> 0 | ... BE12: =Inputs!BA18*IF(Inputs!$E18="Real",1,BE$5) -> 0
D13: ='Project description'!$B$5 -> 0 | E13: =Lists!$B$34 | F13: PP | G13: capex | H13: Installation | I13: Real | J13: =Analysis_year -> 0 | K13: =IF(Inputs!G19="","",Inputs!G19) | L13: =Inputs!H19*IF(Inputs!$E19="Real",1,L$5) -> 0 | M13: =Inputs!I19*IF(Inputs!$E19="Real",1,M$5) -> 0 | N13: =Inputs!J19*IF(Inputs!$E19="Real",1,N$5) -> 0 | O13: =Inputs!K19*IF(Inputs!$E19="Real",1,O$5) -> 0 | P13: =Inputs!L19*IF(Inputs!$E19="Real",1,P$5) -> 0 | Q13: =Inputs!M19*IF(Inputs!$E19="Real",1,Q$5) -> 0 | R13: =Inputs!N19*IF(Inputs!$E19="Real",1,R$5) -> 0 | S13: =Inputs!O19*IF(Inputs!$E19="Real",1,S$5) -> 0 | ... BE13: =Inputs!BA19*IF(Inputs!$E19="Real",1,BE$5) -> 0
D14: ='Project description'!$B$5 -> 0 | E14: =Lists!$B$34 | F14: PP | G14: capex | H14: Indirect costs | I14: Real | J14: =Analysis_year -> 0 | K14: =IF(Inputs!G20="","",Inputs!G20) | L14: =Inputs!H20*IF(Inputs!$E20="Real",1,L$5) -> 0 | M14: =Inputs!I20*IF(Inputs!$E20="Real",1,M$5) -> 0 | N14: =Inputs!J20*IF(Inputs!$E20="Real",1,N$5) -> 0 | O14: =Inputs!K20*IF(Inputs!$E20="Real",1,O$5) -> 0 | P14: =Inputs!L20*IF(Inputs!$E20="Real",1,P$5) -> 0 | Q14: =Inputs!M20*IF(Inputs!$E20="Real",1,Q$5) -> 0 | R14: =Inputs!N20*IF(Inputs!$E20="Real",1,R$5) -> 0 | S14: =Inputs!O20*IF(Inputs!$E20="Real",1,S$5) -> 0 | ... BE14: =Inputs!BA20*IF(Inputs!$E20="Real",1,BE$5) -> 0
D15: ='Project description'!$B$5 -> 0 | E15: =Lists!$B$34 | F15: PP | G15: capex | H15: Project management | I15: Real | J15: =Analysis_year -> 0 | K15: =IF(Inputs!G21="","",Inputs!G21) | L15: =Inputs!H21*IF(Inputs!$E21="Real",1,L$5) -> 0 | M15: =Inputs!I21*IF(Inputs!$E21="Real",1,M$5) -> 0 | N15: =Inputs!J21*IF(Inputs!$E21="Real",1,N$5) -> 0 | O15: =Inputs!K21*IF(Inputs!$E21="Real",1,O$5) -> 0 | P15: =Inputs!L21*IF(Inputs!$E21="Real",1,P$5) -> 0 | Q15: =Inputs!M21*IF(Inputs!$E21="Real",1,Q$5) -> 0 | R15: =Inputs!N21*IF(Inputs!$E21="Real",1,R$5) -> 0 | S15: =Inputs!O21*IF(Inputs!$E21="Real",1,S$5) -> 0 | ... BE15: =Inputs!BA21*IF(Inputs!$E21="Real",1,BE$5) -> 0
D16: ='Project description'!$B$5 -> 0 | E16: =Lists!$B$34 | F16: PP | G16: capex | H16: Other | I16: Real | J16: =Analysis_year -> 0 | K16: =IF(Inputs!G22="","",Inputs!G22) | L16: =Inputs!H22*IF(Inputs!$E22="Real",1,L$5) -> 0 | M16: =Inputs!I22*IF(Inputs!$E22="Real",1,M$5) -> 0 | N16: =Inputs!J22*IF(Inputs!$E22="Real",1,N$5) -> 0 | O16: =Inputs!K22*IF(Inputs!$E22="Real",1,O$5) -> 0 | P16: =Inputs!L22*IF(Inputs!$E22="Real",1,P$5) -> 0 | Q16: =Inputs!M22*IF(Inputs!$E22="Real",1,Q$5) -> 0 | R16: =Inputs!N22*IF(Inputs!$E22="Real",1,R$5) -> 0 | S16: =Inputs!O22*IF(Inputs!$E22="Real",1,S$5) -> 0 | ... BE16: =Inputs!BA22*IF(Inputs!$E22="Real",1,BE$5) -> 0
H17: ="Total capex in "&Analysis_year&" dollars" -> Total capex in dollars | L17: =SUBTOTAL(109,'Real values'!$L$10:$L$16) -> 0 | M17: =SUM(M10:M16)*IF($I$8="Real",1,N$5) -> 0 | N17: =SUM(N10:N16)*IF($I$8="Real",1,O$5) -> 0 | O17: =SUM(O10:O16)*IF($I$8="Real",1,P$5) -> 0 | P17: =SUM(P10:P16)*IF($I$8="Real",1,Q$5) -> 0 | Q17: =SUM(Q10:Q16)*IF($I$8="Real",1,R$5) -> 0 | R17: =SUM(R10:R16)*IF($I$8="Real",1,S$5) -> 0 | S17: =SUM(S10:S16)*IF($I$8="Real",1,T$5) -> 0 | T17: =SUM(T10:T16)*IF($I$8="Real",1,U$5) -> 0 | ... BE17: =SUM(BE10:BE16)*IF($I$8="Real",1,BF$5) -> 0
A19: Base Case (BC) | D19: ProjectId | E19: LifeCycleMonths | F19: Scenario | G19: ExpenseType | H19: Capex item | I19: Value basis | J19: Base year | K19: Applicant comment | L19: 2025 | M19: 2026 | N19: 2027 | O19: 2028 | P19: 2029 | Q19: 2030 | R19: 2031 | S19: 2032 | T19: 2033 | U19: 2034 | V19: 2035 | W19: 2036 | X19: 2037 | Y19: 2038 | Z19: 2039 | AA19: 2040 | AB19: 2041 | AC19: 2042 | AD19: 2043 | AE19: 2044 | AF19: 2045 | AG19: 2046 | AH19: 2047 | AI19: 2048 | AJ19: 2049 | AK19: 2050 | AL19: 2051 | AM19: 2052 | AN19: 2053 | AO19: 2054 | AP19: 2055 | AQ19: 2056 | AR19: 2057 | AS19: 2058 | AT19: 2059 | AU19: 2060 | AV19: 2061 | AW19: 2062 | AX19: 2063 | AY19: 2064 | AZ19: 2065 | BA19: 2066 | BB19: 2067 | BC19: 2068 | BD19: 2069 | BE19: 2070
A20: Expand if more items | D20: ='Project description'!$B$5 -> 0 | E20: =Lists!$B$34 | F20: BC | G20: capex | H20: Equipment purchase | I20: Real | J20: =Analysis_year -> 0 | K20: =IF(Inputs!G28="","",Inputs!G28) | L20: =Inputs!H28*IF(Inputs!$E28="Real",1,L$5) -> 0 | M20: =Inputs!I28*IF(Inputs!$E28="Real",1,M$5) -> 0 | N20: =Inputs!J28*IF(Inputs!$E28="Real",1,N$5) -> 0 | O20: =Inputs!K28*IF(Inputs!$E28="Real",1,O$5) -> 0 | P20: =Inputs!L28*IF(Inputs!$E28="Real",1,P$5) -> 0 | Q20: =Inputs!M28*IF(Inputs!$E28="Real",1,Q$5) -> 0 | R20: =Inputs!N28*IF(Inputs!$E28="Real",1,R$5) -> 0 | S20: =Inputs!O28*IF(Inputs!$E28="Real",1,S$5) -> 0 | ... BE20: =Inputs!BA28*IF(Inputs!$E28="Real",1,BE$5) -> 0
D21: ='Project description'!$B$5 -> 0 | E21: =Lists!$B$34 | F21: BC | G21: capex | H21: Civil works | I21: Real | J21: =Analysis_year -> 0 | K21: =IF(Inputs!G29="","",Inputs!G29) | L21: =Inputs!H29*IF(Inputs!$E29="Real",1,L$5) -> 0 | M21: =Inputs!I29*IF(Inputs!$E29="Real",1,M$5) -> 0 | N21: =Inputs!J29*IF(Inputs!$E29="Real",1,N$5) -> 0 | O21: =Inputs!K29*IF(Inputs!$E29="Real",1,O$5) -> 0 | P21: =Inputs!L29*IF(Inputs!$E29="Real",1,P$5) -> 0 | Q21: =Inputs!M29*IF(Inputs!$E29="Real",1,Q$5) -> 0 | R21: =Inputs!N29*IF(Inputs!$E29="Real",1,R$5) -> 0 | S21: =Inputs!O29*IF(Inputs!$E29="Real",1,S$5) -> 0 | ... BE21: =Inputs!BA29*IF(Inputs!$E29="Real",1,BE$5) -> 0
D22: ='Project description'!$B$5 -> 0 | E22: =Lists!$B$34 | F22: BC | G22: capex | H22: Electrical works | I22: Real | J22: =Analysis_year -> 0 | K22: =IF(Inputs!G30="","",Inputs!G30) | L22: =Inputs!H30*IF(Inputs!$E30="Real",1,L$5) -> 0 | M22: =Inputs!I30*IF(Inputs!$E30="Real",1,M$5) -> 0 | N22: =Inputs!J30*IF(Inputs!$E30="Real",1,N$5) -> 0 | O22: =Inputs!K30*IF(Inputs!$E30="Real",1,O$5) -> 0 | P22: =Inputs!L30*IF(Inputs!$E30="Real",1,P$5) -> 0 | Q22: =Inputs!M30*IF(Inputs!$E30="Real",1,Q$5) -> 0 | R22: =Inputs!N30*IF(Inputs!$E30="Real",1,R$5) -> 0 | S22: =Inputs!O30*IF(Inputs!$E30="Real",1,S$5) -> 0 | ... BE22: =Inputs!BA30*IF(Inputs!$E30="Real",1,BE$5) -> 0
D23: ='Project description'!$B$5 -> 0 | E23: =Lists!$B$34 | F23: BC | G23: capex | H23: Installation | I23: Real | J23: =Analysis_year -> 0 | K23: =IF(Inputs!G31="","",Inputs!G31) | L23: =Inputs!H31*IF(Inputs!$E31="Real",1,L$5) -> 0 | M23: =Inputs!I31*IF(Inputs!$E31="Real",1,M$5) -> 0 | N23: =Inputs!J31*IF(Inputs!$E31="Real",1,N$5) -> 0 | O23: =Inputs!K31*IF(Inputs!$E31="Real",1,O$5) -> 0 | P23: =Inputs!L31*IF(Inputs!$E31="Real",1,P$5) -> 0 | Q23: =Inputs!M31*IF(Inputs!$E31="Real",1,Q$5) -> 0 | R23: =Inputs!N31*IF(Inputs!$E31="Real",1,R$5) -> 0 | S23: =Inputs!O31*IF(Inputs!$E31="Real",1,S$5) -> 0 | ... BE23: =Inputs!BA31*IF(Inputs!$E31="Real",1,BE$5) -> 0
D24: ='Project description'!$B$5 -> 0 | E24: =Lists!$B$34 | F24: BC | G24: capex | H24: Indirect costs | I24: Real | J24: =Analysis_year -> 0 | K24: =IF(Inputs!G32="","",Inputs!G32) | L24: =Inputs!H32*IF(Inputs!$E32="Real",1,L$5) -> 0 | M24: =Inputs!I32*IF(Inputs!$E32="Real",1,M$5) -> 0 | N24: =Inputs!J32*IF(Inputs!$E32="Real",1,N$5) -> 0 | O24: =Inputs!K32*IF(Inputs!$E32="Real",1,O$5) -> 0 | P24: =Inputs!L32*IF(Inputs!$E32="Real",1,P$5) -> 0 | Q24: =Inputs!M32*IF(Inputs!$E32="Real",1,Q$5) -> 0 | R24: =Inputs!N32*IF(Inputs!$E32="Real",1,R$5) -> 0 | S24: =Inputs!O32*IF(Inputs!$E32="Real",1,S$5) -> 0 | ... BE24: =Inputs!BA32*IF(Inputs!$E32="Real",1,BE$5) -> 0
D25: ='Project description'!$B$5 -> 0 | E25: =Lists!$B$34 | F25: BC | G25: capex | H25: Project management | I25: Real | J25: =Analysis_year -> 0 | K25: =IF(Inputs!G33="","",Inputs!G33) | L25: =Inputs!H33*IF(Inputs!$E33="Real",1,L$5) -> 0 | M25: =Inputs!I33*IF(Inputs!$E33="Real",1,M$5) -> 0 | N25: =Inputs!J33*IF(Inputs!$E33="Real",1,N$5) -> 0 | O25: =Inputs!K33*IF(Inputs!$E33="Real",1,O$5) -> 0 | P25: =Inputs!L33*IF(Inputs!$E33="Real",1,P$5) -> 0 | Q25: =Inputs!M33*IF(Inputs!$E33="Real",1,Q$5) -> 0 | R25: =Inputs!N33*IF(Inputs!$E33="Real",1,R$5) -> 0 | S25: =Inputs!O33*IF(Inputs!$E33="Real",1,S$5) -> 0 | ... BE25: =Inputs!BA33*IF(Inputs!$E33="Real",1,BE$5) -> 0
D26: ='Project description'!$B$5 -> 0 | E26: =Lists!$B$34 | F26: BC | G26: capex | H26: Other | I26: Real | J26: =Analysis_year -> 0 | K26: =IF(Inputs!G34="","",Inputs!G34) | L26: =Inputs!H34*IF(Inputs!$E34="Real",1,L$5) -> 0 | M26: =Inputs!I34*IF(Inputs!$E34="Real",1,M$5) -> 0 | N26: =Inputs!J34*IF(Inputs!$E34="Real",1,N$5) -> 0 | O26: =Inputs!K34*IF(Inputs!$E34="Real",1,O$5) -> 0 | P26: =Inputs!L34*IF(Inputs!$E34="Real",1,P$5) -> 0 | Q26: =Inputs!M34*IF(Inputs!$E34="Real",1,Q$5) -> 0 | R26: =Inputs!N34*IF(Inputs!$E34="Real",1,R$5) -> 0 | S26: =Inputs!O34*IF(Inputs!$E34="Real",1,S$5) -> 0 | ... BE26: =Inputs!BA34*IF(Inputs!$E34="Real",1,BE$5) -> 0
H27: ="Total capex in "&Analysis_year&" dollars" -> Total capex in dollars | L27: =SUBTOTAL(109,'Real values'!$L$20:$L$26) -> 0 | M27: =SUBTOTAL(109,'Real values'!$M$20:$M$26) -> 0 | N27: =SUBTOTAL(109,'Real values'!$N$20:$N$26) -> 0 | O27: =SUBTOTAL(109,'Real values'!$O$20:$O$26) -> 0 | P27: =SUBTOTAL(109,'Real values'!$P$20:$P$26) -> 0 | Q27: =SUBTOTAL(109,'Real values'!$Q$20:$Q$26) -> 0 | R27: =SUBTOTAL(109,'Real values'!$R$20:$R$26) -> 0 | S27: =SUBTOTAL(109,'Real values'!$S$20:$S$26) -> 0 | T27: =SUBTOTAL(109,'Real values'!$T$20:$T$26) -> 0 | U27: =SUBTOTAL(109,'Real values'!$U$20:$U$26) -> 0 | V27: =SUBTOTAL(109,'Real values'!$V$20:$V$26) -> 0 | W27: =SUBTOTAL(109,'Real values'!$W$20:$W$26) -> 0 | X27: =SUBTOTAL(109,'Real values'!$X$20:$X$26) -> 0 | Y27: =SUBTOTAL(109,'Real values'!$Y$20:$Y$26) -> 0 | Z27: =SUBTOTAL(109,'Real values'!$Z$20:$Z$26) -> 0 | AA27: =SUBTOTAL(109,'Real values'!$AA$20:$AA$26) -> 0 | AB27: =SUBTOTAL(109,'Real values'!$AB$20:$AB$26) -> 0 | AC27: =SUBTOTAL(109,'Real values'!$AC$20:$AC$26) -> 0 | AD27: =SUBTOTAL(109,'Real values'!$AD$20:$AD$26) -> 0 | AE27: =SUBTOTAL(109,'Real values'!$AE$20:$AE$26) -> 0 | AF27: =SUBTOTAL(109,'Real values'!$AF$20:$AF$26) -> 0 | AG27: =SUBTOTAL(109,'Real values'!$AG$20:$AG$26) -> 0 | AH27: =SUBTOTAL(109,'Real values'!$AH$20:$AH$26) -> 0 | AI27: =SUBTOTAL(109,'Real values'!$AI$20:$AI$26) -> 0 | AJ27: =SUBTOTAL(109,'Real values'!$AJ$20:$AJ$26) -> 0 | AK27: =SUBTOTAL(109,'Real values'!$AK$20:$AK$26) -> 0 | AL27: =SUBTOTAL(109,'Real values'!$AL$20:$AL$26) -> 0 | AM27: =SUBTOTAL(109,'Real values'!$AM$20:$AM$26) -> 0 | AN27: =SUBTOTAL(109,'Real values'!$AN$20:$AN$26) -> 0 | AO27: =SUBTOTAL(109,'Real values'!$AO$20:$AO$26) -> 0 | AP27: =SUBTOTAL(109,'Real values'!$AP$20:$AP$26) -> 0 | AQ27: =SUBTOTAL(109,'Real values'!$AQ$20:$AQ$26) -> 0 | AR27: =SUBTOTAL(109,'Real values'!$AR$20:$AR$26) -> 0 | AS27: =SUBTOTAL(109,'Real values'!$AS$20:$AS$26) -> 0 | AT27: =SUBTOTAL(109,'Real values'!$AT$20:$AT$26) -> 0 | AU27: =SUBTOTAL(109,'Real values'!$AU$20:$AU$26) -> 0 | AV27: =SUBTOTAL(109,'Real values'!$AV$20:$AV$26) -> 0 | AW27: =SUBTOTAL(109,'Real values'!$AW$20:$AW$26) -> 0 | AX27: =SUBTOTAL(109,'Real values'!$AX$20:$AX$26) -> 0 | AY27: =SUBTOTAL(109,'Real values'!$AY$20:$AY$26) -> 0 | AZ27: =SUBTOTAL(109,'Real values'!$AZ$20:$AZ$26) -> 0 | BA27: =SUBTOTAL(109,'Real values'!$BA$20:$BA$26) -> 0 | BB27: =SUBTOTAL(109,'Real values'!$BB$20:$BB$26) -> 0 | BC27: =SUBTOTAL(109,'Real values'!$BC$20:$BC$26) -> 0 | BD27: =SUBTOTAL(109,'Real values'!$BD$20:$BD$26) -> 0 | BE27: =SUBTOTAL(109,'Real values'!$BE$20:$BE$26) -> 0
A29: 2) Operating & Maintenance Expenditure (OPEX) ($) - please enter all costs as positive numbers
A30: 2a) Non-fuel opex
A31: Proposed Project (PP) | D31: ProjectId | E31: LifeCycleMonths | F31: Scenario | G31: ExpenseType | H31: Opex item | I31: Value basis | J31: Base year | K31: Applicant comment | L31: 2025 | M31: 2026 | N31: 2027 | O31: 2028 | P31: 2029 | Q31: 2030 | R31: 2031 | S31: 2032 | T31: 2033 | U31: 2034 | V31: 2035 | W31: 2036 | X31: 2037 | Y31: 2038 | Z31: 2039 | AA31: 2040 | AB31: 2041 | AC31: 2042 | AD31: 2043 | AE31: 2044 | AF31: 2045 | AG31: 2046 | AH31: 2047 | AI31: 2048 | AJ31: 2049 | AK31: 2050 | AL31: 2051 | AM31: 2052 | AN31: 2053 | AO31: 2054 | AP31: 2055 | AQ31: 2056 | AR31: 2057 | AS31: 2058 | AT31: 2059 | AU31: 2060 | AV31: 2061 | AW31: 2062 | AX31: 2063 | AY31: 2064 | AZ31: 2065 | BA31: 2066 | BB31: 2067 | BC31: 2068 | BD31: 2069 | BE31: 2070
D32: ='Project description'!$B$5 -> 0 | E32: =Lists!$B$34 | F32: PP | G32: opex | H32: Equipment Operation Costs | I32: Real | J32: =Analysis_year -> 0 | K32: =IF(Inputs!G42="","",Inputs!G42) | L32: =Inputs!H42*IF(Inputs!$E42="Real",1,L$5) -> 0 | M32: =Inputs!I42*IF(Inputs!$E42="Real",1,M$5) -> 0 | N32: =Inputs!J42*IF(Inputs!$E42="Real",1,N$5) -> 0 | O32: =Inputs!K42*IF(Inputs!$E42="Real",1,O$5) -> 0 | P32: =Inputs!L42*IF(Inputs!$E42="Real",1,P$5) -> 0 | Q32: =Inputs!M42*IF(Inputs!$E42="Real",1,Q$5) -> 0 | R32: =Inputs!N42*IF(Inputs!$E42="Real",1,R$5) -> 0 | S32: =Inputs!O42*IF(Inputs!$E42="Real",1,S$5) -> 0 | ... BE32: =Inputs!BA42*IF(Inputs!$E42="Real",1,BE$5) -> 0
D33: ='Project description'!$B$5 -> 0 | E33: =Lists!$B$34 | F33: PP | G33: opex | H33: Maintenance, Repairs, Inspections | I33: Real | J33: =Analysis_year -> 0 | K33: =IF(Inputs!G43="","",Inputs!G43) | L33: =Inputs!H43*IF(Inputs!$E43="Real",1,L$5) -> 0 | M33: =Inputs!I43*IF(Inputs!$E43="Real",1,M$5) -> 0 | N33: =Inputs!J43*IF(Inputs!$E43="Real",1,N$5) -> 0 | O33: =Inputs!K43*IF(Inputs!$E43="Real",1,O$5) -> 0 | P33: =Inputs!L43*IF(Inputs!$E43="Real",1,P$5) -> 0 | Q33: =Inputs!M43*IF(Inputs!$E43="Real",1,Q$5) -> 0 | R33: =Inputs!N43*IF(Inputs!$E43="Real",1,R$5) -> 0 | S33: =Inputs!O43*IF(Inputs!$E43="Real",1,S$5) -> 0 | ... BE33: =Inputs!BA43*IF(Inputs!$E43="Real",1,BE$5) -> 0
D34: ='Project description'!$B$5 -> 0 | E34: =Lists!$B$34 | F34: PP | G34: opex | H34: Compliance Testing | I34: Real | J34: =Analysis_year -> 0 | K34: =IF(Inputs!G44="","",Inputs!G44) | L34: =Inputs!H44*IF(Inputs!$E44="Real",1,L$5) -> 0 | M34: =Inputs!I44*IF(Inputs!$E44="Real",1,M$5) -> 0 | N34: =Inputs!J44*IF(Inputs!$E44="Real",1,N$5) -> 0 | O34: =Inputs!K44*IF(Inputs!$E44="Real",1,O$5) -> 0 | P34: =Inputs!L44*IF(Inputs!$E44="Real",1,P$5) -> 0 | Q34: =Inputs!M44*IF(Inputs!$E44="Real",1,Q$5) -> 0 | R34: =Inputs!N44*IF(Inputs!$E44="Real",1,R$5) -> 0 | S34: =Inputs!O44*IF(Inputs!$E44="Real",1,S$5) -> 0 | ... BE34: =Inputs!BA44*IF(Inputs!$E44="Real",1,BE$5) -> 0
D35: ='Project description'!$B$5 -> 0 | E35: =Lists!$B$34 | F35: PP | G35: opex | H35: Optimisation | I35: Real | J35: =Analysis_year -> 0 | K35: =IF(Inputs!G45="","",Inputs!G45) | L35: =Inputs!H45*IF(Inputs!$E45="Real",1,L$5) -> 0 | M35: =Inputs!I45*IF(Inputs!$E45="Real",1,M$5) -> 0 | N35: =Inputs!J45*IF(Inputs!$E45="Real",1,N$5) -> 0 | O35: =Inputs!K45*IF(Inputs!$E45="Real",1,O$5) -> 0 | P35: =Inputs!L45*IF(Inputs!$E45="Real",1,P$5) -> 0 | Q35: =Inputs!M45*IF(Inputs!$E45="Real",1,Q$5) -> 0 | R35: =Inputs!N45*IF(Inputs!$E45="Real",1,R$5) -> 0 | S35: =Inputs!O45*IF(Inputs!$E45="Real",1,S$5) -> 0 | ... BE35: =Inputs!BA45*IF(Inputs!$E45="Real",1,BE$5) -> 0
D36: ='Project description'!$B$5 -> 0 | E36: =Lists!$B$34 | F36: PP | G36: opex | H36: Utilities and Consumables | I36: Real | J36: =Analysis_year -> 0 | K36: =IF(Inputs!G46="","",Inputs!G46) | L36: =Inputs!H46*IF(Inputs!$E46="Real",1,L$5) -> 0 | M36: =Inputs!I46*IF(Inputs!$E46="Real",1,M$5) -> 0 | N36: =Inputs!J46*IF(Inputs!$E46="Real",1,N$5) -> 0 | O36: =Inputs!K46*IF(Inputs!$E46="Real",1,O$5) -> 0 | P36: =Inputs!L46*IF(Inputs!$E46="Real",1,P$5) -> 0 | Q36: =Inputs!M46*IF(Inputs!$E46="Real",1,Q$5) -> 0 | R36: =Inputs!N46*IF(Inputs!$E46="Real",1,R$5) -> 0 | S36: =Inputs!O46*IF(Inputs!$E46="Real",1,S$5) -> 0 | ... BE36: =Inputs!BA46*IF(Inputs!$E46="Real",1,BE$5) -> 0
D37: ='Project description'!$B$5 -> 0 | E37: =Lists!$B$34 | F37: PP | G37: opex | H37: Other | I37: Real | J37: =Analysis_year -> 0 | K37: =IF(Inputs!G47="","",Inputs!G47) | L37: =Inputs!H47*IF(Inputs!$E47="Real",1,L$5) -> 0 | M37: =Inputs!I47*IF(Inputs!$E47="Real",1,M$5) -> 0 | N37: =Inputs!J47*IF(Inputs!$E47="Real",1,N$5) -> 0 | O37: =Inputs!K47*IF(Inputs!$E47="Real",1,O$5) -> 0 | P37: =Inputs!L47*IF(Inputs!$E47="Real",1,P$5) -> 0 | Q37: =Inputs!M47*IF(Inputs!$E47="Real",1,Q$5) -> 0 | R37: =Inputs!N47*IF(Inputs!$E47="Real",1,R$5) -> 0 | S37: =Inputs!O47*IF(Inputs!$E47="Real",1,S$5) -> 0 | ... BE37: =Inputs!BA47*IF(Inputs!$E47="Real",1,BE$5) -> 0
H38: ="Total non-fuel opex in "&Analysis_year&" dollars" -> Total non-fuel opex in dollars | L38: =SUBTOTAL(109,'Real values'!$L$32:$L$37) -> 0 | M38: =SUBTOTAL(109,'Real values'!$M$32:$M$37) -> 0 | N38: =SUBTOTAL(109,'Real values'!$N$32:$N$37) -> 0 | O38: =SUBTOTAL(109,'Real values'!$O$32:$O$37) -> 0 | P38: =SUBTOTAL(109,'Real values'!$P$32:$P$37) -> 0 | Q38: =SUBTOTAL(109,'Real values'!$Q$32:$Q$37) -> 0 | R38: =SUBTOTAL(109,'Real values'!$R$32:$R$37) -> 0 | S38: =SUBTOTAL(109,'Real values'!$S$32:$S$37) -> 0 | T38: =SUBTOTAL(109,'Real values'!$T$32:$T$37) -> 0 | U38: =SUBTOTAL(109,'Real values'!$U$32:$U$37) -> 0 | V38: =SUBTOTAL(109,'Real values'!$V$32:$V$37) -> 0 | W38: =SUBTOTAL(109,'Real values'!$W$32:$W$37) -> 0 | X38: =SUBTOTAL(109,'Real values'!$X$32:$X$37) -> 0 | Y38: =SUBTOTAL(109,'Real values'!$Y$32:$Y$37) -> 0 | Z38: =SUBTOTAL(109,'Real values'!$Z$32:$Z$37) -> 0 | AA38: =SUBTOTAL(109,'Real values'!$AA$32:$AA$37) -> 0 | AB38: =SUBTOTAL(109,'Real values'!$AB$32:$AB$37) -> 0 | AC38: =SUBTOTAL(109,'Real values'!$AC$32:$AC$37) -> 0 | AD38: =SUBTOTAL(109,'Real values'!$AD$32:$AD$37) -> 0 | AE38: =SUBTOTAL(109,'Real values'!$AE$32:$AE$37) -> 0 | AF38: =SUBTOTAL(109,'Real values'!$AF$32:$AF$37) -> 0 | AG38: =SUBTOTAL(109,'Real values'!$AG$32:$AG$37) -> 0 | AH38: =SUBTOTAL(109,'Real values'!$AH$32:$AH$37) -> 0 | AI38: =SUBTOTAL(109,'Real values'!$AI$32:$AI$37) -> 0 | AJ38: =SUBTOTAL(109,'Real values'!$AJ$32:$AJ$37) -> 0 | AK38: =SUBTOTAL(109,'Real values'!$AK$32:$AK$37) -> 0 | AL38: =SUBTOTAL(109,'Real values'!$AL$32:$AL$37) -> 0 | AM38: =SUBTOTAL(109,'Real values'!$AM$32:$AM$37) -> 0 | AN38: =SUBTOTAL(109,'Real values'!$AN$32:$AN$37) -> 0 | AO38: =SUBTOTAL(109,'Real values'!$AO$32:$AO$37) -> 0 | AP38: =SUBTOTAL(109,'Real values'!$AP$32:$AP$37) -> 0 | AQ38: =SUBTOTAL(109,'Real values'!$AQ$32:$AQ$37) -> 0 | AR38: =SUBTOTAL(109,'Real values'!$AR$32:$AR$37) -> 0 | AS38: =SUBTOTAL(109,'Real values'!$AS$32:$AS$37) -> 0 | AT38: =SUBTOTAL(109,'Real values'!$AT$32:$AT$37) -> 0 | AU38: =SUBTOTAL(109,'Real values'!$AU$32:$AU$37) -> 0 | AV38: =SUBTOTAL(109,'Real values'!$AV$32:$AV$37) -> 0 | AW38: =SUBTOTAL(109,'Real values'!$AW$32:$AW$37) -> 0 | AX38: =SUBTOTAL(109,'Real values'!$AX$32:$AX$37) -> 0 | AY38: =SUBTOTAL(109,'Real values'!$AY$32:$AY$37) -> 0 | AZ38: =SUBTOTAL(109,'Real values'!$AZ$32:$AZ$37) -> 0 | BA38: =SUBTOTAL(109,'Real values'!$BA$32:$BA$37) -> 0 | BB38: =SUBTOTAL(109,'Real values'!$BB$32:$BB$37) -> 0 | BC38: =SUBTOTAL(109,'Real values'!$BC$32:$BC$37) -> 0 | BD38: =SUBTOTAL(109,'Real values'!$BD$32:$BD$37) -> 0 | BE38: =SUBTOTAL(109,'Real values'!$BE$32:$BE$37) -> 0
A40: Base Case (BC) | D40: ProjectId | E40: LifeCycleMonths | F40: Scenario | G40: ExpenseType | H40: Opex item | I40: Value basis | J40: Base year | K40: Applicant comment | L40: 2025 | M40: 2026 | N40: 2027 | O40: 2028 | P40: 2029 | Q40: 2030 | R40: 2031 | S40: 2032 | T40: 2033 | U40: 2034 | V40: 2035 | W40: 2036 | X40: 2037 | Y40: 2038 | Z40: 2039 | AA40: 2040 | AB40: 2041 | AC40: 2042 | AD40: 2043 | AE40: 2044 | AF40: 2045 | AG40: 2046 | AH40: 2047 | AI40: 2048 | AJ40: 2049 | AK40: 2050 | AL40: 2051 | AM40: 2052 | AN40: 2053 | AO40: 2054 | AP40: 2055 | AQ40: 2056 | AR40: 2057 | AS40: 2058 | AT40: 2059 | AU40: 2060 | AV40: 2061 | AW40: 2062 | AX40: 2063 | AY40: 2064 | AZ40: 2065 | BA40: 2066 | BB40: 2067 | BC40: 2068 | BD40: 2069 | BE40: 2070
D41: ='Project description'!$B$5 -> 0 | E41: =Lists!$B$34 | F41: BC | G41: opex | H41: Equipment Operation Costs | I41: Real | J41: =Analysis_year -> 0 | K41: =IF(Inputs!G53="","",Inputs!G53) | L41: =Inputs!H53*IF(Inputs!$E53="Real",1,L$5) -> 0 | M41: =Inputs!I53*IF(Inputs!$E53="Real",1,M$5) -> 0 | N41: =Inputs!J53*IF(Inputs!$E53="Real",1,N$5) -> 0 | O41: =Inputs!K53*IF(Inputs!$E53="Real",1,O$5) -> 0 | P41: =Inputs!L53*IF(Inputs!$E53="Real",1,P$5) -> 0 | Q41: =Inputs!M53*IF(Inputs!$E53="Real",1,Q$5) -> 0 | R41: =Inputs!N53*IF(Inputs!$E53="Real",1,R$5) -> 0 | S41: =Inputs!O53*IF(Inputs!$E53="Real",1,S$5) -> 0 | ... BE41: =Inputs!BA53*IF(Inputs!$E53="Real",1,BE$5) -> 0
D42: ='Project description'!$B$5 -> 0 | E42: =Lists!$B$34 | F42: BC | G42: opex | H42: Maintenance, Repairs, Inspections | I42: Real | J42: =Analysis_year -> 0 | K42: =IF(Inputs!G54="","",Inputs!G54) | L42: =Inputs!H54*IF(Inputs!$E54="Real",1,L$5) -> 0 | M42: =Inputs!I54*IF(Inputs!$E54="Real",1,M$5) -> 0 | N42: =Inputs!J54*IF(Inputs!$E54="Real",1,N$5) -> 0 | O42: =Inputs!K54*IF(Inputs!$E54="Real",1,O$5) -> 0 | P42: =Inputs!L54*IF(Inputs!$E54="Real",1,P$5) -> 0 | Q42: =Inputs!M54*IF(Inputs!$E54="Real",1,Q$5) -> 0 | R42: =Inputs!N54*IF(Inputs!$E54="Real",1,R$5) -> 0 | S42: =Inputs!O54*IF(Inputs!$E54="Real",1,S$5) -> 0 | ... BE42: =Inputs!BA54*IF(Inputs!$E54="Real",1,BE$5) -> 0
D43: ='Project description'!$B$5 -> 0 | E43: =Lists!$B$34 | F43: BC | G43: opex | H43: Compliance Testing | I43: Real | J43: =Analysis_year -> 0 | K43: =IF(Inputs!G55="","",Inputs!G55) | L43: =Inputs!H55*IF(Inputs!$E55="Real",1,L$5) -> 0 | M43: =Inputs!I55*IF(Inputs!$E55="Real",1,M$5) -> 0 | N43: =Inputs!J55*IF(Inputs!$E55="Real",1,N$5) -> 0 | O43: =Inputs!K55*IF(Inputs!$E55="Real",1,O$5) -> 0 | P43: =Inputs!L55*IF(Inputs!$E55="Real",1,P$5) -> 0 | Q43: =Inputs!M55*IF(Inputs!$E55="Real",1,Q$5) -> 0 | R43: =Inputs!N55*IF(Inputs!$E55="Real",1,R$5) -> 0 | S43: =Inputs!O55*IF(Inputs!$E55="Real",1,S$5) -> 0 | ... BE43: =Inputs!BA55*IF(Inputs!$E55="Real",1,BE$5) -> 0
D44: ='Project description'!$B$5 -> 0 | E44: =Lists!$B$34 | F44: BC | G44: opex | H44: Optimisation | I44: Real | J44: =Analysis_year -> 0 | K44: =IF(Inputs!G56="","",Inputs!G56) | L44: =Inputs!H56*IF(Inputs!$E56="Real",1,L$5) -> 0 | M44: =Inputs!I56*IF(Inputs!$E56="Real",1,M$5) -> 0 | N44: =Inputs!J56*IF(Inputs!$E56="Real",1,N$5) -> 0 | O44: =Inputs!K56*IF(Inputs!$E56="Real",1,O$5) -> 0 | P44: =Inputs!L56*IF(Inputs!$E56="Real",1,P$5) -> 0 | Q44: =Inputs!M56*IF(Inputs!$E56="Real",1,Q$5) -> 0 | R44: =Inputs!N56*IF(Inputs!$E56="Real",1,R$5) -> 0 | S44: =Inputs!O56*IF(Inputs!$E56="Real",1,S$5) -> 0 | ... BE44: =Inputs!BA56*IF(Inputs!$E56="Real",1,BE$5) -> 0
D45: ='Project description'!$B$5 -> 0 | E45: =Lists!$B$34 | F45: BC | G45: opex | H45: Utilities and Consumables | I45: Real | J45: =Analysis_year -> 0 | K45: =IF(Inputs!G57="","",Inputs!G57) | L45: =Inputs!H57*IF(Inputs!$E57="Real",1,L$5) -> 0 | M45: =Inputs!I57*IF(Inputs!$E57="Real",1,M$5) -> 0 | N45: =Inputs!J57*IF(Inputs!$E57="Real",1,N$5) -> 0 | O45: =Inputs!K57*IF(Inputs!$E57="Real",1,O$5) -> 0 | P45: =Inputs!L57*IF(Inputs!$E57="Real",1,P$5) -> 0 | Q45: =Inputs!M57*IF(Inputs!$E57="Real",1,Q$5) -> 0 | R45: =Inputs!N57*IF(Inputs!$E57="Real",1,R$5) -> 0 | S45: =Inputs!O57*IF(Inputs!$E57="Real",1,S$5) -> 0 | ... BE45: =Inputs!BA57*IF(Inputs!$E57="Real",1,BE$5) -> 0
D46: ='Project description'!$B$5 -> 0 | E46: =Lists!$B$34 | F46: BC | G46: opex | H46: Other | I46: Real | J46: =Analysis_year -> 0 | K46: =IF(Inputs!G58="","",Inputs!G58) | L46: =Inputs!H58*IF(Inputs!$E58="Real",1,L$5) -> 0 | M46: =Inputs!I58*IF(Inputs!$E58="Real",1,M$5) -> 0 | N46: =Inputs!J58*IF(Inputs!$E58="Real",1,N$5) -> 0 | O46: =Inputs!K58*IF(Inputs!$E58="Real",1,O$5) -> 0 | P46: =Inputs!L58*IF(Inputs!$E58="Real",1,P$5) -> 0 | Q46: =Inputs!M58*IF(Inputs!$E58="Real",1,Q$5) -> 0 | R46: =Inputs!N58*IF(Inputs!$E58="Real",1,R$5) -> 0 | S46: =Inputs!O58*IF(Inputs!$E58="Real",1,S$5) -> 0 | ... BE46: =Inputs!BA58*IF(Inputs!$E58="Real",1,BE$5) -> 0
H47: ="Total non-fuel opex in "&Analysis_year&" dollars" -> Total non-fuel opex in dollars | L47: =SUBTOTAL(109,'Real values'!$L$41:$L$46) -> 0 | M47: =SUBTOTAL(109,'Real values'!$M$41:$M$46) -> 0 | N47: =SUBTOTAL(109,'Real values'!$N$41:$N$46) -> 0 | O47: =SUBTOTAL(109,'Real values'!$O$41:$O$46) -> 0 | P47: =SUBTOTAL(109,'Real values'!$P$41:$P$46) -> 0 | Q47: =SUBTOTAL(109,'Real values'!$Q$41:$Q$46) -> 0 | R47: =SUBTOTAL(109,'Real values'!$R$41:$R$46) -> 0 | S47: =SUBTOTAL(109,'Real values'!$S$41:$S$46) -> 0 | T47: =SUBTOTAL(109,'Real values'!$T$41:$T$46) -> 0 | U47: =SUBTOTAL(109,'Real values'!$U$41:$U$46) -> 0 | V47: =SUBTOTAL(109,'Real values'!$V$41:$V$46) -> 0 | W47: =SUBTOTAL(109,'Real values'!$W$41:$W$46) -> 0 | X47: =SUBTOTAL(109,'Real values'!$X$41:$X$46) -> 0 | Y47: =SUBTOTAL(109,'Real values'!$Y$41:$Y$46) -> 0 | Z47: =SUBTOTAL(109,'Real values'!$Z$41:$Z$46) -> 0 | AA47: =SUBTOTAL(109,'Real values'!$AA$41:$AA$46) -> 0 | AB47: =SUBTOTAL(109,'Real values'!$AB$41:$AB$46) -> 0 | AC47: =SUBTOTAL(109,'Real values'!$AC$41:$AC$46) -> 0 | AD47: =SUBTOTAL(109,'Real values'!$AD$41:$AD$46) -> 0 | AE47: =SUBTOTAL(109,'Real values'!$AE$41:$AE$46) -> 0 | AF47: =SUBTOTAL(109,'Real values'!$AF$41:$AF$46) -> 0 | AG47: =SUBTOTAL(109,'Real values'!$AG$41:$AG$46) -> 0 | AH47: =SUBTOTAL(109,'Real values'!$AH$41:$AH$46) -> 0 | AI47: =SUBTOTAL(109,'Real values'!$AI$41:$AI$46) -> 0 | AJ47: =SUBTOTAL(109,'Real values'!$AJ$41:$AJ$46) -> 0 | AK47: =SUBTOTAL(109,'Real values'!$AK$41:$AK$46) -> 0 | AL47: =SUBTOTAL(109,'Real values'!$AL$41:$AL$46) -> 0 | AM47: =SUBTOTAL(109,'Real values'!$AM$41:$AM$46) -> 0 | AN47: =SUBTOTAL(109,'Real values'!$AN$41:$AN$46) -> 0 | AO47: =SUBTOTAL(109,'Real values'!$AO$41:$AO$46) -> 0 | AP47: =SUBTOTAL(109,'Real values'!$AP$41:$AP$46) -> 0 | AQ47: =SUBTOTAL(109,'Real values'!$AQ$41:$AQ$46) -> 0 | AR47: =SUBTOTAL(109,'Real values'!$AR$41:$AR$46) -> 0 | AS47: =SUBTOTAL(109,'Real values'!$AS$41:$AS$46) -> 0 | AT47: =SUBTOTAL(109,'Real values'!$AT$41:$AT$46) -> 0 | AU47: =SUBTOTAL(109,'Real values'!$AU$41:$AU$46) -> 0 | AV47: =SUBTOTAL(109,'Real values'!$AV$41:$AV$46) -> 0 | AW47: =SUBTOTAL(109,'Real values'!$AW$41:$AW$46) -> 0 | AX47: =SUBTOTAL(109,'Real values'!$AX$41:$AX$46) -> 0 | AY47: =SUBTOTAL(109,'Real values'!$AY$41:$AY$46) -> 0 | AZ47: =SUBTOTAL(109,'Real values'!$AZ$41:$AZ$46) -> 0 | BA47: =SUBTOTAL(109,'Real values'!$BA$41:$BA$46) -> 0 | BB47: =SUBTOTAL(109,'Real values'!$BB$41:$BB$46) -> 0 | BC47: =SUBTOTAL(109,'Real values'!$BC$41:$BC$46) -> 0 | BD47: =SUBTOTAL(109,'Real values'!$BD$41:$BD$46) -> 0 | BE47: =SUBTOTAL(109,'Real values'!$BE$41:$BE$46) -> 0
A49: 2b) Fuel consumption
A50: Proposed Project (PP) | F50: ProjectId | G50: LifeCycleMonths | H50: Scenario | I50: Fuel type | J50: Units | K50: Applicant comment | L50: 2025 | M50: 2026 | N50: 2027 | O50: 2028 | P50: 2029 | Q50: 2030 | R50: 2031 | S50: 2032 | T50: 2033 | U50: 2034 | V50: 2035 | W50: 2036 | X50: 2037 | Y50: 2038 | Z50: 2039 | AA50: 2040 | AB50: 2041 | AC50: 2042 | AD50: 2043 | AE50: 2044 | AF50: 2045 | AG50: 2046 | AH50: 2047 | AI50: 2048 | AJ50: 2049 | AK50: 2050 | AL50: 2051 | AM50: 2052 | AN50: 2053 | AO50: 2054 | AP50: 2055 | AQ50: 2056 | AR50: 2057 | AS50: 2058 | AT50: 2059 | AU50: 2060 | AV50: 2061 | AW50: 2062 | AX50: 2063 | AY50: 2064 | AZ50: 2065 | BA50: 2066 | BB50: 2067 | BC50: 2068 | BD50: 2069 | BE50: 2070
F51: ='Project description'!$B$5 -> 0 | G51: =Lists!$B$34 | H51: PP | I51: =Inputs!D64 -> Electricity | J51: GJ | K51: =IF(Inputs!G64="","",Inputs!G64) | L51: =Inputs!H64*Data!$F3 -> 0 | M51: =Inputs!I64*Data!$F3 -> 0 | N51: =Inputs!J64*Data!$F3 -> 0 | O51: =Inputs!K64*Data!$F3 -> 0 | P51: =Inputs!L64*Data!$F3 -> 0 | Q51: =Inputs!M64*Data!$F3 -> 0 | R51: =Inputs!N64*Data!$F3 -> 0 | S51: =Inputs!O64*Data!$F3 -> 0 | ... BE51: =Inputs!BA64*Data!$F3 -> 0
F52: ='Project description'!$B$5 -> 0 | G52: =Lists!$B$34 | H52: PP | I52: =Inputs!D65 -> Natural Gas | J52: GJ | K52: =IF(Inputs!G65="","",Inputs!G65) | L52: =Inputs!H65*Data!$F4 -> 0 | M52: =Inputs!I65*Data!$F4 -> 0 | N52: =Inputs!J65*Data!$F4 -> 0 | O52: =Inputs!K65*Data!$F4 -> 0 | P52: =Inputs!L65*Data!$F4 -> 0 | Q52: =Inputs!M65*Data!$F4 -> 0 | R52: =Inputs!N65*Data!$F4 -> 0 | S52: =Inputs!O65*Data!$F4 -> 0 | ... BE52: =Inputs!BA65*Data!$F4 -> 0
F53: ='Project description'!$B$5 -> 0 | G53: =Lists!$B$34 | H53: PP | I53: =Inputs!D66 -> Coal - sub bituminous | J53: GJ | K53: =IF(Inputs!G66="","",Inputs!G66) | L53: =Inputs!H66*Data!$F5 -> 0 | M53: =Inputs!I66*Data!$F5 -> 0 | N53: =Inputs!J66*Data!$F5 -> 0 | O53: =Inputs!K66*Data!$F5 -> 0 | P53: =Inputs!L66*Data!$F5 -> 0 | Q53: =Inputs!M66*Data!$F5 -> 0 | R53: =Inputs!N66*Data!$F5 -> 0 | S53: =Inputs!O66*Data!$F5 -> 0 | ... BE53: =Inputs!BA66*Data!$F5 -> 0
F54: ='Project description'!$B$5 -> 0 | G54: =Lists!$B$34 | H54: PP | I54: =Inputs!D67 -> Coal - bituminous | J54: GJ | K54: =IF(Inputs!G67="","",Inputs!G67) | L54: =Inputs!H67*Data!$F6 -> 0 | M54: =Inputs!I67*Data!$F6 -> 0 | N54: =Inputs!J67*Data!$F6 -> 0 | O54: =Inputs!K67*Data!$F6 -> 0 | P54: =Inputs!L67*Data!$F6 -> 0 | Q54: =Inputs!M67*Data!$F6 -> 0 | R54: =Inputs!N67*Data!$F6 -> 0 | S54: =Inputs!O67*Data!$F6 -> 0 | ... BE54: =Inputs!BA67*Data!$F6 -> 0
F55: ='Project description'!$B$5 -> 0 | G55: =Lists!$B$34 | H55: PP | I55: =Inputs!D68 -> Coal - lignite | J55: GJ | K55: =IF(Inputs!G68="","",Inputs!G68) | L55: =Inputs!H68*Data!$F7 -> 0 | M55: =Inputs!I68*Data!$F7 -> 0 | N55: =Inputs!J68*Data!$F7 -> 0 | O55: =Inputs!K68*Data!$F7 -> 0 | P55: =Inputs!L68*Data!$F7 -> 0 | Q55: =Inputs!M68*Data!$F7 -> 0 | R55: =Inputs!N68*Data!$F7 -> 0 | S55: =Inputs!O68*Data!$F7 -> 0 | ... BE55: =Inputs!BA68*Data!$F7 -> 0
F56: ='Project description'!$B$5 -> 0 | G56: =Lists!$B$34 | H56: PP | I56: =Inputs!D69 -> Diesel | J56: GJ | K56: =IF(Inputs!G69="","",Inputs!G69) | L56: =Inputs!H69*Data!$F8 -> 0 | M56: =Inputs!I69*Data!$F8 -> 0 | N56: =Inputs!J69*Data!$F8 -> 0 | O56: =Inputs!K69*Data!$F8 -> 0 | P56: =Inputs!L69*Data!$F8 -> 0 | Q56: =Inputs!M69*Data!$F8 -> 0 | R56: =Inputs!N69*Data!$F8 -> 0 | S56: =Inputs!O69*Data!$F8 -> 0 | ... BE56: =Inputs!BA69*Data!$F8 -> 0
F57: ='Project description'!$B$5 -> 0 | G57: =Lists!$B$34 | H57: PP | I57: =Inputs!D70 -> LPG | J57: GJ | K57: =IF(Inputs!G70="","",Inputs!G70) | L57: =Inputs!H70*Data!$F9 -> 0 | M57: =Inputs!I70*Data!$F9 -> 0 | N57: =Inputs!J70*Data!$F9 -> 0 | O57: =Inputs!K70*Data!$F9 -> 0 | P57: =Inputs!L70*Data!$F9 -> 0 | Q57: =Inputs!M70*Data!$F9 -> 0 | R57: =Inputs!N70*Data!$F9 -> 0 | S57: =Inputs!O70*Data!$F9 -> 0 | ... BE57: =Inputs!BA70*Data!$F9 -> 0
F58: ='Project description'!$B$5 -> 0 | G58: =Lists!$B$34 | H58: PP | I58: =Inputs!D71 -> Light fuel oil | J58: GJ | K58: =IF(Inputs!G71="","",Inputs!G71) | L58: =Inputs!H71*Data!$F10 -> 0 | M58: =Inputs!I71*Data!$F10 -> 0 | N58: =Inputs!J71*Data!$F10 -> 0 | O58: =Inputs!K71*Data!$F10 -> 0 | P58: =Inputs!L71*Data!$F10 -> 0 | Q58: =Inputs!M71*Data!$F10 -> 0 | R58: =Inputs!N71*Data!$F10 -> 0 | S58: =Inputs!O71*Data!$F10 -> 0 | ... BE58: =Inputs!BA71*Data!$F10 -> 0
F59: ='Project description'!$B$5 -> 0 | G59: =Lists!$B$34 | H59: PP | I59: =Inputs!D72 -> Heavy fuel oil | J59: GJ | K59: =IF(Inputs!G72="","",Inputs!G72) | L59: =Inputs!H72*Data!$F11 -> 0 | M59: =Inputs!I72*Data!$F11 -> 0 | N59: =Inputs!J72*Data!$F11 -> 0 | O59: =Inputs!K72*Data!$F11 -> 0 | P59: =Inputs!L72*Data!$F11 -> 0 | Q59: =Inputs!M72*Data!$F11 -> 0 | R59: =Inputs!N72*Data!$F11 -> 0 | S59: =Inputs!O72*Data!$F11 -> 0 | ... BE59: =Inputs!BA72*Data!$F11 -> 0
F60: ='Project description'!$B$5 -> 0 | G60: =Lists!$B$34 | H60: PP | I60: =Inputs!D73 -> Geothermal | J60: GJ | K60: =IF(Inputs!G73="","",Inputs!G73) | L60: =Inputs!H73*Data!$F12 -> 0 | M60: =Inputs!I73*Data!$F12 -> 0 | N60: =Inputs!J73*Data!$F12 -> 0 | O60: =Inputs!K73*Data!$F12 -> 0 | P60: =Inputs!L73*Data!$F12 -> 0 | Q60: =Inputs!M73*Data!$F12 -> 0 | R60: =Inputs!N73*Data!$F12 -> 0 | S60: =Inputs!O73*Data!$F12 -> 0 | ... BE60: =Inputs!BA73*Data!$F12 -> 0
F61: ='Project description'!$B$5 -> 0 | G61: =Lists!$B$34 | H61: PP | I61: =Inputs!D74 -> Wood or wood chips | J61: GJ | K61: =IF(Inputs!G74="","",Inputs!G74) | L61: =Inputs!H74*Data!$F13 -> 0 | M61: =Inputs!I74*Data!$F13 -> 0 | N61: =Inputs!J74*Data!$F13 -> 0 | O61: =Inputs!K74*Data!$F13 -> 0 | P61: =Inputs!L74*Data!$F13 -> 0 | Q61: =Inputs!M74*Data!$F13 -> 0 | R61: =Inputs!N74*Data!$F13 -> 0 | S61: =Inputs!O74*Data!$F13 -> 0 | ... BE61: =Inputs!BA74*Data!$F13 -> 0
A63: Base Case (BC) | F63: ProjectId | G63: LifeCycleMonths | H63: Scenario | I63: Fuel type | J63: Units | K63: Applicant comment | L63: 2025 | M63: 2026 | N63: 2027 | O63: 2028 | P63: 2029 | Q63: 2030 | R63: 2031 | S63: 2032 | T63: 2033 | U63: 2034 | V63: 2035 | W63: 2036 | X63: 2037 | Y63: 2038 | Z63: 2039 | AA63: 2040 | AB63: 2041 | AC63: 2042 | AD63: 2043 | AE63: 2044 | AF63: 2045 | AG63: 2046 | AH63: 2047 | AI63: 2048 | AJ63: 2049 | AK63: 2050 | AL63: 2051 | AM63: 2052 | AN63: 2053 | AO63: 2054 | AP63: 2055 | AQ63: 2056 | AR63: 2057 | AS63: 2058 | AT63: 2059 | AU63: 2060 | AV63: 2061 | AW63: 2062 | AX63: 2063 | AY63: 2064 | AZ63: 2065 | BA63: 2066 | BB63: 2067 | BC63: 2068 | BD63: 2069 | BE63: 2070
F64: ='Project description'!$B$5 -> 0 | G64: =Lists!$B$34 | H64: BC | I64: =Inputs!D77 -> Electricity | J64: GJ | K64: =IF(Inputs!G77="","",Inputs!G77) | L64: =Inputs!H77*Data!$F3 -> 0 | M64: =Inputs!I77*Data!$F3 -> 0 | N64: =Inputs!J77*Data!$F3 -> 0 | O64: =Inputs!K77*Data!$F3 -> 0 | P64: =Inputs!L77*Data!$F3 -> 0 | Q64: =Inputs!M77*Data!$F3 -> 0 | R64: =Inputs!N77*Data!$F3 -> 0 | S64: =Inputs!O77*Data!$F3 -> 0 | ... BE64: =Inputs!BA77*Data!$F3 -> 0
F65: ='Project description'!$B$5 -> 0 | G65: =Lists!$B$34 | H65: BC | I65: =Inputs!D78 -> Natural Gas | J65: GJ | K65: =IF(Inputs!G78="","",Inputs!G78) | L65: =Inputs!H78*Data!$F4 -> 0 | M65: =Inputs!I78*Data!$F4 -> 0 | N65: =Inputs!J78*Data!$F4 -> 0 | O65: =Inputs!K78*Data!$F4 -> 0 | P65: =Inputs!L78*Data!$F4 -> 0 | Q65: =Inputs!M78*Data!$F4 -> 0 | R65: =Inputs!N78*Data!$F4 -> 0 | S65: =Inputs!O78*Data!$F4 -> 0 | ... BE65: =Inputs!BA78*Data!$F4 -> 0
F66: ='Project description'!$B$5 -> 0 | G66: =Lists!$B$34 | H66: BC | I66: =Inputs!D79 -> Coal - sub bituminous | J66: GJ | K66: =IF(Inputs!G79="","",Inputs!G79) | L66: =Inputs!H79*Data!$F5 -> 0 | M66: =Inputs!I79*Data!$F5 -> 0 | N66: =Inputs!J79*Data!$F5 -> 0 | O66: =Inputs!K79*Data!$F5 -> 0 | P66: =Inputs!L79*Data!$F5 -> 0 | Q66: =Inputs!M79*Data!$F5 -> 0 | R66: =Inputs!N79*Data!$F5 -> 0 | S66: =Inputs!O79*Data!$F5 -> 0 | ... BE66: =Inputs!BA79*Data!$F5 -> 0
F67: ='Project description'!$B$5 -> 0 | G67: =Lists!$B$34 | H67: BC | I67: =Inputs!D80 -> Coal - bituminous | J67: GJ | K67: =IF(Inputs!G80="","",Inputs!G80) | L67: =Inputs!H80*Data!$F6 -> 0 | M67: =Inputs!I80*Data!$F6 -> 0 | N67: =Inputs!J80*Data!$F6 -> 0 | O67: =Inputs!K80*Data!$F6 -> 0 | P67: =Inputs!L80*Data!$F6 -> 0 | Q67: =Inputs!M80*Data!$F6 -> 0 | R67: =Inputs!N80*Data!$F6 -> 0 | S67: =Inputs!O80*Data!$F6 -> 0 | ... BE67: =Inputs!BA80*Data!$F6 -> 0
F68: ='Project description'!$B$5 -> 0 | G68: =Lists!$B$34 | H68: BC | I68: =Inputs!D81 -> Coal - lignite | J68: GJ | K68: =IF(Inputs!G81="","",Inputs!G81) | L68: =Inputs!H81*Data!$F7 -> 0 | M68: =Inputs!I81*Data!$F7 -> 0 | N68: =Inputs!J81*Data!$F7 -> 0 | O68: =Inputs!K81*Data!$F7 -> 0 | P68: =Inputs!L81*Data!$F7 -> 0 | Q68: =Inputs!M81*Data!$F7 -> 0 | R68: =Inputs!N81*Data!$F7 -> 0 | S68: =Inputs!O81*Data!$F7 -> 0 | ... BE68: =Inputs!BA81*Data!$F7 -> 0
F69: ='Project description'!$B$5 -> 0 | G69: =Lists!$B$34 | H69: BC | I69: =Inputs!D82 -> Diesel | J69: GJ | K69: =IF(Inputs!G82="","",Inputs!G82) | L69: =Inputs!H82*Data!$F8 -> 0 | M69: =Inputs!I82*Data!$F8 -> 0 | N69: =Inputs!J82*Data!$F8 -> 0 | O69: =Inputs!K82*Data!$F8 -> 0 | P69: =Inputs!L82*Data!$F8 -> 0 | Q69: =Inputs!M82*Data!$F8 -> 0 | R69: =Inputs!N82*Data!$F8 -> 0 | S69: =Inputs!O82*Data!$F8 -> 0 | ... BE69: =Inputs!BA82*Data!$F8 -> 0
F70: ='Project description'!$B$5 -> 0 | G70: =Lists!$B$34 | H70: BC | I70: =Inputs!D83 -> LPG | J70: GJ | K70: =IF(Inputs!G83="","",Inputs!G83) | L70: =Inputs!H83*Data!$F9 -> 0 | M70: =Inputs!I83*Data!$F9 -> 0 | N70: =Inputs!J83*Data!$F9 -> 0 | O70: =Inputs!K83*Data!$F9 -> 0 | P70: =Inputs!L83*Data!$F9 -> 0 | Q70: =Inputs!M83*Data!$F9 -> 0 | R70: =Inputs!N83*Data!$F9 -> 0 | S70: =Inputs!O83*Data!$F9 -> 0 | ... BE70: =Inputs!BA83*Data!$F9 -> 0
F71: ='Project description'!$B$5 -> 0 | G71: =Lists!$B$34 | H71: BC | I71: =Inputs!D84 -> Light fuel oil | J71: GJ | K71: =IF(Inputs!G84="","",Inputs!G84) | L71: =Inputs!H84*Data!$F10 -> 0 | M71: =Inputs!I84*Data!$F10 -> 0 | N71: =Inputs!J84*Data!$F10 -> 0 | O71: =Inputs!K84*Data!$F10 -> 0 | P71: =Inputs!L84*Data!$F10 -> 0 | Q71: =Inputs!M84*Data!$F10 -> 0 | R71: =Inputs!N84*Data!$F10 -> 0 | S71: =Inputs!O84*Data!$F10 -> 0 | ... BE71: =Inputs!BA84*Data!$F10 -> 0
F72: ='Project description'!$B$5 -> 0 | G72: =Lists!$B$34 | H72: BC | I72: =Inputs!D85 -> Heavy fuel oil | J72: GJ | K72: =IF(Inputs!G85="","",Inputs!G85) | L72: =Inputs!H85*Data!$F11 -> 0 | M72: =Inputs!I85*Data!$F11 -> 0 | N72: =Inputs!J85*Data!$F11 -> 0 | O72: =Inputs!K85*Data!$F11 -> 0 | P72: =Inputs!L85*Data!$F11 -> 0 | Q72: =Inputs!M85*Data!$F11 -> 0 | R72: =Inputs!N85*Data!$F11 -> 0 | S72: =Inputs!O85*Data!$F11 -> 0 | ... BE72: =Inputs!BA85*Data!$F11 -> 0
F73: ='Project description'!$B$5 -> 0 | G73: =Lists!$B$34 | H73: BC | I73: =Inputs!D86 -> Geothermal | J73: GJ | K73: =IF(Inputs!G86="","",Inputs!G86) | L73: =Inputs!H86*Data!$F12 -> 0 | M73: =Inputs!I86*Data!$F12 -> 0 | N73: =Inputs!J86*Data!$F12 -> 0 | O73: =Inputs!K86*Data!$F12 -> 0 | P73: =Inputs!L86*Data!$F12 -> 0 | Q73: =Inputs!M86*Data!$F12 -> 0 | R73: =Inputs!N86*Data!$F12 -> 0 | S73: =Inputs!O86*Data!$F12 -> 0 | ... BE73: =Inputs!BA86*Data!$F12 -> 0
F74: ='Project description'!$B$5 -> 0 | G74: =Lists!$B$34 | H74: BC | I74: =Inputs!D87 -> Wood or wood chips | J74: GJ | K74: =IF(Inputs!G87="","",Inputs!G87) | L74: =Inputs!H87*Data!$F13 -> 0 | M74: =Inputs!I87*Data!$F13 -> 0 | N74: =Inputs!J87*Data!$F13 -> 0 | O74: =Inputs!K87*Data!$F13 -> 0 | P74: =Inputs!L87*Data!$F13 -> 0 | Q74: =Inputs!M87*Data!$F13 -> 0 | R74: =Inputs!N87*Data!$F13 -> 0 | S74: =Inputs!O87*Data!$F13 -> 0 | ... BE74: =Inputs!BA87*Data!$F13 -> 0
A76: 2b) Expected fuel prices (excl GST)
A77: Proposed Project (PP) | C77: ProjectId | D77: LifeCycleMonths | E77: Scenario | F77: Fuel type | G77: Units | H77: ETS cost included? | I77: Value basis | J77: Base year | K77: Applicant comment | L77: 2025 | M77: 2026 | N77: 2027 | O77: 2028 | P77: 2029 | Q77: 2030 | R77: 2031 | S77: 2032 | T77: 2033 | U77: 2034 | V77: 2035 | W77: 2036 | X77: 2037 | Y77: 2038 | Z77: 2039 | AA77: 2040 | AB77: 2041 | AC77: 2042 | AD77: 2043 | AE77: 2044 | AF77: 2045 | AG77: 2046 | AH77: 2047 | AI77: 2048 | AJ77: 2049 | AK77: 2050 | AL77: 2051 | AM77: 2052 | AN77: 2053 | AO77: 2054 | AP77: 2055 | AQ77: 2056 | AR77: 2057 | AS77: 2058 | AT77: 2059 | AU77: 2060 | AV77: 2061 | AW77: 2062 | AX77: 2063 | AY77: 2064 | AZ77: 2065 | BA77: 2066 | BB77: 2067 | BC77: 2068 | BD77: 2069 | BE77: 2070
C78: ='Project description'!$B$5 -> 0 | D78: =Lists!$B$34 | E78: PP | F78: =Inputs!B91 -> Electricity | G78: $/GJ | H78: No | I78: Real | J78: =Analysis_year -> 0 | K78: =IF(Inputs!G91="","",Inputs!G91) | L78: =Data!M22/Data!$F3 -> 45.410647 | M78: =Data!N22/Data!$F3 -> 43.405726 | N78: =Data!O22/Data!$F3 -> 40.705038 | O78: =Data!P22/Data!$F3 -> 38.924093 | P78: =Data!Q22/Data!$F3 -> 37.142659 | Q78: =Data!R22/Data!$F3 -> 35.360941 | R78: =Data!S22/Data!$F3 -> 33.385247 | S78: =Data!T22/Data!$F3 -> 31.680438 | ... BE78: =Data!BF22/Data!$F3 -> 0
C79: ='Project description'!$B$5 -> 0 | D79: =Lists!$B$34 | E79: PP | F79: =Inputs!B92 -> Natural Gas | G79: $/GJ | H79: No | I79: Real | J79: =Analysis_year -> 0 | K79: =IF(Inputs!G92="","",Inputs!G92) | L79: =Inputs!H92*IF(Inputs!$E92="Real",1,M$5)/Data!$F4 -> 10 | M79: =Inputs!I92*IF(Inputs!$E92="Real",1,N$5)/Data!$F4 -> 10 | N79: =Inputs!J92*IF(Inputs!$E92="Real",1,O$5)/Data!$F4 -> 10 | O79: =Inputs!K92*IF(Inputs!$E92="Real",1,P$5)/Data!$F4 -> 10 | P79: =Inputs!L92*IF(Inputs!$E92="Real",1,Q$5)/Data!$F4 -> 10 | Q79: =Inputs!M92*IF(Inputs!$E92="Real",1,R$5)/Data!$F4 -> 10 | R79: =Inputs!N92*IF(Inputs!$E92="Real",1,S$5)/Data!$F4 -> 10 | S79: =Inputs!O92*IF(Inputs!$E92="Real",1,T$5)/Data!$F4 -> 10 | ... BE79: =Inputs!BA92*IF(Inputs!$E92="Real",1,BF$5)/Data!$F4 -> 0
C80: ='Project description'!$B$5 -> 0 | D80: =Lists!$B$34 | E80: PP | F80: =Inputs!B93 -> Coal - sub bituminous | G80: $/GJ | H80: No | I80: Real | J80: =Analysis_year -> 0 | K80: =IF(Inputs!G93="","",Inputs!G93) | L80: =Inputs!H93*IF(Inputs!$E93="Real",1,M$5)/Data!$F5 -> 6.8181818 | M80: =Inputs!I93*IF(Inputs!$E93="Real",1,N$5)/Data!$F5 -> 6.8181818 | N80: =Inputs!J93*IF(Inputs!$E93="Real",1,O$5)/Data!$F5 -> 6.8181818 | O80: =Inputs!K93*IF(Inputs!$E93="Real",1,P$5)/Data!$F5 -> 6.8181818 | P80: =Inputs!L93*IF(Inputs!$E93="Real",1,Q$5)/Data!$F5 -> 6.8181818 | Q80: =Inputs!M93*IF(Inputs!$E93="Real",1,R$5)/Data!$F5 -> 6.8181818 | R80: =Inputs!N93*IF(Inputs!$E93="Real",1,S$5)/Data!$F5 -> 6.8181818 | S80: =Inputs!O93*IF(Inputs!$E93="Real",1,T$5)/Data!$F5 -> 6.8181818 | ... BE80: =Inputs!BA93*IF(Inputs!$E93="Real",1,BF$5)/Data!$F5 -> 0
C81: ='Project description'!$B$5 -> 0 | D81: =Lists!$B$34 | E81: PP | F81: =Inputs!B94 -> Coal - bituminous | G81: $/GJ | H81: No | I81: Real | J81: =Analysis_year -> 0 | K81: =IF(Inputs!G94="","",Inputs!G94) | L81: =Inputs!H94*IF(Inputs!$E94="Real",1,M$5)/Data!$F6 -> 0 | M81: =Inputs!I94*IF(Inputs!$E94="Real",1,N$5)/Data!$F6 -> 0 | N81: =Inputs!J94*IF(Inputs!$E94="Real",1,O$5)/Data!$F6 -> 0 | O81: =Inputs!K94*IF(Inputs!$E94="Real",1,P$5)/Data!$F6 -> 0 | P81: =Inputs!L94*IF(Inputs!$E94="Real",1,Q$5)/Data!$F6 -> 0 | Q81: =Inputs!M94*IF(Inputs!$E94="Real",1,R$5)/Data!$F6 -> 0 | R81: =Inputs!N94*IF(Inputs!$E94="Real",1,S$5)/Data!$F6 -> 0 | S81: =Inputs!O94*IF(Inputs!$E94="Real",1,T$5)/Data!$F6 -> 0 | ... BE81: =Inputs!BA94*IF(Inputs!$E94="Real",1,BF$5)/Data!$F6 -> 0
C82: ='Project description'!$B$5 -> 0 | D82: =Lists!$B$34 | E82: PP | F82: =Inputs!B95 -> Coal - lignite | G82: $/GJ | H82: No | I82: Real | J82: =Analysis_year -> 0 | K82: =IF(Inputs!G95="","",Inputs!G95) | L82: =Inputs!H95*IF(Inputs!$E95="Real",1,M$5)/Data!$F7 -> 0 | M82: =Inputs!I95*IF(Inputs!$E95="Real",1,N$5)/Data!$F7 -> 0 | N82: =Inputs!J95*IF(Inputs!$E95="Real",1,O$5)/Data!$F7 -> 0 | O82: =Inputs!K95*IF(Inputs!$E95="Real",1,P$5)/Data!$F7 -> 0 | P82: =Inputs!L95*IF(Inputs!$E95="Real",1,Q$5)/Data!$F7 -> 0 | Q82: =Inputs!M95*IF(Inputs!$E95="Real",1,R$5)/Data!$F7 -> 0 | R82: =Inputs!N95*IF(Inputs!$E95="Real",1,S$5)/Data!$F7 -> 0 | S82: =Inputs!O95*IF(Inputs!$E95="Real",1,T$5)/Data!$F7 -> 0 | ... BE82: =Inputs!BA95*IF(Inputs!$E95="Real",1,BF$5)/Data!$F7 -> 0
C83: ='Project description'!$B$5 -> 0 | D83: =Lists!$B$34 | E83: PP | F83: =Inputs!B96 -> Diesel | G83: $/GJ | H83: No | I83: Real | J83: =Analysis_year -> 0 | K83: =IF(Inputs!G96="","",Inputs!G96) | L83: =Inputs!H96*IF(Inputs!$E96="Real",1,M$5)/Data!$F8 -> 0.056022409 | M83: =Inputs!I96*IF(Inputs!$E96="Real",1,N$5)/Data!$F8 -> 0.056022409 | N83: =Inputs!J96*IF(Inputs!$E96="Real",1,O$5)/Data!$F8 -> 0.056022409 | O83: =Inputs!K96*IF(Inputs!$E96="Real",1,P$5)/Data!$F8 -> 0.056022409 | P83: =Inputs!L96*IF(Inputs!$E96="Real",1,Q$5)/Data!$F8 -> 0.056022409 | Q83: =Inputs!M96*IF(Inputs!$E96="Real",1,R$5)/Data!$F8 -> 0.056022409 | R83: =Inputs!N96*IF(Inputs!$E96="Real",1,S$5)/Data!$F8 -> 0.056022409 | S83: =Inputs!O96*IF(Inputs!$E96="Real",1,T$5)/Data!$F8 -> 0.056022409 | ... BE83: =Inputs!BA96*IF(Inputs!$E96="Real",1,BF$5)/Data!$F8 -> 0.028011204
C84: ='Project description'!$B$5 -> 0 | D84: =Lists!$B$34 | E84: PP | F84: =Inputs!B97 -> LPG | G84: $/GJ | H84: No | I84: Real | J84: =Analysis_year -> 0 | K84: =IF(Inputs!G97="","",Inputs!G97) | L84: =Inputs!H97*IF(Inputs!$E97="Real",1,M$5)/Data!$F9 -> 0 | M84: =Inputs!I97*IF(Inputs!$E97="Real",1,N$5)/Data!$F9 -> 0 | N84: =Inputs!J97*IF(Inputs!$E97="Real",1,O$5)/Data!$F9 -> 0 | O84: =Inputs!K97*IF(Inputs!$E97="Real",1,P$5)/Data!$F9 -> 0 | P84: =Inputs!L97*IF(Inputs!$E97="Real",1,Q$5)/Data!$F9 -> 0 | Q84: =Inputs!M97*IF(Inputs!$E97="Real",1,R$5)/Data!$F9 -> 0 | R84: =Inputs!N97*IF(Inputs!$E97="Real",1,S$5)/Data!$F9 -> 0 | S84: =Inputs!O97*IF(Inputs!$E97="Real",1,T$5)/Data!$F9 -> 0 | ... BE84: =Inputs!BA97*IF(Inputs!$E97="Real",1,BF$5)/Data!$F9 -> 0
C85: ='Project description'!$B$5 -> 0 | D85: =Lists!$B$34 | E85: PP | F85: =Inputs!B98 -> Light fuel oil | G85: $/GJ | H85: No | I85: Real | J85: =Analysis_year -> 0 | K85: =IF(Inputs!G98="","",Inputs!G98) | L85: =Inputs!H98*IF(Inputs!$E98="Real",1,M$5)/Data!$F10 -> 0 | M85: =Inputs!I98*IF(Inputs!$E98="Real",1,N$5)/Data!$F10 -> 0 | N85: =Inputs!J98*IF(Inputs!$E98="Real",1,O$5)/Data!$F10 -> 0 | O85: =Inputs!K98*IF(Inputs!$E98="Real",1,P$5)/Data!$F10 -> 0 | P85: =Inputs!L98*IF(Inputs!$E98="Real",1,Q$5)/Data!$F10 -> 0 | Q85: =Inputs!M98*IF(Inputs!$E98="Real",1,R$5)/Data!$F10 -> 0 | R85: =Inputs!N98*IF(Inputs!$E98="Real",1,S$5)/Data!$F10 -> 0 | S85: =Inputs!O98*IF(Inputs!$E98="Real",1,T$5)/Data!$F10 -> 0 | ... BE85: =Inputs!BA98*IF(Inputs!$E98="Real",1,BF$5)/Data!$F10 -> 0
C86: ='Project description'!$B$5 -> 0 | D86: =Lists!$B$34 | E86: PP | F86: =Inputs!B99 -> Heavy fuel oil | G86: $/GJ | H86: No | I86: Real | J86: =Analysis_year -> 0 | K86: =IF(Inputs!G99="","",Inputs!G99) | L86: =Inputs!H99*IF(Inputs!$E99="Real",1,M$5)/Data!$F11 -> 0 | M86: =Inputs!I99*IF(Inputs!$E99="Real",1,N$5)/Data!$F11 -> 0 | N86: =Inputs!J99*IF(Inputs!$E99="Real",1,O$5)/Data!$F11 -> 0 | O86: =Inputs!K99*IF(Inputs!$E99="Real",1,P$5)/Data!$F11 -> 0 | P86: =Inputs!L99*IF(Inputs!$E99="Real",1,Q$5)/Data!$F11 -> 0 | Q86: =Inputs!M99*IF(Inputs!$E99="Real",1,R$5)/Data!$F11 -> 0 | R86: =Inputs!N99*IF(Inputs!$E99="Real",1,S$5)/Data!$F11 -> 0 | S86: =Inputs!O99*IF(Inputs!$E99="Real",1,T$5)/Data!$F11 -> 0 | ... BE86: =Inputs!BA99*IF(Inputs!$E99="Real",1,BF$5)/Data!$F11 -> 0
C87: ='Project description'!$B$5 -> 0 | D87: =Lists!$B$34 | E87: PP | F87: =Inputs!B100 -> Geothermal | G87: $/GJ | H87: No | I87: Real | J87: =Analysis_year -> 0 | K87: =IF(Inputs!G100="","",Inputs!G100) | L87: =Inputs!H100*IF(Inputs!$E100="Real",1,M$5)/Data!$F12 -> 0 | M87: =Inputs!I100*IF(Inputs!$E100="Real",1,N$5)/Data!$F12 -> 0 | N87: =Inputs!J100*IF(Inputs!$E100="Real",1,O$5)/Data!$F12 -> 0 | O87: =Inputs!K100*IF(Inputs!$E100="Real",1,P$5)/Data!$F12 -> 0 | P87: =Inputs!L100*IF(Inputs!$E100="Real",1,Q$5)/Data!$F12 -> 0 | Q87: =Inputs!M100*IF(Inputs!$E100="Real",1,R$5)/Data!$F12 -> 0 | R87: =Inputs!N100*IF(Inputs!$E100="Real",1,S$5)/Data!$F12 -> 0 | S87: =Inputs!O100*IF(Inputs!$E100="Real",1,T$5)/Data!$F12 -> 0 | ... BE87: =Inputs!BA100*IF(Inputs!$E100="Real",1,BF$5)/Data!$F12 -> 0
C88: ='Project description'!$B$5 -> 0 | D88: =Lists!$B$34 | E88: PP | F88: =Inputs!B101 -> Wood or wood chips | G88: $/GJ | H88: No | I88: Real | J88: =Analysis_year -> 0 | K88: =IF(Inputs!G101="","",Inputs!G101) | L88: =Inputs!H101*IF(Inputs!$E101="Real",1,M$5)/Data!$F13 -> 0 | M88: =Inputs!I101*IF(Inputs!$E101="Real",1,N$5)/Data!$F13 -> 0 | N88: =Inputs!J101*IF(Inputs!$E101="Real",1,O$5)/Data!$F13 -> 0 | O88: =Inputs!K101*IF(Inputs!$E101="Real",1,P$5)/Data!$F13 -> 0 | P88: =Inputs!L101*IF(Inputs!$E101="Real",1,Q$5)/Data!$F13 -> 0 | Q88: =Inputs!M101*IF(Inputs!$E101="Real",1,R$5)/Data!$F13 -> 0 | R88: =Inputs!N101*IF(Inputs!$E101="Real",1,S$5)/Data!$F13 -> 0 | S88: =Inputs!O101*IF(Inputs!$E101="Real",1,T$5)/Data!$F13 -> 0 | ... BE88: =Inputs!BA101*IF(Inputs!$E101="Real",1,BF$5)/Data!$F13 -> 0
A90: Base Case (BC) | C90: ProjectId | D90: LifeCycleMonths | E90: Scenario | F90: Fuel type | G90: Units | H90: ETS cost included? | I90: Value basis | J90: Base year | K90: Applicant comment | L90: 2025 | M90: 2026 | N90: 2027 | O90: 2028 | P90: 2029 | Q90: 2030 | R90: 2031 | S90: 2032 | T90: 2033 | U90: 2034 | V90: 2035 | W90: 2036 | X90: 2037 | Y90: 2038 | Z90: 2039 | AA90: 2040 | AB90: 2041 | AC90: 2042 | AD90: 2043 | AE90: 2044 | AF90: 2045 | AG90: 2046 | AH90: 2047 | AI90: 2048 | AJ90: 2049 | AK90: 2050 | AL90: 2051 | AM90: 2052 | AN90: 2053 | AO90: 2054 | AP90: 2055 | AQ90: 2056 | AR90: 2057 | AS90: 2058 | AT90: 2059 | AU90: 2060 | AV90: 2061 | AW90: 2062 | AX90: 2063 | AY90: 2064 | AZ90: 2065 | BA90: 2066 | BB90: 2067 | BC90: 2068 | BD90: 2069 | BE90: 2070
C91: ='Project description'!$B$5 -> 0 | D91: =Lists!$B$34 | E91: BC | F91: =Inputs!B104 -> Electricity | G91: $/GJ | H91: No | I91: Real | J91: =Analysis_year -> 0 | K91: =IF(Inputs!G104="","",Inputs!G104) | L91: =Data!M22/Data!$F3 -> 45.410647 | M91: =Data!N22/Data!$F3 -> 43.405726 | N91: =Data!O22/Data!$F3 -> 40.705038 | O91: =Data!P22/Data!$F3 -> 38.924093 | P91: =Data!Q22/Data!$F3 -> 37.142659 | Q91: =Data!R22/Data!$F3 -> 35.360941 | R91: =Data!S22/Data!$F3 -> 33.385247 | S91: =Data!T22/Data!$F3 -> 31.680438 | ... BE91: =Data!BF22/Data!$F3 -> 0
C92: ='Project description'!$B$5 -> 0 | D92: =Lists!$B$34 | E92: BC | F92: =Inputs!B105 -> Natural Gas | G92: $/GJ | H92: No | I92: Real | J92: =Analysis_year -> 0 | K92: =IF(Inputs!G105="","",Inputs!G105) | L92: =Inputs!H105*IF(Inputs!$E105="Real",1,M$5)/Data!$F4 -> 10 | M92: =Inputs!I105*IF(Inputs!$E105="Real",1,N$5)/Data!$F4 -> 10 | N92: =Inputs!J105*IF(Inputs!$E105="Real",1,O$5)/Data!$F4 -> 10 | O92: =Inputs!K105*IF(Inputs!$E105="Real",1,P$5)/Data!$F4 -> 10 | P92: =Inputs!L105*IF(Inputs!$E105="Real",1,Q$5)/Data!$F4 -> 10 | Q92: =Inputs!M105*IF(Inputs!$E105="Real",1,R$5)/Data!$F4 -> 10 | R92: =Inputs!N105*IF(Inputs!$E105="Real",1,S$5)/Data!$F4 -> 10 | S92: =Inputs!O105*IF(Inputs!$E105="Real",1,T$5)/Data!$F4 -> 10 | ... BE92: =Inputs!BA105*IF(Inputs!$E105="Real",1,BF$5)/Data!$F4 -> 0
C93: ='Project description'!$B$5 -> 0 | D93: =Lists!$B$34 | E93: BC | F93: =Inputs!B106 -> Coal - sub bituminous | G93: $/GJ | H93: No | I93: Real | J93: =Analysis_year -> 0 | K93: =IF(Inputs!G106="","",Inputs!G106) | L93: =Inputs!H106*IF(Inputs!$E106="Real",1,M$5)/Data!$F5 -> 6.8181818 | M93: =Inputs!I106*IF(Inputs!$E106="Real",1,N$5)/Data!$F5 -> 6.8181818 | N93: =Inputs!J106*IF(Inputs!$E106="Real",1,O$5)/Data!$F5 -> 6.8181818 | O93: =Inputs!K106*IF(Inputs!$E106="Real",1,P$5)/Data!$F5 -> 6.8181818 | P93: =Inputs!L106*IF(Inputs!$E106="Real",1,Q$5)/Data!$F5 -> 6.8181818 | Q93: =Inputs!M106*IF(Inputs!$E106="Real",1,R$5)/Data!$F5 -> 6.8181818 | R93: =Inputs!N106*IF(Inputs!$E106="Real",1,S$5)/Data!$F5 -> 6.8181818 | S93: =Inputs!O106*IF(Inputs!$E106="Real",1,T$5)/Data!$F5 -> 6.8181818 | ... BE93: =Inputs!BA106*IF(Inputs!$E106="Real",1,BF$5)/Data!$F5 -> 0
C94: ='Project description'!$B$5 -> 0 | D94: =Lists!$B$34 | E94: BC | F94: =Inputs!B107 -> Coal - bituminous | G94: $/GJ | H94: No | I94: Real | J94: =Analysis_year -> 0 | K94: =IF(Inputs!G107="","",Inputs!G107) | L94: =Inputs!H107*IF(Inputs!$E107="Real",1,M$5)/Data!$F6 -> 0 | M94: =Inputs!I107*IF(Inputs!$E107="Real",1,N$5)/Data!$F6 -> 0 | N94: =Inputs!J107*IF(Inputs!$E107="Real",1,O$5)/Data!$F6 -> 0 | O94: =Inputs!K107*IF(Inputs!$E107="Real",1,P$5)/Data!$F6 -> 0 | P94: =Inputs!L107*IF(Inputs!$E107="Real",1,Q$5)/Data!$F6 -> 0 | Q94: =Inputs!M107*IF(Inputs!$E107="Real",1,R$5)/Data!$F6 -> 0 | R94: =Inputs!N107*IF(Inputs!$E107="Real",1,S$5)/Data!$F6 -> 0 | S94: =Inputs!O107*IF(Inputs!$E107="Real",1,T$5)/Data!$F6 -> 0 | ... BE94: =Inputs!BA107*IF(Inputs!$E107="Real",1,BF$5)/Data!$F6 -> 0
C95: ='Project description'!$B$5 -> 0 | D95: =Lists!$B$34 | E95: BC | F95: =Inputs!B108 -> Coal - lignite | G95: $/GJ | H95: No | I95: Real | J95: =Analysis_year -> 0 | K95: =IF(Inputs!G108="","",Inputs!G108) | L95: =Inputs!H108*IF(Inputs!$E108="Real",1,M$5)/Data!$F7 -> 0 | M95: =Inputs!I108*IF(Inputs!$E108="Real",1,N$5)/Data!$F7 -> 0 | N95: =Inputs!J108*IF(Inputs!$E108="Real",1,O$5)/Data!$F7 -> 0 | O95: =Inputs!K108*IF(Inputs!$E108="Real",1,P$5)/Data!$F7 -> 0 | P95: =Inputs!L108*IF(Inputs!$E108="Real",1,Q$5)/Data!$F7 -> 0 | Q95: =Inputs!M108*IF(Inputs!$E108="Real",1,R$5)/Data!$F7 -> 0 | R95: =Inputs!N108*IF(Inputs!$E108="Real",1,S$5)/Data!$F7 -> 0 | S95: =Inputs!O108*IF(Inputs!$E108="Real",1,T$5)/Data!$F7 -> 0 | ... BE95: =Inputs!BA108*IF(Inputs!$E108="Real",1,BF$5)/Data!$F7 -> 0
C96: ='Project description'!$B$5 -> 0 | D96: =Lists!$B$34 | E96: BC | F96: =Inputs!B109 -> Diesel | G96: $/GJ | H96: No | I96: Real | J96: =Analysis_year -> 0 | K96: =IF(Inputs!G109="","",Inputs!G109) | L96: =Inputs!H109*IF(Inputs!$E109="Real",1,M$5)/Data!$F8 -> 0.056022409 | M96: =Inputs!I109*IF(Inputs!$E109="Real",1,N$5)/Data!$F8 -> 0.056022409 | N96: =Inputs!J109*IF(Inputs!$E109="Real",1,O$5)/Data!$F8 -> 0.056022409 | O96: =Inputs!K109*IF(Inputs!$E109="Real",1,P$5)/Data!$F8 -> 0.056022409 | P96: =Inputs!L109*IF(Inputs!$E109="Real",1,Q$5)/Data!$F8 -> 0.056022409 | Q96: =Inputs!M109*IF(Inputs!$E109="Real",1,R$5)/Data!$F8 -> 0.056022409 | R96: =Inputs!N109*IF(Inputs!$E109="Real",1,S$5)/Data!$F8 -> 0.056022409 | S96: =Inputs!O109*IF(Inputs!$E109="Real",1,T$5)/Data!$F8 -> 0.056022409 | ... BE96: =Inputs!BA109*IF(Inputs!$E109="Real",1,BF$5)/Data!$F8 -> 0.056022409
C97: ='Project description'!$B$5 -> 0 | D97: =Lists!$B$34 | E97: BC | F97: =Inputs!B110 -> LPG | G97: $/GJ | H97: No | I97: Real | J97: =Analysis_year -> 0 | K97: =IF(Inputs!G110="","",Inputs!G110) | L97: =Inputs!H110*IF(Inputs!$E110="Real",1,M$5)/Data!$F9 -> 0 | M97: =Inputs!I110*IF(Inputs!$E110="Real",1,N$5)/Data!$F9 -> 0 | N97: =Inputs!J110*IF(Inputs!$E110="Real",1,O$5)/Data!$F9 -> 0 | O97: =Inputs!K110*IF(Inputs!$E110="Real",1,P$5)/Data!$F9 -> 0 | P97: =Inputs!L110*IF(Inputs!$E110="Real",1,Q$5)/Data!$F9 -> 0 | Q97: =Inputs!M110*IF(Inputs!$E110="Real",1,R$5)/Data!$F9 -> 0 | R97: =Inputs!N110*IF(Inputs!$E110="Real",1,S$5)/Data!$F9 -> 0 | S97: =Inputs!O110*IF(Inputs!$E110="Real",1,T$5)/Data!$F9 -> 0 | ... BE97: =Inputs!BA110*IF(Inputs!$E110="Real",1,BF$5)/Data!$F9 -> 0
C98: ='Project description'!$B$5 -> 0 | D98: =Lists!$B$34 | E98: BC | F98: =Inputs!B111 -> Light fuel oil | G98: $/GJ | H98: No | I98: Real | J98: =Analysis_year -> 0 | K98: =IF(Inputs!G111="","",Inputs!G111) | L98: =Inputs!H111*IF(Inputs!$E111="Real",1,M$5)/Data!$F10 -> 0 | M98: =Inputs!I111*IF(Inputs!$E111="Real",1,N$5)/Data!$F10 -> 0 | N98: =Inputs!J111*IF(Inputs!$E111="Real",1,O$5)/Data!$F10 -> 0 | O98: =Inputs!K111*IF(Inputs!$E111="Real",1,P$5)/Data!$F10 -> 0 | P98: =Inputs!L111*IF(Inputs!$E111="Real",1,Q$5)/Data!$F10 -> 0 | Q98: =Inputs!M111*IF(Inputs!$E111="Real",1,R$5)/Data!$F10 -> 0 | R98: =Inputs!N111*IF(Inputs!$E111="Real",1,S$5)/Data!$F10 -> 0 | S98: =Inputs!O111*IF(Inputs!$E111="Real",1,T$5)/Data!$F10 -> 0 | ... BE98: =Inputs!BA111*IF(Inputs!$E111="Real",1,BF$5)/Data!$F10 -> 0
C99: ='Project description'!$B$5 -> 0 | D99: =Lists!$B$34 | E99: BC | F99: =Inputs!B112 -> Heavy fuel oil | G99: $/GJ | H99: No | I99: Real | J99: =Analysis_year -> 0 | K99: =IF(Inputs!G112="","",Inputs!G112) | L99: =Inputs!H112*IF(Inputs!$E112="Real",1,M$5)/Data!$F11 -> 0 | M99: =Inputs!I112*IF(Inputs!$E112="Real",1,N$5)/Data!$F11 -> 0 | N99: =Inputs!J112*IF(Inputs!$E112="Real",1,O$5)/Data!$F11 -> 0 | O99: =Inputs!K112*IF(Inputs!$E112="Real",1,P$5)/Data!$F11 -> 0 | P99: =Inputs!L112*IF(Inputs!$E112="Real",1,Q$5)/Data!$F11 -> 0 | Q99: =Inputs!M112*IF(Inputs!$E112="Real",1,R$5)/Data!$F11 -> 0 | R99: =Inputs!N112*IF(Inputs!$E112="Real",1,S$5)/Data!$F11 -> 0 | S99: =Inputs!O112*IF(Inputs!$E112="Real",1,T$5)/Data!$F11 -> 0 | ... BE99: =Inputs!BA112*IF(Inputs!$E112="Real",1,BF$5)/Data!$F11 -> 0
C100: ='Project description'!$B$5 -> 0 | D100: =Lists!$B$34 | E100: BC | F100: =Inputs!B113 -> Geothermal | G100: $/GJ | H100: No | I100: Real | J100: =Analysis_year -> 0 | K100: =IF(Inputs!G113="","",Inputs!G113) | L100: =Inputs!H113*IF(Inputs!$E113="Real",1,M$5)/Data!$F12 -> 0 | M100: =Inputs!I113*IF(Inputs!$E113="Real",1,N$5)/Data!$F12 -> 0 | N100: =Inputs!J113*IF(Inputs!$E113="Real",1,O$5)/Data!$F12 -> 0 | O100: =Inputs!K113*IF(Inputs!$E113="Real",1,P$5)/Data!$F12 -> 0 | P100: =Inputs!L113*IF(Inputs!$E113="Real",1,Q$5)/Data!$F12 -> 0 | Q100: =Inputs!M113*IF(Inputs!$E113="Real",1,R$5)/Data!$F12 -> 0 | R100: =Inputs!N113*IF(Inputs!$E113="Real",1,S$5)/Data!$F12 -> 0 | S100: =Inputs!O113*IF(Inputs!$E113="Real",1,T$5)/Data!$F12 -> 0 | ... BE100: =Inputs!BA113*IF(Inputs!$E113="Real",1,BF$5)/Data!$F12 -> 0
C101: ='Project description'!$B$5 -> 0 | D101: =Lists!$B$34 | E101: BC | F101: =Inputs!B114 -> Wood or wood chips | G101: $/GJ | H101: No | I101: Real | J101: =Analysis_year -> 0 | K101: =IF(Inputs!G114="","",Inputs!G114) | L101: =Inputs!H114*IF(Inputs!$E114="Real",1,M$5)/Data!$F13 -> 0 | M101: =Inputs!I114*IF(Inputs!$E114="Real",1,N$5)/Data!$F13 -> 0 | N101: =Inputs!J114*IF(Inputs!$E114="Real",1,O$5)/Data!$F13 -> 0 | O101: =Inputs!K114*IF(Inputs!$E114="Real",1,P$5)/Data!$F13 -> 0 | P101: =Inputs!L114*IF(Inputs!$E114="Real",1,Q$5)/Data!$F13 -> 0 | Q101: =Inputs!M114*IF(Inputs!$E114="Real",1,R$5)/Data!$F13 -> 0 | R101: =Inputs!N114*IF(Inputs!$E114="Real",1,S$5)/Data!$F13 -> 0 | S101: =Inputs!O114*IF(Inputs!$E114="Real",1,T$5)/Data!$F13 -> 0 | ... BE101: =Inputs!BA114*IF(Inputs!$E114="Real",1,BF$5)/Data!$F13 -> 0
A103: 2c) Fuel costs
A104: Proposed Project | E104: ProjectId | F104: LifeCycleMonths | G104: Scenario | H104: Fuel type | I104: Value basis | J104: Base year | K104: Applicant comment | L104: 2025 | M104: 2026 | N104: 2027 | O104: 2028 | P104: 2029 | Q104: 2030 | R104: 2031 | S104: 2032 | T104: 2033 | U104: 2034 | V104: 2035 | W104: 2036 | X104: 2037 | Y104: 2038 | Z104: 2039 | AA104: 2040 | AB104: 2041 | AC104: 2042 | AD104: 2043 | AE104: 2044 | AF104: 2045 | AG104: 2046 | AH104: 2047 | AI104: 2048 | AJ104: 2049 | AK104: 2050 | AL104: 2051 | AM104: 2052 | AN104: 2053 | AO104: 2054 | AP104: 2055 | AQ104: 2056 | AR104: 2057 | AS104: 2058 | AT104: 2059 | AU104: 2060 | AV104: 2061 | AW104: 2062 | AX104: 2063 | AY104: 2064 | AZ104: 2065 | BA104: 2066 | BB104: 2067 | BC104: 2068 | BD104: 2069 | BE104: 2070
E105: ='Project description'!$B$5 -> 0 | F105: =Lists!$B$34 | G105: PP | H105: =IF(I51="<Select>","",I51) -> Electricity | I105: =I78 -> Real | J105: =Analysis_year -> 0 | K105: =IF(Inputs!G118="","",Inputs!G118) | L105: =L51*L78 -> 0 | M105: =M51*M78 -> 0 | N105: =N51*N78 -> 0 | O105: =O51*O78 -> 0 | P105: =P51*P78 -> 0 | Q105: =Q51*Q78 -> 0 | R105: =R51*R78 -> 0 | S105: =S51*S78 -> 0 | ... BE105: =BE51*BE78 -> 0
E106: ='Project description'!$B$5 -> 0 | F106: =Lists!$B$34 | G106: PP | H106: =IF(I52="<Select>","",I52) -> Natural Gas | I106: =I79 -> Real | J106: =Analysis_year -> 0 | K106: =IF(Inputs!G119="","",Inputs!G119) | L106: =L52*L79 -> 0 | M106: =M52*M79 -> 0 | N106: =N52*N79 -> 0 | O106: =O52*O79 -> 0 | P106: =P52*P79 -> 0 | Q106: =Q52*Q79 -> 0 | R106: =R52*R79 -> 0 | S106: =S52*S79 -> 0 | ... BE106: =BE52*BE79 -> 0
E107: ='Project description'!$B$5 -> 0 | F107: =Lists!$B$34 | G107: PP | H107: =IF(I53="<Select>","",I53) -> Coal - sub bituminous | I107: =I80 -> Real | J107: =Analysis_year -> 0 | K107: =IF(Inputs!G120="","",Inputs!G120) | L107: =L53*L80 -> 0 | M107: =M53*M80 -> 0 | N107: =N53*N80 -> 0 | O107: =O53*O80 -> 0 | P107: =P53*P80 -> 0 | Q107: =Q53*Q80 -> 0 | R107: =R53*R80 -> 0 | S107: =S53*S80 -> 0 | ... BE107: =BE53*BE80 -> 0
E108: ='Project description'!$B$5 -> 0 | F108: =Lists!$B$34 | G108: PP | H108: =IF(I54="<Select>","",I54) -> Coal - bituminous | I108: =I81 -> Real | J108: =Analysis_year -> 0 | K108: =IF(Inputs!G121="","",Inputs!G121) | L108: =L54*L81 -> 0 | M108: =M54*M81 -> 0 | N108: =N54*N81 -> 0 | O108: =O54*O81 -> 0 | P108: =P54*P81 -> 0 | Q108: =Q54*Q81 -> 0 | R108: =R54*R81 -> 0 | S108: =S54*S81 -> 0 | ... BE108: =BE54*BE81 -> 0
E109: ='Project description'!$B$5 -> 0 | F109: =Lists!$B$34 | G109: PP | H109: =IF(I55="<Select>","",I55) -> Coal - lignite | I109: =I82 -> Real | J109: =Analysis_year -> 0 | K109: =IF(Inputs!G122="","",Inputs!G122) | L109: =L55*L82 -> 0 | M109: =M55*M82 -> 0 | N109: =N55*N82 -> 0 | O109: =O55*O82 -> 0 | P109: =P55*P82 -> 0 | Q109: =Q55*Q82 -> 0 | R109: =R55*R82 -> 0 | S109: =S55*S82 -> 0 | ... BE109: =BE55*BE82 -> 0
E110: ='Project description'!$B$5 -> 0 | F110: =Lists!$B$34 | G110: PP | H110: =IF(I56="<Select>","",I56) -> Diesel | I110: =I83 -> Real | J110: =Analysis_year -> 0 | K110: =IF(Inputs!G123="","",Inputs!G123) | L110: =L56*L83 -> 0 | M110: =M56*M83 -> 0 | N110: =N56*N83 -> 0 | O110: =O56*O83 -> 0 | P110: =P56*P83 -> 0 | Q110: =Q56*Q83 -> 0 | R110: =R56*R83 -> 0 | S110: =S56*S83 -> 0 | ... BE110: =BE56*BE83 -> 0
E111: ='Project description'!$B$5 -> 0 | F111: =Lists!$B$34 | G111: PP | H111: =IF(I57="<Select>","",I57) -> LPG | I111: =I84 -> Real | J111: =Analysis_year -> 0 | K111: =IF(Inputs!G124="","",Inputs!G124) | L111: =L57*L84 -> 0 | M111: =M57*M84 -> 0 | N111: =N57*N84 -> 0 | O111: =O57*O84 -> 0 | P111: =P57*P84 -> 0 | Q111: =Q57*Q84 -> 0 | R111: =R57*R84 -> 0 | S111: =S57*S84 -> 0 | ... BE111: =BE57*BE84 -> 0
...

Sheet Results
A1: ='Project description'!B4 -> <Select> | B1: Years from start: | C1: =Analysis_year-Start_Yr -> 0
A3: National perspective
A4: NPV | B4: 2% | C4: 8%
A5: PP | B5: =Calculations!F65 -> 0 | C5: =Calculations!G65 -> 0
A6: BC | B6: =Calculations!F66 -> 0 | C6: =Calculations!G66 -> 0
A7: Preferred: | B7: =IF(B5>B6,$A5,$A6) -> BC | C7: =IF(C5>C6,$A5,$A6) -> BC
A10: Private perspective
A11: Private Returns | B11: Pre-tax Nominal | C11: IRR
B12: =ReturnType -> <Select>
A13: PP | B13: =Calculations!E76 -> 0 | C13: =Calculations!F76 -> No feasible solution
A14: BC | B14: =Calculations!E77 -> 0 | C14: =Calculations!F77 -> No feasible solution
A15: Preferred: | B15: =IF(B13>B14,$A13,$A14) -> BC | C15: =IF(C13>C14,$A13,$A14) -> BC
A18: Energy savings (GJ) | B18: Total | C18: 2025 | D18: 2026 | E18: 2027 | F18: 2028 | G18: 2029 | H18: 2030 | I18: 2031 | J18: 2032 | K18: 2033 | L18: 2034 | M18: 2035 | N18: 2036 | O18: 2037 | P18: 2038 | Q18: 2039 | R18: 2040 | S18: 2041 | T18: 2042 | U18: 2043 | V18: 2044 | W18: 2045 | X18: 2046 | Y18: 2047 | Z18: 2048 | AA18: 2049 | AB18: 2050 | AC18: 2051 | AD18: 2052 | AE18: 2053 | AF18: 2054 | AG18: 2055 | AH18: 2056 | AI18: 2057 | AJ18: 2058 | AK18: 2059 | AL18: 2060 | AM18: 2061 | AN18: 2062 | AO18: 2063 | AP18: 2064 | AQ18: 2065 | AR18: 2066 | AS18: 2067 | AT18: 2068 | AU18: 2069 | AV18: 2070
A19: Electricity | B19: =SUM(C19:AU19) -> 0 | C19: ='Real values'!L64-'Real values'!L51 -> 0 | D19: ='Real values'!M64-'Real values'!M51 -> 0 | E19: ='Real values'!N64-'Real values'!N51 -> 0 | F19: ='Real values'!O64-'Real values'!O51 -> 0 | G19: ='Real values'!P64-'Real values'!P51 -> 0 | H19: ='Real values'!Q64-'Real values'!Q51 -> 0 | I19: ='Real values'!R64-'Real values'!R51 -> 0 | J19: ='Real values'!S64-'Real values'!S51 -> 0 | ... AR19: ='Real values'!BA64-'Real values'!BA51 -> 0 | AS19: ='Real values'!BC64-'Real values'!BC51 -> 0 | AT19: ='Real values'!BD64-'Real values'!BD51 -> 0 | AU19: ='Real values'!BE64-'Real values'!BE51 -> 0 | AV19: ='Real values'!BF64-'Real values'!BF51 -> 0
A20: Natural Gas | B20: =SUM(C20:AU20) -> 0 | C20: ='Real values'!L65-'Real values'!L52 -> 0 | D20: ='Real values'!M65-'Real values'!M52 -> 0 | E20: ='Real values'!N65-'Real values'!N52 -> 0 | F20: ='Real values'!O65-'Real values'!O52 -> 0 | G20: ='Real values'!P65-'Real values'!P52 -> 0 | H20: ='Real values'!Q65-'Real values'!Q52 -> 0 | I20: ='Real values'!R65-'Real values'!R52 -> 0 | J20: ='Real values'!S65-'Real values'!S52 -> 0 | ... AR20: ='Real values'!BA65-'Real values'!BA52 -> 0 | AS20: ='Real values'!BC65-'Real values'!BC52 -> 0 | AT20: ='Real values'!BD65-'Real values'!BD52 -> 0 | AU20: ='Real values'!BE65-'Real values'!BE52 -> 0 | AV20: ='Real values'!BF65-'Real values'!BF52 -> 0
A21: Coal - sub bituminous | B21: =SUM(C21:AU21) -> 0 | C21: ='Real values'!L66-'Real values'!L53 -> 0 | D21: ='Real values'!M66-'Real values'!M53 -> 0 | E21: ='Real values'!N66-'Real values'!N53 -> 0 | F21: ='Real values'!O66-'Real values'!O53 -> 0 | G21: ='Real values'!P66-'Real values'!P53 -> 0 | H21: ='Real values'!Q66-'Real values'!Q53 -> 0 | I21: ='Real values'!R66-'Real values'!R53 -> 0 | J21: ='Real values'!S66-'Real values'!S53 -> 0 | ... AR21: ='Real values'!BA66-'Real values'!BA53 -> 0 | AS21: ='Real values'!BC66-'Real values'!BC53 -> 0 | AT21: ='Real values'!BD66-'Real values'!BD53 -> 0 | AU21: ='Real values'!BE66-'Real values'!BE53 -> 0 | AV21: ='Real values'!BF66-'Real values'!BF53 -> 0
A22: Coal - bituminous | B22: =SUM(C22:AU22) -> 0 | C22: ='Real values'!L67-'Real values'!L54 -> 0 | D22: ='Real values'!M67-'Real values'!M54 -> 0 | E22: ='Real values'!N67-'Real values'!N54 -> 0 | F22: ='Real values'!O67-'Real values'!O54 -> 0 | G22: ='Real values'!P67-'Real values'!P54 -> 0 | H22: ='Real values'!Q67-'Real values'!Q54 -> 0 | I22: ='Real values'!R67-'Real values'!R54 -> 0 | J22: ='Real values'!S67-'Real values'!S54 -> 0 | ... AR22: ='Real values'!BA67-'Real values'!BA54 -> 0 | AS22: ='Real values'!BC67-'Real values'!BC54 -> 0 | AT22: ='Real values'!BD67-'Real values'!BD54 -> 0 | AU22: ='Real values'!BE67-'Real values'!BE54 -> 0 | AV22: ='Real values'!BF67-'Real values'!BF54 -> 0
A23: Coal - lignite | B23: =SUM(C23:AU23) -> 0 | C23: ='Real values'!L68-'Real values'!L55 -> 0 | D23: ='Real values'!M68-'Real values'!M55 -> 0 | E23: ='Real values'!N68-'Real values'!N55 -> 0 | F23: ='Real values'!O68-'Real values'!O55 -> 0 | G23: ='Real values'!P68-'Real values'!P55 -> 0 | H23: ='Real values'!Q68-'Real values'!Q55 -> 0 | I23: ='Real values'!R68-'Real values'!R55 -> 0 | J23: ='Real values'!S68-'Real values'!S55 -> 0 | ... AR23: ='Real values'!BA68-'Real values'!BA55 -> 0 | AS23: ='Real values'!BC68-'Real values'!BC55 -> 0 | AT23: ='Real values'!BD68-'Real values'!BD55 -> 0 | AU23: ='Real values'!BE68-'Real values'!BE55 -> 0 | AV23: ='Real values'!BF68-'Real values'!BF55 -> 0
A24: Diesel | B24: =SUM(C24:AU24) -> 0 | C24: ='Real values'!L69-'Real values'!L56 -> 0 | D24: ='Real values'!M69-'Real values'!M56 -> 0 | E24: ='Real values'!N69-'Real values'!N56 -> 0 | F24: ='Real values'!O69-'Real values'!O56 -> 0 | G24: ='Real values'!P69-'Real values'!P56 -> 0 | H24: ='Real values'!Q69-'Real values'!Q56 -> 0 | I24: ='Real values'!R69-'Real values'!R56 -> 0 | J24: ='Real values'!S69-'Real values'!S56 -> 0 | ... AR24: ='Real values'!BA69-'Real values'!BA56 -> 0 | AS24: ='Real values'!BC69-'Real values'!BC56 -> 0 | AT24: ='Real values'!BD69-'Real values'!BD56 -> 0 | AU24: ='Real values'!BE69-'Real values'!BE56 -> 0 | AV24: ='Real values'!BF69-'Real values'!BF56 -> 0
A25: LPG | B25: =SUM(C25:AU25) -> 0 | C25: ='Real values'!L70-'Real values'!L57 -> 0 | D25: ='Real values'!M70-'Real values'!M57 -> 0 | E25: ='Real values'!N70-'Real values'!N57 -> 0 | F25: ='Real values'!O70-'Real values'!O57 -> 0 | G25: ='Real values'!P70-'Real values'!P57 -> 0 | H25: ='Real values'!Q70-'Real values'!Q57 -> 0 | I25: ='Real values'!R70-'Real values'!R57 -> 0 | J25: ='Real values'!S70-'Real values'!S57 -> 0 | ... AR25: ='Real values'!BA70-'Real values'!BA57 -> 0 | AS25: ='Real values'!BC70-'Real values'!BC57 -> 0 | AT25: ='Real values'!BD70-'Real values'!BD57 -> 0 | AU25: ='Real values'!BE70-'Real values'!BE57 -> 0 | AV25: ='Real values'!BF70-'Real values'!BF57 -> 0
A26: Light fuel oil | B26: =SUM(C26:AU26) -> 0 | C26: ='Real values'!L71-'Real values'!L58 -> 0 | D26: ='Real values'!M71-'Real values'!M58 -> 0 | E26: ='Real values'!N71-'Real values'!N58 -> 0 | F26: ='Real values'!O71-'Real values'!O58 -> 0 | G26: ='Real values'!P71-'Real values'!P58 -> 0 | H26: ='Real values'!Q71-'Real values'!Q58 -> 0 | I26: ='Real values'!R71-'Real values'!R58 -> 0 | J26: ='Real values'!S71-'Real values'!S58 -> 0 | ... AR26: ='Real values'!BA71-'Real values'!BA58 -> 0 | AS26: ='Real values'!BC71-'Real values'!BC58 -> 0 | AT26: ='Real values'!BD71-'Real values'!BD58 -> 0 | AU26: ='Real values'!BE71-'Real values'!BE58 -> 0 | AV26: ='Real values'!BF71-'Real values'!BF58 -> 0
A27: Heavy fuel oil | B27: =SUM(C27:AU27) -> 0 | C27: ='Real values'!L72-'Real values'!L59 -> 0 | D27: ='Real values'!M72-'Real values'!M59 -> 0 | E27: ='Real values'!N72-'Real values'!N59 -> 0 | F27: ='Real values'!O72-'Real values'!O59 -> 0 | G27: ='Real values'!P72-'Real values'!P59 -> 0 | H27: ='Real values'!Q72-'Real values'!Q59 -> 0 | I27: ='Real values'!R72-'Real values'!R59 -> 0 | J27: ='Real values'!S72-'Real values'!S59 -> 0 | ... AR27: ='Real values'!BA72-'Real values'!BA59 -> 0 | AS27: ='Real values'!BC72-'Real values'!BC59 -> 0 | AT27: ='Real values'!BD72-'Real values'!BD59 -> 0 | AU27: ='Real values'!BE72-'Real values'!BE59 -> 0 | AV27: ='Real values'!BF72-'Real values'!BF59 -> 0
A28: Geothermal | B28: =SUM(C28:AU28) -> 0 | C28: ='Real values'!L73-'Real values'!L60 -> 0 | D28: ='Real values'!M73-'Real values'!M60 -> 0 | E28: ='Real values'!N73-'Real values'!N60 -> 0 | F28: ='Real values'!O73-'Real values'!O60 -> 0 | G28: ='Real values'!P73-'Real values'!P60 -> 0 | H28: ='Real values'!Q73-'Real values'!Q60 -> 0 | I28: ='Real values'!R73-'Real values'!R60 -> 0 | J28: ='Real values'!S73-'Real values'!S60 -> 0 | ... AR28: ='Real values'!BA73-'Real values'!BA60 -> 0 | AS28: ='Real values'!BC73-'Real values'!BC60 -> 0 | AT28: ='Real values'!BD73-'Real values'!BD60 -> 0 | AU28: ='Real values'!BE73-'Real values'!BE60 -> 0 | AV28: ='Real values'!BF73-'Real values'!BF60 -> 0
A29: Wood or wood chips | B29: =SUM(C29:AU29) -> 0 | C29: ='Real values'!L74-'Real values'!L61 -> 0 | D29: ='Real values'!M74-'Real values'!M61 -> 0 | E29: ='Real values'!N74-'Real values'!N61 -> 0 | F29: ='Real values'!O74-'Real values'!O61 -> 0 | G29: ='Real values'!P74-'Real values'!P61 -> 0 | H29: ='Real values'!Q74-'Real values'!Q61 -> 0 | I29: ='Real values'!R74-'Real values'!R61 -> 0 | J29: ='Real values'!S74-'Real values'!S61 -> 0 | ... AR29: ='Real values'!BA74-'Real values'!BA61 -> 0 | AS29: ='Real values'!BC74-'Real values'!BC61 -> 0 | AT29: ='Real values'!BD74-'Real values'!BD61 -> 0 | AU29: ='Real values'!BE74-'Real values'!BE61 -> 0 | AV29: ='Real values'!BF74-'Real values'!BF61 -> 0
A30: Total | B30: =SUM(B19:B29) -> 0 | C30: =SUM(C19:C29) -> 0 | D30: =SUM(D19:D29) -> 0 | E30: =SUM(E19:E29) -> 0 | F30: =SUM(F19:F29) -> 0 | G30: =SUM(G19:G29) -> 0 | H30: =SUM(H19:H29) -> 0 | I30: =SUM(I19:I29) -> 0 | ... AV30: =SUM(AV19:AV29) -> 0
A32: Energy savings ($) | B32: Total | C32: 2025 | D32: 2026 | E32: 2027 | F32: 2028 | G32: 2029 | H32: 2030 | I32: 2031 | J32: 2032 | K32: 2033 | L32: 2034 | M32: 2035 | N32: 2036 | O32: 2037 | P32: 2038 | Q32: 2039 | R32: 2040 | S32: 2041 | T32: 2042 | U32: 2043 | V32: 2044 | W32: 2045 | X32: 2046 | Y32: 2047 | Z32: 2048 | AA32: 2049 | AB32: 2050 | AC32: 2051 | AD32: 2052 | AE32: 2053 | AF32: 2054 | AG32: 2055 | AH32: 2056 | AI32: 2057 | AJ32: 2058 | AK32: 2059 | AL32: 2060 | AM32: 2061 | AN32: 2062 | AO32: 2063 | AP32: 2064 | AQ32: 2065 | AR32: 2066 | AS32: 2067 | AT32: 2068 | AU32: 2069 | AV32: 2070
A33: Electricity | B33: =SUM(C33:AU33) -> 0 | C33: ='Real values'!L119-'Real values'!L105 -> 0 | D33: ='Real values'!M119-'Real values'!M105 -> 0 | E33: ='Real values'!N119-'Real values'!N105 -> 0 | F33: ='Real values'!O119-'Real values'!O105 -> 0 | G33: ='Real values'!P119-'Real values'!P105 -> 0 | H33: ='Real values'!Q119-'Real values'!Q105 -> 0 | I33: ='Real values'!R119-'Real values'!R105 -> 0 | J33: ='Real values'!S119-'Real values'!S105 -> 0 | ... AP33: ='Real values'!AY119-'Real values'!AY105 -> 0 | AQ33: ='Real values'!BA119-'Real values'!BA105 -> 0 | AR33: ='Real values'!BB119-'Real values'!BB105 -> 0 | AS33: ='Real values'!BC119-'Real values'!BC105 -> 0 | AT33: ='Real values'!BD119-'Real values'!BD105 -> 0 | AU33: ='Real values'!BE119-'Real values'!BE105 -> 0 | AV33: ='Real values'!BF119-'Real values'!BF105 -> 0
A34: Natural Gas | B34: =SUM(C34:AU34) -> 0 | C34: ='Real values'!L120-'Real values'!L106 -> 0 | D34: ='Real values'!M120-'Real values'!M106 -> 0 | E34: ='Real values'!N120-'Real values'!N106 -> 0 | F34: ='Real values'!O120-'Real values'!O106 -> 0 | G34: ='Real values'!P120-'Real values'!P106 -> 0 | H34: ='Real values'!Q120-'Real values'!Q106 -> 0 | I34: ='Real values'!R120-'Real values'!R106 -> 0 | J34: ='Real values'!S120-'Real values'!S106 -> 0 | ... AP34: ='Real values'!AY120-'Real values'!AY106 -> 0 | AQ34: ='Real values'!BA120-'Real values'!BA106 -> 0 | AR34: ='Real values'!BB120-'Real values'!BB106 -> 0 | AS34: ='Real values'!BC120-'Real values'!BC106 -> 0 | AT34: ='Real values'!BD120-'Real values'!BD106 -> 0 | AU34: ='Real values'!BE120-'Real values'!BE106 -> 0 | AV34: ='Real values'!BF120-'Real values'!BF106 -> 0
A35: Coal - sub bituminous | B35: =SUM(C35:AU35) -> 0 | C35: ='Real values'!L121-'Real values'!L107 -> 0 | D35: ='Real values'!M121-'Real values'!M107 -> 0 | E35: ='Real values'!N121-'Real values'!N107 -> 0 | F35: ='Real values'!O121-'Real values'!O107 -> 0 | G35: ='Real values'!P121-'Real values'!P107 -> 0 | H35: ='Real values'!Q121-'Real values'!Q107 -> 0 | I35: ='Real values'!R121-'Real values'!R107 -> 0 | J35: ='Real values'!S121-'Real values'!S107 -> 0 | ... AP35: ='Real values'!AY121-'Real values'!AY107 -> 0 | AQ35: ='Real values'!BA121-'Real values'!BA107 -> 0 | AR35: ='Real values'!BB121-'Real values'!BB107 -> 0 | AS35: ='Real values'!BC121-'Real values'!BC107 -> 0 | AT35: ='Real values'!BD121-'Real values'!BD107 -> 0 | AU35: ='Real values'!BE121-'Real values'!BE107 -> 0 | AV35: ='Real values'!BF121-'Real values'!BF107 -> 0
A36: Coal - bituminous | B36: =SUM(C36:AU36) -> 0 | C36: ='Real values'!L122-'Real values'!L108 -> 0 | D36: ='Real values'!M122-'Real values'!M108 -> 0 | E36: ='Real values'!N122-'Real values'!N108 -> 0 | F36: ='Real values'!O122-'Real values'!O108 -> 0 | G36: ='Real values'!P122-'Real values'!P108 -> 0 | H36: ='Real values'!Q122-'Real values'!Q108 -> 0 | I36: ='Real values'!R122-'Real values'!R108 -> 0 | J36: ='Real values'!S122-'Real values'!S108 -> 0 | ... AP36: ='Real values'!AY122-'Real values'!AY108 -> 0 | AQ36: ='Real values'!BA122-'Real values'!BA108 -> 0 | AR36: ='Real values'!BB122-'Real values'!BB108 -> 0 | AS36: ='Real values'!BC122-'Real values'!BC108 -> 0 | AT36: ='Real values'!BD122-'Real values'!BD108 -> 0 | AU36: ='Real values'!BE122-'Real values'!BE108 -> 0 | AV36: ='Real values'!BF122-'Real values'!BF108 -> 0
A37: Coal - lignite | B37: =SUM(C37:AU37) -> 0 | C37: ='Real values'!L123-'Real values'!L109 -> 0 | D37: ='Real values'!M123-'Real values'!M109 -> 0 | E37: ='Real values'!N123-'Real values'!N109 -> 0 | F37: ='Real values'!O123-'Real values'!O109 -> 0 | G37: ='Real values'!P123-'Real values'!P109 -> 0 | H37: ='Real values'!Q123-'Real values'!Q109 -> 0 | I37: ='Real values'!R123-'Real values'!R109 -> 0 | J37: ='Real values'!S123-'Real values'!S109 -> 0 | ... AP37: ='Real values'!AY123-'Real values'!AY109 -> 0 | AQ37: ='Real values'!BA123-'Real values'!BA109 -> 0 | AR37: ='Real values'!BB123-'Real values'!BB109 -> 0 | AS37: ='Real values'!BC123-'Real values'!BC109 -> 0 | AT37: ='Real values'!BD123-'Real values'!BD109 -> 0 | AU37: ='Real values'!BE123-'Real values'!BE109 -> 0 | AV37: ='Real values'!BF123-'Real values'!BF109 -> 0
A38: Diesel | B38: =SUM(C38:AU38) -> 0 | C38: ='Real values'!L124-'Real values'!L110 -> 0 | D38: ='Real values'!M124-'Real values'!M110 -> 0 | E38: ='Real values'!N124-'Real values'!N110 -> 0 | F38: ='Real values'!O124-'Real values'!O110 -> 0 | G38: ='Real values'!P124-'Real values'!P110 -> 0 | H38: ='Real values'!Q124-'Real values'!Q110 -> 0 | I38: ='Real values'!R124-'Real values'!R110 -> 0 | J38: ='Real values'!S124-'Real values'!S110 -> 0 | ... AP38: ='Real values'!AY124-'Real values'!AY110 -> 0 | AQ38: ='Real values'!BA124-'Real values'!BA110 -> 0 | AR38: ='Real values'!BB124-'Real values'!BB110 -> 0 | AS38: ='Real values'!BC124-'Real values'!BC110 -> 0 | AT38: ='Real values'!BD124-'Real values'!BD110 -> 0 | AU38: ='Real values'!BE124-'Real values'!BE110 -> 0 | AV38: ='Real values'!BF124-'Real values'!BF110 -> 0
A39: LPG | B39: =SUM(C39:AU39) -> 0 | C39: ='Real values'!L125-'Real values'!L111 -> 0 | D39: ='Real values'!M125-'Real values'!M111 -> 0 | E39: ='Real values'!N125-'Real values'!N111 -> 0 | F39: ='Real values'!O125-'Real values'!O111 -> 0 | G39: ='Real values'!P125-'Real values'!P111 -> 0 | H39: ='Real values'!Q125-'Real values'!Q111 -> 0 | I39: ='Real values'!R125-'Real values'!R111 -> 0 | J39: ='Real values'!S125-'Real values'!S111 -> 0 | ... AP39: ='Real values'!AY125-'Real values'!AY111 -> 0 | AQ39: ='Real values'!BA125-'Real values'!BA111 -> 0 | AR39: ='Real values'!BB125-'Real values'!BB111 -> 0 | AS39: ='Real values'!BC125-'Real values'!BC111 -> 0 | AT39: ='Real values'!BD125-'Real values'!BD111 -> 0 | AU39: ='Real values'!BE125-'Real values'!BE111 -> 0 | AV39: ='Real values'!BF125-'Real values'!BF111 -> 0
A40: Light fuel oil | B40: =SUM(C40:AU40) -> 0 | C40: ='Real values'!L126-'Real values'!L112 -> 0 | D40: ='Real values'!M126-'Real values'!M112 -> 0 | E40: ='Real values'!N126-'Real values'!N112 -> 0 | F40: ='Real values'!O126-'Real values'!O112 -> 0 | G40: ='Real values'!P126-'Real values'!P112 -> 0 | H40: ='Real values'!Q126-'Real values'!Q112 -> 0 | I40: ='Real values'!R126-'Real values'!R112 -> 0 | J40: ='Real values'!S126-'Real values'!S112 -> 0 | ... AP40: ='Real values'!AY126-'Real values'!AY112 -> 0 | AQ40: ='Real values'!BA126-'Real values'!BA112 -> 0 | AR40: ='Real values'!BB126-'Real values'!BB112 -> 0 | AS40: ='Real values'!BC126-'Real values'!BC112 -> 0 | AT40: ='Real values'!BD126-'Real values'!BD112 -> 0 | AU40: ='Real values'!BE126-'Real values'!BE112 -> 0 | AV40: ='Real values'!BF126-'Real values'!BF112 -> 0
A41: Heavy fuel oil | B41: =SUM(C41:AU41) -> 0 | C41: ='Real values'!L127-'Real values'!L113 -> 0 | D41: ='Real values'!M127-'Real values'!M113 -> 0 | E41: ='Real values'!N127-'Real values'!N113 -> 0 | F41: ='Real values'!O127-'Real values'!O113 -> 0 | G41: ='Real values'!P127-'Real values'!P113 -> 0 | H41: ='Real values'!Q127-'Real values'!Q113 -> 0 | I41: ='Real values'!R127-'Real values'!R113 -> 0 | J41: ='Real values'!S127-'Real values'!S113 -> 0 | ... AP41: ='Real values'!AY127-'Real values'!AY113 -> 0 | AQ41: ='Real values'!BA127-'Real values'!BA113 -> 0 | AR41: ='Real values'!BB127-'Real values'!BB113 -> 0 | AS41: ='Real values'!BC127-'Real values'!BC113 -> 0 | AT41: ='Real values'!BD127-'Real values'!BD113 -> 0 | AU41: ='Real values'!BE127-'Real values'!BE113 -> 0 | AV41: ='Real values'!BF127-'Real values'!BF113 -> 0
A42: Geothermal | B42: =SUM(C42:AU42) -> 0 | C42: ='Real values'!L128-'Real values'!L114 -> 0 | D42: ='Real values'!M128-'Real values'!M114 -> 0 | E42: ='Real values'!N128-'Real values'!N114 -> 0 | F42: ='Real values'!O128-'Real values'!O114 -> 0 | G42: ='Real values'!P128-'Real values'!P114 -> 0 | H42: ='Real values'!Q128-'Real values'!Q114 -> 0 | I42: ='Real values'!R128-'Real values'!R114 -> 0 | J42: ='Real values'!S128-'Real values'!S114 -> 0 | ... AP42: ='Real values'!AY128-'Real values'!AY114 -> 0 | AQ42: ='Real values'!BA128-'Real values'!BA114 -> 0 | AR42: ='Real values'!BB128-'Real values'!BB114 -> 0 | AS42: ='Real values'!BC128-'Real values'!BC114 -> 0 | AT42: ='Real values'!BD128-'Real values'!BD114 -> 0 | AU42: ='Real values'!BE128-'Real values'!BE114 -> 0 | AV42: ='Real values'!BF128-'Real values'!BF114 -> 0
A43: Wood or wood chips | B43: =SUM(C43:AU43) -> 0 | C43: ='Real values'!L129-'Real values'!L115 -> 0 | D43: ='Real values'!M129-'Real values'!M115 -> 0 | E43: ='Real values'!N129-'Real values'!N115 -> 0 | F43: ='Real values'!O129-'Real values'!O115 -> 0 | G43: ='Real values'!P129-'Real values'!P115 -> 0 | H43: ='Real values'!Q129-'Real values'!Q115 -> 0 | I43: ='Real values'!R129-'Real values'!R115 -> 0 | J43: ='Real values'!S129-'Real values'!S115 -> 0 | ... AP43: ='Real values'!AY129-'Real values'!AY115 -> 0 | AQ43: ='Real values'!BA129-'Real values'!BA115 -> 0 | AR43: ='Real values'!BB129-'Real values'!BB115 -> 0 | AS43: ='Real values'!BC129-'Real values'!BC115 -> 0 | AT43: ='Real values'!BD129-'Real values'!BD115 -> 0 | AU43: ='Real values'!BE129-'Real values'!BE115 -> 0 | AV43: ='Real values'!BF129-'Real values'!BF115 -> 0
A44: Total | B44: =SUM(B33:B43) -> 0 | C44: =SUM(C33:C43) -> 0 | D44: =SUM(D33:D43) -> 0 | E44: =SUM(E33:E43) -> 0 | F44: =SUM(F33:F43) -> 0 | G44: =SUM(G33:G43) -> 0 | H44: =SUM(H33:H43) -> 0 | I44: =SUM(I33:I43) -> 0 | ... AV44: =SUM(AV33:AV43) -> 0
A46: Repayment | B46: Total | C46: 2025 | D46: 2026 | E46: 2027 | F46: 2028 | G46: 2029 | H46: 2030 | I46: 2031 | J46: 2032 | K46: 2033 | L46: 2034 | M46: 2035 | N46: 2036 | O46: 2037 | P46: 2038 | Q46: 2039 | R46: 2040 | S46: 2041 | T46: 2042 | U46: 2043 | V46: 2044 | W46: 2045 | X46: 2046 | Y46: 2047 | Z46: 2048 | AA46: 2049 | AB46: 2050 | AC46: 2051 | AD46: 2052 | AE46: 2053 | AF46: 2054 | AG46: 2055 | AH46: 2056 | AI46: 2057 | AJ46: 2058 | AK46: 2059 | AL46: 2060 | AM46: 2061 | AN46: 2062 | AO46: 2063 | AP46: 2064 | AQ46: 2065 | AR46: 2066 | AS46: 2067 | AT46: 2068 | AU46: 2069 | AV46: 2070
A47: Initial schedule | B47: =SUM(C47:AV47) -> 0 | C47: =Calculations!J160 -> 0 | D47: =Calculations!K160 -> 0 | E47: =Calculations!L160 -> 0 | F47: =Calculations!M160 -> 0 | G47: =Calculations!N160 -> 0 | H47: =Calculations!O160 -> 0 | I47: =Calculations!P160 -> 0 | J47: =Calculations!Q160 -> 0 | ... AV47: =Calculations!BC160 -> 0
A48: Payments made to date | B48: =SUM(C48:AV48) -> 0
A49: Revised schedule | B49: =B47-B48 -> 0 | C49: =Calculations!J164 -> 0 | D49: =Calculations!K164 -> 0 | E49: =Calculations!L164 -> 0 | F49: =Calculations!M164 -> 0 | G49: =Calculations!N164 -> 0 | H49: =Calculations!O164 -> 0 | I49: =Calculations!P164 -> 0 | J49: =Calculations!Q164 -> 0 | ... AV49: =Calculations!BC164 -> 0

Sheet Calculations
B1: Final Year
A2: Proposed Project | B2: =IF('Project description'!B15="Retrofit of existing asset",'Project description'!B16,YEAR('Project description'!B12)+'Project description'!B17) -> 1900
A3: Base Case | B3: =IF('Project description'!B15="Retrofit of existing asset",'Project description'!B16,YEAR('Project description'!B12)+'Project description'!B19) -> 1900
D5: Emissions
B6: ProjectId | C6: LifeCycleMonths | D6: Scenario | E6: Fuel type | F6: 2025 | G6: 2026 | H6: 2027 | I6: 2028 | J6: 2029 | K6: 2030 | L6: 2031 | M6: 2032 | N6: 2033 | O6: 2034 | P6: 2035 | Q6: 2036 | R6: 2037 | S6: 2038 | T6: 2039 | U6: 2040 | V6: 2041 | W6: 2042 | X6: 2043 | Y6: 2044 | Z6: 2045 | AA6: 2046 | AB6: 2047 | AC6: 2048 | AD6: 2049 | AE6: 2050 | AF6: 2051 | AG6: 2052 | AH6: 2053 | AI6: 2054 | AJ6: 2055 | AK6: 2056 | AL6: 2057 | AM6: 2058 | AN6: 2059 | AO6: 2060 | AP6: 2061 | AQ6: 2062 | AR6: 2063 | AS6: 2064 | AT6: 2065 | AU6: 2066 | AV6: 2067 | AW6: 2068 | AX6: 2069 | AY6: 2070
B7: ='Project description'!$B$5 -> 0 | C7: =Lists!$B$34 | D7: PP | E7: Electricity | F7: =Inputs!H64*Data!M2 -> 0 | G7: =Inputs!I64*Data!N2 -> 0 | H7: =Inputs!J64*Data!O2 -> 0 | I7: =Inputs!K64*Data!P2 -> 0 | J7: =Inputs!L64*Data!Q2 -> 0 | K7: =Inputs!M64*Data!R2 -> 0 | L7: =Inputs!N64*Data!S2 -> 0 | M7: =Inputs!O64*Data!T2 -> 0 | ... AY7: =Inputs!BA64*Data!BF2 -> 0
B8: ='Project description'!$B$5 -> 0 | C8: =Lists!$B$34 | D8: PP | E8: Natural Gas | F8: =Inputs!H65*Data!M3 -> 0 | G8: =Inputs!I65*Data!N3 -> 0 | H8: =Inputs!J65*Data!O3 -> 0 | I8: =Inputs!K65*Data!P3 -> 0 | J8: =Inputs!L65*Data!Q3 -> 0 | K8: =Inputs!M65*Data!R3 -> 0 | L8: =Inputs!N65*Data!S3 -> 0 | M8: =Inputs!O65*Data!T3 -> 0 | ... AY8: =Inputs!BA65*Data!BF3 -> 0
B9: ='Project description'!$B$5 -> 0 | C9: =Lists!$B$34 | D9: PP | E9: Coal - sub bituminous | F9: =Inputs!H66*Data!M4 -> 0 | G9: =Inputs!I66*Data!N4 -> 0 | H9: =Inputs!J66*Data!O4 -> 0 | I9: =Inputs!K66*Data!P4 -> 0 | J9: =Inputs!L66*Data!Q4 -> 0 | K9: =Inputs!M66*Data!R4 -> 0 | L9: =Inputs!N66*Data!S4 -> 0 | M9: =Inputs!O66*Data!T4 -> 0 | ... AY9: =Inputs!BA66*Data!BF4 -> 0
B10: ='Project description'!$B$5 -> 0 | C10: =Lists!$B$34 | D10: PP | E10: Coal - bituminous | F10: =Inputs!H67*Data!M5 -> 0 | G10: =Inputs!I67*Data!N5 -> 0 | H10: =Inputs!J67*Data!O5 -> 0 | I10: =Inputs!K67*Data!P5 -> 0 | J10: =Inputs!L67*Data!Q5 -> 0 | K10: =Inputs!M67*Data!R5 -> 0 | L10: =Inputs!N67*Data!S5 -> 0 | M10: =Inputs!O67*Data!T5 -> 0 | ... AY10: =Inputs!BA67*Data!BF5 -> 0
B11: ='Project description'!$B$5 -> 0 | C11: =Lists!$B$34 | D11: PP | E11: Coal - lignite | F11: =Inputs!H68*Data!M6 -> 0 | G11: =Inputs!I68*Data!N6 -> 0 | H11: =Inputs!J68*Data!O6 -> 0 | I11: =Inputs!K68*Data!P6 -> 0 | J11: =Inputs!L68*Data!Q6 -> 0 | K11: =Inputs!M68*Data!R6 -> 0 | L11: =Inputs!N68*Data!S6 -> 0 | M11: =Inputs!O68*Data!T6 -> 0 | ... AY11: =Inputs!BA68*Data!BF6 -> 0
B12: ='Project description'!$B$5 -> 0 | C12: =Lists!$B$34 | D12: PP | E12: Diesel | F12: =Inputs!H69*Data!M7 -> 0 | G12: =Inputs!I69*Data!N7 -> 0 | H12: =Inputs!J69*Data!O7 -> 0 | I12: =Inputs!K69*Data!P7 -> 0 | J12: =Inputs!L69*Data!Q7 -> 0 | K12: =Inputs!M69*Data!R7 -> 0 | L12: =Inputs!N69*Data!S7 -> 0 | M12: =Inputs!O69*Data!T7 -> 0 | ... AY12: =Inputs!BA69*Data!BF7 -> 0
B13: ='Project description'!$B$5 -> 0 | C13: =Lists!$B$34 | D13: PP | E13: LPG | F13: =Inputs!H70*Data!M8 -> 0 | G13: =Inputs!I70*Data!N8 -> 0 | H13: =Inputs!J70*Data!O8 -> 0 | I13: =Inputs!K70*Data!P8 -> 0 | J13: =Inputs!L70*Data!Q8 -> 0 | K13: =Inputs!M70*Data!R8 -> 0 | L13: =Inputs!N70*Data!S8 -> 0 | M13: =Inputs!O70*Data!T8 -> 0 | ... AY13: =Inputs!BA70*Data!BF8 -> 0
B14: ='Project description'!$B$5 -> 0 | C14: =Lists!$B$34 | D14: PP | E14: Light fuel oil | F14: =Inputs!H71*Data!M9 -> 0 | G14: =Inputs!I71*Data!N9 -> 0 | H14: =Inputs!J71*Data!O9 -> 0 | I14: =Inputs!K71*Data!P9 -> 0 | J14: =Inputs!L71*Data!Q9 -> 0 | K14: =Inputs!M71*Data!R9 -> 0 | L14: =Inputs!N71*Data!S9 -> 0 | M14: =Inputs!O71*Data!T9 -> 0 | ... AY14: =Inputs!BA71*Data!BF9 -> 0
B15: ='Project description'!$B$5 -> 0 | C15: =Lists!$B$34 | D15: PP | E15: Heavy fuel oil | F15: =Inputs!H72*Data!M10 -> 0 | G15: =Inputs!I72*Data!N10 -> 0 | H15: =Inputs!J72*Data!O10 -> 0 | I15: =Inputs!K72*Data!P10 -> 0 | J15: =Inputs!L72*Data!Q10 -> 0 | K15: =Inputs!M72*Data!R10 -> 0 | L15: =Inputs!N72*Data!S10 -> 0 | M15: =Inputs!O72*Data!T10 -> 0 | ... AY15: =Inputs!BA72*Data!BF10 -> 0
B16: ='Project description'!$B$5 -> 0 | C16: =Lists!$B$34 | D16: PP | E16: Geothermal | F16: =Inputs!H73*Data!M11 -> 0 | G16: =Inputs!I73*Data!N11 -> 0 | H16: =Inputs!J73*Data!O11 -> 0 | I16: =Inputs!K73*Data!P11 -> 0 | J16: =Inputs!L73*Data!Q11 -> 0 | K16: =Inputs!M73*Data!R11 -> 0 | L16: =Inputs!N73*Data!S11 -> 0 | M16: =Inputs!O73*Data!T11 -> 0 | ... AY16: =Inputs!BA73*Data!BF11 -> 0
B17: ='Project description'!$B$5 -> 0 | C17: =Lists!$B$34 | D17: PP | E17: Wood or wood chips | F17: =Inputs!H74*Data!M12 -> 0 | G17: =Inputs!I74*Data!N12 -> 0 | H17: =Inputs!J74*Data!O12 -> 0 | I17: =Inputs!K74*Data!P12 -> 0 | J17: =Inputs!L74*Data!Q12 -> 0 | K17: =Inputs!M74*Data!R12 -> 0 | L17: =Inputs!N74*Data!S12 -> 0 | M17: =Inputs!O74*Data!T12 -> 0 | ... AY17: =Inputs!BA74*Data!BF12 -> 0
B18: ='Project description'!$B$5 -> 0 | C18: =Lists!$B$34 | D18: BC | E18: Electricity | F18: =Inputs!H77*Data!M2 -> 0 | G18: =Inputs!I77*Data!N2 -> 0 | H18: =Inputs!J77*Data!O2 -> 0 | I18: =Inputs!K77*Data!P2 -> 0 | J18: =Inputs!L77*Data!Q2 -> 0 | K18: =Inputs!M77*Data!R2 -> 0 | L18: =Inputs!N77*Data!S2 -> 0 | M18: =Inputs!O77*Data!T2 -> 0 | ... AY18: =Inputs!BA77*Data!BF2 -> 0
B19: ='Project description'!$B$5 -> 0 | C19: =Lists!$B$34 | D19: BC | E19: Natural Gas | F19: =Inputs!H78*Data!M3 -> 0 | G19: =Inputs!I78*Data!N3 -> 0 | H19: =Inputs!J78*Data!O3 -> 0 | I19: =Inputs!K78*Data!P3 -> 0 | J19: =Inputs!L78*Data!Q3 -> 0 | K19: =Inputs!M78*Data!R3 -> 0 | L19: =Inputs!N78*Data!S3 -> 0 | M19: =Inputs!O78*Data!T3 -> 0 | ... AY19: =Inputs!BA78*Data!BF3 -> 0
B20: ='Project description'!$B$5 -> 0 | C20: =Lists!$B$34 | D20: BC | E20: Coal - sub bituminous | F20: =Inputs!H79*Data!M4 -> 0 | G20: =Inputs!I79*Data!N4 -> 0 | H20: =Inputs!J79*Data!O4 -> 0 | I20: =Inputs!K79*Data!P4 -> 0 | J20: =Inputs!L79*Data!Q4 -> 0 | K20: =Inputs!M79*Data!R4 -> 0 | L20: =Inputs!N79*Data!S4 -> 0 | M20: =Inputs!O79*Data!T4 -> 0 | ... AY20: =Inputs!BA79*Data!BF4 -> 0
B21: ='Project description'!$B$5 -> 0 | C21: =Lists!$B$34 | D21: BC | E21: Coal - bituminous | F21: =Inputs!H80*Data!M5 -> 0 | G21: =Inputs!I80*Data!N5 -> 0 | H21: =Inputs!J80*Data!O5 -> 0 | I21: =Inputs!K80*Data!P5 -> 0 | J21: =Inputs!L80*Data!Q5 -> 0 | K21: =Inputs!M80*Data!R5 -> 0 | L21: =Inputs!N80*Data!S5 -> 0 | M21: =Inputs!O80*Data!T5 -> 0 | ... AY21: =Inputs!BA80*Data!BF5 -> 0
B22: ='Project description'!$B$5 -> 0 | C22: =Lists!$B$34 | D22: BC | E22: Coal - lignite | F22: =Inputs!H81*Data!M6 -> 0 | G22: =Inputs!I81*Data!N6 -> 0 | H22: =Inputs!J81*Data!O6 -> 0 | I22: =Inputs!K81*Data!P6 -> 0 | J22: =Inputs!L81*Data!Q6 -> 0 | K22: =Inputs!M81*Data!R6 -> 0 | L22: =Inputs!N81*Data!S6 -> 0 | M22: =Inputs!O81*Data!T6 -> 0 | ... AY22: =Inputs!BA81*Data!BF6 -> 0
B23: ='Project description'!$B$5 -> 0 | C23: =Lists!$B$34 | D23: BC | E23: Diesel | F23: =Inputs!H82*Data!M7 -> 0 | G23: =Inputs!I82*Data!N7 -> 0 | H23: =Inputs!J82*Data!O7 -> 0 | I23: =Inputs!K82*Data!P7 -> 0 | J23: =Inputs!L82*Data!Q7 -> 0 | K23: =Inputs!M82*Data!R7 -> 0 | L23: =Inputs!N82*Data!S7 -> 0 | M23: =Inputs!O82*Data!T7 -> 0 | ... AY23: =Inputs!BA82*Data!BF7 -> 0
B24: ='Project description'!$B$5 -> 0 | C24: =Lists!$B$34 | D24: BC | E24: LPG | F24: =Inputs!H83*Data!M8 -> 0 | G24: =Inputs!I83*Data!N8 -> 0 | H24: =Inputs!J83*Data!O8 -> 0 | I24: =Inputs!K83*Data!P8 -> 0 | J24: =Inputs!L83*Data!Q8 -> 0 | K24: =Inputs!M83*Data!R8 -> 0 | L24: =Inputs!N83*Data!S8 -> 0 | M24: =Inputs!O83*Data!T8 -> 0 | ... AY24: =Inputs!BA83*Data!BF8 -> 0
B25: ='Project description'!$B$5 -> 0 | C25: =Lists!$B$34 | D25: BC | E25: Light fuel oil | F25: =Inputs!H84*Data!M9 -> 0 | G25: =Inputs!I84*Data!N9 -> 0 | H25: =Inputs!J84*Data!O9 -> 0 | I25: =Inputs!K84*Data!P9 -> 0 | J25: =Inputs!L84*Data!Q9 -> 0 | K25: =Inputs!M84*Data!R9 -> 0 | L25: =Inputs!N84*Data!S9 -> 0 | M25: =Inputs!O84*Data!T9 -> 0 | ... AY25: =Inputs!BA84*Data!BF9 -> 0
B26: ='Project description'!$B$5 -> 0 | C26: =Lists!$B$34 | D26: BC | E26: Heavy fuel oil | F26: =Inputs!H85*Data!M10 -> 0 | G26: =Inputs!I85*Data!N10 -> 0 | H26: =Inputs!J85*Data!O10 -> 0 | I26: =Inputs!K85*Data!P10 -> 0 | J26: =Inputs!L85*Data!Q10 -> 0 | K26: =Inputs!M85*Data!R10 -> 0 | L26: =Inputs!N85*Data!S10 -> 0 | M26: =Inputs!O85*Data!T10 -> 0 | ... AY26: =Inputs!BA85*Data!BF10 -> 0
B27: ='Project description'!$B$5 -> 0 | C27: =Lists!$B$34 | D27: BC | E27: Geothermal | F27: =Inputs!H86*Data!M11 -> 0 | G27: =Inputs!I86*Data!N11 -> 0 | H27: =Inputs!J86*Data!O11 -> 0 | I27: =Inputs!K86*Data!P11 -> 0 | J27: =Inputs!L86*Data!Q11 -> 0 | K27: =Inputs!M86*Data!R11 -> 0 | L27: =Inputs!N86*Data!S11 -> 0 | M27: =Inputs!O86*Data!T11 -> 0 | ... AY27: =Inputs!BA86*Data!BF11 -> 0
B28: ='Project description'!$B$5 -> 0 | C28: =Lists!$B$34 | D28: BC | E28: Wood or wood chips | F28: =Inputs!H87*Data!M12 -> 0 | G28: =Inputs!I87*Data!N12 -> 0 | H28: =Inputs!J87*Data!O12 -> 0 | I28: =Inputs!K87*Data!P12 -> 0 | J28: =Inputs!L87*Data!Q12 -> 0 | K28: =Inputs!M87*Data!R12 -> 0 | L28: =Inputs!N87*Data!S12 -> 0 | M28: =Inputs!O87*Data!T12 -> 0 | ... AY28: =Inputs!BA87*Data!BF12 -> 0
B29: ='Project description'!$B$5 -> 0 | C29: =Lists!$B$34 | D29: Total PP | F29: =SUM(F7:F17) -> 0 | G29: =SUM(G7:G17) -> 0 | H29: =SUM(H7:H17) -> 0 | I29: =SUM(I7:I17) -> 0 | J29: =SUM(J7:J17) -> 0 | K29: =SUM(K7:K17) -> 0 | L29: =SUM(L7:L17) -> 0 | M29: =SUM(M7:M17) -> 0 | ... AY29: =SUM(AY7:AY17) -> 0
B30: ='Project description'!$B$5 -> 0 | C30: =Lists!$B$34 | D30: Total BC | F30: =SUM(F18:F28) -> 0 | G30: =SUM(G18:G28) -> 0 | H30: =SUM(H18:H28) -> 0 | I30: =SUM(I18:I28) -> 0 | J30: =SUM(J18:J28) -> 0 | K30: =SUM(K18:K28) -> 0 | L30: =SUM(L18:L28) -> 0 | M30: =SUM(M18:M28) -> 0 | ... AY30: =SUM(AY18:AY28) -> 0
D33: Shadow costs | F33: 2025 | G33: 2026 | H33: 2027 | I33: 2028 | J33: 2029 | K33: 2030 | L33: 2031 | M33: 2032 | N33: 2033 | O33: 2034 | P33: 2035 | Q33: 2036 | R33: 2037 | S33: 2038 | T33: 2039 | U33: 2040 | V33: 2041 | W33: 2042 | X33: 2043 | Y33: 2044 | Z33: 2045 | AA33: 2046 | AB33: 2047 | AC33: 2048 | AD33: 2049 | AE33: 2050 | AF33: 2051 | AG33: 2052 | AH33: 2053 | AI33: 2054 | AJ33: 2055 | AK33: 2056 | AL33: 2057 | AM33: 2058 | AN33: 2059 | AO33: 2060 | AP33: 2061 | AQ33: 2062 | AR33: 2063 | AS33: 2064 | AT33: 2065 | AU33: 2066 | AV33: 2067 | AW33: 2068 | AX33: 2069 | AY33: 2070
D34: PP | F34: =F29*Data!L24 -> 0 | G34: =G29*Data!M24 -> 0 | H34: =H29*Data!N24 -> 0 | I34: =I29*Data!O24 -> 0 | J34: =J29*Data!P24 -> 0 | K34: =K29*Data!Q24 -> 0 | L34: =L29*Data!R24 -> 0 | M34: =M29*Data!S24 -> 0 | ... AY34: =AY29*Data!BE24 -> 0
D35: BC | F35: =F30*Data!L24 -> 0 | G35: =G30*Data!M24 -> 0 | H35: =H30*Data!N24 -> 0 | I35: =I30*Data!O24 -> 0 | J35: =J30*Data!P24 -> 0 | K35: =K30*Data!Q24 -> 0 | L35: =L30*Data!R24 -> 0 | M35: =M30*Data!S24 -> 0 | ... AY35: =AY30*Data!BE24 -> 0
D36: ETS costs
D37: PP | F37: =(F7/Data!L2*Data!L19+SUM(Calculations!F8:F17))*Data!L23 -> 0 | G37: =(G7/Data!M2*Data!M19+SUM(Calculations!G8:G17))*Data!M23 -> 0 | H37: =(H7/Data!N2*Data!N19+SUM(Calculations!H8:H17))*Data!N23 -> 0 | I37: =(I7/Data!O2*Data!O19+SUM(Calculations!I8:I17))*Data!O23 -> 0 | J37: =(J7/Data!P2*Data!P19+SUM(Calculations!J8:J17))*Data!P23 -> 0 | K37: =(K7/Data!Q2*Data!Q19+SUM(Calculations!K8:K17))*Data!Q23 -> 0 | L37: =(L7/Data!R2*Data!R19+SUM(Calculations!L8:L17))*Data!R23 -> 0 | M37: =(M7/Data!S2*Data!S19+SUM(Calculations!M8:M17))*Data!S23 -> 0 | ... AY37: =(AY7/Data!BE2*Data!BE19+SUM(Calculations!AY8:AY17))*Data!BE23 -> 0
D38: BC | F38: =(F18/Data!L2*Data!L19+SUM(F19:F28))*Data!L23 -> 0 | G38: =(G18/Data!M2*Data!M19+SUM(G19:G28))*Data!M23 -> 0 | H38: =(H18/Data!N2*Data!N19+SUM(H19:H28))*Data!N23 -> 0 | I38: =(I18/Data!O2*Data!O19+SUM(I19:I28))*Data!O23 -> 0 | J38: =(J18/Data!P2*Data!P19+SUM(J19:J28))*Data!P23 -> 0 | K38: =(K18/Data!Q2*Data!Q19+SUM(K19:K28))*Data!Q23 -> 0 | L38: =(L18/Data!R2*Data!R19+SUM(L19:L28))*Data!R23 -> 0 | M38: =(M18/Data!S2*Data!S19+SUM(M19:M28))*Data!S23 -> 0 | ... AY38: =(AY18/Data!BE2*Data!BE19+SUM(AY19:AY28))*Data!BE23 -> 0
D40: Summary - National Perspective | F40: 2025 | G40: 2026 | H40: 2027 | I40: 2028 | J40: 2029 | K40: 2030 | L40: 2031 | M40: 2032 | N40: 2033 | O40: 2034 | P40: 2035 | Q40: 2036 | R40: 2037 | S40: 2038 | T40: 2039 | U40: 2040 | V40: 2041 | W40: 2042 | X40: 2043 | Y40: 2044 | Z40: 2045 | AA40: 2046 | AB40: 2047 | AC40: 2048 | AD40: 2049 | AE40: 2050 | AF40: 2051 | AG40: 2052 | AH40: 2053 | AI40: 2054 | AJ40: 2055 | AK40: 2056 | AL40: 2057 | AM40: 2058 | AN40: 2059 | AO40: 2060 | AP40: 2061 | AQ40: 2062 | AR40: 2063 | AS40: 2064 | AT40: 2065 | AU40: 2066 | AV40: 2067 | AW40: 2068 | AX40: 2069 | AY40: 2070
D41: PP | E41: Capex | F41: ='Real values'!L17 -> 0 | G41: ='Real values'!M17 -> 0 | H41: ='Real values'!N17 -> 0 | I41: ='Real values'!O17 -> 0 | J41: ='Real values'!P17 -> 0 | K41: ='Real values'!Q17 -> 0 | L41: ='Real values'!R17 -> 0 | M41: ='Real values'!S17 -> 0 | ... AY41: ='Real values'!BE17 -> 0
E42: Non-fuel opex | F42: ='Real values'!L38 -> 0 | G42: ='Real values'!M38 -> 0 | H42: ='Real values'!N38 -> 0 | I42: ='Real values'!O38 -> 0 | J42: ='Real values'!P38 -> 0 | K42: ='Real values'!Q38 -> 0 | L42: ='Real values'!R38 -> 0 | M42: ='Real values'!S38 -> 0 | ... AY42: ='Real values'!BE38 -> 0
E43: Fuel opex | F43: ='Real values'!L116 -> 0 | G43: ='Real values'!M116 -> 0 | H43: ='Real values'!N116 -> 0 | I43: ='Real values'!O116 -> 0 | J43: ='Real values'!P116 -> 0 | K43: ='Real values'!Q116 -> 0 | L43: ='Real values'!R116 -> 0 | M43: ='Real values'!S116 -> 0 | ... AY43: ='Real values'!BE116 -> 0
E44: Emission costs | F44: =F34 -> 0 | G44: =G34 -> 0 | H44: =H34 -> 0 | I44: =I34 -> 0 | J44: =J34 -> 0 | K44: =K34 -> 0 | L44: =L34 -> 0 | M44: =M34 -> 0 | ... AY44: =AY34 -> 0
E45: Total costs | F45: =SUM(F41:F44) -> 0 | G45: =SUM(G41:G44) -> 0 | H45: =SUM(H41:H44) -> 0 | I45: =SUM(I41:I44) -> 0 | J45: =SUM(J41:J44) -> 0 | K45: =SUM(K41:K44) -> 0 | L45: =SUM(L41:L44) -> 0 | M45: =SUM(M41:M44) -> 0 | ... AY45: =SUM(AY41:AY44) -> 0
E46: Revenues | F46: {='Real values'!$L$157:$L$157} -> 0 | G46: {='Real values'!$M$157:$M$157} -> 0 | H46: {='Real values'!$N$157:$N$157} -> 0 | I46: {='Real values'!$O$157:$O$157} -> 0 | J46: {='Real values'!$P$157:$P$157} -> 0 | K46: {='Real values'!$Q$157:$Q$157} -> 0 | L46: {='Real values'!$R$157:$R$157} -> 0 | M46: {='Real values'!$S$157:$S$157} -> 0 | N46: {='Real values'!$T$157:$T$157} -> 0 | O46: {='Real values'!$U$157:$U$157} -> 0 | P46: {='Real values'!$V$157:$V$157} -> 0 | Q46: {='Real values'!$W$157:$W$157} -> 0 | R46: {='Real values'!$X$157:$X$157} -> 0 | S46: {='Real values'!$Y$157:$Y$157} -> 0 | T46: {='Real values'!$Z$157:$Z$157} -> 0 | U46: {='Real values'!$AA$157:$AA$157} -> 0 | V46: {='Real values'!$AB$157:$AB$157} -> 0 | W46: {='Real values'!$AC$157:$AC$157} -> 0 | X46: {='Real values'!$AD$157:$AD$157} -> 0 | Y46: {='Real values'!$AE$157:$AE$157} -> 0 | Z46: {='Real values'!$AF$157:$AF$157} -> 0 | AA46: {='Real values'!$AG$157:$AG$157} -> 0 | AB46: {='Real values'!$AH$157:$AH$157} -> 0 | AC46: {='Real values'!$AI$157:$AI$157} -> 0 | AD46: {='Real values'!$AJ$157:$AJ$157} -> 0 | AE46: {='Real values'!$AK$157:$AK$157} -> 0 | AF46: {='Real values'!$AL$157:$AL$157} -> 0 | AG46: {='Real values'!$AM$157:$AM$157} -> 0 | AH46: {='Real values'!$AN$157:$AN$157} -> 0 | AI46: {='Real values'!$AO$157:$AO$157} -> 0 | AJ46: {='Real values'!$AP$157:$AP$157} -> 0 | AK46: {='Real values'!$AQ$157:$AQ$157} -> 0 | AL46: {='Real values'!$AR$157:$AR$157} -> 0 | AM46: {='Real values'!$AS$157:$AS$157} -> 0 | AN46: {='Real values'!$AT$157:$AT$157} -> 0 | AO46: {='Real values'!$AU$157:$AU$157} -> 0 | AP46: {='Real values'!$AV$157:$AV$157} -> 0 | AQ46: {='Real values'!$AW$157:$AW$157} -> 0 | AR46: {='Real values'!$AX$157:$AX$157} -> 0 | AS46: {='Real values'!$AY$157:$AY$157} -> 0 | AT46: {='Real values'!$AZ$157:$AZ$157} -> 0 | AU46: {='Real values'!$BA$157:$BA$157} -> 0 | AV46: {='Real values'!$BB$157:$BB$157} -> 0 | AW46: {='Real values'!$BC$157:$BC$157} -> 0 | AX46: {='Real values'!$BD$157:$BD$157} -> 0 | AY46: {='Real values'!$BE$157:$BE$157} -> 0
E47: Net | F47: =F46-F45 -> 0 | G47: =G46-G45 -> 0 | H47: =H46-H45 -> 0 | I47: =I46-I45 -> 0 | J47: =J46-J45 -> 0 | K47: =K46-K45 -> 0 | L47: =L46-L45 -> 0 | M47: =M46-M45 -> 0 | ... AY47: =AY46-AY45 -> 0
D48: BC | E48: Capex | F48: ='Real values'!L27 -> 0 | G48: ='Real values'!M27 -> 0 | H48: ='Real values'!N27 -> 0 | I48: ='Real values'!O27 -> 0 | J48: ='Real values'!P27 -> 0 | K48: ='Real values'!Q27 -> 0 | L48: ='Real values'!R27 -> 0 | M48: ='Real values'!S27 -> 0 | ... AY48: ='Real values'!BE27 -> 0
E49: =E42 -> Non-fuel opex | F49: ='Real values'!L47 -> 0 | G49: ='Real values'!M47 -> 0 | H49: ='Real values'!N47 -> 0 | I49: ='Real values'!O47 -> 0 | J49: ='Real values'!P47 -> 0 | K49: ='Real values'!Q47 -> 0 | L49: ='Real values'!R47 -> 0 | M49: ='Real values'!S47 -> 0 | ... AY49: ='Real values'!BE47 -> 0
E50: =E43 -> Fuel opex | F50: ='Real values'!L130 -> 0 | G50: ='Real values'!M130 -> 0 | H50: ='Real values'!N130 -> 0 | I50: ='Real values'!O130 -> 0 | J50: ='Real values'!P130 -> 0 | K50: ='Real values'!Q130 -> 0 | L50: ='Real values'!R130 -> 0 | M50: ='Real values'!S130 -> 0 | ... AY50: ='Real values'!BE130 -> 0
E51: Emission costs | F51: =F35 -> 0 | G51: =G35 -> 0 | H51: =H35 -> 0 | I51: =I35 -> 0 | J51: =J35 -> 0 | K51: =K35 -> 0 | L51: =L35 -> 0 | M51: =M35 -> 0 | ... AY51: =AY35 -> 0
E52: Total costs | F52: =SUM(F48:F51) -> 0 | G52: =SUM(G48:G51) -> 0 | H52: =SUM(H48:H51) -> 0 | I52: =SUM(I48:I51) -> 0 | J52: =SUM(J48:J51) -> 0 | K52: =SUM(K48:K51) -> 0 | L52: =SUM(L48:L51) -> 0 | M52: =SUM(M48:M51) -> 0 | ... AY52: =SUM(AY48:AY51) -> 0
E53: Revenues | F53: {='Real values'!$L$160:$L$160} -> 0 | G53: {='Real values'!$M$160:$M$160} -> 0 | H53: {='Real values'!$N$160:$N$160} -> 0 | I53: {='Real values'!$O$160:$O$160} -> 0 | J53: {='Real values'!$P$160:$P$160} -> 0 | K53: {='Real values'!$Q$160:$Q$160} -> 0 | L53: {='Real values'!$R$160:$R$160} -> 0 | M53: {='Real values'!$S$160:$S$160} -> 0 | N53: {='Real values'!$T$160:$T$160} -> 0 | O53: {='Real values'!$U$160:$U$160} -> 0 | P53: {='Real values'!$V$160:$V$160} -> 0 | Q53: {='Real values'!$W$160:$W$160} -> 0 | R53: {='Real values'!$X$160:$X$160} -> 0 | S53: {='Real values'!$Y$160:$Y$160} -> 0 | T53: {='Real values'!$Z$160:$Z$160} -> 0 | U53: {='Real values'!$AA$160:$AA$160} -> 0 | V53: {='Real values'!$AB$160:$AB$160} -> 0 | W53: {='Real values'!$AC$160:$AC$160} -> 0 | X53: {='Real values'!$AD$160:$AD$160} -> 0 | Y53: {='Real values'!$AE$160:$AE$160} -> 0 | Z53: {='Real values'!$AF$160:$AF$160} -> 0 | AA53: {='Real values'!$AG$160:$AG$160} -> 0 | AB53: {='Real values'!$AH$160:$AH$160} -> 0 | AC53: {='Real values'!$AI$160:$AI$160} -> 0 | AD53: {='Real values'!$AJ$160:$AJ$160} -> 0 | AE53: {='Real values'!$AK$160:$AK$160} -> 0 | AF53: {='Real values'!$AL$160:$AL$160} -> 0 | AG53: {='Real values'!$AM$160:$AM$160} -> 0 | AH53: {='Real values'!$AN$160:$AN$160} -> 0 | AI53: {='Real values'!$AO$160:$AO$160} -> 0 | AJ53: {='Real values'!$AP$160:$AP$160} -> 0 | AK53: {='Real values'!$AQ$160:$AQ$160} -> 0 | AL53: {='Real values'!$AR$160:$AR$160} -> 0 | AM53: {='Real values'!$AS$160:$AS$160} -> 0 | AN53: {='Real values'!$AT$160:$AT$160} -> 0 | AO53: {='Real values'!$AU$160:$AU$160} -> 0 | AP53: {='Real values'!$AV$160:$AV$160} -> 0 | AQ53: {='Real values'!$AW$160:$AW$160} -> 0 | AR53: {='Real values'!$AX$160:$AX$160} -> 0 | AS53: {='Real values'!$AY$160:$AY$160} -> 0 | AT53: {='Real values'!$AZ$160:$AZ$160} -> 0 | AU53: {='Real values'!$BA$160:$BA$160} -> 0 | AV53: {='Real values'!$BB$160:$BB$160} -> 0 | AW53: {='Real values'!$BC$160:$BC$160} -> 0 | AX53: {='Real values'!$BD$160:$BD$160} -> 0 | AY53: {='Real values'!$BE$160:$BE$160} -> 0
E54: Net | F54: =F53-F52 -> 0 | G54: =G53-G52 -> 0 | H54: =H53-H52 -> 0 | I54: =I53-I52 -> 0 | J54: =J53-J52 -> 0 | K54: =K53-K52 -> 0 | L54: =L53-L52 -> 0 | M54: =M53-M52 -> 0 | ... AY54: =AY53-AY52 -> 0
D57: Discount factor | E57: DR | F57: 2025 | G57: 2026 | H57: 2027 | I57: 2028 | J57: 2029 | K57: 2030 | L57: 2031 | M57: 2032 | N57: 2033 | O57: 2034 | P57: 2035 | Q57: 2036 | R57: 2037 | S57: 2038 | T57: 2039 | U57: 2040 | V57: 2041 | W57: 2042 | X57: 2043 | Y57: 2044 | Z57: 2045 | AA57: 2046 | AB57: 2047 | AC57: 2048 | AD57: 2049 | AE57: 2050 | AF57: 2051 | AG57: 2052 | AH57: 2053 | AI57: 2054 | AJ57: 2055 | AK57: 2056 | AL57: 2057 | AM57: 2058 | AN57: 2059 | AO57: 2060 | AP57: 2061 | AQ57: 2062 | AR57: 2063 | AS57: 2064 | AT57: 2065 | AU57: 2066 | AV57: 2067 | AW57: 2068 | AX57: 2069 | AY57: 2070
E58: Year: | F58: =F$57-Analysis_year -> 2025 | G58: =G$57-Analysis_year -> 2026 | H58: =H$57-Analysis_year -> 2027 | I58: =I$57-Analysis_year -> 2028 | J58: =J$57-Analysis_year -> 2029 | K58: =K$57-Analysis_year -> 2030 | L58: =L$57-Analysis_year -> 2031 | M58: =M$57-Analysis_year -> 2032 | ... AY58: =AY$57-Analysis_year -> 2070
E59: 0.02 | F59: =IF(F58>30,1/(1.015^F58),1/((1+$E59)^F58)) -> 8.0586899e-14 | G59: =IF(G58>30,1/(1.015^G58),1/((1+$E59)^G58)) -> 7.939596e-14 | H59: =IF(H58>30,1/(1.015^H58),1/((1+$E59)^H58)) -> 7.822262e-14 | I59: =IF(I58>30,1/(1.015^I58),1/((1+$E59)^I58)) -> 7.7066621e-14 | J59: =IF(J58>30,1/(1.015^J58),1/((1+$E59)^J58)) -> 7.5927706e-14 | K59: =IF(K58>30,1/(1.015^K58),1/((1+$E59)^K58)) -> 7.4805621e-14 | L59: =IF(L58>30,1/(1.015^L58),1/((1+$E59)^L58)) -> 7.3700119e-14 | M59: =IF(M58>30,1/(1.015^M58),1/((1+$E59)^M58)) -> 7.2610955e-14 | ... AY59: =IF(AY58>30,1/(1.015^AY58),1/((1+$E59)^AY58)) -> 4.123752e-14
E60: 0.08 | F60: =1/((1+$E60)^F58) -> 2.0744126e-68 | G60: =1/((1+$E60)^G58) -> 1.9207524e-68 | H60: =1/((1+$E60)^H58) -> 1.7784744e-68 | I60: =1/((1+$E60)^I58) -> 1.6467356e-68 | J60: =1/((1+$E60)^J58) -> 1.5247552e-68 | K60: =1/((1+$E60)^K58) -> 1.4118104e-68 | L60: =1/((1+$E60)^L58) -> 1.3072318e-68 | M60: =1/((1+$E60)^M58) -> 1.2103998e-68 | ... AY60: =1/((1+$E60)^AY58) -> 6.4986948e-70
D61: Final year for assessment (PP) | E61: =FinalYear_PP -> 1900 | F61: =IF(F$57>$E61,0,1) -> 0 | G61: =IF(G$57>$E61,0,1) -> 0 | H61: =IF(H$57>$E61,0,1) -> 0 | I61: =IF(I$57>$E61,0,1) -> 0 | J61: =IF(J$57>$E61,0,1) -> 0 | K61: =IF(K$57>$E61,0,1) -> 0 | L61: =IF(L$57>$E61,0,1) -> 0 | M61: =IF(M$57>$E61,0,1) -> 0 | ... AY61: =IF(AY$57>$E61,0,1) -> 0
D62: Final year for assessment (BC) | E62: =FinalYear_BC -> 1900 | F62: =IF(F$57>$E62,0,1) -> 0 | G62: =IF(G$57>$E62,0,1) -> 0 | H62: =IF(H$57>$E62,0,1) -> 0 | I62: =IF(I$57>$E62,0,1) -> 0 | J62: =IF(J$57>$E62,0,1) -> 0 | K62: =IF(K$57>$E62,0,1) -> 0 | L62: =IF(L$57>$E62,0,1) -> 0 | M62: =IF(M$57>$E62,0,1) -> 0 | ... AY62: =IF(AY$57>$E62,0,1) -> 0
D64: NPV | F64: 0.02 | G64: 0.08
E65: PP | F65: =SUMPRODUCT($F$47:$AY$47,$F$59:$AY$59,$F61:$AY61) -> 0 | G65: =SUMPRODUCT($F$47:$AY$47,$F$60:$AY$60,$F62:$AY62) -> 0
E66: BC | F66: =SUMPRODUCT($F$54:$AY$54,$F$59:$AY$59,$F61:$AY61) -> 0 | G66: =SUMPRODUCT($F$54:$AY$54,$F$60:$AY$60,$F62:$AY62) -> 0
E67: Preferred: | F67: =IF(F65>F66,$E65,$E66) -> BC | G67: =IF(G65>G66,$E65,$E66) -> BC
E69: Basis | F69: 2025 | G69: 2026 | H69: 2027 | I69: 2028 | J69: 2029 | K69: 2030 | L69: 2031 | M69: 2032 | N69: 2033 | O69: 2034 | P69: 2035 | Q69: 2036 | R69: 2037 | S69: 2038 | T69: 2039 | U69: 2040 | V69: 2041 | W69: 2042 | X69: 2043 | Y69: 2044 | Z69: 2045 | AA69: 2046 | AB69: 2047 | AC69: 2048 | AD69: 2049 | AE69: 2050 | AF69: 2051 | AG69: 2052 | AH69: 2053 | AI69: 2054 | AJ69: 2055 | AK69: 2056 | AL69: 2057 | AM69: 2058 | AN69: 2059 | AO69: 2060 | AP69: 2061 | AQ69: 2062 | AR69: 2063 | AS69: 2064 | AT69: 2065 | AU69: 2066 | AV69: 2067 | AW69: 2068 | AX69: 2069 | AY69: 2070
D70: Hurdle factor | E70: =HurdleRateBasis -> <Select> | F70: =1/((1+'Project description'!$B$28)^F58) -> 1 | G70: =1/((1+'Project description'!$B$28)^G58) -> 1 | H70: =1/((1+'Project description'!$B$28)^H58) -> 1 | I70: =1/((1+'Project description'!$B$28)^I58) -> 1 | J70: =1/((1+'Project description'!$B$28)^J58) -> 1 | K70: =1/((1+'Project description'!$B$28)^K58) -> 1 | L70: =1/((1+'Project description'!$B$28)^L58) -> 1 | M70: =1/((1+'Project description'!$B$28)^M58) -> 1 | ... AY70: =1/((1+'Project description'!$B$28)^AY58) -> 1
D71: PP | E71: Net costs/revenues | F71: {=IFERROR(OFFSET(J1,SUMPRODUCT(($L$76:$L$79=HurdleRateBasis)*($M$75:$N$75=ReturnType)*($M$76:$N$79))-1,0)*F61,0)} -> 0 | G71: {=IFERROR(OFFSET(K1,SUMPRODUCT(($L$76:$L$79=HurdleRateBasis)*($M$75:$N$75=ReturnType)*($M$76:$N$79))-1,0)*G61,0)} -> 0 | H71: {=IFERROR(OFFSET(L1,SUMPRODUCT(($L$76:$L$79=HurdleRateBasis)*($M$75:$N$75=ReturnType)*($M$76:$N$79))-1,0)*H61,0)} -> 0 | I71: {=IFERROR(OFFSET(M1,SUMPRODUCT(($L$76:$L$79=HurdleRateBasis)*($M$75:$N$75=ReturnType)*($M$76:$N$79))-1,0)*I61,0)} -> 0 | J71: {=IFERROR(OFFSET(N1,SUMPRODUCT(($L$76:$L$79=HurdleRateBasis)*($M$75:$N$75=ReturnType)*($M$76:$N$79))-1,0)*J61,0)} -> 0 | K71: {=IFERROR(OFFSET(O1,SUMPRODUCT(($L$76:$L$79=HurdleRateBasis)*($M$75:$N$75=ReturnType)*($M$76:$N$79))-1,0)*K61,0)} -> 0 | L71: {=IFERROR(OFFSET(P1,SUMPRODUCT(($L$76:$L$79=HurdleRateBasis)*($M$75:$N$75=ReturnType)*($M$76:$N$79))-1,0)*L61,0)} -> 0 | M71: {=IFERROR(OFFSET(Q1,SUMPRODUCT(($L$76:$L$79=HurdleRateBasis)*($M$75:$N$75=ReturnType)*($M$76:$N$79))-1,0)*M61,0)} -> 0 | ... AY71: {=IFERROR(OFFSET(BC1,SUMPRODUCT(($L$76:$L$79=HurdleRateBasis)*($M$75:$N$75=ReturnType)*($M$76:$N$79))-1,0)*AY61,0)} -> 0
D72: BC | E72: Net costs/revenues | F72: {=IFERROR(OFFSET(J1,SUMPRODUCT(($L$76:$L$79=HurdleRateBasis)*($O$75:$P$75=ReturnType)*($O$76:$P$79))-1,0)*F62,0)} -> 0 | G72: {=IFERROR(OFFSET(K1,SUMPRODUCT(($L$76:$L$79=HurdleRateBasis)*($O$75:$P$75=ReturnType)*($O$76:$P$79))-1,0)*G62,0)} -> 0 | H72: {=IFERROR(OFFSET(L1,SUMPRODUCT(($L$76:$L$79=HurdleRateBasis)*($O$75:$P$75=ReturnType)*($O$76:$P$79))-1,0)*H62,0)} -> 0 | I72: {=IFERROR(OFFSET(M1,SUMPRODUCT(($L$76:$L$79=HurdleRateBasis)*($O$75:$P$75=ReturnType)*($O$76:$P$79))-1,0)*I62,0)} -> 0 | J72: {=IFERROR(OFFSET(N1,SUMPRODUCT(($L$76:$L$79=HurdleRateBasis)*($O$75:$P$75=ReturnType)*($O$76:$P$79))-1,0)*J62,0)} -> 0 | K72: {=IFERROR(OFFSET(O1,SUMPRODUCT(($L$76:$L$79=HurdleRateBasis)*($O$75:$P$75=ReturnType)*($O$76:$P$79))-1,0)*K62,0)} -> 0 | L72: {=IFERROR(OFFSET(P1,SUMPRODUCT(($L$76:$L$79=HurdleRateBasis)*($O$75:$P$75=ReturnType)*($O$76:$P$79))-1,0)*L62,0)} -> 0 | M72: {=IFERROR(OFFSET(Q1,SUMPRODUCT(($L$76:$L$79=HurdleRateBasis)*($O$75:$P$75=ReturnType)*($O$76:$P$79))-1,0)*M62,0)} -> 0 | ... AY72: {=IFERROR(OFFSET(BC1,SUMPRODUCT(($L$76:$L$79=HurdleRateBasis)*($O$75:$P$75=ReturnType)*($O$76:$P$79))-1,0)*AY62,0)} -> 0
D74: Private Returns | E74: =HurdleRateBasis -> <Select> | L74: Row No | M74: PP | O74: BC
E75: =ReturnType -> <Select> | M75: =Lists!A17 -> Return on Equity | N75: =Lists!A18 -> Return on Whole Investment | O75: =M75 -> Return on Equity | P75: =N75 -> Return on Whole Investment
D76: PP | E76: =SUMPRODUCT($F$71:$AX$71,$F$70:$AX$70) -> 0 | F76: =IFERROR(IRR(F71:AX71,0.05),"No feasible solution") -> No feasible solution | L76: =Lists!A11 -> Pre-tax Real | M76: =ROW(D127) -> 127 | N76: =M76+1 -> 128 | O76: =M76+16 -> 143 | P76: =N76+16 -> 144
D77: BC | E77: =SUMPRODUCT($F$72:$AX$72,$F$70:$AX$70) -> 0 | F77: =IFERROR(IRR(F72:AX72,0.05),"No feasible solution") -> No feasible solution | L77: =Lists!A12 -> Post-tax Real | M77: =ROW(J130) -> 130 | N77: =M77+1 -> 131 | O77: =M77+16 -> 146 | P77: =N77+16 -> 147
D78: Preferred: | E78: =IF(E76>E77,$D76,$D77) -> BC | L78: =Lists!A13 -> Pre-tax Nominal | M78: =ROW(J94) -> 94 | N78: =M78+1 -> 95 | O78: =M78+16 -> 110 | P78: =N78+16 -> 111
L79: =Lists!A14 -> Post-tax Nominal | M79: =ROW(J97) -> 97 | N79: =M79+1 -> 98 | O79: =M79+16 -> 113 | P79: =N79+16 -> 114
D82: Summary - Private perspective
D83: a) Nominal
D84: Proposed Project (PP) | J84: =Start_Yr -> 0 | K84: =J84+1 -> 1 | L84: =K84+1 -> 2 | M84: =L84+1 -> 3 | N84: =M84+1 -> 4 | O84: =N84+1 -> 5 | P84: =O84+1 -> 6 | Q84: =P84+1 -> 7 | R84: =Q84+1 -> 8 | ... BC84: =BB84+1 -> 45
D85: Capex - equity funded | I85: Nominal | J85: =J87-J86 -> 0 | K85: =K87-K86 -> 0 | L85: =L87-L86 -> 0 | M85: =M87-M86 -> 0 | N85: =N87-N86 -> 0 | O85: =O87-O86 -> 0 | P85: =P87-P86 -> 0 | Q85: =Q87-Q86 -> 0 | ... BC85: =BC87-BC86 -> 0
D86: Capex - debt funded | I86: Nominal | J86: ='Real values'!L134*'Real values'!M4 -> 0 | K86: ='Real values'!M134*'Real values'!N4 -> 0 | L86: ='Real values'!N134*'Real values'!O4 -> 0 | M86: ='Real values'!O134*'Real values'!P4 -> 0 | N86: ='Real values'!P134*'Real values'!Q4 -> 0 | O86: ='Real values'!Q134*'Real values'!R4 -> 0 | P86: ='Real values'!R134*'Real values'!S4 -> 0 | Q86: ='Real values'!S134*'Real values'!T4 -> 0 | ... AW86: ='Real values'!AY134*'Real values'!AZ4 -> 0 | AX86: ='Real values'!BA134*'Real values'!BA4 -> 0 | AY86: ='Real values'!BB134*'Real values'!BB4 -> 0 | AZ86: ='Real values'!BC134*'Real values'!BC4 -> 0 | BA86: ='Real values'!BD134*'Real values'!BD4 -> 0 | BB86: ='Real values'!BE134*'Real values'!BE4 -> 0 | BC86: ='Real values'!BF134*'Real values'!BF4 -> 0
D87: Capex total | I87: Nominal | J87: =Calculations!F41*'Real values'!M4 -> 0 | K87: =Calculations!G41*'Real values'!N4 -> 0 | L87: =Calculations!H41*'Real values'!O4 -> 0 | M87: =Calculations!I41*'Real values'!P4 -> 0 | N87: =Calculations!J41*'Real values'!Q4 -> 0 | O87: =Calculations!K41*'Real values'!R4 -> 0 | P87: =Calculations!L41*'Real values'!S4 -> 0 | Q87: =Calculations!M41*'Real values'!T4 -> 0 | ... BC87: =Calculations!AY41*'Real values'!BF4 -> 0
D88: Non-fuel opex | I88: Nominal | J88: =J121*'Real values'!M$4 -> 0 | K88: =K121*'Real values'!N$4 -> 0 | L88: =L121*'Real values'!O$4 -> 0 | M88: =M121*'Real values'!P$4 -> 0 | N88: =N121*'Real values'!Q$4 -> 0 | O88: =O121*'Real values'!R$4 -> 0 | P88: =P121*'Real values'!S$4 -> 0 | Q88: =Q121*'Real values'!T$4 -> 0 | ... BC88: =BC121*'Real values'!BF$4 -> 0
D89: Fuel opex | I89: Nominal | J89: =J122*'Real values'!M$4 -> 0 | K89: =K122*'Real values'!N$4 -> 0 | L89: =L122*'Real values'!O$4 -> 0 | M89: =M122*'Real values'!P$4 -> 0 | N89: =N122*'Real values'!Q$4 -> 0 | O89: =O122*'Real values'!R$4 -> 0 | P89: =P122*'Real values'!S$4 -> 0 | Q89: =Q122*'Real values'!T$4 -> 0 | ... BC89: =BC122*'Real values'!BF$4 -> 0
D90: Cost of debt | I90: Nominal | J90: =J123*'Real values'!M$4 -> 0 | K90: =K123*'Real values'!N$4 -> 0 | L90: =L123*'Real values'!O$4 -> 0 | M90: =M123*'Real values'!P$4 -> 0 | N90: =N123*'Real values'!Q$4 -> 0 | O90: =O123*'Real values'!R$4 -> 0 | P90: =P123*'Real values'!S$4 -> 0 | Q90: =Q123*'Real values'!T$4 -> 0 | ... BC90: =BC123*'Real values'!BF$4 -> 0
D91: Total annual costs (ROE basis) | I91: Nominal | J91: =J85+SUM(J88:J90) -> 0 | K91: =K85+SUM(K88:K90) -> 0 | L91: =L85+SUM(L88:L90) -> 0 | M91: =M85+SUM(M88:M90) -> 0 | N91: =N85+SUM(N88:N90) -> 0 | O91: =O85+SUM(O88:O90) -> 0 | P91: =P85+SUM(P88:P90) -> 0 | Q91: =Q85+SUM(Q88:Q90) -> 0 | ... BC91: =BC85+SUM(BC88:BC90) -> 0
D92: Total annual costs (ROI basis) | I92: Nominal | J92: =SUM(J87:J89) -> 0 | K92: =SUM(K87:K89) -> 0 | L92: =SUM(L87:L89) -> 0 | M92: =SUM(M87:M89) -> 0 | N92: =SUM(N87:N89) -> 0 | O92: =SUM(O87:O89) -> 0 | P92: =SUM(P87:P89) -> 0 | Q92: =SUM(Q87:Q89) -> 0 | ... BC92: =SUM(BC87:BC89) -> 0
D93: Revenue | I93: Nominal | J93: =J126*'Real values'!M$4 -> 0 | K93: =K126*'Real values'!N$4 -> 0 | L93: =L126*'Real values'!O$4 -> 0 | M93: =M126*'Real values'!P$4 -> 0 | N93: =N126*'Real values'!Q$4 -> 0 | O93: =O126*'Real values'!R$4 -> 0 | P93: =P126*'Real values'!S$4 -> 0 | Q93: =Q126*'Real values'!T$4 -> 0 | ... BC93: =BC126*'Real values'!BF$4 -> 0
D94: Net costs/revenue before tax (ROE) | I94: Nominal | J94: =J93-J91 -> 0 | K94: =K93-K91 -> 0 | L94: =L93-L91 -> 0 | M94: =M93-M91 -> 0 | N94: =N93-N91 -> 0 | O94: =O93-O91 -> 0 | P94: =P93-P91 -> 0 | Q94: =Q93-Q91 -> 0 | ... BC94: =BC93-BC91 -> 0
D95: Net costs/revenue before tax (ROI) | I95: Nominal | J95: =J93-J92 -> 0 | K95: =K93-K92 -> 0 | L95: =L93-L92 -> 0 | M95: =M93-M92 -> 0 | N95: =N93-N92 -> 0 | O95: =O93-O92 -> 0 | P95: =P93-P92 -> 0 | Q95: =Q93-Q92 -> 0 | ... BC95: =BC93-BC92 -> 0
D96: Tax | I96: Nominal | J96: =Inputs!H181 -> 0 | K96: =Inputs!I181 -> 0 | L96: =Inputs!J181 -> 0 | M96: =Inputs!K181 -> 0 | N96: =Inputs!L181 -> 0 | O96: =Inputs!M181 -> 0 | P96: =Inputs!N181 -> 0 | Q96: =Inputs!O181 -> 0 | ... BC96: =Inputs!BA181 -> 0
D97: Net costs/revenue after tax (ROE) | I97: Nominal | J97: =J94-J$96 -> 0 | K97: =K94-K$96 -> 0 | L97: =L94-L$96 -> 0 | M97: =M94-M$96 -> 0 | N97: =N94-N$96 -> 0 | O97: =O94-O$96 -> 0 | P97: =P94-P$96 -> 0 | Q97: =Q94-Q$96 -> 0 | ... BC97: =BC94-BC$96 -> 0
D98: Net costs/revenue after tax (ROI) | I98: Nominal | J98: =J95-J$96 -> 0 | K98: =K95-K$96 -> 0 | L98: =L95-L$96 -> 0 | M98: =M95-M$96 -> 0 | N98: =N95-N$96 -> 0 | O98: =O95-O$96 -> 0 | P98: =P95-P$96 -> 0 | Q98: =Q95-Q$96 -> 0 | ... BC98: =BC95-BC$96 -> 0
D100: Base Case (BC) | J100: =Start_Yr -> 0 | K100: =J100+1 -> 1 | L100: =K100+1 -> 2 | M100: =L100+1 -> 3 | N100: =M100+1 -> 4 | O100: =N100+1 -> 5 | P100: =O100+1 -> 6 | Q100: =P100+1 -> 7 | R100: =Q100+1 -> 8 | ... BC100: =BB100+1 -> 45
D101: Capex - equity funded | I101: Nominal | J101: =J103-J102 -> 0 | K101: =K103-K102 -> 0 | L101: =L103-L102 -> 0 | M101: =M103-M102 -> 0 | N101: =N103-N102 -> 0 | O101: =O103-O102 -> 0 | P101: =P103-P102 -> 0 | Q101: =Q103-Q102 -> 0 | ... BC101: =BC103-BC102 -> 0
D102: Capex - debt funded | I102: Nominal | J102: ='Real values'!L144*'Real values'!M$4 -> 0 | K102: ='Real values'!M144*'Real values'!N$4 -> 0 | L102: ='Real values'!N144*'Real values'!O$4 -> 0 | M102: ='Real values'!O144*'Real values'!P$4 -> 0 | N102: ='Real values'!P144*'Real values'!Q$4 -> 0 | O102: ='Real values'!Q144*'Real values'!R$4 -> 0 | P102: ='Real values'!R144*'Real values'!S$4 -> 0 | Q102: ='Real values'!S144*'Real values'!T$4 -> 0 | ... AW102: ='Real values'!AY144*'Real values'!AZ$4 -> 0 | AX102: ='Real values'!BA144*'Real values'!BA$4 -> 0 | AY102: ='Real values'!BB144*'Real values'!BB$4 -> 0 | AZ102: ='Real values'!BC144*'Real values'!BC$4 -> 0 | BA102: ='Real values'!BD144*'Real values'!BD$4 -> 0 | BB102: ='Real values'!BE144*'Real values'!BE$4 -> 0 | BC102: ='Real values'!BF144*'Real values'!BF$4 -> 0
D103: Capex total | I103: Nominal | J103: =F48*'Real values'!M$4 -> 0 | K103: =G48*'Real values'!N$4 -> 0 | L103: =H48*'Real values'!O$4 -> 0 | M103: =I48*'Real values'!P$4 -> 0 | N103: =J48*'Real values'!Q$4 -> 0 | O103: =K48*'Real values'!R$4 -> 0 | P103: =L48*'Real values'!S$4 -> 0 | Q103: =M48*'Real values'!T$4 -> 0 | ... BC103: =AY48*'Real values'!BF$4 -> 0
D104: Non-fuel opex | I104: Nominal | J104: =J137*'Real values'!M$4 -> 0 | K104: =K137*'Real values'!N$4 -> 0 | L104: =L137*'Real values'!O$4 -> 0 | M104: =M137*'Real values'!P$4 -> 0 | N104: =N137*'Real values'!Q$4 -> 0 | O104: =O137*'Real values'!R$4 -> 0 | P104: =P137*'Real values'!S$4 -> 0 | Q104: =Q137*'Real values'!T$4 -> 0 | ... BC104: =BC137*'Real values'!BF$4 -> 0
D105: Fuel opex | I105: Nominal | J105: =J138*'Real values'!M$4 -> 0 | K105: =K138*'Real values'!N$4 -> 0 | L105: =L138*'Real values'!O$4 -> 0 | M105: =M138*'Real values'!P$4 -> 0 | N105: =N138*'Real values'!Q$4 -> 0 | O105: =O138*'Real values'!R$4 -> 0 | P105: =P138*'Real values'!S$4 -> 0 | Q105: =Q138*'Real values'!T$4 -> 0 | ... BC105: =BC138*'Real values'!BF$4 -> 0
D106: Cost of debt | I106: Nominal | J106: =J139*'Real values'!M$4 -> 0 | K106: =K139*'Real values'!N$4 -> 0 | L106: =L139*'Real values'!O$4 -> 0 | M106: =M139*'Real values'!P$4 -> 0 | N106: =N139*'Real values'!Q$4 -> 0 | O106: =O139*'Real values'!R$4 -> 0 | P106: =P139*'Real values'!S$4 -> 0 | Q106: =Q139*'Real values'!T$4 -> 0 | ... BC106: =BC139*'Real values'!BF$4 -> 0
D107: Total annual costs (ROE basis) | I107: Nominal | J107: =J101+SUM(J104:J106) -> 0 | K107: =K101+SUM(K104:K106) -> 0 | L107: =L101+SUM(L104:L106) -> 0 | M107: =M101+SUM(M104:M106) -> 0 | N107: =N101+SUM(N104:N106) -> 0 | O107: =O101+SUM(O104:O106) -> 0 | P107: =P101+SUM(P104:P106) -> 0 | Q107: =Q101+SUM(Q104:Q106) -> 0 | ... BC107: =BC101+SUM(BC104:BC106) -> 0
D108: Total annual costs (ROI basis) | I108: Nominal | J108: =SUM(J103:J105) -> 0 | K108: =SUM(K103:K105) -> 0 | L108: =SUM(L103:L105) -> 0 | M108: =SUM(M103:M105) -> 0 | N108: =SUM(N103:N105) -> 0 | O108: =SUM(O103:O105) -> 0 | P108: =SUM(P103:P105) -> 0 | Q108: =SUM(Q103:Q105) -> 0 | ... BC108: =SUM(BC103:BC105) -> 0
D109: Revenue | I109: Nominal | J109: =J142*'Real values'!M$4 -> 0 | K109: =K142*'Real values'!N$4 -> 0 | L109: =L142*'Real values'!O$4 -> 0 | M109: =M142*'Real values'!P$4 -> 0 | N109: =N142*'Real values'!Q$4 -> 0 | O109: =O142*'Real values'!R$4 -> 0 | P109: =P142*'Real values'!S$4 -> 0 | Q109: =Q142*'Real values'!T$4 -> 0 | ... BC109: =BC142*'Real values'!BF$4 -> 0
D110: Net costs/revenue before tax (ROE) | I110: Nominal | J110: =J109-J107 -> 0 | K110: =K109-K107 -> 0 | L110: =L109-L107 -> 0 | M110: =M109-M107 -> 0 | N110: =N109-N107 -> 0 | O110: =O109-O107 -> 0 | P110: =P109-P107 -> 0 | Q110: =Q109-Q107 -> 0 | ... BC110: =BC109-BC107 -> 0
D111: Net costs/revenue before tax (ROI) | I111: Nominal | J111: =J109-J108 -> 0 | K111: =K109-K108 -> 0 | L111: =L109-L108 -> 0 | M111: =M109-M108 -> 0 | N111: =N109-N108 -> 0 | O111: =O109-O108 -> 0 | P111: =P109-P108 -> 0 | Q111: =Q109-Q108 -> 0 | ... BC111: =BC109-BC108 -> 0
D112: Tax | I112: Nominal | J112: =Inputs!H184 -> 0 | K112: =Inputs!I184 -> 0 | L112: =Inputs!J184 -> 0 | M112: =Inputs!K184 -> 0 | N112: =Inputs!L184 -> 0 | O112: =Inputs!M184 -> 0 | P112: =Inputs!N184 -> 0 | Q112: =Inputs!O184 -> 0 | ... BC112: =Inputs!BA184 -> 0
...

Sheet Data
A1: Sectors | B1: Regions | D1: Fuel | E1: Consump-tion unit | F1: GJ conversion | G1: Unit for Emission Factor | H1: Emission factor (kg CO2-e/unit) | I1: Emission factor (t CO2-e/ consumption unit) | K1: Emission factors by year | L1: 2025 | M1: 2026 | N1: 2027 | O1: 2028 | P1: 2029 | Q1: 2030 | R1: 2031 | S1: 2032 | T1: 2033 | U1: 2034 | V1: 2035 | W1: 2036 | X1: 2037 | Y1: 2038 | Z1: 2039 | AA1: 2040 | AB1: 2041 | AC1: 2042 | AD1: 2043 | AE1: 2044 | AF1: 2045 | AG1: 2046 | AH1: 2047 | AI1: 2048 | AJ1: 2049 | AK1: 2050 | AL1: 2051 | AM1: 2052 | AN1: 2053 | AO1: 2054 | AP1: 2055 | AQ1: 2056 | AR1: 2057 | AS1: 2058 | AT1: 2059 | AU1: 2060 | AV1: 2061 | AW1: 2062 | AX1: 2063 | AY1: 2064 | AZ1: 2065 | BA1: 2066 | BB1: 2067 | BC1: 2068 | BD1: 2069 | BE1: 2070
A2: <Select> | B2: <Select> | D2: <Select> | K2: =D3 -> Electricity | L2: =L18 -> 0.066978754 | M2: =M18 -> 0.067432426 | N2: =N18 -> 0.067544021 | O2: =O18 -> 0.065221804 | P2: =P18 -> 0.061132009 | Q2: =Q18 -> 0.054806089 | R2: =R18 -> 0.053734391 | S2: =S18 -> 0.054925985 | ... AK2: =AK18 -> 0.04070517 | AL2: =AK2 -> 0.04070517 | AM2: =AL2 -> 0.04070517 | AN2: =AM2 -> 0.04070517 | AO2: =AN2 -> 0.04070517 | AP2: =AO2 -> 0.04070517 | AQ2: =AP2 -> 0.04070517 | AR2: =AQ2 -> 0.04070517 | AS2: =AR2 -> 0.04070517 | ... BE2: =BD2 -> 0.04070517
A3: Commercial | B3: Northland | D3: Electricity | E3: MWh | F3: 3.6 | G3: kWh | K3: =D4 -> Natural Gas | L3: =I4 -> 0.057212 | M3: =L3 -> 0.057212 | N3: =M3 -> 0.057212 | O3: =N3 -> 0.057212 | P3: =O3 -> 0.057212 | Q3: =P3 -> 0.057212 | R3: =Q3 -> 0.057212 | S3: =R3 -> 0.057212 | T3: =S3 -> 0.057212 | ... BE3: =BD3 -> 0.057212
A4: Construction | B4: Auckland | D4: Natural Gas | E4: GJ | F4: 1 | G4: GJ | H4: 57.212 | I4: {=IF(E4=G4,H4/1000,(H4/$H$20)*INDEX($H$18:$H$23,MATCH(1,(G4=$E$18:$E$23)*(E4=$G$18:$G$23),0)))} -> 0.057212 | K4: =D5 -> Coal - sub bituminous | L4: =I5 -> 2.0125536 | M4: =L4 -> 2.0125536 | N4: =M4 -> 2.0125536 | O4: =N4 -> 2.0125536 | P4: =O4 -> 2.0125536 | Q4: =P4 -> 2.0125536 | R4: =Q4 -> 2.0125536 | S4: =R4 -> 2.0125536 | T4: =S4 -> 2.0125536 | ... BE4: =BD4 -> 2.0125536
A5: Agriculture, Forestry and Fishing | B5: Waikato | D5: Coal - sub bituminous | E5: tonnes | F5: 22 | G5: kg | H5: 2.0125536 | I5: {=IF(E5=G5,H5/1000,(H5/$H$20)*INDEX($H$18:$H$23,MATCH(1,(G5=$E$18:$E$23)*(E5=$G$18:$G$23),0)))} -> 2.0125536 | K5: =D6 -> Coal - bituminous | L5: =I6 -> 2.6225536 | M5: =L5 -> 2.6225536 | N5: =M5 -> 2.6225536 | O5: =N5 -> 2.6225536 | P5: =O5 -> 2.6225536 | Q5: =P5 -> 2.6225536 | R5: =Q5 -> 2.6225536 | S5: =R5 -> 2.6225536 | T5: =S5 -> 2.6225536 | ... BE5: =BD5 -> 2.6225536
A6: Dairy Product Manufacturing | B6: Bay of Plenty | D6: Coal - bituminous | E6: tonnes | F6: 27 | G6: kg | H6: 2.6225536 | I6: {=IF(E6=G6,H6/1000,(H6/$H$20)*INDEX($H$18:$H$23,MATCH(1,(G6=$E$18:$E$23)*(E6=$G$18:$G$23),0)))} -> 2.6225536 | K6: =D7 -> Coal - lignite | L6: =I7 -> 1.4325536 | M6: =L6 -> 1.4325536 | N6: =M6 -> 1.4325536 | O6: =N6 -> 1.4325536 | P6: =O6 -> 1.4325536 | Q6: =P6 -> 1.4325536 | R6: =Q6 -> 1.4325536 | S6: =R6 -> 1.4325536 | T6: =S6 -> 1.4325536 | ... BE6: =BD6 -> 1.4325536
A7: Industrial others | B7: Gisborne | D7: Coal - lignite | E7: tonnes | F7: 19 | G7: kg | H7: 1.4325536 | I7: {=IF(E7=G7,H7/1000,(H7/$H$20)*INDEX($H$18:$H$23,MATCH(1,(G7=$E$18:$E$23)*(E7=$G$18:$G$23),0)))} -> 1.4325536 | K7: =D8 -> Diesel | L7: =I8 -> 0.00266 | M7: =L7 -> 0.00266 | N7: =M7 -> 0.00266 | O7: =N7 -> 0.00266 | P7: =O7 -> 0.00266 | Q7: =P7 -> 0.00266 | R7: =Q7 -> 0.00266 | S7: =R7 -> 0.00266 | T7: =S7 -> 0.00266 | ... BE7: =BD7 -> 0.00266
A8: Meat and Meat Product Manufacturing and Seafood | B8: Hawke’s Bay | D8: Diesel | E8: litres | F8: 35.7 | G8: litres | H8: 2.66 | I8: {=IF(E8=G8,H8/1000,(H8/$H$20)*INDEX($H$18:$H$23,MATCH(1,(G8=$E$18:$E$23)*(E8=$G$18:$G$23),0)))} -> 0.00266 | K8: =D9 -> LPG | L8: =I9 -> 0.00164892 | M8: =L8 -> 0.00164892 | N8: =M8 -> 0.00164892 | O8: =N8 -> 0.00164892 | P8: =O8 -> 0.00164892 | Q8: =P8 -> 0.00164892 | R8: =Q8 -> 0.00164892 | S8: =R8 -> 0.00164892 | T8: =S8 -> 0.00164892 | ... BE8: =BD8 -> 0.00164892
A9: Mining | B9: Taranaki | D9: LPG | E9: m3 | F9: =0.025/0.546 -> 0.045787546 | G9: kg | H9: 3.02 | I9: {=IF(E9=G9,H9/1000,(H9/$H$20)*INDEX($H$18:$H$23,MATCH(1,(G9=$E$18:$E$23)*(E9=$G$18:$G$23),0)))} -> 0.00164892 | K9: =D10 -> Light fuel oil | L9: =I10 -> 0.00292 | M9: =L9 -> 0.00292 | N9: =M9 -> 0.00292 | O9: =N9 -> 0.00292 | P9: =O9 -> 0.00292 | Q9: =P9 -> 0.00292 | R9: =Q9 -> 0.00292 | S9: =R9 -> 0.00292 | T9: =S9 -> 0.00292 | ... BE9: =BD9 -> 0.00292
A10: Non-Metallic Mineral Product Manufacturing | B10: Manawatu-Whanganui | D10: Light fuel oil | E10: litres | F10: 37.3 | G10: litres | H10: 2.92 | I10: {=IF(E10=G10,H10/1000,(H10/$H$20)*INDEX($H$18:$H$23,MATCH(1,(G10=$E$18:$E$23)*(E10=$G$18:$G$23),0)))} -> 0.00292 | K10: =D11 -> Heavy fuel oil | L10: =I11 -> 0.00302 | M10: =L10 -> 0.00302 | N10: =M10 -> 0.00302 | O10: =N10 -> 0.00302 | P10: =O10 -> 0.00302 | Q10: =P10 -> 0.00302 | R10: =Q10 -> 0.00302 | S10: =R10 -> 0.00302 | T10: =S10 -> 0.00302 | ... BE10: =BD10 -> 0.00302
A11: Other Food Product Manufacturing | B11: Wellington | D11: Heavy fuel oil | E11: litres | F11: 38.4 | G11: litres | H11: 3.02 | I11: {=IF(E11=G11,H11/1000,(H11/$H$20)*INDEX($H$18:$H$23,MATCH(1,(G11=$E$18:$E$23)*(E11=$G$18:$G$23),0)))} -> 0.00302 | K11: =D12 -> Geothermal | L11: =I12 -> 6.2e-05 | M11: =L11 -> 6.2e-05 | N11: =M11 -> 6.2e-05 | O11: =N11 -> 6.2e-05 | P11: =O11 -> 6.2e-05 | Q11: =P11 -> 6.2e-05 | R11: =Q11 -> 6.2e-05 | S11: =R11 -> 6.2e-05 | T11: =S11 -> 6.2e-05 | ... BE11: =BD11 -> 6.2e-05
A12: Petroleum, Basic Chemical and Rubber Product Manufacturing | B12: Tasman | D12: Geothermal | E12: kWh | F12: =3.6/1000 -> 0.0036 | G12: kWh | H12: 0.062 | I12: {=IF(E12=G12,H12/1000,(H12/$H$20)*INDEX($H$18:$H$23,MATCH(1,(G12=$E$18:$E$23)*(E12=$G$18:$G$23),0)))} -> 6.2e-05 | K12: =D13 -> Wood or wood chips | L12: =I13 -> 0.0201072 | M12: =L12 -> 0.0201072 | N12: =M12 -> 0.0201072 | O12: =N12 -> 0.0201072 | P12: =O12 -> 0.0201072 | Q12: =P12 -> 0.0201072 | R12: =Q12 -> 0.0201072 | S12: =R12 -> 0.0201072 | T12: =S12 -> 0.0201072 | ... BE12: =BD12 -> 0.0201072
A13: Primary Metal and Metal Product Manufacturing | B13: Nelson | D13: Wood or wood chips | E13: tonnes | F13: 10 | G13: kg | H13: 0.0201072 | I13: {=IF(E13=G13,H13/1000,(H13/$H$20)*INDEX($H$18:$H$23,MATCH(1,(G13=$E$18:$E$23)*(E13=$G$18:$G$23),0)))} -> 0.0201072
A14: Pulp, Paper and Converted Paper Product Manufacturing | B14: Marlborough
A15: Wood Product Manufacturing | B15: West Coast
B16: Canterbury | K16: Electricity emisisons
B17: Otago | D17: Fuel | E17: Unit 1 | G17: Unit 2 | H17: Multiplier | K17: Parameter | L17: 2025 | M17: 2026 | N17: 2027 | O17: 2028 | P17: 2029 | Q17: 2030 | R17: 2031 | S17: 2032 | T17: 2033 | U17: 2034 | V17: 2035 | W17: 2036 | X17: 2037 | Y17: 2038 | Z17: 2039 | AA17: 2040 | AB17: 2041 | AC17: 2042 | AD17: 2043 | AE17: 2044 | AF17: 2045 | AG17: 2046 | AH17: 2047 | AI17: 2048 | AJ17: 2049 | AK17: 2050 | AL17: 2051 | AM17: 2052 | AN17: 2053 | AO17: 2054 | AP17: 2055 | AQ17: 2056 | AR17: 2057 | AS17: 2058 | AT17: 2059 | AU17: 2060 | AV17: 2061 | AW17: 2062 | AX17: 2063 | AY17: 2064 | AZ17: 2065 | BA17: 2066 | BB17: 2067 | BC17: 2068 | BD17: 2069 | BE17: 2070
B18: Southland | D18: Any | E18: kWh | G18: MWh | H18: 1000 | K18: EDGS - Reference scenario | L18: 0.066978754 | M18: 0.067432426 | N18: 0.067544021 | O18: 0.065221804 | P18: 0.061132009 | Q18: 0.054806089 | R18: 0.053734391 | S18: 0.054925985 | T18: 0.054936469 | U18: 0.054465043 | V18: 0.05468982 | W18: 0.054134259 | X18: 0.039401193 | Y18: 0.038607524 | Z18: 0.038397025 | AA18: 0.038662375 | AB18: 0.038547358 | AC18: 0.039380983 | AD18: 0.040377288 | AE18: 0.040909475 | AF18: 0.040725118 | AG18: 0.040571248 | AH18: 0.040806592 | AI18: 0.04072376 | AJ18: 0.040516878 | AK18: 0.04070517 | AL18: =AK18 -> 0.04070517 | AM18: =AL18 -> 0.04070517 | AN18: =AM18 -> 0.04070517 | AO18: =AN18 -> 0.04070517 | AP18: =AO18 -> 0.04070517 | AQ18: =AP18 -> 0.04070517 | AR18: =AQ18 -> 0.04070517 | AS18: =AR18 -> 0.04070517 | ... BE18: =BD18 -> 0.04070517
D19: Any | E19: MWh | G19: kWh | H19: 0.001 | K19: Electricity Allocation Factor (t CO2e/MWh) | L19: 0.554 | M19: =L19 -> 0.554 | N19: =M19 -> 0.554 | O19: =N19 -> 0.554 | P19: =O19 -> 0.554 | Q19: =P19 -> 0.554 | R19: =Q19 -> 0.554 | S19: =R19 -> 0.554 | T19: =S19 -> 0.554 | ... BE19: =BD19 -> 0.554
D20: Any | E20: kg | G20: tonnes | H20: 1000 | K20: Wholesale price projection no ETS ($/MWh) | L20: =L30 -> 123.04524 | M20: =M30 -> 113.47833 | N20: =N30 -> 106.26061 | O20: =O30 -> 96.538137 | P20: =P30 -> 90.126734 | Q20: =Q30 -> 83.713572 | R20: =R30 -> 77.299388 | S20: =S30 -> 70.186889 | ... AK20: =AK30 -> 67.44064 | AL20: =AK20 -> 67.44064 | AM20: =AL20 -> 67.44064 | AN20: =AM20 -> 67.44064 | AO20: =AN20 -> 67.44064 | AP20: =AO20 -> 67.44064 | AQ20: =AP20 -> 67.44064 | AR20: =AQ20 -> 67.44064 | AS20: =AR20 -> 67.44064 | ... BE20: =BD20 -> 67.44064
D21: Any | E21: tonnes | G21: kg | H21: 0.001 | K21: Distribution costs ($/MWh) | L21: 50 | M21: =L21 -> 50 | N21: =M21 -> 50 | O21: =N21 -> 50 | P21: =O21 -> 50 | Q21: =P21 -> 50 | R21: =Q21 -> 50 | S21: =R21 -> 50 | T21: =S21 -> 50 | ... BE21: =BD21 -> 50
D22: LPG | E22: m3 | G22: kg | H22: 1.8315 | K22: Total marginal cost ($/MWh) | L22: =L20+L21 -> 173.04524 | M22: =M20+M21 -> 163.47833 | N22: =N20+N21 -> 156.26061 | O22: =O20+O21 -> 146.53814 | P22: =P20+P21 -> 140.12673 | Q22: =Q20+Q21 -> 133.71357 | R22: =R20+R21 -> 127.29939 | S22: =S20+S21 -> 120.18689 | ... BE22: =BE20+BE21 -> 117.44064
D23: LPG | E23: kg | G23: m3 | H23: 0.546 | K23: NZU Price projection | L23: 67.551 | M23: 69.948 | N23: 72.43 | O23: 75 | P23: 71.429 | Q23: 67.857 | R23: 64.286 | S23: 60.714 | T23: 57.143 | U23: 53.571 | V23: 50 | W23: 50 | X23: 50 | Y23: 50 | Z23: 50 | AA23: 50 | AB23: 50 | AC23: 50 | AD23: 50 | AE23: 50 | AF23: 50 | AG23: 50 | AH23: 50 | AI23: 50 | AJ23: 50 | AK23: 50 | AL23: =AK23 -> 50 | AM23: =AL23 -> 50 | AN23: =AM23 -> 50 | AO23: =AN23 -> 50 | AP23: =AO23 -> 50 | AQ23: =AP23 -> 50 | AR23: =AQ23 -> 50 | AS23: =AR23 -> 50 | ... BE23: =BD23 -> 50
K24: Shadow price (central) | L24: 120 | M24: 132 | N24: 143 | O24: 155 | P24: 166 | Q24: 178 | R24: 183 | S24: 189 | T24: 194 | U24: 200 | V24: 206 | W24: 212 | X24: 219 | Y24: 225 | Z24: 232 | AA24: 239 | AB24: 246 | AC24: 253 | AD24: 261 | AE24: 269 | AF24: 277 | AG24: 285 | AH24: 294 | AI24: 303 | AJ24: 312 | AK24: 321 | AL24: 331 | AM24: 341 | AN24: 351 | AO24: 361 | AP24: 372 | AQ24: 383 | AR24: 395 | AS24: 407 | AT24: 419 | AU24: 432 | AV24: 444 | AW24: 458 | AX24: 472 | AY24: 486 | AZ24: 500 | BA24: 515 | BB24: 531 | BC24: 547 | BD24: 563 | BE24: 580
K25: Shadow price (low) | L25: 80 | M25: 88 | N25: 96 | O25: 103 | P25: 111 | Q25: 119 | R25: 122 | S25: 126 | T25: 130 | U25: 133 | V25: 137 | W25: 142 | X25: 146 | Y25: 150 | Z25: 155 | AA25: 159 | AB25: 164 | AC25: 169 | AD25: 174 | AE25: 179 | AF25: 185 | AG25: 190 | AH25: 196 | AI25: 202 | AJ25: 208 | AK25: 214 | AL25: 216 | AM25: 218 | AN25: 221 | AO25: 223 | AP25: 225 | AQ25: 227 | AR25: 230 | AS25: 232 | AT25: 234 | AU25: 236 | AV25: 239 | AW25: 241 | AX25: 244 | AY25: 246 | AZ25: 249 | BA25: 251 | BB25: 254 | BC25: 256 | BD25: 259 | BE25: 261
K26: Shadow price (chigh) | L26: 161 | M26: 176 | N26: 191 | O26: 206 | P26: 222 | Q26: 237 | R26: 244 | S26: 251 | T26: 259 | U26: 267 | V26: 275 | W26: 283 | X26: 292 | Y26: 300 | Z26: 309 | AA26: 319 | AB26: 328 | AC26: 338 | AD26: 348 | AE26: 359 | AF26: 369 | AG26: 380 | AH26: 392 | AI26: 404 | AJ26: 416 | AK26: 428 | AL26: 450 | AM26: 472 | AN26: 496 | AO26: 520 | AP26: 546 | AQ26: 574 | AR26: 602 | AS26: 633 | AT26: 664 | AU26: 697 | AV26: 732 | AW26: 769 | AX26: 807 | AY26: 848 | AZ26: 890 | BA26: 935 | BB26: 981 | BC26: 1030 | BD26: 1082 | BE26: 1136
K28: CCC Current Policy Reference ($/MWh) | L28: 160.60644 | M28: 152.36913 | N28: 146.48101 | O28: 138.08814 | P28: 129.69816 | Q28: 121.30643 | R28: 112.91367 | S28: 103.8226 | T28: 95.706718 | U28: 95.64526 | V28: 95.664687 | W28: 95.643748 | X28: 95.880619 | Y28: 95.837553 | Z28: 95.779528 | AA28: 95.721738 | AB28: 95.663761 | AC28: 95.6058 | AD28: 95.547798 | AE28: 95.489736 | AF28: 95.431571 | AG28: 95.373442 | AH28: 95.31523 | AI28: 95.257074 | AJ28: 95.198909 | AK28: 95.14064
K29: Carbon price assumption | L29: 67.8 | M29: 70.2 | N29: 72.6 | O29: 75 | P29: 71.428571 | Q29: 67.857143 | R29: 64.285714 | S29: 60.714286 | T29: 57.142857 | U29: 53.571429 | V29: 50 | W29: 50 | X29: 50 | Y29: 50 | Z29: 50 | AA29: 50 | AB29: 50 | AC29: 50 | AD29: 50 | AE29: 50 | AF29: 50 | AG29: 50 | AH29: 50 | AI29: 50 | AJ29: 50 | AK29: 50
K30: Ex ETS | L30: =L28-L19*L29 -> 123.04524 | M30: =M28-M19*M29 -> 113.47833 | N30: =N28-N19*N29 -> 106.26061 | O30: =O28-O19*O29 -> 96.538137 | P30: =P28-P19*P29 -> 90.126734 | Q30: =Q28-Q19*Q29 -> 83.713572 | R30: =R28-R19*R29 -> 77.299388 | S30: =S28-S19*S29 -> 70.186889 | ... AK30: =AK28-AK19*AK29 -> 67.44064
K32: Inflation | L32: 2025 | M32: 2026 | N32: 2027 | O32: 2028 | P32: 2029 | Q32: 2030 | R32: 2031 | S32: 2032 | T32: 2033 | U32: 2034 | V32: 2035 | W32: 2036 | X32: 2037 | Y32: 2038 | Z32: 2039 | AA32: 2040 | AB32: 2041 | AC32: 2042 | AD32: 2043 | AE32: 2044 | AF32: 2045 | AG32: 2046 | AH32: 2047 | AI32: 2048 | AJ32: 2049 | AK32: 2050 | AL32: 2051 | AM32: 2052 | AN32: 2053 | AO32: 2054 | AP32: 2055 | AQ32: 2056 | AR32: 2057 | AS32: 2058 | AT32: 2059 | AU32: 2060 | AV32: 2061 | AW32: 2062 | AX32: 2063 | AY32: 2064 | AZ32: 2065 | BA32: 2066 | BB32: 2067 | BC32: 2068 | BD32: 2069 | BE32: 2070
L33: 0.022 | M33: 0.02 | N33: 0.02 | O33: 0.02 | P33: 0.02 | Q33: 0.02 | R33: 0.02 | S33: 0.02 | T33: 0.02 | U33: 0.02 | V33: 0.02 | W33: 0.02 | X33: 0.02 | Y33: 0.02 | Z33: 0.02 | AA33: 0.02 | AB33: 0.02 | AC33: 0.02 | AD33: 0.02 | AE33: 0.02 | AF33: 0.02 | AG33: 0.02 | AH33: 0.02 | AI33: 0.02 | AJ33: 0.02 | AK33: 0.02 | AL33: 0.02 | AM33: 0.02 | AN33: 0.02 | AO33: 0.02 | AP33: 0.02 | AQ33: 0.02 | AR33: 0.02 | AS33: 0.02 | AT33: 0.02 | AU33: 0.02 | AV33: 0.02 | AW33: 0.02 | AX33: 0.02 | AY33: 0.02 | AZ33: 0.02 | BA33: 0.02 | BB33: 0.02 | BC33: 0.02 | BD33: 0.02 | BE33: 0.02

Sheet Lists
A1: Project Options | C1: Q2 | D1: Final year | E1: Q3 | F1: Q4 | G1: Q5
A2: <Select> | B2: 0 | D2: 2026
A3: Retrofit of existing asset | B3: 1 | C3: Expected final year of operation/use of existing asset | D3: ='Project description'!B16 -> 0 | E3: Information not required | F3: =E3 -> Information not required | G3: =F3 -> Information not required
A4: Replacing asset at the end of its life | B4: 2 | C4: Information not required | D4: =YEAR('Project description'!B12)+'Project description'!B17 -> 1900 | E4: Without the loan, what would the existing asset be replaced with at the end of its life? | F4: What would be the expected life of the replacement asset in the base case (no loan) | G4: If not a retrofit, what is the expected economic or useful life of the new investment?
A5: Early replacement of asset | B5: 3 | C5: Expected final year of operation/use of existing asset if not replaced early | D5: =IF('Project description'!B18=Lists!E9,Lists!D3,Lists!D4) -> 1900 | E5: Without the loan, what would the existing asset be replaced with at the end of its life? | F5: What would be the expected life of the replacement asset in the base case (no loan) | G5: If not a retrofit, what is the expected economic or useful life of the new investment?
A6: Choice | B6: =INDEX(B2:B5,MATCH('Project description'!B15,$A$2:$A$5,0)) -> 0 | E6: Options
E7: <Select>
E8: The same as the current asset
A9: Hurdle rate | E9: The same as the the proposed project
A10: <Select> | E10: Something different
A11: Pre-tax Real | B11: 1
A12: Post-tax Real | B12: 2
A13: Pre-tax Nominal | B13: 3
A14: Post-tax Nominal | B14: 4
A16: <Select>
A17: Return on Equity | B17: 1
A18: Return on Whole Investment | B18: 2
A20: Occasion | C20: Min/Max Validation Values
A21: <Select> | C21: 0
A22: Initial application | B22: 0 | C22: 10000000
A23: 12 months | B23: 12
A24: 24 months | B24: 24
A25: 36 months | B25: 36
A26: 48 months | B26: 48
A27: 60 months | B27: 60
A28: 72 months | B28: 72
A29: 84 months | B29: 84
A30: 96 months | B30: 96
A31: 108 months | B31: 108
A32: 120 months | B32: 120
A34: Choice | B34: =IFERROR(VLOOKUP('Project description'!B4,Lists!A22:B32,2,FALSE),"")

Sheet Output
